Workbook

Sheet NAV
A1: Scheme Name | B1: Fund Name | C1: Category | D1: 46111 | E1: 46112 | F1: 46113 | G1: 46114 | H1: 46118 | I1: 46119 | J1: 46120 | K1: 46121 | L1: 46122 | M1: 46125 | N1: 46127 | O1: 46128 | P1: 46129 | Q1: 46132 | R1: 46133 | S1: 46134 | T1: 46135 | U1: 46136 | V1: 46139 | W1: 46140 | X1: 46141 | Y1: 46142 | Z1: 46146 | AA1: 46147 | AB1: 46148 | AC1: 46149 | AD1: 46150 | AE1: 46153 | AF1: 46154 | AG1: 46155 | AH1: 46156 | AI1: 46157 | AJ1: 46160 | AK1: 46161 | AL1: 46162 | AM1: 46163 | AN1: 46164 | AO1: 46167 | AP1: 46168 | AQ1: 46169 | AR1: 46171
A2: 360 ONE Balanced Hybrid Fund | B2: 360 ONE | C2: BALANCED HYBRID | D2: 11.9842 | E2: 11.9849 | G2: 12.0828 | H2: 12.1517 | I2: 12.1905 | J2: 12.4602 | K2: 12.4323 | L2: 12.5287 | M2: 12.4834 | N2: 12.6104 | O2: 12.6252 | P2: 12.6903 | Q2: 12.6844 | R2: 12.7206 | S2: 12.6873 | T2: 12.6426 | U2: 12.5902 | V2: 12.6483 | W2: 12.6296 | X2: 12.6639 | Y2: 12.5998 | Z2: 12.6573 | AA2: 12.6693 | AB2: 12.7801 | AC2: 12.8329 | AD2: 12.811 | AE2: 12.7265 | AF2: 12.5757 | AG2: 12.5839 | AH2: 12.6374 | AI2: 12.6331 | AJ2: 12.606 | AK2: 12.6246 | AL2: 12.6512 | AM2: 12.6458 | AN2: 12.6797 | AO2: 12.7572 | AP2: 12.7528 | AQ2: 12.7882 | AR2: 12.7432
A3: 360 ONE Flexicap Fund | B3: 360 ONE | C3: FLEXI CAP | D3: 13.1454 | E3: 13.1447 | F3: 13.4198 | G3: 13.4138 | H3: 13.5864 | I3: 13.682 | J3: 14.2693 | K3: 14.204 | L3: 14.4501 | M3: 14.3498 | N3: 14.6117 | O3: 14.6519 | P3: 14.8019 | Q3: 14.7812 | R3: 14.8847 | S3: 14.8105 | T3: 14.7134 | U3: 14.605 | V3: 14.7159 | W3: 14.6841 | X3: 14.7764 | Y3: 14.6199 | Z3: 14.7281 | AA3: 14.7453 | AB3: 14.9851 | AC3: 15.1176 | AD3: 15.0644 | AE3: 14.8968 | AF3: 14.5438 | AG3: 14.5824 | AH3: 14.7124 | AI3: 14.7285 | AJ3: 14.6707 | AK3: 14.7208 | AL3: 14.7872 | AM3: 14.7891 | AN3: 14.8575 | AO3: 15.0317 | AP3: 15.0187 | AQ3: 15.1209 | AR3: 15.0069
A4: 360 ONE Focused Fund | B4: 360 ONE | C4: FOCUSED | D4: 41.3556 | E4: 41.3536 | F4: 42.1818 | G4: 42.1643 | H4: 42.675 | I4: 42.9814 | J4: 44.9583 | K4: 44.6187 | L4: 45.3147 | M4: 44.9372 | N4: 45.5416 | O4: 45.6178 | P4: 45.9123 | Q4: 45.8675 | R4: 46.3036 | S4: 46.0475 | T4: 45.7121 | U4: 45.4132 | V4: 45.5719 | W4: 45.4412 | X4: 45.6504 | Y4: 45.2021 | Z4: 45.4976 | AA4: 45.5098 | AB4: 46.2202 | AC4: 46.5182 | AD4: 46.4041 | AE4: 45.636 | AF4: 44.5 | AG4: 44.668 | AH4: 45.1999 | AI4: 45.2481 | AJ4: 45.2326 | AK4: 45.3216 | AL4: 45.5001 | AM4: 45.5496 | AN4: 45.8247 | AO4: 46.259 | AP4: 46.1592 | AQ4: 46.6008 | AR4: 46.0619
A5: 360 ONE Multi Asset Allocation Fund | B5: 360 ONE | C5: MULTI ASSET ALLOCATION | D5: 11.505 | E5: 11.5012 | G5: 11.5457 | H5: 11.6555 | I5: 11.6682 | J5: 11.8916 | K5: 11.822 | L5: 11.8976 | M5: 11.8631 | N5: 11.975 | O5: 11.9797 | P5: 11.9964 | Q5: 11.9765 | R5: 12.0196 | S5: 11.9813 | T5: 11.9229 | U5: 11.8964 | V5: 11.9339 | W5: 11.8682 | X5: 11.8606 | Y5: 11.8757 | Z5: 11.8704 | AA5: 11.852 | AB5: 11.9657 | AC5: 12.0118 | AD5: 11.9823 | AE5: 11.8807 | AF5: 11.8609 | AG5: 12.0144 | AH5: 12.0956 | AI5: 12.035 | AJ5: 12.0068 | AK5: 12.0493 | AL5: 12.0541 | AM5: 12.0566 | AN5: 12.0859 | AO5: 12.1216 | AP5: 12.0876 | AQ5: 12.0945 | AR5: 12.0594
A6: 360 ONE Quant Fund | B6: 360 ONE | C6: SECTORAL / THEMATIC | D6: 17.0029 | E6: 17.002 | F6: 17.2181 | G6: 17.1019 | H6: 17.3066 | I6: 17.3427 | J6: 18.18 | K6: 18.1291 | L6: 18.4814 | M6: 18.1988 | N6: 18.5528 | O6: 18.562 | P6: 18.7114 | Q6: 18.7349 | R6: 18.778 | S6: 18.7274 | T6: 18.5196 | U6: 18.3624 | V6: 18.5218 | W6: 18.402 | X6: 18.4783 | Y6: 18.2678 | Z6: 18.424 | AA6: 18.4857 | AB6: 18.8411 | AC6: 18.9782 | AD6: 18.9216 | AE6: 18.7264 | AF6: 18.3092 | AG6: 18.3736 | AH6: 18.5495 | AI6: 18.4641 | AJ6: 18.3441 | AK6: 18.3325 | AL6: 18.331 | AM6: 18.3705 | AN6: 18.4025 | AO6: 18.6237 | AP6: 18.5929 | AQ6: 18.7332 | AR6: 18.4041
A7: Abakkus Flexi Cap Fund | B7: Abakkus | C7: FLEXI CAP | D7: 9.08 | E7: 9.08 | F7: 9.267 | G7: 9.243 | H7: 9.33 | I7: 9.364 | J7: 9.691 | K7: 9.687 | L7: 9.879 | M7: 9.85 | N7: 10.024 | O7: 10.071 | P7: 10.163 | Q7: 10.16 | R7: 10.264 | S7: 10.285 | T7: 10.219 | U7: 10.115 | V7: 10.253 | W7: 10.226 | X7: 10.287 | Y7: 10.196 | Z7: 10.3 | AA7: 10.264 | AB7: 10.418 | AC7: 10.489 | AD7: 10.423 | AE7: 10.282 | AF7: 10.07 | AG7: 10.11 | AH7: 10.171 | AI7: 10.15 | AJ7: 10.094 | AK7: 10.155 | AL7: 10.201 | AM7: 10.223 | AN7: 10.262 | AO7: 10.405 | AP7: 10.397 | AQ7: 10.445 | AR7: 10.338
A8: Abakkus Small Cap Fund | B8: Abakkus | C8: SMALL CAP | D8: 9.854 | E8: 9.855 | F8: 10.007 | G8: 9.984 | H8: 10.04 | I8: 10.071 | J8: 10.343 | K8: 10.351 | L8: 10.508 | M8: 10.513 | N8: 10.74 | O8: 10.826 | P8: 10.911 | Q8: 10.871 | R8: 10.95 | S8: 11.037 | T8: 11.005 | U8: 10.906 | V8: 11.062 | W8: 11.035 | X8: 11.063 | Y8: 11.007 | Z8: 11.139 | AA8: 11.125 | AB8: 11.286 | AC8: 11.347 | AD8: 11.339 | AE8: 11.185 | AF8: 10.944 | AG8: 10.952 | AH8: 10.989 | AI8: 10.975 | AJ8: 10.856 | AK8: 10.958 | AL8: 10.969 | AM8: 11.048 | AN8: 11.044 | AO8: 11.158 | AP8: 11.181 | AQ8: 11.237 | AR8: 11.246
A9: Aditya Birla Sun Life Arbitrage Fund | B9: Aditya Birla Sun Life | C9: ARBITRAGE | D9: 27.7263 | E9: 27.7276 | F9: 27.7102 | G9: 27.7371 | H9: 27.7333 | I9: 27.751 | J9: 27.7549 | K9: 27.7578 | L9: 27.7795 | M9: 27.7987 | N9: 27.8138 | O9: 27.8186 | P9: 27.8157 | Q9: 27.8479 | R9: 27.8322 | S9: 27.8399 | T9: 27.8417 | U9: 27.8253 | V9: 27.8343 | W9: 27.8391 | X9: 27.8526 | Y9: 27.8377 | Z9: 27.8462 | AA9: 27.8535 | AB9: 27.8245 | AC9: 27.8621 | AD9: 27.8765 | AE9: 27.884 | AF9: 27.8844 | AG9: 27.8781 | AH9: 27.8886 | AI9: 27.919 | AJ9: 27.9172 | AK9: 27.923 | AL9: 27.9011 | AM9: 27.9046 | AN9: 27.8825 | AO9: 27.8981 | AP9: 27.9016 | AQ9: 27.8895 | AR9: 27.8437
A10: Aditya Birla Sun Life Balanced Advantage Fund | B10: Aditya Birla Sun Life | C10: DYNAMIC ASSET ALLOCATION OR BALANCED ADVANTAGE | D10: 102.25 | E10: 102.25 | F10: 103.41 | G10: 103.36 | H10: 104.18 | I10: 104.52 | J10: 107.02 | K10: 106.74 | L10: 107.86 | M10: 107.51 | N10: 108.82 | O10: 108.85 | P10: 109.57 | Q10: 109.63 | R10: 110.25 | S10: 110.11 | T10: 109.42 | U10: 108.41 | V10: 109.27 | W10: 108.98 | X10: 109.02 | Y10: 108.52 | Z10: 108.96 | AA10: 108.93 | AB10: 109.84 | AC10: 110.05 | AD10: 109.78 | AE10: 108.9 | AF10: 107.28 | AG10: 107.62 | AH10: 108.2 | AI10: 108.02 | AJ10: 107.87 | AK10: 108.23 | AL10: 108.19 | AM10: 107.99 | AN10: 108.31 | AO10: 109.14 | AP10: 109.18 | AQ10: 109.37 | AR10: 108.69
A11: Aditya Birla Sun Life Banking & Financial Services Fund | B11: Aditya Birla Sun Life | C11: SECTORAL / THEMATIC | D11: 54.66 | E11: 54.65 | F11: 55.87 | G11: 55.94 | H11: 57.17 | I11: 57.32 | J11: 60.61 | K11: 59.91 | L11: 61.15 | M11: 60.76 | N11: 61.58 | O11: 61.72 | P11: 62.2 | Q11: 62.29 | R11: 63.46 | S11: 63.18 | T11: 62.46 | U11: 62.24 | V11: 62.09 | W11: 61.48 | X11: 61.6 | Y11: 61.05 | Z11: 61.41 | AA11: 61.32 | AB11: 62.64 | AC11: 62.82 | AD11: 62.05 | AE11: 61.13 | AF11: 59.69 | AG11: 59.67 | AH11: 60.28 | AI11: 60.05 | AJ11: 59.74 | AK11: 59.77 | AL11: 59.78 | AM11: 59.68 | AN11: 60.15 | AO11: 61.34 | AP11: 61.11 | AQ11: 60.85 | AR11: 59.99
A12: Aditya Birla Sun Life Business Cycle Fund | B12: Aditya Birla Sun Life | C12: SECTORAL / THEMATIC | D12: 13.62 | E12: 13.62 | F12: 13.87 | G12: 13.86 | H12: 14.03 | I12: 14.08 | J12: 14.63 | K12: 14.55 | L12: 14.79 | M12: 14.74 | N12: 14.98 | O12: 15.02 | P12: 15.17 | Q12: 15.19 | R12: 15.34 | S12: 15.29 | T12: 15.14 | U12: 14.97 | V12: 15.13 | W12: 15.02 | X12: 15.01 | Y12: 14.91 | Z12: 15.04 | AA12: 15 | AB12: 15.17 | AC12: 15.27 | AD12: 15.19 | AE12: 14.99 | AF12: 14.65 | AG12: 14.66 | AH12: 14.78 | AI12: 14.69 | AJ12: 14.62 | AK12: 14.74 | AL12: 14.74 | AM12: 14.77 | AN12: 14.78 | AO12: 14.96 | AP12: 14.97 | AQ12: 15.03 | AR12: 14.93
A13: Aditya Birla Sun Life Conglomerate Fund | B13: Aditya Birla Sun Life | C13: SECTORAL / THEMATIC | D13: 9.2 | E13: 9.2 | F13: 9.44 | G13: 9.45 | H13: 9.52 | I13: 9.55 | J13: 9.96 | K13: 9.9 | L13: 10.06 | M13: 9.97 | N13: 10.2 | O13: 10.28 | P13: 10.35 | Q13: 10.35 | R13: 10.42 | S13: 10.44 | T13: 10.37 | U13: 10.24 | V13: 10.41 | W13: 10.46 | X13: 10.55 | Y13: 10.46 | Z13: 10.57 | AA13: 10.56 | AB13: 10.69 | AC13: 10.75 | AD13: 10.73 | AE13: 10.58 | AF13: 10.31 | AG13: 10.38 | AH13: 10.44 | AI13: 10.36 | AJ13: 10.32 | AK13: 10.37 | AL13: 10.43 | AM13: 10.45 | AN13: 10.47 | AO13: 10.63 | AP13: 10.67 | AQ13: 10.74 | AR13: 10.63
A14: Aditya Birla Sun Life Consumption Fund | B14: Aditya Birla Sun Life | C14: SECTORAL / THEMATIC | D14: 184.13 | E14: 184.12 | F14: 187.43 | G14: 187.3 | H14: 190.03 | I14: 190.29 | J14: 197.01 | K14: 196.08 | L14: 199.06 | M14: 197.18 | N14: 200.55 | O14: 200.62 | P14: 202.8 | Q14: 203.07 | R14: 205.54 | S14: 205.7 | T14: 203.67 | U14: 201.79 | V14: 203.28 | W14: 202.15 | X14: 203.37 | Y14: 201.42 | Z14: 202.3 | AA14: 201.81 | AB14: 204.34 | AC14: 204.54 | AD14: 204.32 | AE14: 201.44 | AF14: 197.14 | AG14: 197.39 | AH14: 199.5 | AI14: 199.33 | AJ14: 198.58 | AK14: 198.72 | AL14: 198.16 | AM14: 198.05 | AN14: 198.74 | AO14: 200.13 | AP14: 199.54 | AQ14: 199.97 | AR14: 196.92
A15: Aditya Birla Sun Life Digital India Fund | B15: Aditya Birla Sun Life | C15: SECTORAL / THEMATIC | D15: 135.22 | E15: 135.3 | F15: 138.44 | G15: 141.27 | H15: 142.03 | I15: 144.16 | J15: 146.64 | K15: 146.74 | L15: 145.76 | M15: 144.66 | N15: 148.46 | O15: 150.4 | P15: 150.87 | Q15: 149.91 | R15: 150.8 | S15: 148.04 | T15: 146.4 | U15: 141.07 | V15: 142.95 | W15: 142.41 | X15: 143.62 | Y15: 143.6 | Z15: 142.92 | AA15: 142.86 | AB15: 145.29 | AC15: 144.81 | AD15: 147 | AE15: 145.61 | AF15: 141.05 | AG15: 140.12 | AH15: 139.58 | AI15: 140.45 | AJ15: 142.73 | AK15: 146.32 | AL15: 145.52 | AM15: 144.65 | AN15: 144.63 | AO15: 145.93 | AP15: 146.17 | AQ15: 146.06 | AR15: 145.81
A16: Aditya Birla Sun Life Dividend Yield Fund | B16: Aditya Birla Sun Life | C16: DIVIDEND YIELD | D16: 413.1 | E16: 413.29 | F16: 422.19 | G16: 422.93 | H16: 429.69 | I16: 432.53 | J16: 443.64 | K16: 444.56 | L16: 447.52 | M16: 446.58 | N16: 453.9 | O16: 454.85 | P16: 460.1 | Q16: 460.22 | R16: 463.69 | S16: 461.35 | T16: 457.39 | U16: 452.1 | V16: 456.01 | W16: 454.34 | X16: 458.4 | Y16: 455.08 | Z16: 455.93 | AA16: 456.12 | AB16: 462.58 | AC16: 463.54 | AD16: 461.8 | AE16: 457.52 | AF16: 449.5 | AG16: 451.24 | AH16: 453.3 | AI16: 453.17 | AJ16: 450.94 | AK16: 455.46 | AL16: 455.46 | AM16: 453.58 | AN16: 452.82 | AO16: 457.65 | AP16: 457.03 | AQ16: 457.43 | AR16: 451.16
A17: Aditya Birla Sun Life ELSS Tax Saver Fund | B17: Aditya Birla Sun Life | C17: ELSS | D17: 54.36 | E17: 54.36 | F17: 55.58 | G17: 55.54 | H17: 56.26 | I17: 56.58 | J17: 58.65 | K17: 58.35 | L17: 59.16 | M17: 58.78 | N17: 59.78 | O17: 59.9 | P17: 60.48 | Q17: 60.47 | R17: 61.04 | S17: 60.95 | T17: 60.42 | U17: 59.72 | V17: 60.36 | W17: 60.06 | X17: 60.32 | Y17: 59.87 | Z17: 60.49 | AA17: 60.41 | AB17: 61.21 | AC17: 61.32 | AD17: 60.93 | AE17: 59.96 | AF17: 58.72 | AG17: 58.8 | AH17: 59.34 | AI17: 59.24 | AJ17: 59.1 | AK17: 59.27 | AL17: 59.41 | AM17: 59.32 | AN17: 59.52 | AO17: 60.27 | AP17: 60.16 | AQ17: 60.42 | AR17: 59.69
... A34: Aditya Birla Sun Life Quant Fund | B34: Aditya Birla Sun Life | C34: SECTORAL / THEMATIC | D34: 8.91 | E34: 8.91 | F34: 9.04 | G34: 9.01 | H34: 9.14 | I34: 9.2 | J34: 9.6 | K34: 9.58 | L34: 9.74 | M34: 9.64 | N34: 9.78 | O34: 9.78 | P34: 9.86 | Q34: 9.9 | R34: 9.91 | S34: 9.87 | T34: 9.78 | U34: 9.72 | V34: 9.84 | W34: 9.78 | X34: 9.81 | Y34: 9.7 | Z34: 9.77 | AA34: 9.79 | AB34: 9.97 | AC34: 10.06 | AD34: 10.02 | AE34: 9.93 | AF34: 9.76 | AG34: 9.8 | AH34: 9.91 | AI34: 9.85 | AJ34: 9.78 | AK34: 9.81 | AL34: 9.86 | AM34: 9.87 | AN34: 9.9 | AO34: 10.04 | AP34: 10.01 | AQ34: 10.07 | AR34: 9.92
A35: Aditya Birla Sun Life Regular Savings Fund | B35: Aditya Birla Sun Life | C35: CONSERVATIVE HYRBID | D35: 67.0697 | E35: 67.0895 | G35: 67.1641 | H35: 67.3988 | I35: 67.5138 | J35: 68.2278 | K35: 68.2235 | L35: 68.4753 | M35: 68.3599 | N35: 68.7058 | O35: 68.7124 | P35: 68.8416 | Q35: 68.8466 | R35: 68.9738 | S35: 68.9118 | T35: 68.7224 | U35: 68.5566 | V35: 68.7469 | W35: 68.695 | X35: 68.7055 | Y35: 68.5543 | Z35: 68.7193 | AA35: 68.6961 | AB35: 69.0035 | AC35: 69.0836 | AD35: 69.0182 | AE35: 68.8083 | AF35: 68.5395 | AG35: 68.5487 | AH35: 68.7144 | AI35: 68.609 | AJ35: 68.4192 | AK35: 68.43 | AL35: 68.4776 | AM35: 68.462 | AN35: 68.5233 | AO35: 68.7889 | AP35: 68.7847 | AQ35: 68.8661 | AR35: 68.7522
A36: Aditya Birla Sun Life Small cap Fund | B36: Aditya Birla Sun Life | C36: SMALL CAP | D36: 76.2251 | E36: 76.2218 | F36: 78.1433 | G36: 78.0308 | H36: 79.2089 | I36: 79.2352 | J36: 82.0232 | K36: 82.059 | L36: 83.2372 | M36: 82.9096 | N36: 84.3057 | O36: 84.8954 | P36: 86.0144 | Q36: 86.2474 | R36: 87.0972 | S36: 87.8899 | T36: 87.7067 | U36: 87.4017 | V36: 88.7495 | W36: 88.6403 | X36: 89.1451 | Y36: 88.8412 | Z36: 90.1122 | AA36: 89.7456 | AB36: 90.6651 | AC36: 92.1379 | AD36: 92.103 | AE36: 91.09 | AF36: 88.7621 | AG36: 88.961 | AH36: 89.6799 | AI36: 89.8147 | AJ36: 88.8786 | AK36: 90.0184 | AL36: 90.2036 | AM36: 90.5962 | AN36: 90.4121 | AO36: 91.6148 | AP36: 91.8316 | AQ36: 91.745 | AR36: 91.2669
A37: Aditya Birla Sun Life Special Opportunities Fund | B37: Aditya Birla Sun Life | C37: SECTORAL / THEMATIC | D37: 23.38 | E37: 23.37 | F37: 23.8 | G37: 23.79 | H37: 24.11 | I37: 24.23 | J37: 25.13 | K37: 25.09 | L37: 25.41 | M37: 25.31 | N37: 25.77 | O37: 25.85 | P37: 26.11 | Q37: 26.1 | R37: 26.41 | S37: 26.34 | T37: 26.14 | U37: 25.89 | V37: 26.15 | W37: 26.06 | X37: 26.24 | Y37: 26.03 | Z37: 26.23 | AA37: 26.24 | AB37: 26.59 | AC37: 26.71 | AD37: 26.65 | AE37: 26.34 | AF37: 25.83 | AG37: 25.92 | AH37: 26.16 | AI37: 26.1 | AJ37: 26 | AK37: 26.13 | AL37: 26.14 | AM37: 26.08 | AN37: 26.18 | AO37: 26.55 | AP37: 26.6 | AQ37: 26.63 | AR37: 26.55
A38: Aditya Birla Sun Life Transportation and Logistics Fund | B38: Aditya Birla Sun Life | C38: SECTORAL / THEMATIC | D38: 12.99 | E38: 12.99 | F38: 13.3 | G38: 13.21 | H38: 13.37 | I38: 13.36 | J38: 14.13 | K38: 14.04 | L38: 14.37 | M38: 14.09 | N38: 14.37 | O38: 14.41 | P38: 14.5 | Q38: 14.53 | R38: 14.62 | S38: 14.67 | T38: 14.41 | U38: 14.25 | V38: 14.5 | W38: 14.36 | X38: 14.41 | Y38: 14.32 | Z38: 14.43 | AA38: 14.45 | AB38: 14.76 | AC38: 14.99 | AD38: 15.02 | AE38: 14.73 | AF38: 14.33 | AG38: 14.29 | AH38: 14.35 | AI38: 14.34 | AJ38: 14.16 | AK38: 14.28 | AL38: 14.34 | AM38: 14.5 | AN38: 14.54 | AO38: 14.75 | AP38: 14.76 | AQ38: 14.99 | AR38: 14.75
A39: Aditya Birla Sun Life Value Fund | B39: Aditya Birla Sun Life | C39: VALUE | D39: 113.9322 | E39: 113.9268 | F39: 116.3411 | G39: 116.4956 | H39: 118.016 | I39: 118.7063 | J39: 123.1663 | K39: 123.0909 | L39: 124.5489 | M39: 124.2168 | N39: 126.7858 | O39: 127.4767 | P39: 129.0816 | Q39: 129.1341 | R39: 130.1124 | S39: 130.2569 | T39: 129.751 | U39: 128.061 | V39: 129.5452 | W39: 129.1364 | X39: 129.6306 | Y39: 128.7588 | Z39: 129.8865 | AA39: 129.746 | AB39: 131.6491 | AC39: 132.6191 | AD39: 132.6744 | AE39: 131.3783 | AF39: 128.3605 | AG39: 128.6369 | AH39: 129.5487 | AI39: 129.4134 | AJ39: 128.7731 | AK39: 129.8606 | AL39: 129.9578 | AM39: 130.3176 | AN39: 130.6344 | AO39: 132.3016 | AP39: 132.497 | AQ39: 133.0251 | AR39: 131.5397
A40: Axis Aggressive Hybrid Fund | B40: Axis | C40: AGGRESSIVE HYBRID | D40: 18.95 | E40: 18.95 | F40: 19.18 | G40: 19.19 | H40: 19.33 | I40: 19.4 | J40: 19.95 | K40: 19.82 | L40: 20.02 | M40: 19.91 | N40: 20.19 | O40: 20.2 | P40: 20.31 | Q40: 20.29 | R40: 20.43 | S40: 20.36 | T40: 20.22 | U40: 20.07 | V40: 20.25 | W40: 20.19 | X40: 20.25 | Y40: 20.14 | Z40: 20.21 | AA40: 20.2 | AB40: 20.4 | AC40: 20.42 | AD40: 20.36 | AE40: 20.15 | AF40: 19.81 | AG40: 19.82 | AH40: 19.93 | AI40: 19.89 | AJ40: 19.84 | AK40: 19.89 | AL40: 19.91 | AM40: 19.94 | AN40: 19.99 | AO40: 20.16 | AP40: 20.11 | AQ40: 20.14 | AR40: 19.94
A41: Axis Arbitrage Fund | B41: Axis | C41: ARBITRAGE | D41: 19.515 | E41: 19.5158 | F41: 19.5024 | G41: 19.5202 | H41: 19.513 | I41: 19.5306 | J41: 19.5303 | K41: 19.5387 | L41: 19.5509 | M41: 19.5661 | N41: 19.5757 | O41: 19.578 | P41: 19.579 | Q41: 19.6013 | R41: 19.5874 | S41: 19.5911 | T41: 19.5946 | U41: 19.5833 | V41: 19.5842 | W41: 19.5933 | X41: 19.6041 | Y41: 19.5899 | Z41: 19.5976 | AA41: 19.6025 | AB41: 19.5823 | AC41: 19.6091 | AD41: 19.621 | AE41: 19.6251 | AF41: 19.6225 | AG41: 19.6187 | AH41: 19.6265 | AI41: 19.6469 | AJ41: 19.6479 | AK41: 19.6509 | AL41: 19.6346 | AM41: 19.6404 | AN41: 19.6247 | AO41: 19.6336 | AP41: 19.6357 | AQ41: 19.6275 | AR41: 19.5935
A42: Axis Balanced Advantage Fund | B42: Axis | C42: DYNAMIC ASSET ALLOCATION OR BALANCED ADVANTAGE | D42: 20.03 | E42: 20.03 | F42: 20.21 | G42: 20.2 | H42: 20.33 | I42: 20.41 | J42: 20.91 | K42: 20.78 | L42: 20.95 | M42: 20.85 | N42: 21.1 | O42: 21.11 | P42: 21.21 | Q42: 21.21 | R42: 21.33 | S42: 21.26 | T42: 21.12 | U42: 20.98 | V42: 21.12 | W42: 21.05 | X42: 21.11 | Y42: 21.01 | Z42: 21.06 | AA42: 21.05 | AB42: 21.23 | AC42: 21.25 | AD42: 21.22 | AE42: 21.04 | AF42: 20.77 | AG42: 20.76 | AH42: 20.86 | AI42: 20.86 | AJ42: 20.83 | AK42: 20.85 | AL42: 20.86 | AM42: 20.85 | AN42: 20.89 | AO42: 21.05 | AP42: 21 | AQ42: 21.02 | AR42: 20.86
A43: Axis Business Cycles Fund | B43: Axis | C43: SECTORAL / THEMATIC | D43: 14.49 | E43: 14.49 | F43: 14.78 | G43: 14.77 | H43: 14.97 | I43: 15.04 | J43: 15.69 | K43: 15.58 | L43: 15.85 | M43: 15.72 | N43: 15.99 | O43: 16.05 | P43: 16.2 | Q43: 16.22 | R43: 16.38 | S43: 16.38 | T43: 16.26 | U43: 16.1 | V43: 16.29 | W43: 16.26 | X43: 16.28 | Y43: 16.17 | Z43: 16.28 | AA43: 16.3 | AB43: 16.51 | AC43: 16.63 | AD43: 16.56 | AE43: 16.41 | AF43: 16.04 | AG43: 16.08 | AH43: 16.23 | AI43: 16.14 | AJ43: 16.1 | AK43: 16.12 | AL43: 16.16 | AM43: 16.13 | AN43: 16.15 | AO43: 16.35 | AP43: 16.35 | AQ43: 16.42 | AR43: 16.19
A44: Axis Conservative Hybrid Fund | B44: Axis | C44: CONSERVATIVE HYRBID | D44: 29.5106 | E44: 29.5134 | G44: 29.5201 | H44: 29.6692 | I44: 29.7263 | J44: 30.0559 | K44: 29.9716 | L44: 30.0613 | M44: 30.0277 | N44: 30.1947 | O44: 30.1845 | P44: 30.2063 | Q44: 30.2226 | R44: 30.273 | S44: 30.1954 | T44: 30.123 | U44: 30.0226 | V44: 30.1062 | W44: 30.0511 | X44: 30.085 | Y44: 30.0314 | Z44: 30.0725 | AA44: 30.0682 | AB44: 30.2166 | AC44: 30.2166 | AD44: 30.1645 | AE44: 30.0157 | AF44: 29.8958 | AG44: 29.9158 | AH44: 29.9947 | AI44: 29.9468 | AJ44: 29.8911 | AK44: 29.9268 | AL44: 29.9119 | AM44: 29.8846 | AN44: 29.9311 | AO44: 30.0484 | AP44: 30.0204 | AQ44: 30.0186 | AR44: 29.9466
A45: Axis Consumption Fund | B45: Axis | C45: SECTORAL / THEMATIC | D45: 8.1 | E45: 8.1 | F45: 8.24 | G45: 8.24 | H45: 8.33 | I45: 8.36 | J45: 8.65 | K45: 8.61 | L45: 8.75 | M45: 8.65 | N45: 8.79 | O45: 8.78 | P45: 8.88 | Q45: 8.9 | R45: 9.02 | S45: 9 | T45: 8.91 | U45: 8.85 | V45: 8.93 | W45: 8.88 | X45: 8.96 | Y45: 8.87 | Z45: 8.88 | AA45: 8.88 | AB45: 9.01 | AC45: 9.02 | AD45: 9.06 | AE45: 8.89 | AF45: 8.72 | AG45: 8.73 | AH45: 8.84 | AI45: 8.85 | AJ45: 8.8 | AK45: 8.8 | AL45: 8.78 | AM45: 8.78 | AN45: 8.79 | AO45: 8.87 | AP45: 8.86 | AQ45: 8.91 | AR45: 8.76
A46: Axis ELSS Tax Saver Fund | B46: Axis | C46: ELSS | D46: 84.8179 | E46: 84.8148 | F46: 86.0844 | G46: 85.9079 | H46: 87.0296 | I46: 87.5442 | J46: 90.9738 | K46: 90.3255 | L46: 91.7201 | M46: 90.9178 | N46: 92.4074 | O46: 92.5739 | P46: 93.3343 | Q46: 93.5261 | R46: 94.4374 | S46: 94.0714 | T46: 93.4532 | U46: 92.538 | V46: 93.3775 | W46: 92.9957 | X46: 93.3887 | Y46: 92.6954 | Z46: 93.0932 | AA46: 93.1739 | AB46: 94.4895 | AC46: 94.7847 | AD46: 94.3225 | AE46: 92.9582 | AF46: 90.9598 | AG46: 91.0087 | AH46: 92.0254 | AI46: 91.7936 | AJ46: 91.6685 | AK46: 91.7733 | AL46: 92.0602 | AM46: 91.9588 | AN46: 92.2029 | AO46: 93.2104 | AP46: 92.8476 | AQ46: 93.2138 | AR46: 91.7876
A47: Axis ESG Integration Strategy Fund | B47: Axis | C47: SECTORAL / THEMATIC | D47: 18.92 | E47: 18.92 | F47: 19.15 | G47: 19.17 | H47: 19.36 | I47: 19.44 | J47: 20.12 | K47: 20 | L47: 20.25 | M47: 20.09 | N47: 20.37 | O47: 20.39 | P47: 20.58 | Q47: 20.62 | R47: 20.74 | S47: 20.66 | T47: 20.51 | U47: 20.34 | V47: 20.5 | W47: 20.38 | X47: 20.44 | Y47: 20.29 | Z47: 20.37 | AA47: 20.38 | AB47: 20.66 | AC47: 20.76 | AD47: 20.73 | AE47: 20.51 | AF47: 20.11 | AG47: 20.07 | AH47: 20.22 | AI47: 20.27 | AJ47: 20.21 | AK47: 20.25 | AL47: 20.29 | AM47: 20.33 | AN47: 20.39 | AO47: 20.62 | AP47: 20.56 | AQ47: 20.62 | AR47: 20.35
A48: Axis Equity Savings Fund | B48: Axis | C48: EQUITY SAVINGS | D48: 21.72 | E48: 21.72 | F48: 21.82 | G48: 21.81 | H48: 21.87 | I48: 21.94 | J48: 22.24 | K48: 22.18 | L48: 22.29 | M48: 22.25 | N48: 22.39 | O48: 22.39 | P48: 22.45 | Q48: 22.48 | R48: 22.52 | S48: 22.47 | T48: 22.4 | U48: 22.28 | V48: 22.39 | W48: 22.37 | X48: 22.42 | Y48: 22.38 | Z48: 22.45 | AA48: 22.45 | AB48: 22.55 | AC48: 22.58 | AD48: 22.53 | AE48: 22.44 | AF48: 22.28 | AG48: 22.28 | AH48: 22.38 | AI48: 22.35 | AJ48: 22.33 | AK48: 22.35 | AL48: 22.36 | AM48: 22.35 | AN48: 22.38 | AO48: 22.5 | AP48: 22.48 | AQ48: 22.48 | AR48: 22.37
A49: Axis Flexi Cap Fund | B49: Axis | C49: FLEXI CAP | D49: 23.44 | E49: 23.44 | F49: 23.85 | G49: 23.87 | H49: 24.22 | I49: 24.34 | J49: 25.3 | K49: 25.18 | L49: 25.62 | M49: 25.44 | N49: 25.78 | O49: 25.86 | P49: 26.06 | Q49: 26.15 | R49: 26.36 | S49: 26.37 | T49: 26.24 | U49: 26.01 | V49: 26.14 | W49: 25.93 | X49: 25.98 | Y49: 25.77 | Z49: 25.92 | AA49: 26 | AB49: 26.41 | AC49: 26.56 | AD49: 26.45 | AE49: 26.1 | AF49: 25.46 | AG49: 25.51 | AH49: 25.74 | AI49: 25.67 | AJ49: 25.55 | AK49: 25.62 | AL49: 25.78 | AM49: 25.88 | AN49: 25.95 | AO49: 26.21 | AP49: 26.15 | AQ49: 26.35 | AR49: 25.98
A50: Axis Focused Fund | B50: Axis | C50: FOCUSED | D50: 46.94 | E50: 46.94 | F50: 47.57 | G50: 47.51 | H50: 48.12 | I50: 48.36 | J50: 50.13 | K50: 49.81 | L50: 50.63 | M50: 50.06 | N50: 50.82 | O50: 51.04 | P50: 51.51 | Q50: 51.79 | R50: 52.26 | S50: 52.14 | T50: 51.98 | U50: 51.58 | V50: 51.85 | W50: 51.49 | X50: 51.64 | Y50: 51.28 | Z50: 51.61 | AA50: 51.67 | AB50: 52.39 | AC50: 52.52 | AD50: 52.36 | AE50: 51.5 | AF50: 50.48 | AG50: 50.4 | AH50: 51.01 | AI50: 50.82 | AJ50: 50.7 | AK50: 50.76 | AL50: 51.04 | AM50: 51.1 | AN50: 51.29 | AO50: 51.72 | AP50: 51.54 | AQ50: 51.95 | AR50: 51.09
A51: Axis India Manufacturing Fund | B51: Axis | C51: SECTORAL / THEMATIC | D51: 13.14 | E51: 13.14 | F51: 13.35 | G51: 13.3 | H51: 13.36 | I51: 13.42 | J51: 13.86 | K51: 13.91 | L51: 14.14 | M51: 14.03 | N51: 14.28 | O51: 14.36 | P51: 14.51 | Q51: 14.52 | R51: 14.55 | S51: 14.6 | T51: 14.53 | U51: 14.4 | V51: 14.64 | W51: 14.62 | X51: 14.71 | Y51: 14.6 | Z51: 14.73 | AA51: 14.78 | AB51: 14.94 | AC51: 15.12 | AD51: 15.1 | AE51: 14.94 | AF51: 14.62 | AG51: 14.71 | AH51: 14.81 | AI51: 14.71 | AJ51: 14.59 | AK51: 14.63 | AL51: 14.75 | AM51: 14.87 | AN51: 14.86 | AO51: 14.97 | AP51: 14.99 | AQ51: 15.22 | AR51: 15.04
A52: Axis Innovation Fund | B52: Axis | C52: SECTORAL / THEMATIC | D52: 16.63 | E52: 16.73 | F52: 17.09 | G52: 17.03 | H52: 17.18 | I52: 17.18 | J52: 17.83 | K52: 17.85 | L52: 18.19 | M52: 18.13 | N52: 18.53 | O52: 18.64 | P52: 18.78 | Q52: 18.77 | R52: 18.99 | S52: 19.15 | T52: 19.01 | U52: 18.92 | V52: 19.09 | W52: 19.03 | X52: 18.99 | Y52: 18.97 | Z52: 19.19 | AA52: 19.13 | AB52: 19.31 | AC52: 19.41 | AD52: 19.44 | AE52: 19.21 | AF52: 18.71 | AG52: 18.79 | AH52: 18.94 | AI52: 18.81 | AJ52: 18.67 | AK52: 18.65 | AL52: 18.79 | AM52: 18.8 | AN52: 18.79 | AO52: 18.87 | AP52: 19.01 | AQ52: 19.13 | AR52: 18.96
A53: Axis Large & Mid Cap Fund | B53: Axis | C53: LARGE & MID CAP | D53: 29.47 | E53: 29.53 | F53: 30.08 | G53: 30.04 | H53: 30.44 | I53: 30.56 | J53: 31.7 | K53: 31.59 | L53: 32.02 | M53: 31.87 | N53: 32.42 | O53: 32.44 | P53: 32.74 | Q53: 32.77 | R53: 33.01 | S53: 32.96 | T53: 32.81 | U53: 32.59 | V53: 32.96 | W53: 32.82 | X53: 32.94 | Y53: 32.74 | Z53: 32.85 | AA53: 32.88 | AB53: 33.42 | AC53: 33.55 | AD53: 33.49 | AE53: 33.12 | AF53: 32.4 | AG53: 32.45 | AH53: 32.87 | AI53: 32.75 | AJ53: 32.74 | AK53: 32.81 | AL53: 33.02 | AM53: 33.01 | AN53: 33.1 | AO53: 33.38 | AP53: 33.41 | AQ53: 33.57 | AR53: 33.15
A54: Axis Large Cap Fund | B54: Axis | C54: LARGE CAP | D54: 53.79 | E54: 53.78 | F54: 54.53 | G54: 54.54 | H54: 55.2 | I54: 55.47 | J54: 57.63 | K54: 57.02 | L54: 57.74 | M54: 57.3 | N54: 58.18 | O54: 58.14 | P54: 58.49 | Q54: 58.54 | R54: 59.05 | S54: 58.67 | T54: 58.1 | U54: 57.51 | V54: 57.92 | W54: 57.61 | X54: 57.92 | Y54: 57.49 | Z54: 57.7 | AA54: 57.64 | AB54: 58.43 | AC54: 58.53 | AD54: 58.24 | AE54: 57.36 | AF54: 56.29 | AG54: 56.29 | AH54: 56.95 | AI54: 56.86 | AJ54: 56.87 | AK54: 56.81 | AL54: 56.88 | AM54: 56.91 | AN54: 57.12 | AO54: 57.85 | AP54: 57.53 | AQ54: 57.67 | AR54: 56.91
A55: Axis Midcap Fund | B55: Axis | C55: MID CAP | D55: 102.63 | E55: 102.63 | F55: 104.28 | G55: 103.98 | H55: 105.35 | I55: 105.79 | J55: 109.5 | K55: 109.65 | L55: 111.43 | M55: 110.73 | N55: 112.63 | O55: 113.06 | P55: 114.2 | Q55: 114.54 | R55: 115.26 | S55: 115.44 | T55: 115.24 | U55: 114.26 | V55: 115.55 | W55: 115.34 | X55: 115.21 | Y55: 114.39 | Z55: 115.08 | AA55: 115.28 | AB55: 117.01 | AC55: 117.94 | AD55: 117.72 | AE55: 116.57 | AF55: 113.71 | AG55: 113.87 | AH55: 115.1 | AI55: 114.93 | AJ55: 114.82 | AK55: 115.54 | AL55: 116.29 | AM55: 116.29 | AN55: 116.24 | AO55: 117.06 | AP55: 117.3 | AQ55: 117.95 | AR55: 116.21
A56: Axis Momentum Fund | B56: Axis | C56: SECTORAL / THEMATIC | D56: 8.03 | E56: 8.03 | F56: 8.24 | G56: 8.22 | H56: 8.38 | I56: 8.38 | J56: 8.73 | K56: 8.74 | L56: 8.88 | M56: 8.8 | N56: 8.96 | O56: 9 | P56: 9.07 | Q56: 9.06 | R56: 9.07 | S56: 9.04 | T56: 8.98 | U56: 8.92 | V56: 8.97 | W56: 8.96 | X56: 8.98 | Y56: 8.9 | Z56: 8.92 | AA56: 8.89 | AB56: 8.98 | AC56: 8.99 | AD56: 8.93 | AE56: 8.83 | AF56: 8.68 | AG56: 8.73 | AH56: 8.8 | AI56: 8.76 | AJ56: 8.74 | AK56: 8.75 | AL56: 8.77 | AM56: 8.8 | AN56: 8.81 | AO56: 8.88 | AP56: 8.84 | AQ56: 8.88 | AR56: 8.7
... A79: Bandhan Business Cycle Fund | B79: Bandhan | C79: SECTORAL / THEMATIC | D79: 8.483 | E79: 8.483 | F79: 8.692 | G79: 8.726 | H79: 8.852 | I79: 8.906 | J79: 9.279 | K79: 9.225 | L79: 9.346 | M79: 9.279 | N79: 9.47 | O79: 9.501 | P79: 9.587 | Q79: 9.581 | R79: 9.658 | S79: 9.666 | T79: 9.578 | U79: 9.469 | V79: 9.582 | W79: 9.526 | X79: 9.531 | Y79: 9.48 | Z79: 9.557 | AA79: 9.545 | AB79: 9.709 | AC79: 9.731 | AD79: 9.665 | AE79: 9.533 | AF79: 9.308 | AG79: 9.32 | AH79: 9.401 | AI79: 9.374 | AJ79: 9.326 | AK79: 9.367 | AL79: 9.378 | AM79: 9.393 | AN79: 9.407 | AO79: 9.519 | AP79: 9.514 | AQ79: 9.541 | AR79: 9.467
A80: Bandhan Conservative Hybrid Fund | B80: Bandhan | C80: CONSERVATIVE HYRBID | D80: 31.5875 | E80: 31.5906 | G80: 31.6925 | H80: 31.8539 | I80: 31.8815 | J80: 32.3373 | K80: 32.2914 | L80: 32.4094 | M80: 32.2877 | N80: 32.4795 | O80: 32.4726 | P80: 32.5039 | Q80: 32.5257 | R80: 32.5929 | S80: 32.5025 | T80: 32.3943 | U80: 32.2922 | V80: 32.3929 | W80: 32.3131 | X80: 32.3934 | Y80: 32.3028 | Z80: 32.3461 | AA80: 32.3357 | AB80: 32.5027 | AC80: 32.5136 | AD80: 32.5049 | AE80: 32.3186 | AF80: 32.122 | AG80: 32.1232 | AH80: 32.1516 | AI80: 32.1341 | AJ80: 32.031 | AK80: 32.0356 | AL80: 32.0534 | AM80: 32.0209 | AN80: 32.0508 | AO80: 32.2261 | AP80: 32.168 | AQ80: 32.1675 | AR80: 32.0814
A81: Bandhan ELSS Tax saver Fund | B81: Bandhan | C81: ELSS | D81: 137.75 | E81: 137.744 | F81: 140.183 | G81: 140.349 | H81: 141.89 | I81: 142.815 | J81: 147.501 | K81: 146.892 | L81: 148.489 | M81: 147.539 | N81: 150.04 | O81: 149.908 | P81: 151.12 | Q81: 151.142 | R81: 152.443 | S81: 152.056 | T81: 150.79 | U81: 149.067 | V81: 150.761 | W81: 150.403 | X81: 151.461 | Y81: 150.485 | Z81: 150.788 | AA81: 150.617 | AB81: 152.665 | AC81: 153.385 | AD81: 153.087 | AE81: 151.273 | AF81: 148.755 | AG81: 148.808 | AH81: 150.214 | AI81: 149.979 | AJ81: 149.524 | AK81: 149.061 | AL81: 148.982 | AM81: 148.926 | AN81: 149.56 | AO81: 151.302 | AP81: 151.094 | AQ81: 151.256 | AR81: 149.475
A82: Bandhan Equity Savings Fund | B82: Bandhan | C82: EQUITY SAVINGS | D82: 31.281 | E82: 31.282 | F82: 31.322 | G82: 31.332 | H82: 31.421 | I82: 31.476 | J82: 31.678 | K82: 31.662 | L82: 31.74 | M82: 31.706 | N82: 31.832 | O82: 31.833 | P82: 31.88 | Q82: 31.907 | R82: 31.949 | S82: 31.895 | T82: 31.874 | U82: 31.767 | V82: 31.851 | W82: 31.821 | X82: 31.854 | Y82: 31.808 | Z82: 31.843 | AA82: 31.851 | AB82: 31.922 | AC82: 31.968 | AD82: 31.968 | AE82: 31.898 | AF82: 31.787 | AG82: 31.786 | AH82: 31.867 | AI82: 31.899 | AJ82: 31.87 | AK82: 31.878 | AL82: 31.857 | AM82: 31.84 | AN82: 31.846 | AO82: 31.939 | AP82: 31.922 | AQ82: 31.922 | AR82: 31.829
A83: Bandhan Financial Services Fund | B83: Bandhan | C83: SECTORAL / THEMATIC | D83: 12.83 | E83: 12.83 | F83: 13.081 | G83: 13.102 | H83: 13.374 | I83: 13.403 | J83: 14.135 | K83: 13.985 | L83: 14.264 | M83: 14.17 | N83: 14.41 | O83: 14.394 | P83: 14.533 | Q83: 14.521 | R83: 14.718 | S83: 14.624 | T83: 14.451 | U83: 14.371 | V83: 14.423 | W83: 14.316 | X83: 14.361 | Y83: 14.225 | Z83: 14.327 | AA83: 14.298 | AB83: 14.644 | AC83: 14.722 | AD83: 14.6 | AE83: 14.415 | AF83: 14.076 | AG83: 14.078 | AH83: 14.215 | AI83: 14.154 | AJ83: 14.073 | AK83: 14.097 | AL83: 14.105 | AM83: 14.088 | AN83: 14.182 | AO83: 14.432 | AP83: 14.389 | AQ83: 14.308 | AR83: 14.125
A84: Bandhan Flexi Cap Fund | B84: Bandhan | C84: FLEXI CAP | D84: 186.795 | E84: 186.786 | F84: 189.793 | G84: 190.21 | H84: 193.067 | I84: 193.918 | J84: 200.917 | K84: 199.607 | L84: 201.767 | M84: 200.749 | N84: 204.321 | O84: 204.555 | P84: 206.415 | Q84: 206.224 | R84: 208.046 | S84: 207.283 | T84: 205.399 | U84: 202.917 | V84: 204.751 | W84: 204.082 | X84: 205.681 | Y84: 204.236 | Z84: 205.623 | AA84: 204.984 | AB84: 207.521 | AC84: 207.967 | AD84: 207.416 | AE84: 205.227 | AF84: 201.575 | AG84: 201.819 | AH84: 203.705 | AI84: 203.416 | AJ84: 203.156 | AK84: 203.248 | AL84: 202.977 | AM84: 203.04 | AN84: 203.912 | AO84: 206.368 | AP84: 206.042 | AQ84: 205.971 | AR84: 203.163
A85: Bandhan Focused Fund | B85: Bandhan | C85: FOCUSED | D85: 77.186 | E85: 77.182 | F85: 79.148 | G85: 79.676 | H85: 80.418 | I85: 80.72 | J85: 84.181 | K85: 83.667 | L85: 84.565 | M85: 83.934 | N85: 85.757 | O85: 86.281 | P85: 87.383 | Q85: 87.333 | R85: 88.093 | S85: 88.292 | T85: 87.841 | U85: 87.073 | V85: 88.413 | W85: 88.109 | X85: 87.913 | Y85: 87.379 | Z85: 88.144 | AA85: 88.202 | AB85: 89.282 | AC85: 89.78 | AD85: 89.566 | AE85: 87.966 | AF85: 85.864 | AG85: 86.143 | AH85: 86.699 | AI85: 86.326 | AJ85: 85.703 | AK85: 86.626 | AL85: 86.626 | AM85: 86.871 | AN85: 86.69 | AO85: 87.673 | AP85: 87.781 | AQ85: 87.442 | AR85: 86.423
A86: Bandhan Infrastructure Fund | B86: Bandhan | C86: SECTORAL / THEMATIC | D86: 41.437 | E86: 41.435 | F86: 42.819 | G86: 42.96 | H86: 43.397 | I86: 43.466 | J86: 45.327 | K86: 45.198 | L86: 46.05 | M86: 46.059 | N86: 47.271 | O86: 47.664 | P86: 48.251 | Q86: 48.104 | R86: 48.365 | S86: 48.899 | T86: 48.817 | U86: 48.294 | V86: 49.155 | W86: 49.07 | X86: 49.085 | Y86: 48.691 | Z86: 49.173 | AA86: 49.125 | AB86: 49.437 | AC86: 49.673 | AD86: 49.587 | AE86: 48.698 | AF86: 47.602 | AG86: 47.76 | AH86: 48.15 | AI86: 47.921 | AJ86: 47.618 | AK86: 47.497 | AL86: 47.758 | AM86: 48.106 | AN86: 48.165 | AO86: 48.668 | AP86: 48.72 | AQ86: 49.239 | AR86: 48.652
A87: Bandhan Innovation Fund | B87: Bandhan | C87: SECTORAL / THEMATIC | D87: 11.652 | E87: 11.651 | F87: 11.927 | G87: 11.909 | H87: 12.031 | I87: 12.1 | J87: 12.581 | K87: 12.583 | L87: 12.796 | M87: 12.796 | N87: 13.067 | O87: 13.158 | P87: 13.244 | Q87: 13.258 | R87: 13.364 | S87: 13.402 | T87: 13.326 | U87: 13.172 | V87: 13.36 | W87: 13.318 | X87: 13.333 | Y87: 13.261 | Z87: 13.343 | AA87: 13.362 | AB87: 13.588 | AC87: 13.759 | AD87: 13.77 | AE87: 13.64 | AF87: 13.248 | AG87: 13.241 | AH87: 13.388 | AI87: 13.322 | AJ87: 13.225 | AK87: 13.322 | AL87: 13.438 | AM87: 13.507 | AN87: 13.553 | AO87: 13.693 | AP87: 13.735 | AQ87: 13.813 | AR87: 13.695
A88: Bandhan Large & Mid Cap Fund | B88: Bandhan | C88: LARGE & MID CAP | D88: 122.697 | E88: 122.694 | F88: 125.238 | G88: 125.451 | H88: 126.801 | I88: 127.058 | J88: 131.724 | K88: 131.319 | L88: 132.895 | M88: 132.129 | N88: 134.883 | O88: 135.647 | P88: 136.836 | Q88: 136.805 | R88: 137.897 | S88: 137.986 | T88: 137.591 | U88: 136.378 | V88: 138.078 | W88: 138.043 | X88: 138.265 | Y88: 137.379 | Z88: 138.163 | AA88: 137.9 | AB88: 139.771 | AC88: 140.843 | AD88: 140.457 | AE88: 138.765 | AF88: 135.835 | AG88: 136.72 | AH88: 137.875 | AI88: 137.57 | AJ88: 137.025 | AK88: 137.754 | AL88: 138.068 | AM88: 138.372 | AN88: 138.223 | AO88: 139.588 | AP88: 139.683 | AQ88: 139.923 | AR88: 137.861
A89: Bandhan Large Cap Fund | B89: Bandhan | C89: LARGE CAP | D89: 69.441 | E89: 69.437 | F89: 70.652 | G89: 70.65 | H89: 71.471 | I89: 71.931 | J89: 74.691 | K89: 74.169 | L89: 75.117 | M89: 74.724 | N89: 75.967 | O89: 76.022 | P89: 76.543 | Q89: 76.656 | R89: 77.208 | S89: 76.843 | T89: 76.081 | U89: 75.178 | V89: 76.004 | W89: 75.639 | X89: 76.101 | Y89: 75.487 | Z89: 75.923 | AA89: 75.833 | AB89: 76.841 | AC89: 77.138 | AD89: 76.799 | AE89: 75.703 | AF89: 74.104 | AG89: 74.089 | AH89: 74.861 | AI89: 74.647 | AJ89: 74.535 | AK89: 74.689 | AL89: 74.916 | AM89: 74.975 | AN89: 75.184 | AO89: 76.08 | AP89: 75.814 | AQ89: 75.964 | AR89: 74.98
A90: Bandhan Midcap Fund | B90: Bandhan | C90: MID CAP | D90: 15.488 | E90: 15.487 | F90: 15.745 | G90: 15.709 | H90: 15.959 | I90: 15.997 | J90: 16.592 | K90: 16.624 | L90: 16.918 | M90: 16.781 | N90: 17.103 | O90: 17.176 | P90: 17.359 | Q90: 17.421 | R90: 17.538 | S90: 17.617 | T90: 17.61 | U90: 17.477 | V90: 17.642 | W90: 17.587 | X90: 17.576 | Y90: 17.442 | Z90: 17.605 | AA90: 17.665 | AB90: 17.912 | AC90: 18.071 | AD90: 18.072 | AE90: 17.909 | AF90: 17.419 | AG90: 17.468 | AH90: 17.61 | AI90: 17.592 | AJ90: 17.542 | AK90: 17.653 | AL90: 17.791 | AM90: 17.84 | AN90: 17.832 | AO90: 17.973 | AP90: 18.008 | AQ90: 18.13 | AR90: 17.925
A91: Bandhan Multi Asset Allocation Fund | B91: Bandhan | C91: MULTI ASSET ALLOCATION | D91: 12.8757 | E91: 12.8802 | F91: 13.0902 | G91: 13.0331 | H91: 13.1561 | I91: 13.1693 | J91: 13.5089 | K91: 13.4552 | L91: 13.5672 | M91: 13.531 | N91: 13.7414 | O91: 13.7873 | P91: 13.8603 | Q91: 13.8633 | R91: 13.9202 | S91: 13.9291 | T91: 13.8334 | U91: 13.7414 | V91: 13.8287 | W91: 13.7791 | X91: 13.8282 | Y91: 13.8116 | Z91: 13.8794 | AA91: 13.8677 | AB91: 14.0147 | AC91: 14.0744 | AD91: 14.0776 | AE91: 14.0029 | AF91: 13.9011 | AG91: 14.0277 | AH91: 14.1143 | AI91: 14.0001 | AJ91: 13.9824 | AK91: 13.9988 | AL91: 14.008 | AM91: 14.0032 | AN91: 14.0337 | AO91: 14.1138 | AP91: 14.1086 | AQ91: 14.1225 | AR91: 14.0133
A92: Bandhan Multi-Factor Fund | B92: Bandhan | C92: SECTORAL / THEMATIC | D92: 9.419 | E92: 9.418 | F92: 9.495 | G92: 9.483 | H92: 9.603 | I92: 9.647 | J92: 9.911 | K92: 9.94 | L92: 10.046 | M92: 9.942 | N92: 10.072 | O92: 10.059 | P92: 10.137 | Q92: 10.124 | R92: 10.165 | S92: 10.089 | T92: 10.016 | U92: 9.923 | V92: 10.007 | W92: 10.004 | X92: 10.043 | Y92: 9.936 | Z92: 9.897 | AA92: 9.912 | AB92: 10.049 | AC92: 10.03 | AD92: 9.96 | AE92: 9.829 | AF92: 9.713 | AG92: 9.784 | AH92: 9.882 | AI92: 9.836 | AJ92: 9.775 | AK92: 9.815 | AL92: 9.827 | AM92: 9.844 | AN92: 9.828 | AO92: 9.916 | AP92: 9.892 | AQ92: 9.944 | AR92: 9.795
... A100: Bank of India Business Cycle Fund | B100: Bank of India | C100: SECTORAL / THEMATIC | D100: 8.01 | E100: 8.01 | F100: 8.18 | G100: 8.18 | H100: 8.27 | I100: 8.3 | J100: 8.58 | K100: 8.57 | L100: 8.73 | M100: 8.71 | N100: 8.92 | O100: 8.96 | P100: 9.08 | Q100: 9.1 | R100: 9.17 | S100: 9.18 | T100: 9.15 | U100: 9.11 | V100: 9.23 | W100: 9.2 | X100: 9.25 | Y100: 9.17 | Z100: 9.22 | AA100: 9.22 | AB100: 9.28 | AC100: 9.36 | AD100: 9.33 | AE100: 9.15 | AF100: 9 | AG100: 9.01 | AH100: 9.06 | AI100: 9.04 | AJ100: 8.98 | AK100: 9.01 | AL100: 9.06 | AM100: 9.09 | AN100: 9.06 | AO100: 9.17 | AP100: 9.17 | AQ100: 9.22 | AR100: 9.13
A101: Bank of India Conservative Hybrid Fund | B101: Bank of India | C101: CONSERVATIVE HYRBID | D101: 34.0546 | E101: 34.0566 | G101: 34.1336 | H101: 34.2167 | I101: 34.2563 | J101: 34.5665 | K101: 34.5752 | L101: 34.6956 | M101: 34.6757 | N101: 34.8743 | O101: 34.9196 | P101: 34.9715 | Q101: 34.9783 | R101: 35.003 | S101: 34.991 | T101: 34.9435 | U101: 34.8699 | V101: 34.9753 | W101: 34.9774 | X101: 35.0013 | Y101: 34.8891 | Z101: 34.9407 | AA101: 34.9431 | AB101: 35.0787 | AC101: 35.1061 | AD101: 35.0771 | AE101: 34.9137 | AF101: 34.7564 | AG101: 34.8393 | AH101: 34.9345 | AI101: 34.8365 | AJ101: 34.726 | AK101: 34.7756 | AL101: 34.7574 | AM101: 34.7493 | AN101: 34.7186 | AO101: 34.8419 | AP101: 34.8503 | AQ101: 34.9374 | AR101: 34.8206
A102: Bank of India Consumption Fund | B102: Bank of India | C102: SECTORAL / THEMATIC | D102: 9.59 | E102: 9.59 | F102: 9.72 | G102: 9.73 | H102: 9.85 | I102: 9.89 | J102: 10.15 | K102: 10.13 | L102: 10.24 | M102: 10.18 | N102: 10.33 | O102: 10.33 | P102: 10.46 | Q102: 10.41 | R102: 10.5 | S102: 10.46 | T102: 10.43 | U102: 10.36 | V102: 10.44 | W102: 10.42 | X102: 10.53 | Y102: 10.46 | Z102: 10.47 | AA102: 10.49 | AB102: 10.59 | AC102: 10.64 | AD102: 10.62 | AE102: 10.44 | AF102: 10.23 | AG102: 10.27 | AH102: 10.42 | AI102: 10.47 | AJ102: 10.45 | AK102: 10.52 | AL102: 10.51 | AM102: 10.5 | AN102: 10.5 | AO102: 10.55 | AP102: 10.5 | AQ102: 10.5 | AR102: 10.39
A103: Bank of India ELSS Tax Saver | B103: Bank of India | C103: ELSS | D103: 146.09 | E103: 146.08 | F103: 148.93 | G103: 148.12 | H103: 149.67 | I103: 150.42 | J103: 155.78 | K103: 155.71 | L103: 158.17 | M103: 158.09 | N103: 160.83 | O103: 162.39 | P103: 163.85 | Q103: 164.36 | R103: 165.26 | S103: 165.59 | T103: 164.72 | U103: 163.31 | V103: 165.26 | W103: 164.51 | X103: 165.02 | Y103: 162.84 | Z103: 164 | AA103: 163.79 | AB103: 165.18 | AC103: 165.96 | AD103: 164.67 | AE103: 162.29 | AF103: 159.93 | AG103: 161.16 | AH103: 161.75 | AI103: 160.81 | AJ103: 159.1 | AK103: 159.29 | AL103: 159.68 | AM103: 160.54 | AN103: 160.29 | AO103: 161.95 | AP103: 162.01 | AQ103: 162.56 | AR103: 160.73
A104: Bank of India Flexi Cap Fund | B104: Bank of India | C104: FLEXI CAP | D104: 31.79 | E104: 31.79 | F104: 32.6 | G104: 32.51 | H104: 32.94 | I104: 33.09 | J104: 34.28 | K104: 34.26 | L104: 34.76 | M104: 34.67 | N104: 35.35 | O104: 35.75 | P104: 36.1 | Q104: 36.18 | R104: 36.35 | S104: 36.37 | T104: 36.25 | U104: 35.94 | V104: 36.39 | W104: 36.32 | X104: 36.52 | Y104: 36.18 | Z104: 36.46 | AA104: 36.5 | AB104: 36.81 | AC104: 37.07 | AD104: 37.06 | AE104: 36.49 | AF104: 35.74 | AG104: 35.94 | AH104: 36.07 | AI104: 35.85 | AJ104: 35.52 | AK104: 35.56 | AL104: 35.65 | AM104: 35.88 | AN104: 35.88 | AO104: 36.27 | AP104: 36.36 | AQ104: 36.42 | AR104: 36.15
A105: Bank of India Large & Mid Cap Fund | B105: Bank of India | C105: LARGE & MID CAP | D105: 82.04 | E105: 82.03 | F105: 83.53 | G105: 83.72 | H105: 84.61 | I105: 84.84 | J105: 87.46 | K105: 87.13 | L105: 87.96 | M105: 87.37 | N105: 88.92 | O105: 89.37 | P105: 90.16 | Q105: 89.72 | R105: 90.19 | S105: 89.83 | T105: 89.68 | U105: 89.05 | V105: 90.05 | W105: 89.93 | X105: 90.43 | Y105: 89.76 | Z105: 90.19 | AA105: 90.42 | AB105: 91.29 | AC105: 91.49 | AD105: 91.19 | AE105: 90.06 | AF105: 88.39 | AG105: 88.92 | AH105: 89.74 | AI105: 89.57 | AJ105: 89.33 | AK105: 89.58 | AL105: 89.81 | AM105: 90.11 | AN105: 90.25 | AO105: 90.95 | AP105: 90.69 | AQ105: 90.39 | AR105: 89.35
A106: Bank of India Large Cap Fund | B106: Bank of India | C106: LARGE CAP | D106: 14.74 | E106: 14.73 | F106: 15.05 | G106: 15.08 | H106: 15.28 | I106: 15.35 | J106: 15.9 | K106: 15.86 | L106: 16.08 | M106: 16 | N106: 16.28 | O106: 16.34 | P106: 16.51 | Q106: 16.52 | R106: 16.64 | S106: 16.54 | T106: 16.44 | U106: 16.3 | V106: 16.41 | W106: 16.36 | X106: 16.46 | Y106: 16.32 | Z106: 16.42 | AA106: 16.41 | AB106: 16.6 | AC106: 16.69 | AD106: 16.59 | AE106: 16.33 | AF106: 15.99 | AG106: 16.05 | AH106: 16.17 | AI106: 16.14 | AJ106: 16.07 | AK106: 16.05 | AL106: 16.08 | AM106: 16.14 | AN106: 16.17 | AO106: 16.38 | AP106: 16.39 | AQ106: 16.41 | AR106: 16.25
A107: Bank of India Manufacturing & Infrastructure Fund | B107: Bank of India | C107: SECTORAL / THEMATIC | D107: 55.14 | E107: 55.14 | F107: 56.29 | G107: 56.2 | H107: 56.75 | I107: 56.91 | J107: 58.76 | K107: 58.81 | L107: 59.55 | M107: 59.29 | N107: 60.6 | O107: 61.05 | P107: 61.57 | Q107: 61.47 | R107: 61.68 | S107: 61.92 | T107: 61.95 | U107: 61.39 | V107: 62.32 | W107: 62.54 | X107: 62.92 | Y107: 62.78 | Z107: 63.56 | AA107: 63.42 | AB107: 63.65 | AC107: 64.26 | AD107: 64.02 | AE107: 63.18 | AF107: 62.14 | AG107: 62.63 | AH107: 63.04 | AI107: 62.91 | AJ107: 62.44 | AK107: 62.44 | AL107: 62.66 | AM107: 63.1 | AN107: 63.01 | AO107: 63.55 | AP107: 63.89 | AQ107: 63.92 | AR107: 63.52
A108: Bank of India Mid & Small Cap Equity & Debt Fund | B108: Bank of India | C108: AGGRESSIVE HYBRID | D108: 35.58 | E108: 35.58 | F108: 36.42 | G108: 36.31 | H108: 36.72 | I108: 36.73 | J108: 37.81 | K108: 37.85 | L108: 38.34 | M108: 38.16 | N108: 38.87 | O108: 39.34 | P108: 39.68 | Q108: 39.73 | R108: 40.03 | S108: 40.24 | T108: 40.3 | U108: 40.07 | V108: 40.55 | W108: 40.43 | X108: 40.49 | Y108: 40.02 | Z108: 40.2 | AA108: 40.3 | AB108: 40.57 | AC108: 41 | AD108: 41.01 | AE108: 40.69 | AF108: 39.99 | AG108: 40.29 | AH108: 40.48 | AI108: 40.25 | AJ108: 40 | AK108: 40.02 | AL108: 40.18 | AM108: 40.48 | AN108: 40.43 | AO108: 40.66 | AP108: 40.87 | AQ108: 40.95 | AR108: 40.48
A109: Bank of India Mid Cap Fund | B109: Bank of India | C109: MID CAP | D109: 8.89 | E109: 8.88 | F109: 9.08 | G109: 9.05 | H109: 9.18 | I109: 9.16 | J109: 9.46 | K109: 9.49 | L109: 9.62 | M109: 9.58 | N109: 9.77 | O109: 9.86 | P109: 9.98 | Q109: 9.98 | R109: 10.04 | S109: 10.06 | T109: 10.06 | U109: 9.98 | V109: 10.07 | W109: 10.08 | X109: 10.1 | Y109: 9.99 | Z109: 10.01 | AA109: 10.05 | AB109: 10.14 | AC109: 10.27 | AD109: 10.27 | AE109: 10.18 | AF109: 10.01 | AG109: 10.11 | AH109: 10.19 | AI109: 10.16 | AJ109: 10.08 | AK109: 10.12 | AL109: 10.18 | AM109: 10.23 | AN109: 10.2 | AO109: 10.24 | AP109: 10.29 | AQ109: 10.25 | AR109: 10.1
A110: Bank of India Multi Asset Allocation Fund | B110: Bank of India | C110: MULTI ASSET ALLOCATION | D110: 11.7429 | E110: 11.7434 | G110: 11.8187 | H110: 11.9138 | I110: 11.9276 | J110: 12.1442 | K110: 12.1402 | L110: 12.2121 | M110: 12.2077 | N110: 12.328 | O110: 12.3654 | P110: 12.4112 | Q110: 12.4257 | R110: 12.4518 | S110: 12.4344 | T110: 12.4042 | U110: 12.3554 | V110: 12.4091 | W110: 12.3755 | X110: 12.3992 | Y110: 12.378 | Z110: 12.3848 | AA110: 12.4178 | AB110: 12.5056 | AC110: 12.5488 | AD110: 12.5419 | AE110: 12.4381 | AF110: 12.3515 | AG110: 12.447 | AH110: 12.4643 | AI110: 12.4084 | AJ110: 12.3521 | AK110: 12.3765 | AL110: 12.3754 | AM110: 12.4056 | AN110: 12.4044 | AO110: 12.4645 | AP110: 12.4509 | AQ110: 12.4517 | AR110: 12.4053
A111: Bank of India Multicap Fund | B111: Bank of India | C111: MULTI CAP | D111: 16.68 | E111: 16.68 | F111: 17.01 | G111: 17.05 | H111: 17.25 | I111: 17.3 | J111: 17.85 | K111: 17.82 | L111: 17.99 | M111: 17.91 | N111: 18.26 | O111: 18.38 | P111: 18.58 | Q111: 18.49 | R111: 18.61 | S111: 18.59 | T111: 18.59 | U111: 18.45 | V111: 18.68 | W111: 18.66 | X111: 18.76 | Y111: 18.67 | Z111: 18.83 | AA111: 18.86 | AB111: 19.03 | AC111: 19.16 | AD111: 19.08 | AE111: 18.84 | AF111: 18.48 | AG111: 18.58 | AH111: 18.7 | AI111: 18.68 | AJ111: 18.6 | AK111: 18.67 | AL111: 18.71 | AM111: 18.82 | AN111: 18.82 | AO111: 18.95 | AP111: 18.96 | AQ111: 18.91 | AR111: 18.78
A112: Bank of India Small Cap Fund | B112: Bank of India | C112: SMALL CAP | D112: 40.39 | E112: 40.39 | F112: 41.75 | G112: 41.81 | H112: 42.45 | I112: 42.6 | J112: 44.13 | K112: 44.29 | L112: 45.16 | M112: 45.09 | N112: 46.19 | O112: 46.87 | P112: 47.53 | Q112: 47.65 | R112: 47.87 | S112: 48.22 | T112: 48.27 | U112: 48.1 | V112: 49.13 | W112: 48.9 | X112: 48.96 | Y112: 48.69 | Z112: 49.17 | AA112: 49.4 | AB112: 49.8 | AC112: 50.61 | AD112: 50.8 | AE112: 50.33 | AF112: 49.16 | AG112: 49.43 | AH112: 49.29 | AI112: 49.11 | AJ112: 48.61 | AK112: 48.87 | AL112: 49.11 | AM112: 49.73 | AN112: 49.67 | AO112: 50.11 | AP112: 50.66 | AQ112: 51.05 | AR112: 51.23
A113: Baroda BNP Paribas Aggressive Hybrid Fund | B113: Baroda BNP Paribas | C113: AGGRESSIVE HYBRID | D113: 25.6866 | E113: 25.6866 | F113: 26.0343 | G113: 26.061 | H113: 26.2094 | I113: 26.3081 | J113: 27.0228 | K113: 26.9806 | L113: 27.257 | M113: 27.1183 | N113: 27.4566 | O113: 27.5317 | P113: 27.6836 | Q113: 27.7018 | R113: 27.8314 | S113: 27.7418 | T113: 27.6524 | U113: 27.4454 | V113: 27.6854 | W113: 27.6994 | X113: 27.8022 | Y113: 27.7116 | Z113: 27.8017 | AA113: 27.7859 | AB113: 27.9936 | AC113: 28.1382 | AD113: 28.025 | AE113: 27.6978 | AF113: 27.2887 | AG113: 27.2803 | AH113: 27.4978 | AI113: 27.4468 | AJ113: 27.4263 | AK113: 27.4618 | AL113: 27.5376 | AM113: 27.504 | AN113: 27.5223 | AO113: 27.7488 | AP113: 27.7114 | AQ113: 27.7578 | AR113: 27.5638
A114: Baroda BNP Paribas Arbitrage Fund | B114: Baroda BNP Paribas | C114: ARBITRAGE | D114: 16.7371 | E114: 16.7375 | F114: 16.7301 | G114: 16.7407 | H114: 16.7359 | I114: 16.7474 | J114: 16.7449 | K114: 16.7458 | L114: 16.7606 | M114: 16.7716 | N114: 16.775 | O114: 16.7787 | P114: 16.7821 | Q114: 16.8046 | R114: 16.7926 | S114: 16.8006 | T114: 16.7963 | U114: 16.7921 | V114: 16.7889 | W114: 16.7937 | X114: 16.805 | Y114: 16.7944 | Z114: 16.797 | AA114: 16.8031 | AB114: 16.7867 | AC114: 16.807 | AD114: 16.8192 | AE114: 16.8209 | AF114: 16.8175 | AG114: 16.8226 | AH114: 16.8243 | AI114: 16.8443 | AJ114: 16.847 | AK114: 16.8508 | AL114: 16.8365 | AM114: 16.8453 | AN114: 16.8297 | AO114: 16.8359 | AP114: 16.841 | AQ114: 16.8358 | AR114: 16.801
A115: Baroda BNP Paribas Balanced Advantage Fund | B115: Baroda BNP Paribas | C115: DYNAMIC ASSET ALLOCATION OR BALANCED ADVANTAGE | D115: 22.9686 | E115: 22.9683 | F115: 23.2621 | G115: 23.174 | H115: 23.3361 | I115: 23.4198 | J115: 24.1325 | K115: 24.1112 | L115: 24.3888 | M115: 24.2866 | N115: 24.6408 | O115: 24.7075 | P115: 24.9233 | Q115: 24.9582 | R115: 25.0929 | S115: 25.0553 | T115: 24.951 | U115: 24.7412 | V115: 24.9833 | W115: 24.943 | X115: 25.0608 | Y115: 24.94 | Z115: 25.1149 | AA115: 25.1328 | AB115: 25.418 | AC115: 25.6192 | AD115: 25.5739 | AE115: 25.3372 | AF115: 24.9002 | AG115: 24.9337 | AH115: 25.1709 | AI115: 25.1291 | AJ115: 25.0617 | AK115: 25.1295 | AL115: 25.2239 | AM115: 25.2146 | AN115: 25.2054 | AO115: 25.4641 | AP115: 25.4605 | AQ115: 25.5784 | AR115: 25.3319
A116: Baroda BNP Paribas Banking and Financial Services Fund | B116: Baroda BNP Paribas | C116: SECTORAL / THEMATIC | D116: 42.8391 | E116: 42.8367 | F116: 43.8275 | G116: 43.7934 | H116: 44.7264 | I116: 44.7614 | J116: 47.1794 | K116: 46.6594 | L116: 47.6286 | M116: 47.3471 | N116: 47.9483 | O116: 47.8356 | P116: 48.1603 | Q116: 48.1553 | R116: 48.7545 | S116: 48.4686 | T116: 47.6947 | U116: 47.4445 | V116: 47.5847 | W116: 47.1313 | X116: 47.3271 | Y116: 46.972 | Z116: 47.1998 | AA116: 47.0222 | AB116: 48.1001 | AC116: 48.3853 | AD116: 47.8223 | AE116: 47.1796 | AF116: 46.269 | AG116: 46.2557 | AH116: 46.8091 | AI116: 46.6766 | AJ116: 46.3893 | AK116: 46.4276 | AL116: 46.4967 | AM116: 46.4009 | AN116: 46.7435 | AO116: 47.7196 | AP116: 47.5957 | AQ116: 47.3652 | AR116: 46.7637
A117: Baroda BNP Paribas Business Conglomerates Fund | B117: Baroda BNP Paribas | C117: SECTORAL / THEMATIC | D117: 8.9074 | E117: 8.9069 | F117: 9.0815 | G117: 9.0694 | H117: 9.163 | I117: 9.1983 | J117: 9.5739 | K117: 9.5199 | L117: 9.6515 | M117: 9.5595 | N117: 9.7424 | O117: 9.7898 | P117: 9.8299 | Q117: 9.8445 | R117: 9.8797 | S117: 9.8232 | T117: 9.7466 | U117: 9.6567 | V117: 9.8081 | W117: 9.7893 | X117: 9.8631 | Y117: 9.7951 | Z117: 9.8618 | AA117: 9.8806 | AB117: 9.9975 | AC117: 10.0077 | AD117: 9.9911 | AE117: 9.8338 | AF117: 9.6172 | AG117: 9.6292 | AH117: 9.7264 | AI117: 9.6782 | AJ117: 9.6426 | AK117: 9.6735 | AL117: 9.7116 | AM117: 9.6848 | AN117: 9.7051 | AO117: 9.8412 | AP117: 9.8284 | AQ117: 9.8452 | AR117: 9.722
A118: Baroda BNP Paribas Business Cycle Fund | B118: Baroda BNP Paribas | C118: SECTORAL / THEMATIC | D118: 14.0961 | E118: 14.0954 | F118: 14.3342 | G118: 14.3376 | H118: 14.4356 | I118: 14.5166 | J118: 15.0315 | K118: 15.0135 | L118: 15.2249 | M118: 15.1203 | N118: 15.3691 | O118: 15.4349 | P118: 15.5573 | Q118: 15.5731 | R118: 15.6831 | S118: 15.6343 | T118: 15.5915 | U118: 15.4515 | V118: 15.6459 | W118: 15.6093 | X118: 15.6736 | Y118: 15.609 | Z118: 15.7187 | AA118: 15.706 | AB118: 15.8607 | AC118: 15.9648 | AD118: 15.8968 | AE118: 15.6755 | AF118: 15.3626 | AG118: 15.3406 | AH118: 15.4644 | AI118: 15.4259 | AJ118: 15.4201 | AK118: 15.4496 | AL118: 15.5369 | AM118: 15.5473 | AN118: 15.5453 | AO118: 15.7277 | AP118: 15.6778 | AQ118: 15.7139 | AR118: 15.5733
A119: Baroda BNP Paribas Conservative Hybrid Fund | B119: Baroda BNP Paribas | C119: CONSERVATIVE HYRBID | D119: 44.241 | E119: 44.2455 | G119: 44.3473 | H119: 44.5143 | I119: 44.5652 | J119: 45.1336 | K119: 45.104 | L119: 45.3134 | M119: 45.2232 | N119: 45.4602 | O119: 45.518 | P119: 45.5976 | Q119: 45.6116 | R119: 45.7081 | S119: 45.664 | T119: 45.5854 | U119: 45.4705 | V119: 45.599 | W119: 45.5626 | X119: 45.5896 | Y119: 45.5277 | Z119: 45.6742 | AA119: 45.6653 | AB119: 45.871 | AC119: 45.9857 | AD119: 45.9216 | AE119: 45.7424 | AF119: 45.5207 | AG119: 45.5057 | AH119: 45.5726 | AI119: 45.5301 | AJ119: 45.4234 | AK119: 45.4773 | AL119: 45.5036 | AM119: 45.4422 | AN119: 45.479 | AO119: 45.6617 | AP119: 45.6667 | AQ119: 45.7257 | AR119: 45.6649
A120: Baroda BNP Paribas Dividend Yield Fund | B120: Baroda BNP Paribas | C120: DIVIDEND YIELD | D120: 8.7427 | E120: 8.7422 | F120: 8.8539 | G120: 8.8447 | H120: 8.8984 | I120: 8.9441 | J120: 9.1837 | K120: 9.1738 | L120: 9.2863 | M120: 9.2286 | N120: 9.3834 | O120: 9.4094 | P120: 9.4941 | Q120: 9.4922 | R120: 9.5359 | S120: 9.4831 | T120: 9.4379 | U120: 9.3537 | V120: 9.4739 | W120: 9.4849 | X120: 9.561 | Y120: 9.4926 | Z120: 9.5475 | AA120: 9.5529 | AB120: 9.6118 | AC120: 9.6512 | AD120: 9.5801 | AE120: 9.4831 | AF120: 9.3342 | AG120: 9.3591 | AH120: 9.4293 | AI120: 9.3984 | AJ120: 9.3914 | AK120: 9.4013 | AL120: 9.4405 | AM120: 9.432 | AN120: 9.4362 | AO120: 9.5203 | AP120: 9.5033 | AQ120: 9.5137 | AR120: 9.394
A121: Baroda BNP Paribas ELSS Tax Saver Fund | B121: Baroda BNP Paribas | C121: ELSS | D121: 87.2894 | E121: 87.2851 | F121: 88.8006 | G121: 88.8533 | H121: 89.7334 | I121: 90.0752 | J121: 93.6031 | K121: 93.2618 | L121: 94.6922 | M121: 93.881 | N121: 95.3474 | O121: 95.7411 | P121: 96.517 | Q121: 96.6637 | R121: 97.2675 | S121: 96.8524 | T121: 96.2632 | U121: 95.4729 | V121: 96.2395 | W121: 96.0625 | X121: 96.5386 | Y121: 96.0919 | Z121: 96.8778 | AA121: 96.9532 | AB121: 98.0011 | AC121: 98.7842 | AD121: 98.2461 | AE121: 96.5388 | AF121: 94.4987 | AG121: 94.4164 | AH121: 95.2506 | AI121: 94.8879 | AJ121: 94.4605 | AK121: 94.7615 | AL121: 95.2959 | AM121: 95.2158 | AN121: 95.3817 | AO121: 96.7636 | AP121: 96.6616 | AQ121: 96.9902 | AR121: 95.9696
A122: Baroda BNP Paribas ESG Best-in-Class Strategy Fund | B122: Baroda BNP Paribas | C122: SECTORAL / THEMATIC | D122: 9.7998 | E122: 9.8005 | F122: 9.8887 | G122: 9.9141 | H122: 9.9644 | I122: 10.0093 | J122: 10.193 | K122: 10.1921 | L122: 10.2641 | M122: 10.2182 | N122: 10.3294 | O122: 10.3413 | P122: 10.407 | Q122: 10.414 | R122: 10.4743 | S122: 10.4091 | T122: 10.3235 | U122: 10.1905 | V122: 10.2791 | W122: 10.2351 | X122: 10.2849 | Y122: 10.2294 | Z122: 10.2559 | AA122: 10.261 | AB122: 10.3833 | AC122: 10.4216 | AD122: 10.3825 | AE122: 10.2254 | AF122: 10.039 | AG122: 10.0189 | AH122: 10.1214 | AI122: 10.1258 | AJ122: 10.1236 | AK122: 10.175 | AL122: 10.1902 | AM122: 10.1744 | AN122: 10.201 | AO122: 10.3007 | AP122: 10.2836 | AQ122: 10.3167 | AR122: 10.2077
A123: Baroda BNP Paribas Energy Opportunities Fund | B123: Baroda BNP Paribas | C123: SECTORAL / THEMATIC | D123: 11.0973 | E123: 11.0967 | F123: 11.2409 | G123: 11.217 | H123: 11.2074 | I123: 11.2516 | J123: 11.4153 | K123: 11.5045 | L123: 11.582 | M123: 11.5706 | N123: 11.7581 | O123: 11.8178 | P123: 11.9849 | Q123: 12.0483 | R123: 12.0595 | S123: 12.1835 | T123: 12.2027 | U123: 12.1771 | V123: 12.3422 | W123: 12.4739 | X123: 12.4833 | Y123: 12.4673 | Z123: 12.5104 | AA123: 12.4905 | AB123: 12.4366 | AC123: 12.5126 | AD123: 12.421 | AE123: 12.2526 | AF123: 12.1207 | AG123: 12.1764 | AH123: 12.3086 | AI123: 12.2096 | AJ123: 12.113 | AK123: 12.1445 | AL123: 12.3071 | AM123: 12.309 | AN123: 12.2544 | AO123: 12.309 | AP123: 12.3221 | AQ123: 12.5099 | AR123: 12.3184
A124: Baroda BNP Paribas Equity Savings Fund | B124: Baroda BNP Paribas | C124: EQUITY SAVINGS | D124: 16.2679 | E124: 16.2679 | F124: 16.3708 | G124: 16.3639 | H124: 16.4173 | I124: 16.4554 | J124: 16.7164 | K124: 16.7071 | L124: 16.802 | M124: 16.78 | N124: 16.9122 | O124: 16.9342 | P124: 16.9827 | Q124: 16.9991 | R124: 17.0493 | S124: 17.0232 | T124: 16.9881 | U124: 16.9108 | V124: 17.0075 | W124: 17.0147 | X124: 17.0393 | Y124: 16.9953 | Z124: 17.0623 | AA124: 17.0623 | AB124: 17.1628 | AC124: 17.2345 | AD124: 17.2087 | AE124: 17.0991 | AF124: 16.9502 | AG124: 16.9104 | AH124: 16.9708 | AI124: 16.9424 | AJ124: 16.9056 | AK124: 16.949 | AL124: 16.9729 | AM124: 16.9503 | AN124: 16.9487 | AO124: 17.057 | AP124: 17.0602 | AQ124: 17.0733 | AR124: 17.0058
A125: Baroda BNP Paribas Flexi Cap Fund | B125: Baroda BNP Paribas | C125: FLEXI CAP | D125: 13.8073 | E125: 13.8066 | F125: 14.0541 | G125: 14.0393 | H125: 14.1492 | I125: 14.2046 | J125: 14.7371 | K125: 14.7001 | L125: 14.9134 | M125: 14.8151 | N125: 15.0596 | O125: 15.122 | P125: 15.2451 | Q125: 15.2604 | R125: 15.3568 | S125: 15.3454 | T125: 15.2732 | U125: 15.1301 | V125: 15.2861 | W125: 15.2631 | X125: 15.3065 | Y125: 15.2313 | Z125: 15.3666 | AA125: 15.379 | AB125: 15.5652 | AC125: 15.7132 | AD125: 15.6785 | AE125: 15.4762 | AF125: 15.1568 | AG125: 15.1519 | AH125: 15.3252 | AI125: 15.2756 | AJ125: 15.2818 | AK125: 15.3393 | AL125: 15.4325 | AM125: 15.4095 | AN125: 15.4017 | AO125: 15.568 | AP125: 15.586 | AQ125: 15.6885 | AR125: 15.52
A126: Baroda BNP Paribas Focused Fund | B126: Baroda BNP Paribas | C126: FOCUSED | D126: 18.8845 | E126: 18.8835 | F126: 19.1224 | G126: 19.1022 | H126: 19.3695 | I126: 19.4879 | J126: 20.1421 | K126: 20.1087 | L126: 20.2859 | M126: 20.2354 | N126: 20.5795 | O126: 20.6354 | P126: 20.7799 | Q126: 20.7917 | R126: 20.9042 | S126: 20.7271 | T126: 20.5993 | U126: 20.4013 | V126: 20.6415 | W126: 20.6617 | X126: 20.8409 | Y126: 20.7711 | Z126: 20.7789 | AA126: 20.7182 | AB126: 21.0097 | AC126: 21.0964 | AD126: 21.0674 | AE126: 20.8391 | AF126: 20.4239 | AG126: 20.4496 | AH126: 20.6787 | AI126: 20.6884 | AJ126: 20.6986 | AK126: 20.761 | AL126: 20.7694 | AM126: 20.7131 | AN126: 20.6641 | AO126: 20.9594 | AP126: 20.9053 | AQ126: 20.8948 | AR126: 20.5758
A127: Baroda BNP Paribas Health and Wellness Fund | B127: Baroda BNP Paribas | C127: SECTORAL / THEMATIC | D127: 9.1041 | E127: 9.1037 | F127: 9.0642 | G127: 8.9599 | H127: 8.9948 | I127: 9.0336 | J127: 9.1244 | K127: 9.1775 | L127: 9.2309 | M127: 9.2322 | N127: 9.3458 | O127: 9.3252 | P127: 9.3677 | Q127: 9.3308 | R127: 9.3069 | S127: 9.3037 | T127: 9.3743 | U127: 9.2723 | V127: 9.4592 | W127: 9.4238 | X127: 9.4723 | Y127: 9.4451 | Z127: 9.6333 | AA127: 9.6298 | AB127: 9.7904 | AC127: 9.8373 | AD127: 9.8663 | AE127: 9.9429 | AF127: 9.7535 | AG127: 9.7547 | AH127: 9.9143 | AI127: 9.9546 | AJ127: 9.9876 | AK127: 10.0769 | AL127: 10.0444 | AM127: 10.0911 | AN127: 10.0176 | AO127: 10.059 | AP127: 10.0267 | AQ127: 10.0165 | AR127: 9.8556
A128: Baroda BNP Paribas India Consumption Fund | B128: Baroda BNP Paribas | C128: SECTORAL / THEMATIC | D128: 27.1086 | E128: 27.1074 | F128: 27.5838 | G128: 27.5942 | H128: 27.9591 | I128: 27.9836 | J128: 28.9057 | K128: 28.8066 | L128: 29.2617 | M128: 28.8623 | N128: 29.279 | O128: 29.2323 | P128: 29.5803 | Q128: 29.6163 | R128: 29.9735 | S128: 29.9361 | T128: 29.6527 | U128: 29.4413 | V128: 29.6757 | W128: 29.5424 | X128: 29.8668 | Y128: 29.551 | Z128: 29.603 | AA128: 29.6619 | AB128: 29.9474 | AC128: 29.938 | AD128: 29.975 | AE128: 29.5068 | AF128: 29.0136 | AG128: 29.0187 | AH128: 29.2679 | AI128: 29.3195 | AJ128: 29.1256 | AK128: 29.0879 | AL128: 29.078 | AM128: 29.0467 | AN128: 29.0574 | AO128: 29.293 | AP128: 29.23 | AQ128: 29.3408 | AR128: 28.9848
A129: Baroda BNP Paribas Innovation Fund | B129: Baroda BNP Paribas | C129: SECTORAL / THEMATIC | D129: 11.3733 | E129: 11.3727 | F129: 11.5759 | G129: 11.5726 | H129: 11.6719 | I129: 11.6655 | J129: 12.1202 | K129: 12.1288 | L129: 12.3551 | M129: 12.2807 | N129: 12.4565 | O129: 12.5478 | P129: 12.6336 | Q129: 12.6551 | R129: 12.706 | S129: 12.6796 | T129: 12.6575 | U129: 12.5811 | V129: 12.6994 | W129: 12.7102 | X129: 12.7545 | Y129: 12.6917 | Z129: 12.7885 | AA129: 12.8064 | AB129: 12.9576 | AC129: 13.1219 | AD129: 13.0627 | AE129: 12.9136 | AF129: 12.6228 | AG129: 12.5855 | AH129: 12.7118 | AI129: 12.6953 | AJ129: 12.606 | AK129: 12.733 | AL129: 12.7928 | AM129: 12.7979 | AN129: 12.757 | AO129: 12.8555 | AP129: 12.8951 | AQ129: 12.9446 | AR129: 12.8152
A130: Baroda BNP Paribas Large Cap Fund | B130: Baroda BNP Paribas | C130: LARGE CAP | D130: 198.5936 | E130: 198.5843 | F130: 201.4161 | G130: 201.5493 | H130: 203.2088 | I130: 204.4642 | J130: 211.2679 | K130: 210.8971 | L130: 213.5437 | M130: 212.0539 | N130: 215.578 | O130: 216.0126 | P130: 217.711 | Q130: 217.9988 | R130: 219.6571 | S130: 218.8094 | T130: 217.5495 | U130: 215.4306 | V130: 217.8893 | W130: 217.703 | X130: 219.2393 | Y130: 218.1107 | Z130: 219.0153 | AA130: 218.5778 | AB130: 220.4581 | AC130: 221.0244 | AD130: 219.5526 | AE130: 216.3636 | AF130: 212.6632 | AG130: 212.7338 | AH130: 215.0401 | AI130: 214.5368 | AJ130: 214.7366 | AK130: 215.0557 | AL130: 215.8383 | AM130: 215.4749 | AN130: 215.7421 | AO130: 218.303 | AP130: 217.8117 | AQ130: 218.347 | AR130: 215.7633
A131: Baroda BNP Paribas Large and Mid Cap Fund | B131: Baroda BNP Paribas | C131: LARGE & MID CAP | D131: 23.9316 | E131: 23.9305 | F131: 24.3416 | G131: 24.2485 | H131: 24.4852 | I131: 24.549 | J131: 25.5295 | K131: 25.464 | L131: 25.8447 | M131: 25.6986 | N131: 26.1391 | O131: 26.2443 | P131: 26.4909 | Q131: 26.5609 | R131: 26.6829 | S131: 26.6018 | T131: 26.3841 | U131: 26.1039 | V131: 26.4383 | W131: 26.3691 | X131: 26.4492 | Y131: 26.2893 | Z131: 26.5148 | AA131: 26.4944 | AB131: 26.9385 | AC131: 27.1825 | AD131: 27.0859 | AE131: 26.7207 | AF131: 26.1117 | AG131: 26.14 | AH131: 26.4503 | AI131: 26.4143 | AJ131: 26.3829 | AK131: 26.5321 | AL131: 26.6297 | AM131: 26.6096 | AN131: 26.6323 | AO131: 26.9566 | AP131: 26.9258 | AQ131: 27.0173 | AR131: 26.6556
... A139: Canara Robeco Banking and Financial Services Fund | B139: Canara Robeco | C139: SECTORAL / THEMATIC | D139: 9.78 | E139: 9.78 | F139: 9.88 | G139: 9.88 | H139: 10.02 | I139: 10.03 | J139: 10.38 | K139: 10.31 | L139: 10.48 | M139: 10.43 | N139: 10.53 | O139: 10.53 | P139: 10.61 | Q139: 10.61 | R139: 10.73 | S139: 10.67 | T139: 10.57 | U139: 10.52 | V139: 10.5 | W139: 10.44 | X139: 10.47 | Y139: 10.39 | Z139: 10.45 | AA139: 10.45 | AB139: 10.67 | AC139: 10.74 | AD139: 10.59 | AE139: 10.44 | AF139: 10.24 | AG139: 10.22 | AH139: 10.37 | AI139: 10.35 | AJ139: 10.29 | AK139: 10.3 | AL139: 10.33 | AM139: 10.29 | AN139: 10.34 | AO139: 10.54 | AP139: 10.52 | AQ139: 10.45 | AR139: 10.31
A140: Canara Robeco Conservative Hybrid Fund | B140: Canara Robeco | C140: CONSERVATIVE HYRBID | D140: 94.2787 | E140: 94.2884 | G140: 94.734 | H140: 95.129 | I140: 95.2205 | J140: 96.1828 | K140: 96.0358 | L140: 96.4308 | M140: 96.308 | N140: 96.8603 | O140: 96.8978 | P140: 97.1136 | Q140: 97.1407 | R140: 97.4806 | S140: 97.4489 | T140: 97.1956 | U140: 96.9381 | V140: 97.1855 | W140: 96.9996 | X140: 97.0358 | Y140: 96.7605 | Z140: 97.0421 | AA140: 97.0324 | AB140: 97.5393 | AC140: 97.6249 | AD140: 97.4307 | AE140: 97.0884 | AF140: 96.4055 | AG140: 96.3665 | AH140: 96.6362 | AI140: 96.5972 | AJ140: 96.5003 | AK140: 96.6406 | AL140: 96.5649 | AM140: 96.4766 | AN140: 96.5685 | AO140: 96.9279 | AP140: 96.8181 | AQ140: 96.8743 | AR140: 96.5753
A141: Canara Robeco Consumption Fund | B141: Canara Robeco | C141: SECTORAL / THEMATIC | D141: 92.5 | E141: 92.5 | F141: 94.48 | G141: 94.37 | H141: 95.98 | I141: 95.92 | J141: 100.4 | K141: 99.53 | L141: 101.23 | M141: 100.14 | N141: 102.07 | O141: 102.22 | P141: 103.43 | Q141: 103.45 | R141: 104.89 | S141: 104.8 | T141: 103.46 | U141: 102.81 | V141: 103.74 | W141: 103.38 | X141: 103.74 | Y141: 102.83 | Z141: 103.34 | AA141: 103.2 | AB141: 105.03 | AC141: 105.3 | AD141: 105.03 | AE141: 102.85 | AF141: 100.54 | AG141: 100.56 | AH141: 102.04 | AI141: 102.12 | AJ141: 101.87 | AK141: 102.38 | AL141: 102.19 | AM141: 102.15 | AN141: 102.5 | AO141: 103.38 | AP141: 103.26 | AQ141: 103.54 | AR141: 101.93
A142: Canara Robeco ELSS Tax Saver Fund | B142: Canara Robeco | C142: ELSS | D142: 157.68 | E142: 157.67 | F142: 160.67 | G142: 160.82 | H142: 162.73 | I142: 163.38 | J142: 169.65 | K142: 168.53 | L142: 170.93 | M142: 169.76 | N142: 172.67 | O142: 173.06 | P142: 174.37 | Q142: 174.61 | R142: 176.48 | S142: 176.04 | T142: 174.71 | U142: 173.08 | V142: 174.75 | W142: 173.81 | X142: 174.35 | Y142: 172.93 | Z142: 174.1 | AA142: 173.86 | AB142: 176.35 | AC142: 177.26 | AD142: 176.12 | AE142: 173.45 | AF142: 169.82 | AG142: 169.95 | AH142: 171.61 | AI142: 171.38 | AJ142: 170.91 | AK142: 171.44 | AL142: 171.88 | AM142: 172.41 | AN142: 172.87 | AO142: 174.6 | AP142: 174.14 | AQ142: 174.73 | AR142: 172.52
A143: Canara Robeco Equity Hybrid Fund | B143: Canara Robeco | C143: AGGRESSIVE HYBRID | D143: 332.83 | E143: 332.84 | F143: 337.88 | G143: 337.89 | H143: 341.15 | I143: 341.99 | J143: 352.52 | K143: 351.12 | L143: 354.85 | M143: 352.81 | N143: 357.82 | O143: 358.9 | P143: 361.31 | Q143: 361.7 | R143: 364.03 | S143: 363.42 | T143: 361.05 | U143: 358.41 | V143: 361.19 | W143: 359.91 | X143: 360.5 | Y143: 357.89 | Z143: 359.47 | AA143: 358.98 | AB143: 363.33 | AC143: 364.52 | AD143: 363.06 | AE143: 358.59 | AF143: 352.51 | AG143: 352.58 | AH143: 355.55 | AI143: 354.99 | AJ143: 353.92 | AK143: 355 | AL143: 355.27 | AM143: 355.84 | AN143: 356.48 | AO143: 359.58 | AP143: 358.85 | AQ143: 359.55 | AR143: 355.97
A144: Canara Robeco Flexi Cap Fund | B144: Canara Robeco | C144: FLEXI CAP | D144: 301.29 | E144: 301.28 | F144: 307.03 | G144: 307.4 | H144: 311.4 | I144: 312.5 | J144: 324.8 | K144: 322.34 | L144: 326.86 | M144: 324.13 | N144: 330.27 | O144: 331.26 | P144: 333.79 | Q144: 334.46 | R144: 337.06 | S144: 335.63 | T144: 332.72 | U144: 329.27 | V144: 332.24 | W144: 331.05 | X144: 332.54 | Y144: 329.62 | Z144: 331.38 | AA144: 331.14 | AB144: 335.92 | AC144: 337.16 | AD144: 335.68 | AE144: 331.54 | AF144: 324.44 | AG144: 324.56 | AH144: 328.34 | AI144: 328.11 | AJ144: 327.75 | AK144: 328.5 | AL144: 329.32 | AM144: 329.63 | AN144: 330.4 | AO144: 333.52 | AP144: 332.35 | AQ144: 333.04 | AR144: 328.34
A145: Canara Robeco Focused Fund | B145: Canara Robeco | C145: FOCUSED | D145: 17.58 | E145: 17.58 | F145: 17.89 | G145: 17.87 | H145: 18.13 | I145: 18.17 | J145: 18.89 | K145: 18.71 | L145: 19.02 | M145: 18.89 | N145: 19.21 | O145: 19.28 | P145: 19.38 | Q145: 19.45 | R145: 19.63 | S145: 19.49 | T145: 19.3 | U145: 19.11 | V145: 19.25 | W145: 19.15 | X145: 19.23 | Y145: 19.03 | Z145: 19.13 | AA145: 19.08 | AB145: 19.37 | AC145: 19.41 | AD145: 19.25 | AE145: 18.97 | AF145: 18.59 | AG145: 18.6 | AH145: 18.81 | AI145: 18.75 | AJ145: 18.73 | AK145: 18.79 | AL145: 18.84 | AM145: 18.87 | AN145: 18.92 | AO145: 19.1 | AP145: 19 | AQ145: 19 | AR145: 18.72
A146: Canara Robeco Infrastructure Fund | B146: Canara Robeco | C146: SECTORAL / THEMATIC | D146: 151.49 | E146: 151.48 | F146: 154.96 | G146: 155.03 | H146: 156.4 | I146: 156.5 | J146: 161.37 | K146: 161.78 | L146: 164.05 | M146: 163.44 | N146: 167.11 | O146: 167.98 | P146: 169.97 | Q146: 170.7 | R146: 171.23 | S146: 172.11 | T146: 171.96 | U146: 170.96 | V146: 173.1 | W146: 173.2 | X146: 172.96 | Y146: 171.12 | Z146: 171.98 | AA146: 172.01 | AB146: 172.71 | AC146: 173.72 | AD146: 172.54 | AE146: 169.45 | AF146: 165.84 | AG146: 166.96 | AH146: 168.51 | AI146: 167.76 | AJ146: 166.51 | AK146: 166.97 | AL146: 168.25 | AM146: 169.22 | AN146: 169.06 | AO146: 170.22 | AP146: 170.33 | AQ146: 172.78 | AR146: 170.46
A147: Canara Robeco Large Cap Fund | B147: Canara Robeco | C147: LARGE CAP | D147: 55.62 | E147: 55.61 | F147: 56.54 | G147: 56.58 | H147: 57.31 | I147: 57.63 | J147: 59.87 | K147: 59.3 | L147: 60.09 | M147: 59.6 | N147: 60.6 | O147: 60.66 | P147: 61.06 | Q147: 61.13 | R147: 61.71 | S147: 61.32 | T147: 60.71 | U147: 60.1 | V147: 60.55 | W147: 60.24 | X147: 60.59 | Y147: 60.09 | Z147: 60.37 | AA147: 60.27 | AB147: 61.1 | AC147: 61.19 | AD147: 60.8 | AE147: 60 | AF147: 58.79 | AG147: 58.83 | AH147: 59.47 | AI147: 59.39 | AJ147: 59.37 | AK147: 59.41 | AL147: 59.47 | AM147: 59.42 | AN147: 59.61 | AO147: 60.32 | AP147: 60.03 | AQ147: 60.11 | AR147: 59.22
A148: Canara Robeco Large and Mid Cap Fund | B148: Canara Robeco | C148: LARGE & MID CAP | D148: 219.39 | E148: 219.38 | F148: 224.51 | G148: 224.56 | H148: 227.83 | I148: 228.24 | J148: 236.57 | K148: 235.57 | L148: 239.22 | M148: 237.77 | N148: 242.19 | O148: 243.78 | P148: 245.67 | Q148: 246.47 | R148: 248.77 | S148: 248.26 | T148: 246.36 | U148: 243.77 | V148: 246.29 | W148: 245.58 | X148: 245.77 | Y148: 243.58 | Z148: 245.02 | AA148: 245.13 | AB148: 248.89 | AC148: 250.24 | AD148: 249.51 | AE148: 246.57 | AF148: 240.3 | AG148: 240.28 | AH148: 242.58 | AI148: 242.51 | AJ148: 242.05 | AK148: 243.52 | AL148: 243.85 | AM148: 243.89 | AN148: 244.23 | AO148: 246.35 | AP148: 245.85 | AQ148: 245.98 | AR148: 241.91
A149: Canara Robeco Manufacturing Fund | B149: Canara Robeco | C149: SECTORAL / THEMATIC | D149: 11.34 | E149: 11.34 | F149: 11.61 | G149: 11.57 | H149: 11.64 | I149: 11.68 | J149: 12.1 | K149: 12.19 | L149: 12.41 | M149: 12.33 | N149: 12.57 | O149: 12.7 | P149: 12.86 | Q149: 12.92 | R149: 12.96 | S149: 13 | T149: 12.94 | U149: 12.84 | V149: 13.04 | W149: 13.03 | X149: 13.08 | Y149: 13.01 | Z149: 13.22 | AA149: 13.26 | AB149: 13.42 | AC149: 13.6 | AD149: 13.54 | AE149: 13.36 | AF149: 13.03 | AG149: 13.1 | AH149: 13.25 | AI149: 13.16 | AJ149: 13.05 | AK149: 13.11 | AL149: 13.18 | AM149: 13.3 | AN149: 13.27 | AO149: 13.35 | AP149: 13.38 | AQ149: 13.56 | AR149: 13.4
A150: Canara Robeco Mid Cap Fund | B150: Canara Robeco | C150: MID CAP | D150: 15.26 | E150: 15.26 | F150: 15.63 | G150: 15.62 | H150: 15.87 | I150: 15.89 | J150: 16.49 | K150: 16.52 | L150: 16.82 | M150: 16.73 | N150: 17.05 | O150: 17.15 | P150: 17.32 | Q150: 17.39 | R150: 17.53 | S150: 17.51 | T150: 17.38 | U150: 17.22 | V150: 17.43 | W150: 17.34 | X150: 17.33 | Y150: 17.17 | Z150: 17.33 | AA150: 17.33 | AB150: 17.68 | AC150: 17.86 | AD150: 17.85 | AE150: 17.64 | AF150: 17.18 | AG150: 17.19 | AH150: 17.34 | AI150: 17.29 | AJ150: 17.25 | AK150: 17.4 | AL150: 17.47 | AM150: 17.53 | AN150: 17.52 | AO150: 17.65 | AP150: 17.67 | AQ150: 17.74 | AR150: 17.54
A151: Canara Robeco Multi Asset Allocation Fund | B151: Canara Robeco | C151: MULTI ASSET ALLOCATION | D151: 10.17 | E151: 10.17 | F151: 10.32 | G151: 10.28 | H151: 10.4 | I151: 10.4 | J151: 10.7 | K151: 10.63 | L151: 10.75 | M151: 10.69 | N151: 10.84 | O151: 10.87 | P151: 10.91 | Q151: 10.92 | R151: 11 | S151: 10.97 | T151: 10.88 | U151: 10.83 | V151: 10.88 | W151: 10.83 | X151: 10.83 | Y151: 10.78 | Z151: 10.83 | AA151: 10.8 | AB151: 10.94 | AC151: 10.99 | AD151: 10.94 | AE151: 10.84 | AF151: 10.71 | AG151: 10.8 | AH151: 10.88 | AI151: 10.83 | AJ151: 10.83 | AK151: 10.86 | AL151: 10.86 | AM151: 10.86 | AN151: 10.87 | AO151: 10.93 | AP151: 10.91 | AQ151: 10.9 | AR151: 10.8
A152: Canara Robeco Multi Cap Fund | B152: Canara Robeco | C152: MULTI CAP | D152: 12.85 | E152: 12.85 | F152: 13.11 | G152: 13.1 | H152: 13.25 | I152: 13.25 | J152: 13.73 | K152: 13.67 | L152: 13.86 | M152: 13.77 | N152: 14.03 | O152: 14.09 | P152: 14.22 | Q152: 14.24 | R152: 14.38 | S152: 14.37 | T152: 14.26 | U152: 14.12 | V152: 14.27 | W152: 14.22 | X152: 14.28 | Y152: 14.16 | Z152: 14.28 | AA152: 14.27 | AB152: 14.49 | AC152: 14.56 | AD152: 14.5 | AE152: 14.34 | AF152: 13.99 | AG152: 13.99 | AH152: 14.12 | AI152: 14.13 | AJ152: 14.09 | AK152: 14.19 | AL152: 14.18 | AM152: 14.2 | AN152: 14.21 | AO152: 14.33 | AP152: 14.31 | AQ152: 14.31 | AR152: 14.11
...

Sheet Daily AUM
A1: Scheme Name | B1: Fund Name | C1: Category | D1: 46111 | E1: 46112 | F1: 46113 | G1: 46114 | H1: 46118 | I1: 46119 | J1: 46120 | K1: 46121 | L1: 46122 | M1: 46125 | N1: 46127 | O1: 46128 | P1: 46129 | Q1: 46132 | R1: 46133 | S1: 46134 | T1: 46135 | U1: 46136 | V1: 46139 | W1: 46140 | X1: 46141 | Y1: 46142 | Z1: 46146 | AA1: 46147 | AB1: 46148 | AC1: 46149 | AD1: 46150 | AE1: 46153 | AF1: 46154 | AG1: 46155 | AH1: 46156 | AI1: 46157 | AJ1: 46160 | AK1: 46161 | AL1: 46162 | AM1: 46163 | AN1: 46164 | AO1: 46167 | AP1: 46168 | AQ1: 46169 | AR1: 46171
A2: 360 ONE Balanced Hybrid Fund | B2: 360 ONE | C2: BALANCED HYBRID | D2: 714.69 | E2: 714.69 | G2: 720.06 | H2: 721.73 | I2: 722.91 | J2: 738.41 | K2: 736.71 | L2: 742.45 | M2: 732.63 | N2: 738.81 | O2: 738.23 | P2: 742.04 | Q2: 741.66 | R2: 743.69 | S2: 741.46 | T2: 738.09 | U2: 734.8 | V2: 738.25 | W2: 737.08 | X2: 739.26 | Y2: 734.47 | Z2: 737.88 | AA2: 738.75 | AB2: 745.19 | AC2: 748.32 | AD2: 746.37 | AE2: 741.47 | AF2: 732.36 | AG2: 732.81 | AH2: 735.95 | AI2: 734.75 | AJ2: 733.17 | AK2: 731.02 | AL2: 728.41 | AM2: 728.09 | AN2: 728.09 | AO2: 734.28 | AP2: 733.79 | AQ2: 734.62 | AR2: 732.07
A3: 360 ONE Flexicap Fund | B3: 360 ONE | C3: FLEXI CAP | D3: 1789.32 | E3: 1789.32 | F3: 1824.56 | G3: 1824.2 | H3: 1848.75 | I3: 1863.89 | J3: 1944.2 | K3: 1936.11 | L3: 1968.69 | M3: 1955.21 | N3: 1991.61 | O3: 1998.38 | P3: 2018.63 | Q3: 2014.95 | R3: 2029.47 | S3: 2021.08 | T3: 2006.88 | U3: 1992.26 | V3: 2006.8 | W3: 2002.69 | X3: 2015.75 | Y3: 1993.89 | Z3: 2008.11 | AA3: 2010.87 | AB3: 2043.85 | AC3: 2060.9 | AD3: 2054.14 | AE3: 2027.87 | AF3: 1980.54 | AG3: 1986.17 | AH3: 2004.1 | AI3: 2006.69 | AJ3: 2000.79 | AK3: 2008.43 | AL3: 2017.98 | AM3: 2014.49 | AN3: 2014.49 | AO3: 2046.94 | AP3: 2044.41 | AQ3: 2058.6 | AR3: 2042.92
A4: 360 ONE Focused Fund | B4: 360 ONE | C4: FOCUSED | D4: 6057.57 | E4: 6057.57 | F4: 6167.75 | G4: 6150.24 | H4: 6216.69 | I4: 6259.36 | J4: 6545.4 | K4: 6494.99 | L4: 6593.64 | M4: 6525.18 | N4: 6612.62 | O4: 6622.69 | P4: 6662.53 | Q4: 6656.14 | R4: 6717 | S4: 6673.4 | T4: 6624.59 | U4: 6577.17 | V4: 6598.66 | W4: 6577.37 | X4: 6607.18 | Y4: 6537.1 | Z4: 6579.4 | AA4: 6561.61 | AB4: 6662.93 | AC4: 6698.44 | AD4: 6684.43 | AE4: 6569.65 | AF4: 6400.81 | AG4: 6423.14 | AH4: 6497.26 | AI4: 6499.61 | AJ4: 6497.76 | AK4: 6507.99 | AL4: 6531.29 | AM4: 6535.6 | AN4: 6535.6 | AO4: 6621.1 | AP4: 6604.19 | AQ4: 6663.06 | AR4: 6584.77
A5: 360 ONE Multi Asset Allocation Fund | B5: 360 ONE | C5: MULTI ASSET ALLOCATION | D5: 387.47 | E5: 387.47 | G5: 389.26 | H5: 394.28 | I5: 396.93 | J5: 405.78 | K5: 404.07 | L5: 409.56 | M5: 409.28 | N5: 413.42 | O5: 414.68 | P5: 416.28 | Q5: 414.02 | R5: 416.81 | S5: 416.81 | T5: 415.91 | U5: 425.3 | V5: 428.87 | W5: 428.8 | X5: 429.53 | Y5: 430.57 | Z5: 432.26 | AA5: 432.72 | AB5: 438 | AC5: 439.58 | AD5: 438.74 | AE5: 436.03 | AF5: 436.51 | AG5: 443.49 | AH5: 446.8 | AI5: 444.84 | AJ5: 445.68 | AK5: 448.67 | AL5: 448.89 | AM5: 449.71 | AN5: 449.71 | AO5: 454.11 | AP5: 453.9 | AQ5: 455.05 | AR5: 454.17
A6: 360 ONE Quant Fund | B6: 360 ONE | C6: SECTORAL / THEMATIC | D6: 806.72 | E6: 806.72 | F6: 817.67 | G6: 812.33 | H6: 823.55 | I6: 829.12 | J6: 870.43 | K6: 868.74 | L6: 886.32 | M6: 874.05 | N6: 891.39 | O6: 892.91 | P6: 900.64 | Q6: 899.22 | R6: 901.79 | S6: 899.27 | T6: 889.32 | U6: 883.36 | V6: 891.47 | W6: 886.55 | X6: 890.59 | Y6: 879.56 | Z6: 887.27 | AA6: 890.69 | AB6: 908.82 | AC6: 915.88 | AD6: 913.58 | AE6: 884.08 | AF6: 864.86 | AG6: 868.35 | AH6: 877.39 | AI6: 873.57 | AJ6: 868.44 | AK6: 863.35 | AL6: 859.24 | AM6: 860.93 | AN6: 860.93 | AO6: 872.87 | AP6: 871.66 | AQ6: 878.29 | AR6: 862.77
A7: Abakkus Flexi Cap Fund | B7: Abakkus | C7: FLEXI CAP | D7: 3124.465 | E7: 3140.6846 | F7: 3205.6282 | G7: 3207.2637 | H7: 3264.424 | I7: 3308.8987 | J7: 3435.146 | K7: 3453.838 | L7: 3539.0803 | M7: 3540.355 | N7: 3618.4153 | O7: 3647.2776 | P7: 3700.2324 | Q7: 3743.2783 | R7: 3800.9927 | S7: 3828.7588 | T7: 3824.6118 | U7: 3808.3 | V7: 3880.358 | W7: 3894.4932 | X7: 3924.9512 | Y7: 3901.185 | Z7: 4179.3433 | AA7: 4178.858 | AB7: 4266.236 | AC7: 4314.709 | AD7: 4310.3765 | AE7: 4271.224 | AF7: 4198.735 | AG7: 4236.5464 | AH7: 4275.798 | AI7: 4314.742 | AJ7: 4311.1035 | AK7: 4350.541 | AL7: 4396.007 | AM7: 4426.394 | AN7: 4426.394 | AO7: 4566.509 | AP7: 4573.8657 | AQ7: 4608.777 | AR7: 4595.9463
A8: Abakkus Small Cap Fund | B8: Abakkus | C8: SMALL CAP | D8: 442.1605 | E8: 453.3766 | F8: 460.7434 | G8: 466.1826 | H8: 481.2368 | I8: 495.7582 | J8: 518.9619 | K8: 535.3229 | L8: 564.1524 | M8: 579.0963 | N8: 606.6468 | O8: 631.4845 | P8: 651.4239 | Q8: 667.4582 | R8: 698.0518 | S8: 716.7818 | T8: 724.6415 | U8: 734.55 | V8: 756.9808 | W8: 768.4932 | X8: 785.2932 | Y8: 816.7575 | Z8: 837.4553 | AA8: 857.3814 | AB8: 877.7815 | AC8: 899.0356 | AD8: 908.7972 | AE8: 910.3614 | AF8: 907.7453 | AG8: 919.9828 | AH8: 938.0538 | AI8: 951.5583 | AJ8: 956.3951 | AK8: 973.1456 | AL8: 988.0453 | AM8: 1005.9785 | AN8: 1005.9785 | AO8: 1039.1243 | AP8: 1051.8866 | AQ8: 1065.6925 | AR8: 1073.7545
A9: Aditya Birla Sun Life Arbitrage Fund | B9: Aditya Birla Sun Life | C9: ARBITRAGE | D9: 24864.025 | E9: 25064.553 | F9: 25049.188 | G9: 25019.309 | H9: 25149.37 | I9: 25144.477 | J9: 25140.443 | K9: 25306.627 | L9: 25507.2 | M9: 25315.344 | N9: 25154.703 | O9: 25195.072 | P9: 25264.504 | Q9: 25330.47 | R9: 25331.506 | S9: 25344.332 | T9: 25278.137 | U9: 25358.955 | V9: 25561.94 | W9: 25531.799 | X9: 25548.604 | Y9: 25678.504 | Z9: 25785.06 | AA9: 25766.172 | AB9: 25621.975 | AC9: 25698.887 | AD9: 25715.129 | AE9: 25727.838 | AF9: 25779.19 | AG9: 25784.854 | AH9: 25774.328 | AI9: 25848.246 | AJ9: 26083.916 | AK9: 26092.64 | AL9: 26175.094 | AM9: 26177.346 | AN9: 26137.12 | AO9: 26176.135 | AP9: 26027.951 | AQ9: 26011.266 | AR9: 26059.46
A10: Aditya Birla Sun Life Balanced Advantage Fund | B10: Aditya Birla Sun Life | C10: DYNAMIC ASSET ALLOCATION OR BALANCED ADVANTAGE | D10: 8532.136 | E10: 8539.877 | F10: 8636.936 | G10: 8627.432 | H10: 8701.606 | I10: 8729.112 | J10: 8948.255 | K10: 8931.775 | L10: 9050.222 | M10: 9024.955 | N10: 9134.521 | O10: 9137.024 | P10: 9227.855 | Q10: 9237.995 | R10: 9291.296 | S10: 9282.333 | T10: 9228.756 | U10: 9146.053 | V10: 9229.636 | W10: 9210.793 | X10: 9219.283 | Y10: 9182.391 | Z10: 9222.99 | AA10: 9219.533 | AB10: 9293.199 | AC10: 9318.613 | AD10: 9298.444 | AE10: 9230.484 | AF10: 9096.755 | AG10: 9128.904 | AH10: 9183.16 | AI10: 9171.015 | AJ10: 9161.602 | AK10: 9192.669 | AL10: 9192.735 | AM10: 9181.828 | AN10: 9209.405 | AO10: 9284.715 | AP10: 9291.7 | AQ10: 9304.154 | AR10: 9250.3125
A11: Aditya Birla Sun Life Banking & Financial Services Fund | B11: Aditya Birla Sun Life | C11: SECTORAL / THEMATIC | D11: 3155.414 | E11: 3154.8567 | F11: 3224.997 | G11: 3228.6257 | H11: 3303.5168 | I11: 3313.4067 | J11: 3504.21 | K11: 3464.643 | L11: 3534.3262 | M11: 3514.6343 | N11: 3562.5688 | O11: 3572.719 | P11: 3604.233 | Q11: 3610.4841 | R11: 3678.9583 | S11: 3664.0698 | T11: 3622.5095 | U11: 3610.0747 | V11: 3600.4421 | W11: 3565.2349 | X11: 3573.1716 | Y11: 3541.0872 | Z11: 3561.4253 | AA11: 3555.613 | AB11: 3631.6838 | AC11: 3641.0613 | AD11: 3597.4587 | AE11: 3544.1648 | AF11: 3460.3357 | AG11: 3454.5916 | AH11: 3489.2483 | AI11: 3475.7927 | AJ11: 3458.772 | AK11: 3458.3687 | AL11: 3457.5464 | AM11: 3448.5334 | AN11: 3475.8389 | AO11: 3544.2056 | AP11: 3532.4963 | AQ11: 3516.9424 | AR11: 3466.1643
A12: Aditya Birla Sun Life Business Cycle Fund | B12: Aditya Birla Sun Life | C12: SECTORAL / THEMATIC | D12: 1541.9215 | E12: 1540.4275 | F12: 1568.7871 | G12: 1567.0724 | H12: 1587.5558 | I12: 1594.287 | J12: 1655.9078 | K12: 1646.936 | L12: 1674.8918 | M12: 1669.3259 | N12: 1696.6942 | O12: 1700.7206 | P12: 1718.3027 | Q12: 1720.6064 | R12: 1736.8901 | S12: 1731.1495 | T12: 1713.8689 | U12: 1693.8441 | V12: 1711.313 | W12: 1699.9368 | X12: 1699.0259 | Y12: 1687.282 | Z12: 1701.9218 | AA12: 1697.0967 | AB12: 1717.0604 | AC12: 1727.6213 | AD12: 1717.2588 | AE12: 1694.997 | AF12: 1655.8811 | AG12: 1656.2449 | AH12: 1669.5868 | AI12: 1658.4622 | AJ12: 1651.3412 | AK12: 1663.7284 | AL12: 1663.502 | AM12: 1667.2407 | AN12: 1668.3589 | AO12: 1688.0278 | AP12: 1689.5236 | AQ12: 1694.9678 | AR12: 1684.1193
A13: Aditya Birla Sun Life Conglomerate Fund | B13: Aditya Birla Sun Life | C13: SECTORAL / THEMATIC | D13: 1438.5851 | E13: 1437.6033 | F13: 1474.5978 | G13: 1475.9995 | H13: 1488.6349 | I13: 1493.7084 | J13: 1556.449 | K13: 1547.7166 | L13: 1572.8307 | M13: 1560.2872 | N13: 1595.6292 | O13: 1608.8251 | P13: 1619.5615 | Q13: 1611.2615 | R13: 1621.7054 | S13: 1624.6483 | T13: 1613.2097 | U13: 1592.4159 | V13: 1618.273 | W13: 1623.577 | X13: 1637.5641 | Y13: 1622.5085 | Z13: 1640.5773 | AA13: 1639.0851 | AB13: 1658.9846 | AC13: 1659.0302 | AD13: 1655.2567 | AE13: 1631.5358 | AF13: 1590.5002 | AG13: 1600.6653 | AH13: 1609.4176 | AI13: 1596.6516 | AJ13: 1591.3606 | AK13: 1596.134 | AL13: 1603.9608 | AM13: 1604.7645 | AN13: 1607.0328 | AO13: 1629.0317 | AP13: 1633.1586 | AQ13: 1642.7664 | AR13: 1625.4442
A14: Aditya Birla Sun Life Consumption Fund | B14: Aditya Birla Sun Life | C14: SECTORAL / THEMATIC | D14: 5480.929 | E14: 5477.9106 | F14: 5576.2886 | G14: 5569.918 | H14: 5651.579 | I14: 5660.44 | J14: 5861.0474 | K14: 5833.31 | L14: 5922.6577 | M14: 5871.999 | N14: 5972.099 | O14: 5977.1416 | P14: 6043.236 | Q14: 6052.0703 | R14: 6125.7285 | S14: 6131.3335 | T14: 6068.989 | U14: 6012.4224 | V14: 6055.2383 | W14: 6019.2456 | X14: 6056.563 | Y14: 5996.2676 | Z14: 6021.1006 | AA14: 6003.3296 | AB14: 6078.642 | AC14: 6083.2886 | AD14: 6076.369 | AE14: 5990.027 | AF14: 5865.9214 | AG14: 5872.9688 | AH14: 5934.9053 | AI14: 5928.3037 | AJ14: 5910.378 | AK14: 5911.4043 | AL14: 5892.197 | AM14: 5890.1665 | AN14: 5910.182 | AO14: 5944.611 | AP14: 5926.4795 | AQ14: 5936.96 | AR14: 5844.728
A15: Aditya Birla Sun Life Digital India Fund | B15: Aditya Birla Sun Life | C15: SECTORAL / THEMATIC | D15: 3593.2747 | E15: 3589.8882 | F15: 3673.159 | G15: 3745.497 | H15: 3767.509 | I15: 3826.106 | J15: 3891.6035 | K15: 3893.9753 | L15: 3867.9963 | M15: 3841.7585 | N15: 3942.2522 | O15: 3990.199 | P15: 4001.7427 | Q15: 3975.2869 | R15: 3998.0608 | S15: 3923.0273 | T15: 3880.0706 | U15: 3737.4277 | V15: 3785.4385 | W15: 3769.6272 | X15: 3800.7056 | Y15: 3798.7854 | Z15: 3778.8892 | AA15: 3775.4983 | AB15: 3838.9475 | AC15: 3824.2126 | AD15: 3880.5464 | AE15: 3842.0874 | AF15: 3721.1267 | AG15: 3695.4111 | AH15: 3677.6106 | AI15: 3698.9722 | AJ15: 3758.0093 | AK15: 3848.6155 | AL15: 3825.1545 | AM15: 3802.3906 | AN15: 3800.001 | AO15: 3830.7874 | AP15: 3834.1313 | AQ15: 3827.9036 | AR15: 3819.5312
A16: Aditya Birla Sun Life Dividend Yield Fund | B16: Aditya Birla Sun Life | C16: DIVIDEND YIELD | D16: 1338.5585 | E16: 1338.9503 | F16: 1367.7981 | G16: 1369.8768 | H16: 1392.0577 | I16: 1401.6936 | J16: 1437.4338 | K16: 1440.6587 | L16: 1450.0544 | M16: 1447.5452 | N16: 1471.2201 | O16: 1474.571 | P16: 1491.4149 | Q16: 1492.0145 | R16: 1503.3973 | S16: 1495.7905 | T16: 1482.9647 | U16: 1465.1924 | V16: 1477.7389 | W16: 1472.0973 | X16: 1485.593 | Y16: 1475.1729 | Z16: 1477.9335 | AA16: 1477.8564 | AB16: 1498.8652 | AC16: 1501.8706 | AD16: 1496.0142 | AE16: 1481.7793 | AF16: 1456.2877 | AG16: 1461.6943 | AH16: 1468.7756 | AI16: 1468.244 | AJ16: 1461.2421 | AK16: 1475.537 | AL16: 1473.9586 | AM16: 1467.9651 | AN16: 1465.223 | AO16: 1480.6154 | AP16: 1478.5658 | AQ16: 1479.4829 | AR16: 1459.1869
A17: Aditya Birla Sun Life ELSS Tax Saver Fund | B17: Aditya Birla Sun Life | C17: ELSS | D17: 13126.825 | E17: 13117.288 | F17: 13411.292 | G17: 13398.838 | H17: 13570.04 | I17: 13641.816 | J17: 14141.59 | K17: 14064.438 | L17: 14256.553 | M17: 14167.586 | N17: 14403.001 | O17: 14428.905 | P17: 14564.289 | Q17: 14557.483 | R17: 14688.928 | S17: 14663.643 | T17: 14530.485 | U17: 14357.072 | V17: 14506.875 | W17: 14428.99 | X17: 14490.44 | Y17: 14378.229 | Z17: 14523.418 | AA17: 14498.031 | AB17: 14686.84 | AC17: 14707.705 | AD17: 14613.802 | AE17: 14376.779 | AF17: 14077.728 | AG17: 14094.105 | AH17: 14217.24 | AI17: 14189.281 | AJ17: 14156.932 | AK17: 14189.089 | AL17: 14219.024 | AM17: 14193.626 | AN17: 14236.966 | AO17: 14412.295 | AP17: 14377.255 | AQ17: 14433.757 | AR17: 14253.906
... A34: Aditya Birla Sun Life Quant Fund | B34: Aditya Birla Sun Life | C34: SECTORAL / THEMATIC | D34: 1868.6692 | E34: 1867.5317 | F34: 1894.1735 | G34: 1886.9379 | H34: 1916.5131 | I34: 1929.1764 | J34: 2013.5669 | K34: 2010.9996 | L34: 2043.9825 | M34: 2023.8503 | N34: 2052.767 | O34: 2053.6045 | P34: 2071.1323 | Q34: 2079.2349 | R34: 2080.451 | S34: 2071.996 | T34: 2051.312 | U34: 2036.7866 | V34: 2061.533 | W34: 2048.3792 | X34: 2050.1304 | Y34: 2027.0596 | Z34: 2039.5048 | AA34: 2044.5768 | AB34: 2072.5618 | AC34: 2090.291 | AD34: 2079.9502 | AE34: 2060.7104 | AF34: 2026.023 | AG34: 2031.7853 | AH34: 2054.2224 | AI34: 2041.341 | AJ34: 2026.0406 | AK34: 2031.7429 | AL34: 2040.8688 | AM34: 2043.3179 | AN34: 2046.5145 | AO34: 2075.4724 | AP34: 2069.543 | AQ34: 2078.939 | AR34: 2046.6152
A35: Aditya Birla Sun Life Regular Savings Fund | B35: Aditya Birla Sun Life | C35: CONSERVATIVE HYRBID | D35: 1457.4606 | E35: 1455.9271 | G35: 1457.5641 | H35: 1457.2861 | I35: 1459.2848 | J35: 1472.6641 | K35: 1472.3032 | L35: 1477.8148 | M35: 1476.5625 | N35: 1485.4645 | O35: 1484.9924 | P35: 1487.431 | Q35: 1488.3934 | R35: 1490.3629 | S35: 1487.5835 | T35: 1483.7313 | U35: 1480.5359 | V35: 1485.4629 | W35: 1483.3687 | X35: 1482.7213 | Y35: 1479.2755 | Z35: 1482.9631 | AA35: 1481.3405 | AB35: 1487.9635 | AC35: 1490.1614 | AD35: 1485.4065 | AE35: 1480.9194 | AF35: 1474.3639 | AG35: 1474.0963 | AH35: 1477.4717 | AI35: 1474.8047 | AJ35: 1470.52 | AK35: 1470.4421 | AL35: 1471.1711 | AM35: 1470.1178 | AN35: 1470.554 | AO35: 1476.3367 | AP35: 1477.0914 | AQ35: 1477.5615 | AR35: 1473.9827
A36: Aditya Birla Sun Life Small cap Fund | B36: Aditya Birla Sun Life | C36: SMALL CAP | D36: 4447.294 | E36: 4449.155 | F36: 4561.1445 | G36: 4553.9717 | H36: 4626.4824 | I36: 4630.805 | J36: 4795.472 | K36: 4809.903 | L36: 4879.7563 | M36: 4865.624 | N36: 4948.379 | O36: 5001.398 | P36: 5072.3687 | Q36: 5088.778 | R36: 5141.387 | S36: 5190.7607 | T36: 5181.736 | U36: 5164.0586 | V36: 5244.239 | W36: 5239.288 | X36: 5271.4644 | Y36: 5253.496 | Z36: 5339.01 | AA36: 5319.448 | AB36: 5391.172 | AC36: 5479.7915 | AD36: 5478.9634 | AE36: 5421.115 | AF36: 5287.3223 | AG36: 5299.349 | AH36: 5343.22 | AI36: 5351.095 | AJ36: 5298.9663 | AK36: 5364.915 | AL36: 5376.0156 | AM36: 5401.7876 | AN36: 5391.4233 | AO36: 5463.4233 | AP36: 5482.5356 | AQ36: 5477.251 | AR36: 5450.2446
A37: Aditya Birla Sun Life Special Opportunities Fund | B37: Aditya Birla Sun Life | C37: SECTORAL / THEMATIC | D37: 889.7754 | E37: 890.118 | F37: 906.2483 | G37: 906.1972 | H37: 920.4597 | I37: 931.8195 | J37: 966.1865 | K37: 966.3132 | L37: 981.0853 | M37: 979.6625 | N37: 998.6684 | O37: 1002.9356 | P37: 1014.2393 | Q37: 1016.6697 | R37: 1029.8871 | S37: 1029.6122 | T37: 1022.9605 | U37: 1021.3895 | V37: 1032.4897 | W37: 1029.7994 | X37: 1038.0173 | Y37: 1030.2155 | Z37: 1039.4563 | AA37: 1040.6731 | AB37: 1055.703 | AC37: 1060.8655 | AD37: 1060.3416 | AE37: 1048.8494 | AF37: 1030.9355 | AG37: 1036.2495 | AH37: 1046.9926 | AI37: 1046.1637 | AJ37: 1043.3342 | AK37: 1049.3854 | AL37: 1050.6312 | AM37: 1048.912 | AN37: 1053.2294 | AO37: 1068.9751 | AP37: 1071.8235 | AQ37: 1074.5415 | AR37: 1071.6044
A38: Aditya Birla Sun Life Transportation and Logistics Fund | B38: Aditya Birla Sun Life | C38: SECTORAL / THEMATIC | D38: 1320.1431 | E38: 1319.6266 | F38: 1351.8254 | G38: 1341.9265 | H38: 1358.2604 | I38: 1358.9147 | J38: 1436.591 | K38: 1427.2285 | L38: 1460.2935 | M38: 1433.2325 | N38: 1461.424 | O38: 1466.0767 | P38: 1475.6964 | Q38: 1478.33 | R38: 1487.4707 | S38: 1492.4689 | T38: 1464.7446 | U38: 1448.4761 | V38: 1473.4327 | W38: 1459.434 | X38: 1463.7406 | Y38: 1454.7826 | Z38: 1466.3802 | AA38: 1468.4465 | AB38: 1500.7216 | AC38: 1523.7228 | AD38: 1525.9578 | AE38: 1495.7405 | AF38: 1456.695 | AG38: 1451.5304 | AH38: 1457.8181 | AI38: 1455.9324 | AJ38: 1439.0728 | AK38: 1447.8071 | AL38: 1453.3717 | AM38: 1469.1559 | AN38: 1473.1099 | AO38: 1493.4436 | AP38: 1493.8411 | AQ38: 1516.6447 | AR38: 1492.327
A39: Aditya Birla Sun Life Value Fund | B39: Aditya Birla Sun Life | C39: VALUE | D39: 5637.185 | E39: 5638.6396 | F39: 5758.001 | G39: 5766.8887 | H39: 5843.3086 | I39: 5878.17 | J39: 6101.6597 | K39: 6097.414 | L39: 6169.4736 | M39: 6157.743 | N39: 6284.617 | O39: 6321.919 | P39: 6401.2104 | Q39: 6403.5737 | R39: 6454.105 | S39: 6460.789 | T39: 6435.444 | U39: 6351.11 | V39: 6424.3887 | W39: 6403.9517 | X39: 6430.9683 | Y39: 6387.7773 | Z39: 6443.055 | AA39: 6435.558 | AB39: 6530.2944 | AC39: 6577.264 | AD39: 6582.2007 | AE39: 6517.293 | AF39: 6371.9175 | AG39: 6385.382 | AH39: 6430.2617 | AI39: 6422.923 | AJ39: 6393.818 | AK39: 6446.8413 | AL39: 6450.479 | AM39: 6470.9844 | AN39: 6486.8403 | AO39: 6569.195 | AP39: 6577.854 | AQ39: 6603.403 | AR39: 6528.5845
A40: Axis Aggressive Hybrid Fund | B40: Axis | C40: AGGRESSIVE HYBRID | D40: 1398.6599 | E40: 1376.8906 | F40: 1376.8906 | G40: 1393.1064 | H40: 1394.0502 | I40: 1403.9083 | J40: 1409.0681 | K40: 1447.5709 | L40: 1437.9824 | M40: 1452.2106 | N40: 1439.115 | O40: 1458.8995 | P40: 1459.5027 | Q40: 1467.0125 | R40: 1464.8857 | S40: 1474.685 | T40: 1469.3351 | U40: 1458.9271 | V40: 1447.8384 | W40: 1460.0953 | X40: 1455.2123 | Y40: 1459.2877 | Z40: 1451.4524 | AA40: 1455.6553 | AB40: 1454.5194 | AC40: 1468.844 | AD40: 1470.2604 | AE40: 1465.8002 | AF40: 1449.6697 | AG40: 1424.7821 | AH40: 1425.473 | AI40: 1433.1179 | AJ40: 1430.0543 | AK40: 1426.3195 | AL40: 1429.6478 | AM40: 1430.9685 | AN40: 1433.1302 | AO40: 1435.5 | AP40: 1446.848 | AQ40: 1442.7242 | AR40: 1444.3026
A41: Axis Arbitrage Fund | B41: Axis | C41: ARBITRAGE | D41: 8993.552 | E41: 9022.162 | F41: 9022.69 | G41: 8997.845 | H41: 9045.597 | I41: 9010.49 | J41: 9089.549 | K41: 9106.703 | L41: 9184.397 | M41: 9194.557 | N41: 9195.073 | O41: 9329.495 | P41: 9343.958 | Q41: 9428.797 | R41: 9516.6045 | S41: 9522.236 | T41: 9556.995 | U41: 9570.576 | V41: 9645.193 | W41: 9666.059 | X41: 9657.055 | Y41: 9724.7 | Z41: 9813.865 | AA41: 9777.448 | AB41: 9575.249 | AC41: 9566.68 | AD41: 9675.275 | AE41: 9706.167 | AF41: 9756.704 | AG41: 9736.999 | AH41: 9726.302 | AI41: 9759.434 | AJ41: 9784.336 | AK41: 9795.27 | AL41: 9840.342 | AM41: 9826.266 | AN41: 9880.87 | AO41: 9883.555 | AP41: 9828.964 | AQ41: 9823.84 | AR41: 9832.639
A42: Axis Balanced Advantage Fund | B42: Axis | C42: DYNAMIC ASSET ALLOCATION OR BALANCED ADVANTAGE | D42: 3601.2666 | E42: 3557.3828 | F42: 3557.3828 | G42: 3588.3027 | H42: 3592.9165 | I42: 3616.6958 | J42: 3629.5205 | K42: 3719.9485 | L42: 3699.7073 | M42: 3730.7954 | N42: 3712.7073 | O42: 3757.267 | P42: 3782.084 | Q42: 3800.6536 | R42: 3801.3198 | S42: 3823.534 | T42: 3810.5615 | U42: 3781.5896 | V42: 3756.99 | W42: 3782.1687 | X42: 3770.8506 | Y42: 3781.2778 | Z42: 3764.9807 | AA42: 3775.7014 | AB42: 3776.1592 | AC42: 3814.2043 | AD42: 3818.444 | AE42: 3814.2573 | AF42: 3781.5464 | AG42: 3733.582 | AH42: 3732.4426 | AI42: 3750.0789 | AJ42: 3749.9653 | AK42: 3744.3616 | AL42: 3746.2375 | AM42: 3749.7507 | AN42: 3748.25 | AO42: 3755.144 | AP42: 3783.614 | AQ42: 3774.1643 | AR42: 3778.5586
A43: Axis Business Cycles Fund | B43: Axis | C43: SECTORAL / THEMATIC | D43: 1916.8031 | E43: 1866.7982 | F43: 1866.7947 | G43: 1903.2412 | H43: 1902.23 | I43: 1927.269 | J43: 1935.8317 | K43: 2019.0516 | L43: 2004.3228 | M43: 2038.8971 | N43: 2021.5325 | O43: 2056.1814 | P43: 2062.9124 | Q43: 2081.8616 | R43: 2082.9626 | S43: 2102.5305 | T43: 2100.761 | U43: 2085.322 | V43: 2064.422 | W43: 2087.6135 | X43: 2078.457 | Y43: 2079.4204 | Z43: 2064.754 | AA43: 2079.2725 | AB43: 2081.987 | AC43: 2107.4084 | AD43: 2122.242 | AE43: 2111.5146 | AF43: 2093.1023 | AG43: 2045.1349 | AH43: 2049.443 | AI43: 2073.4348 | AJ43: 2061.6926 | AK43: 2054.956 | AL43: 2056.865 | AM43: 2061.9185 | AN43: 2057.4763 | AO43: 2058.8203 | AP43: 2083.41 | AQ43: 2082.1787 | AR43: 2090.5432
A44: Axis Conservative Hybrid Fund | B44: Axis | C44: CONSERVATIVE HYRBID | D44: 216.5943 | E44: 214.7598 | G44: 214.7806 | H44: 214.5318 | I44: 215.4795 | J44: 215.8494 | K44: 218.0309 | L44: 217.0445 | M44: 217.7156 | N44: 217.7707 | O44: 218.7808 | P44: 218.6336 | Q44: 218.7971 | R44: 219.1506 | S44: 219.5504 | T44: 218.901 | U44: 218.7797 | V44: 218.0263 | W44: 218.2857 | X44: 218.0317 | Y44: 218.2027 | Z44: 217.8159 | AA44: 218.115 | AB44: 218.0756 | AC44: 218.9645 | AD44: 218.9407 | AE44: 218.5522 | AF44: 217.2512 | AG44: 216.3805 | AH44: 216.4981 | AI44: 217.9307 | AJ44: 217.9303 | AK44: 218.0922 | AL44: 218.4068 | AM44: 218.446 | AN44: 218.2345 | AO44: 218.5134 | AP44: 219.2458 | AQ44: 219.1428 | AR44: 218.6055
A45: Axis Consumption Fund | B45: Axis | C45: SECTORAL / THEMATIC | D45: 2698.2793 | E45: 2639.109 | F45: 2639.109 | G45: 2683.197 | H45: 2683.8357 | I45: 2713.6028 | J45: 2722.6846 | K45: 2816.963 | L45: 2803.575 | M45: 2849.622 | N45: 2816.4067 | O45: 2859.7083 | P45: 2855.7722 | Q45: 2886.272 | R45: 2898.1506 | S45: 2934.8936 | T45: 2924.2285 | U45: 2892.4329 | V45: 2870.1406 | W45: 2893.4226 | X45: 2875.5815 | Y45: 2899.6936 | Z45: 2867.571 | AA45: 2868.9248 | AB45: 2854.8782 | AC45: 2894.718 | AD45: 2895.6753 | AE45: 2906.0828 | AF45: 2846.9739 | AG45: 2789.927 | AH45: 2787.3003 | AI45: 2819.1707 | AJ45: 2808.981 | AK45: 2786.5295 | AL45: 2784.6294 | AM45: 2777.2053 | AN45: 2775.3032 | AO45: 2775.5205 | AP45: 2798.0115 | AQ45: 2791.7966 | AR45: 2804.8232
A46: Axis ELSS Tax Saver Fund | B46: Axis | C46: ELSS | D46: 29830.31 | E46: 29076.658 | F46: 29075.783 | G46: 29496.125 | H46: 29432.758 | I46: 29807.426 | J46: 29979.262 | K46: 31143.604 | L46: 30912.969 | M46: 31389.385 | N46: 31100.152 | O46: 31597.355 | P46: 31643.273 | Q46: 31891.2 | R46: 31939.586 | S46: 32233.56 | T46: 32095.707 | U46: 31872.25 | V46: 31549.674 | W46: 31821.525 | X46: 31680.207 | Y46: 31802.008 | Z46: 31554.889 | AA46: 31676.836 | AB46: 31699.883 | AC46: 32137.668 | AD46: 32227.172 | AE46: 32058.139 | AF46: 31583.258 | AG46: 30892.207 | AH46: 30894.54 | AI46: 31228.848 | AJ46: 31143.553 | AK46: 31083.473 | AL46: 31106.09 | AM46: 31195.125 | AN46: 31149.447 | AO46: 31221.902 | AP46: 31545.164 | AQ46: 31409.26 | AR46: 31522.766
A47: Axis ESG Integration Strategy Fund | B47: Axis | C47: SECTORAL / THEMATIC | D47: 1027.5824 | E47: 1006.5715 | F47: 1006.5715 | G47: 1018.0847 | H47: 1019.2322 | I47: 1029.1829 | J47: 1033.4579 | K47: 1069.0396 | L47: 1062.4944 | M47: 1075.6693 | N47: 1066.8676 | O47: 1081.3972 | P47: 1081.8582 | Q47: 1090.9268 | R47: 1092.7399 | S47: 1098.7853 | T47: 1094.0885 | U47: 1085.5181 | V47: 1076.1088 | W47: 1084.2034 | X47: 1077.4297 | Y47: 1079.9004 | Z47: 1071.4512 | AA47: 1075.4489 | AB47: 1076.3446 | AC47: 1090.4624 | AD47: 1095.4255 | AE47: 1093.6333 | AF47: 1082.1807 | AG47: 1060.3287 | AH47: 1057.5543 | AI47: 1064.453 | AJ47: 1066.9786 | AK47: 1063.49 | AL47: 1064.8212 | AM47: 1066.7673 | AN47: 1068.4841 | AO47: 1071.076 | AP47: 1077.7424 | AQ47: 1074.2113 | AR47: 1076.7456
A48: Axis Equity Savings Fund | B48: Axis | C48: EQUITY SAVINGS | D48: 860.7493 | E48: 849.6179 | F48: 849.6179 | G48: 852.833 | H48: 852.046 | I48: 853.6588 | J48: 856.3364 | K48: 868.1183 | L48: 865.8195 | M48: 869.9938 | N48: 869.1621 | O48: 873.5812 | P48: 872.9085 | Q48: 875.4983 | R48: 873.4326 | S48: 874.7238 | T48: 872.8213 | U48: 870.2063 | V48: 865.157 | W48: 868.7195 | X48: 865.5909 | Y48: 867.5102 | Z48: 866.0685 | AA48: 867.8104 | AB48: 868.0897 | AC48: 873.7491 | AD48: 874.1788 | AE48: 871.4419 | AF48: 868.1857 | AG48: 861.8961 | AH48: 861.9258 | AI48: 865.808 | AJ48: 864.5992 | AK48: 861.5236 | AL48: 861.2585 | AM48: 862.9597 | AN48: 862.6876 | AO48: 863.8119 | AP48: 868.5056 | AQ48: 867.0917 | AR48: 867.5176
A49: Axis Flexi Cap Fund | B49: Axis | C49: FLEXI CAP | D49: 11709.303 | E49: 11412.194 | F49: 11412.196 | G49: 11606.803 | H49: 11617.366 | I49: 11792.258 | J49: 11851.655 | K49: 12329.185 | L49: 12269.253 | M49: 12492.517 | N49: 12403.118 | O49: 12571.351 | P49: 12609.188 | Q49: 12703.914 | R49: 12748.273 | S49: 12847.572 | T49: 12849.45 | U49: 12783.084 | V49: 12668.807 | W49: 12731.802 | X49: 12627.965 | Y49: 12647.419 | Z49: 12542.739 | AA49: 12613.118 | AB49: 12656.926 | AC49: 12853.551 | AD49: 12925.511 | AE49: 12868.082 | AF49: 12704.236 | AG49: 12390.733 | AH49: 12412.672 | AI49: 12523.427 | AJ49: 12493.683 | AK49: 12433.071 | AL49: 12462.79 | AM49: 12542.063 | AN49: 12588.765 | AO49: 12620.529 | AP49: 12746.141 | AQ49: 12712.73 | AR49: 12806.75
A50: Axis Focused Fund | B50: Axis | C50: FOCUSED | D50: 10226.178 | E50: 9966.295 | F50: 9966.295 | G50: 10095.49 | H50: 10083.838 | I50: 10214.262 | J50: 10257.896 | K50: 10624.88 | L50: 10553.403 | M50: 10732.178 | N50: 10607.222 | O50: 10768.209 | P50: 10809.785 | Q50: 10904.527 | R50: 10958.261 | S50: 11051.765 | T50: 11020.444 | U50: 10981.56 | V50: 10893.281 | W50: 10945.174 | X50: 10865.102 | Y50: 10870.444 | Z50: 10789.463 | AA50: 10855.412 | AB50: 10868.865 | AC50: 11010.424 | AD50: 11033.858 | AE50: 10995.31 | AF50: 10817.08 | AG50: 10598.642 | AH50: 10577.131 | AI50: 10699.28 | AJ50: 10660.917 | AK50: 10628.207 | AL50: 10635.457 | AM50: 10689.804 | AN50: 10698.531 | AO50: 10731.573 | AP50: 10815.052 | AQ50: 10771.581 | AR50: 10852.226
A51: Axis India Manufacturing Fund | B51: Axis | C51: SECTORAL / THEMATIC | D51: 4754.8286 | E51: 4681.7876 | F51: 4681.7876 | G51: 4754.658 | H51: 4749.6436 | I51: 4773.4067 | J51: 4794.733 | K51: 4949.4604 | L51: 4967.5303 | M51: 5051.6885 | N51: 5011.643 | O51: 5112.122 | P51: 5140.287 | Q51: 5191.7256 | R51: 5194.2393 | S51: 5202.2485 | T51: 5218.482 | U51: 5191.318 | V51: 5143.293 | W51: 5227.2803 | X51: 5215.5005 | Y51: 5245.5347 | Z51: 5203.788 | AA51: 5251.709 | AB51: 5269.2017 | AC51: 5335.382 | AD51: 5398.551 | AE51: 5389.3013 | AF51: 5334.8394 | AG51: 5218.594 | AH51: 5248.9346 | AI51: 5282.017 | AJ51: 5244.7793 | AK51: 5200.123 | AL51: 5212.2993 | AM51: 5254.6543 | AN51: 5295.4956 | AO51: 5290.668 | AP51: 5327.0117 | AQ51: 5330.238 | AR51: 5410.2925
A52: Axis Innovation Fund | B52: Axis | C52: SECTORAL / THEMATIC | D52: 1062.7924 | E52: 1033.3287 | F52: 1039.5626 | G52: 1061.3087 | H52: 1056.7495 | I52: 1066.0767 | J52: 1066.138 | K52: 1106.3783 | L52: 1107.6852 | M52: 1129.153 | N52: 1125.0714 | O52: 1150.2913 | P52: 1156.9888 | Q52: 1165.6001 | R52: 1164.7318 | S52: 1178.255 | T52: 1187.8264 | U52: 1179.0566 | V52: 1173.3776 | W52: 1183.8342 | X52: 1180.0159 | Y52: 1177.5491 | Z52: 1176.5824 | AA52: 1190.0134 | AB52: 1186.4227 | AC52: 1197.6868 | AD52: 1203.9357 | AE52: 1206.0222 | AF52: 1192.1628 | AG52: 1160.8973 | AH52: 1165.7892 | AI52: 1175.0101 | AJ52: 1166.9607 | AK52: 1158.3202 | AL52: 1153.6016 | AM52: 1162.2762 | AN52: 1162.9061 | AO52: 1162.1107 | AP52: 1162.2109 | AQ52: 1170.1667 | AR52: 1177.6273
A53: Axis Large & Mid Cap Fund | B53: Axis | C53: LARGE & MID CAP | D53: 14266.582 | E53: 13945.196 | F53: 13973.884 | G53: 14231.882 | H53: 14221.679 | I53: 14426.284 | J53: 14488.854 | K53: 15030.305 | L53: 14982.67 | M53: 15202.14 | N53: 15135.217 | O53: 15404.27 | P53: 15415.557 | Q53: 15558.69 | R53: 15586.485 | S53: 15700.201 | T53: 15677.369 | U53: 15605.058 | V53: 15501.424 | W53: 15684.069 | X53: 15621.808 | Y53: 15677.494 | Z53: 15606.904 | AA53: 15664.618 | AB53: 15689.518 | AC53: 15947.855 | AD53: 16013.157 | AE53: 15986.736 | AF53: 15824.441 | AG53: 15483.824 | AH53: 15507.658 | AI53: 15726.041 | AJ53: 15677.462 | AK53: 15673.965 | AL53: 15706.463 | AM53: 15812.052 | AN53: 15804.795 | AO53: 15847.153 | AP53: 15986.618 | AQ53: 16001.371 | AR53: 16078.692
A54: Axis Large Cap Fund | B54: Axis | C54: LARGE CAP | D54: 29358.56 | E54: 28663.168 | F54: 28659.938 | G54: 29044.902 | H54: 29056.059 | I54: 29422.826 | J54: 29567.195 | K54: 30710.588 | L54: 30376.568 | M54: 30771.344 | N54: 30515.744 | O54: 30978.787 | P54: 30950.475 | Q54: 31123.62 | R54: 31138.959 | S54: 31396.643 | T54: 31176.637 | U54: 30860.844 | V54: 30534.635 | W54: 30744.543 | X54: 30574.613 | Y54: 30726.023 | Z54: 30488.629 | AA54: 30608.195 | AB54: 30575.54 | AC54: 30989.781 | AD54: 31036.504 | AE54: 30873.83 | AF54: 30408.373 | AG54: 29832.414 | AH54: 29817.508 | AI54: 30155.807 | AJ54: 30109.096 | AK54: 30099.54 | AL54: 30053.068 | AM54: 30082.475 | AN54: 30090.21 | AO54: 30183.299 | AP54: 30550.723 | AQ54: 30367.723 | AR54: 30430.56
A55: Axis Midcap Fund | B55: Axis | C55: MID CAP | D55: 29468.963 | E55: 28833.928 | F55: 28834.754 | G55: 29293.148 | H55: 29241.105 | I55: 29654.96 | J55: 29786.855 | K55: 30835.87 | L55: 30881.633 | M55: 31407.67 | N55: 31213.723 | O55: 31761.916 | P55: 31887.81 | Q55: 32208.082 | R55: 32312.156 | S55: 32513.285 | T55: 32562.244 | U55: 32506.059 | V55: 32228.162 | W55: 32603.285 | X55: 32547.365 | Y55: 32508.025 | Z55: 32278.658 | AA55: 32492.22 | AB55: 32565.406 | AC55: 33057.85 | AD55: 33319.98 | AE55: 33258.18 | AF55: 32955.793 | AG55: 32151.719 | AH55: 32196.207 | AI55: 32538.318 | AJ55: 32504.43 | AK55: 32470.459 | AL55: 32670.676 | AM55: 32890.355 | AN55: 32887.133 | AO55: 32864.746 | AP55: 33093.16 | AQ55: 33158.31 | AR55: 33344.027
A56: Axis Momentum Fund | B56: Axis | C56: SECTORAL / THEMATIC | D56: 945.8029 | E56: 924.0254 | F56: 924.0254 | G56: 947.9885 | H56: 945.8152 | I56: 964.8511 | J56: 964.7966 | K56: 1004.9257 | L56: 1006.8192 | M56: 1023.3619 | N56: 1013.5884 | O56: 1031.7246 | P56: 1035.2981 | Q56: 1042.6993 | R56: 1040.8418 | S56: 1042.3628 | T56: 1038.8263 | U56: 1031.0646 | V56: 1022.0594 | W56: 1027.3279 | X56: 1025.6742 | Y56: 1027.764 | Z56: 1018.3984 | AA56: 1020.1321 | AB56: 1016.4089 | AC56: 1025.1696 | AD56: 1025.9344 | AE56: 1017.7162 | AF56: 1005.6638 | AG56: 986.9648 | AH56: 991.7841 | AI56: 998.5322 | AJ56: 993.2488 | AK56: 987.9865 | AL56: 988.6104 | AM56: 990.1542 | AN56: 992.1461 | AO56: 992.1408 | AP56: 998.0851 | AQ56: 991.9159 | AR56: 995.8237
... A79: Bandhan Business Cycle Fund | B79: Bandhan | C79: SECTORAL / THEMATIC | D79: 1145.8368 | E79: 1145.8368 | F79: 1135.71 | G79: 1139.32 | H79: 1155.0454 | I79: 1160.977 | J79: 1209.3794 | K79: 1202.5289 | L79: 1218.33 | M79: 1209.8927 | N79: 1234.5011 | O79: 1238.9619 | P79: 1249.4838 | Q79: 1248.6201 | R79: 1257.1853 | S79: 1257.3973 | T79: 1245.5109 | U79: 1229.5206 | V79: 1243.3312 | W79: 1236.2224 | X79: 1234.2588 | Y79: 1226.6963 | Z79: 1235.9891 | AA79: 1232.4778 | AB79: 1253.2316 | AC79: 1254.6904 | AD79: 1244.9265 | AE79: 1227.5133 | AF79: 1197.237 | AG79: 1197.0302 | AH79: 1206.6112 | AI79: 1202.6234 | AJ79: 1196.1528 | AK79: 1199.9327 | AL79: 1199.8866 | AM79: 1200.6714 | AN79: 1201.5907 | AO79: 1215.4945 | AP79: 1213.8563 | AQ79: 1215.8982 | AR79: 1215.8982
A80: Bandhan Conservative Hybrid Fund | B80: Bandhan | C80: CONSERVATIVE HYRBID | D80: 95.7581 | E80: 95.7581 | G80: 95.64 | H80: 96.0546 | I80: 96.1222 | J80: 97.4819 | K80: 97.31 | L80: 97.61 | M80: 97.1939 | N80: 98.009 | O80: 97.9295 | P80: 98.1414 | Q80: 98.1988 | R80: 98.5688 | S80: 98.2993 | T80: 97.9553 | U80: 97.6299 | V80: 97.9084 | W80: 97.6307 | X80: 97.8796 | Y80: 97.5911 | Z80: 97.635 | AA80: 97.5154 | AB80: 98.0184 | AC80: 98.0059 | AD80: 97.9627 | AE80: 97.4008 | AF80: 96.7649 | AG80: 96.7667 | AH80: 96.9393 | AI80: 96.8846 | AJ80: 96.5589 | AK80: 96.5398 | AL80: 96.5151 | AM80: 96.2944 | AN80: 96.3843 | AO80: 96.9077 | AP80: 96.6957 | AQ80: 96.7024 | AR80: 96.7024
A81: Bandhan ELSS Tax saver Fund | B81: Bandhan | C81: ELSS | D81: 6415.002 | E81: 6415.002 | F81: 6384.96 | G81: 6390.81 | H81: 6461.28 | I81: 6504.7183 | J81: 6718.043 | K81: 6689.28 | L81: 6761.25 | M81: 6719.8813 | N81: 6832.4443 | O81: 6825.887 | P81: 6879.149 | Q81: 6878.1094 | R81: 6935.4775 | S81: 6915.4863 | T81: 6855.8066 | U81: 6775.744 | V81: 6850.67 | W81: 6834.773 | X81: 6882.058 | Y81: 6835.3115 | Z81: 6847.815 | AA81: 6839.9443 | AB81: 6934.4336 | AC81: 6965.65 | AD81: 6951.3076 | AE81: 6867.5947 | AF81: 6755.008 | AG81: 6756.135 | AH81: 6817.837 | AI81: 6805.703 | AJ81: 6786.094 | AK81: 6762.211 | AL81: 6756.953 | AM81: 6753.4946 | AN81: 6780.815 | AO81: 6857.899 | AP81: 6846.6494 | AQ81: 6851.2695 | AR81: 6851.2695
A82: Bandhan Equity Savings Fund | B82: Bandhan | C82: EQUITY SAVINGS | D82: 394.141 | E82: 394.141 | F82: 392.61 | G82: 392.2 | H82: 392.4574 | I82: 392.8321 | J82: 393.2381 | K82: 392.828 | L82: 394.19 | M82: 393.7958 | N82: 395.3042 | O82: 393.6341 | P82: 392.9297 | Q82: 392.3571 | R82: 392.8449 | S82: 391.2178 | T82: 390.4363 | U82: 389.1255 | V82: 389.9922 | W82: 389.4406 | X82: 389.8718 | Y82: 389.3898 | Z82: 389.2976 | AA82: 389.038 | AB82: 390.0084 | AC82: 390.2821 | AD82: 390.3586 | AE82: 389.0566 | AF82: 387.6831 | AG82: 387.442 | AH82: 388.5484 | AI82: 389.5213 | AJ82: 389.4292 | AK82: 390.2814 | AL82: 390.7694 | AM82: 392.1684 | AN82: 391.2547 | AO82: 392.3238 | AP82: 391.5088 | AQ82: 391.8402 | AR82: 391.8402
A83: Bandhan Financial Services Fund | B83: Bandhan | C83: SECTORAL / THEMATIC | D83: 989.0472 | E83: 989.0472 | F83: 974.98 | G83: 976.04 | H83: 996.8262 | I83: 998.3833 | J83: 1053.1964 | K83: 1042.2971 | L83: 1063.37 | M83: 1057.7632 | N83: 1075.5433 | O83: 1075.0345 | P83: 1085.609 | Q83: 1085.0542 | R83: 1100.0634 | S83: 1093.2174 | T83: 1080.3297 | U83: 1074.0721 | V83: 1078.2504 | W83: 1070.6901 | X83: 1070.0846 | Y83: 1059.8833 | Z83: 1067.074 | AA83: 1065.1162 | AB83: 1091.153 | AC83: 1096.8984 | AD83: 1087.9036 | AE83: 1074.1718 | AF83: 1049.4274 | AG83: 1049.5559 | AH83: 1059.7013 | AI83: 1054.3424 | AJ83: 1048.6891 | AK83: 1050.0083 | AL83: 1050.448 | AM83: 1049.2582 | AN83: 1054.1803 | AO83: 1072.7358 | AP83: 1069.3975 | AQ83: 1063.4905 | AR83: 1063.4905
A84: Bandhan Flexi Cap Fund | B84: Bandhan | C84: FLEXI CAP | D84: 6802.737 | E84: 6802.737 | F84: 6758.22 | G84: 6771.66 | H84: 6875.944 | I84: 6907.552 | J84: 7158.308 | K84: 7111.4067 | L84: 7188.41 | M84: 7154.812 | N84: 7282.1177 | O84: 7292.4404 | P84: 7359.37 | Q84: 7353.301 | R84: 7419.546 | S84: 7391.825 | T84: 7324.7373 | U84: 7236.456 | V84: 7302.059 | W84: 7279.726 | X84: 7337.214 | Y84: 7285.4375 | Z84: 7334.4463 | AA84: 7309.395 | AB84: 7401.4062 | AC84: 7416.9614 | AD84: 7397.8193 | AE84: 7319.554 | AF84: 7190.195 | AG84: 7199.4507 | AH84: 7266.3896 | AI84: 7255.7783 | AJ84: 7248.4697 | AK84: 7262.013 | AL84: 7252.09 | AM84: 7254.3833 | AN84: 7284.555 | AO84: 7372.037 | AP84: 7360.2666 | AQ84: 7357.1895 | AR84: 7357.1895
A85: Bandhan Focused Fund | B85: Bandhan | C85: FOCUSED | D85: 1859.8156 | E85: 1859.8156 | F85: 1856.07 | G85: 1868.18 | H85: 1886.8094 | I85: 1894.7306 | J85: 1976.1669 | K85: 1964.6058 | L85: 1985.96 | M85: 1972.7267 | N85: 2016.2977 | O85: 2029.8203 | P85: 2056.0374 | Q85: 2055.2852 | R85: 2073.596 | S85: 2078.6628 | T85: 2067.42 | U85: 2049.2625 | V85: 2080.5535 | W85: 2074.3557 | X85: 2070.1528 | Y85: 2057.5334 | Z85: 2075.64 | AA85: 2077.596 | AB85: 2103.62 | AC85: 2115.7942 | AD85: 2111.129 | AE85: 2073.4043 | AF85: 2025.1058 | AG85: 2032.1488 | AH85: 2045.6051 | AI85: 2036.8003 | AJ85: 2023.2445 | AK85: 2045.4205 | AL85: 2045.174 | AM85: 2051.6865 | AN85: 2048.2512 | AO85: 2071.826 | AP85: 2075.2605 | AQ85: 2067.9421 | AR85: 2067.9421
A86: Bandhan Infrastructure Fund | B86: Bandhan | C86: SECTORAL / THEMATIC | D86: 1317.9738 | E86: 1317.9738 | F86: 1320.38 | G86: 1324.39 | H86: 1338.345 | I86: 1341.4224 | J86: 1399.0057 | K86: 1394.2804 | L86: 1420.81 | M86: 1421.745 | N86: 1459.4989 | O86: 1472.5052 | P86: 1490.0304 | Q86: 1485.4387 | R86: 1493.1504 | S86: 1509.0999 | T86: 1506.7257 | U86: 1490.2501 | V86: 1516.1243 | W86: 1514.2828 | X86: 1514.6497 | Y86: 1501.9054 | Z86: 1516.5936 | AA86: 1514.7738 | AB86: 1524.7891 | AC86: 1532.5315 | AD86: 1529.566 | AE86: 1502.1874 | AF86: 1467.9819 | AG86: 1472.8016 | AH86: 1483.6824 | AI86: 1476.0552 | AJ86: 1466.8569 | AK86: 1462.6683 | AL86: 1470.2476 | AM86: 1481.1036 | AN86: 1482.5792 | AO86: 1497.6753 | AP86: 1498.5459 | AQ86: 1513.9467 | AR86: 1513.9467
A87: Bandhan Innovation Fund | B87: Bandhan | C87: SECTORAL / THEMATIC | D87: 1861.0222 | E87: 1861.0222 | F87: 1842.52 | G87: 1839.14 | H87: 1860.3517 | I87: 1874.6782 | J87: 1950.4039 | K87: 1951.9987 | L87: 1986.97 | M87: 1991.0372 | N87: 2034.9186 | O87: 2054.856 | P87: 2069.6584 | Q87: 2072.4673 | R87: 2091.2288 | S87: 2114.2139 | T87: 2103.2034 | U87: 2079.4827 | V87: 2112.2048 | W87: 2108.4292 | X87: 2111.911 | Y87: 2101.6396 | Z87: 2115.6665 | AA87: 2121.0735 | AB87: 2159.7744 | AC87: 2186.5645 | AD87: 2189.339 | AE87: 2169.8298 | AF87: 2110.4077 | AG87: 2111.5042 | AH87: 2137.3577 | AI87: 2127.8386 | AJ87: 2115.0012 | AK87: 2131.9932 | AL87: 2151.3425 | AM87: 2165.9067 | AN87: 2174.063 | AO87: 2197.3833 | AP87: 2205.494 | AQ87: 2220.101 | AR87: 2220.101
A88: Bandhan Large & Mid Cap Fund | B88: Bandhan | C88: LARGE & MID CAP | D88: 14306.701 | E88: 14306.701 | F88: 14401.3 | G88: 14435.86 | H88: 14648.92 | I88: 14755.869 | J88: 15344.494 | K88: 15367.605 | L88: 15621.74 | M88: 15577.984 | N88: 15942.838 | O88: 16080.375 | P88: 16262.963 | Q88: 16296.663 | R88: 16480.758 | S88: 16524.135 | T88: 16507.781 | U88: 16411.156 | V88: 16654.129 | W88: 16685.434 | X88: 16747.156 | Y88: 16671.94 | Z88: 16805.291 | AA88: 16803.658 | AB88: 17082.22 | AC88: 17239.203 | AD88: 17227.797 | AE88: 17054.604 | AF88: 16748.74 | AG88: 16900.756 | AH88: 17074.574 | AI88: 17095.053 | AJ88: 17071.469 | AK88: 17191.1 | AL88: 17256.752 | AM88: 17319.215 | AN88: 17338.809 | AO88: 17540.723 | AP88: 17586.627 | AQ88: 17645.125 | AR88: 17645.125
A89: Bandhan Large Cap Fund | B89: Bandhan | C89: LARGE CAP | D89: 1856.3533 | E89: 1856.3533 | F89: 1852.71 | G89: 1852.67 | H89: 1878.8519 | I89: 1894.4563 | J89: 1973.6117 | K89: 1962.2456 | L89: 1988.26 | M89: 1979.1227 | N89: 2013.2839 | O89: 2015.889 | P89: 2029.7844 | Q89: 2033.2795 | R89: 2048.6162 | S89: 2039.0602 | T89: 2019.3392 | U89: 1995.7434 | V89: 2018.443 | W89: 2009.7971 | X89: 2023.9729 | Y89: 2007.2695 | Z89: 2018.0331 | AA89: 2017.0302 | AB89: 2045.022 | AC89: 2053.375 | AD89: 2044.142 | AE89: 2015.0967 | AF89: 1974.2935 | AG89: 1974.1357 | AH89: 1995.2257 | AI89: 1989.6144 | AJ89: 1987.5696 | AK89: 1990.7255 | AL89: 1996.8779 | AM89: 1997.5969 | AN89: 2003.9344 | AO89: 2028.1368 | AP89: 2021.572 | AQ89: 2026.0188 | AR89: 2026.0188
A90: Bandhan Midcap Fund | B90: Bandhan | C90: MID CAP | D90: 1882.4781 | E90: 1882.4781 | F90: 1871.42 | G90: 1867.09 | H90: 1895.4113 | I90: 1905.1256 | J90: 1977.9434 | K90: 1983.5607 | L90: 2020.16 | M90: 2008.4801 | N90: 2049.7566 | O90: 2062.6816 | P90: 2085.9463 | Q90: 2093.8489 | R90: 2109.898 | S90: 2120.2925 | T90: 2120.4983 | U90: 2106.4873 | V90: 2127.4429 | W90: 2124.262 | X90: 2125.0676 | Y90: 2108.5493 | Z90: 2129.2996 | AA90: 2138.2837 | AB90: 2171.9253 | AC90: 2193.261 | AD90: 2194.9368 | AE90: 2177.056 | AF90: 2122.5544 | AG90: 2130.095 | AH90: 2148.9907 | AI90: 2147.797 | AJ90: 2144.1602 | AK90: 2158.8599 | AL90: 2176.1982 | AM90: 2184.6958 | AN90: 2185.1821 | AO90: 2202.907 | AP90: 2210.5005 | AQ90: 2227.2751 | AR90: 2227.2751
A91: Bandhan Multi Asset Allocation Fund | B91: Bandhan | C91: MULTI ASSET ALLOCATION | D91: 2954.633 | E91: 2954.633 | F91: 2987.63 | G91: 2976.97 | H91: 3011.0747 | I91: 3017.0874 | J91: 3098.1453 | K91: 3091.5735 | L91: 3123.88 | M91: 3122.3267 | N91: 3173.7046 | O91: 3187.541 | P91: 3208.1182 | Q91: 3211.726 | R91: 3230.6714 | S91: 3237.3264 | T91: 3219.3005 | U91: 3206.3965 | V91: 3230.9082 | W91: 3223.1606 | X91: 3240.4202 | Y91: 3240.293 | Z91: 3259.6052 | AA91: 3261.793 | AB91: 3300.8767 | AC91: 3318.734 | AD91: 3322.4255 | AE91: 3308.5115 | AF91: 3288.659 | AG91: 3324.084 | AH91: 3348.1538 | AI91: 3324.2905 | AJ91: 3323.6724 | AK91: 3333.0364 | AL91: 3340.0386 | AM91: 3343.0085 | AN91: 3354.7505 | AO91: 3378.6108 | AP91: 3387.2783 | AQ91: 3397.184 | AR91: 3397.184
A92: Bandhan Multi-Factor Fund | B92: Bandhan | C92: SECTORAL / THEMATIC | D92: 604.2756 | E92: 604.2756 | F92: 600.38 | G92: 600.69 | H92: 611.022 | I92: 615.8576 | J92: 634.9074 | K92: 638.5338 | L92: 650.19 | M92: 659.0724 | N92: 669.2387 | O92: 670.0029 | P92: 676.657 | Q92: 676.8333 | R92: 680.606 | S92: 676.8541 | T92: 673.2372 | U92: 668.1679 | V92: 674.7341 | W92: 675.9207 | X92: 679.491 | Y92: 672.5989 | Z92: 671.0822 | AA92: 673.7574 | AB92: 684.1083 | AC92: 684.7003 | AD92: 680.5339 | AE92: 672.6182 | AF92: 665.5438 | AG92: 670.3688 | AH92: 678.318 | AI92: 676.1908 | AJ92: 673.1562 | AK92: 676.139 | AL92: 678.0379 | AM92: 680.2535 | AN92: 679.5923 | AO92: 685.8962 | AP92: 684.3774 | AQ92: 688.796 | AR92: 688.796
... A100: Bank of India Business Cycle Fund | B100: Bank of India | C100: SECTORAL / THEMATIC | D100: 411.03 | E100: 410.56 | F100: 419.26 | G100: 419.2 | H100: 423.67 | I100: 425.44 | J100: 439.75 | K100: 439.18 | L100: 447.01 | M100: 447.01 | N100: 456.54 | O100: 458.42 | P100: 464.4 | Q100: 465.21 | R100: 468.63 | S100: 468.69 | T100: 467.14 | U100: 464.94 | V100: 471.01 | W100: 469.58 | X100: 471.11 | Y100: 466.61 | Z100: 469.04 | AA100: 468.2 | AB100: 471.08 | AC100: 474.72 | AD100: 472.72 | AE100: 463.35 | AF100: 455.49 | AG100: 455.84 | AH100: 458.34 | AI100: 457.45 | AJ100: 454.11 | AK100: 455.63 | AL100: 457.47 | AM100: 458.13 | AN100: 456.7 | AO100: 461.64 | AP100: 461.51 | AQ100: 463.04 | AR100: 458.51
A101: Bank of India Conservative Hybrid Fund | B101: Bank of India | C101: CONSERVATIVE HYRBID | D101: 64.4 | E101: 64.37 | G101: 64.52 | H101: 64.6 | I101: 64.59 | J101: 65.22 | K101: 65.25 | L101: 65.5 | M101: 65.5 | N101: 65.76 | O101: 65.84 | P101: 65.9 | Q101: 65.92 | R101: 66 | S101: 65.8 | T101: 65.63 | U101: 65.54 | V101: 65.74 | W101: 65.54 | X101: 65.6 | Y101: 65.35 | Z101: 65.5 | AA101: 65.48 | AB101: 65.8 | AC101: 65.51 | AD101: 65.45 | AE101: 63.89 | AF101: 63.57 | AG101: 63.8 | AH101: 63.99 | AI101: 63.8 | AJ101: 63.61 | AK101: 63.68 | AL101: 63.72 | AM101: 63.89 | AN101: 63.83 | AO101: 64.12 | AP101: 64.07 | AQ101: 64.19 | AR101: 63.98
A102: Bank of India Consumption Fund | B102: Bank of India | C102: SECTORAL / THEMATIC | D102: 345.57 | E102: 345 | F102: 349.72 | G102: 349.91 | H102: 354.26 | I102: 355.78 | J102: 364.89 | K102: 364.07 | L102: 368.29 | M102: 368.29 | N102: 371.65 | O102: 371.15 | P102: 375.62 | Q102: 373.61 | R102: 376.95 | S102: 375.6 | T102: 374.25 | U102: 372.05 | V102: 375.13 | W102: 374.28 | X102: 378.16 | Y102: 375.33 | Z102: 375.71 | AA102: 376.09 | AB102: 379.45 | AC102: 381.42 | AD102: 380.5 | AE102: 373.54 | AF102: 364.46 | AG102: 365.75 | AH102: 370.24 | AI102: 371.97 | AJ102: 371.06 | AK102: 373.52 | AL102: 373.05 | AM102: 367.46 | AN102: 367.42 | AO102: 369.04 | AP102: 367.09 | AQ102: 366.66 | AR102: 362.82
A103: Bank of India ELSS Tax Saver | B103: Bank of India | C103: ELSS | D103: 1260 | E103: 1259.66 | F103: 1284.21 | G103: 1277.08 | H103: 1290.94 | I103: 1297.97 | J103: 1344.36 | K103: 1343.29 | L103: 1364.49 | M103: 1364.49 | N103: 1387.86 | O103: 1401.1 | P103: 1413.52 | Q103: 1417.57 | R103: 1424.85 | S103: 1427.25 | T103: 1419.47 | U103: 1407.36 | V103: 1424.05 | W103: 1417.63 | X103: 1421.78 | Y103: 1402.59 | Z103: 1412.42 | AA103: 1411.17 | AB103: 1423.42 | AC103: 1429.56 | AD103: 1418.28 | AE103: 1397.47 | AF103: 1377.29 | AG103: 1387.54 | AH103: 1392.17 | AI103: 1382.69 | AJ103: 1368.34 | AK103: 1369.72 | AL103: 1372.61 | AM103: 1380.12 | AN103: 1377.78 | AO103: 1391.92 | AP103: 1392.24 | AQ103: 1396.8 | AR103: 1380.82
A104: Bank of India Flexi Cap Fund | B104: Bank of India | C104: FLEXI CAP | D104: 2030.73 | E104: 2033.61 | F104: 2085.35 | G104: 2082.52 | H104: 2115.3 | I104: 2131.85 | J104: 2210.74 | K104: 2212.24 | L104: 2247.55 | M104: 2247.55 | N104: 2296.11 | O104: 2325.76 | P104: 2351.74 | Q104: 2359.66 | R104: 2377.14 | S104: 2379.55 | T104: 2374.59 | U104: 2357.7 | V104: 2390.03 | W104: 2388.13 | X104: 2403.3 | Y104: 2387.56 | Z104: 2407.95 | AA104: 2416.38 | AB104: 2442.81 | AC104: 2464.2 | AD104: 2466.95 | AE104: 2432 | AF104: 2392.89 | AG104: 2412.86 | AH104: 2424.88 | AI104: 2413.93 | AJ104: 2395.73 | AK104: 2401.33 | AL104: 2409.48 | AM104: 2428.44 | AN104: 2432.16 | AO104: 2460.31 | AP104: 2468.97 | AQ104: 2476.54 | AR104: 2460.84
A105: Bank of India Large & Mid Cap Fund | B105: Bank of India | C105: LARGE & MID CAP | D105: 420.98 | E105: 421.84 | F105: 429.57 | G105: 430.54 | H105: 435.64 | I105: 437.36 | J105: 451.13 | K105: 449.6 | L105: 454.62 | M105: 454.62 | N105: 460.91 | O105: 464.2 | P105: 468.67 | Q105: 466.4 | R105: 469.23 | S105: 467.58 | T105: 466.92 | U105: 463.96 | V105: 469.35 | W105: 469.39 | X105: 471.61 | Y105: 468.3 | Z105: 471.44 | AA105: 472.92 | AB105: 478.24 | AC105: 479.19 | AD105: 478.15 | AE105: 472.4 | AF105: 464.21 | AG105: 467.47 | AH105: 471.92 | AI105: 471.25 | AJ105: 470.72 | AK105: 472.03 | AL105: 473.32 | AM105: 475.31 | AN105: 476.35 | AO105: 479.81 | AP105: 478.92 | AQ105: 477.79 | AR105: 472.45
A106: Bank of India Large Cap Fund | B106: Bank of India | C106: LARGE CAP | D106: 188.55 | E106: 188.17 | F106: 192.19 | G106: 192.69 | H106: 196.18 | I106: 197.64 | J106: 204.86 | K106: 204.71 | L106: 207.79 | M106: 207.79 | N106: 211.24 | O106: 212.3 | P106: 214.67 | Q106: 214.62 | R106: 216.32 | S106: 214.76 | T106: 213.62 | U106: 212.16 | V106: 213.7 | W106: 212.79 | X106: 214.42 | Y106: 212.6 | Z106: 213.88 | AA106: 213.89 | AB106: 216.45 | AC106: 217.75 | AD106: 216.41 | AE106: 213.09 | AF106: 208.94 | AG106: 210.14 | AH106: 211.84 | AI106: 211.72 | AJ106: 210.45 | AK106: 210.33 | AL106: 210.79 | AM106: 211.32 | AN106: 211.57 | AO106: 214.46 | AP106: 214.64 | AQ106: 214.81 | AR106: 213.23
A107: Bank of India Manufacturing & Infrastructure Fund | B107: Bank of India | C107: SECTORAL / THEMATIC | D107: 647.79 | E107: 647.14 | F107: 660.72 | G107: 659.8 | H107: 667.36 | I107: 671.17 | J107: 693.86 | K107: 694.96 | L107: 705.73 | M107: 705.73 | N107: 720.49 | O107: 726.86 | P107: 733.04 | Q107: 732.52 | R107: 736.11 | S107: 739.54 | T107: 740.71 | U107: 734.59 | V107: 746.59 | W107: 750.99 | X107: 756.45 | Y107: 755.26 | Z107: 765.99 | AA107: 765.8 | AB107: 770.55 | AC107: 779.52 | AD107: 777.55 | AE107: 769.02 | AF107: 758.78 | AG107: 766.54 | AH107: 772.57 | AI107: 772.05 | AJ107: 768.07 | AK107: 769.12 | AL107: 772.01 | AM107: 778.28 | AN107: 778.12 | AO107: 784.92 | AP107: 790.49 | AQ107: 791.55 | AR107: 787.52
A108: Bank of India Mid & Small Cap Equity & Debt Fund | B108: Bank of India | C108: AGGRESSIVE HYBRID | D108: 1281.24 | E108: 1281.95 | F108: 1312.06 | G108: 1308.21 | H108: 1325.3 | I108: 1328.55 | J108: 1368.61 | K108: 1371.25 | L108: 1390.77 | M108: 1390.77 | N108: 1414.63 | O108: 1433.76 | P108: 1447.81 | Q108: 1451.66 | R108: 1465.3 | S108: 1474.14 | T108: 1479.73 | U108: 1473.08 | V108: 1493.36 | W108: 1491 | X108: 1494.85 | Y108: 1481.51 | Z108: 1490.09 | AA108: 1497.3 | AB108: 1510.75 | AC108: 1529.51 | AD108: 1531.79 | AE108: 1521.61 | AF108: 1498.67 | AG108: 1512.98 | AH108: 1526.96 | AI108: 1520.76 | AJ108: 1514.04 | AK108: 1517.32 | AL108: 1525.44 | AM108: 1540.13 | AN108: 1539.67 | AO108: 1549.99 | AP108: 1560.42 | AQ108: 1565.19 | AR108: 1551.03
A109: Bank of India Mid Cap Fund | B109: Bank of India | C109: MID CAP | D109: 638.04 | E109: 638.38 | F109: 652.42 | G109: 650.6 | H109: 660.01 | I109: 659.79 | J109: 681.55 | K109: 684.4 | L109: 694.42 | M109: 694.42 | N109: 706.46 | O109: 713.72 | P109: 722.99 | Q109: 723.46 | R109: 728.11 | S109: 729.19 | T109: 729.05 | U109: 723.93 | V109: 730.52 | W109: 731.01 | X109: 727.87 | Y109: 719.78 | Z109: 721.34 | AA109: 724.17 | AB109: 731.9 | AC109: 741.24 | AD109: 741.09 | AE109: 735.2 | AF109: 722.94 | AG109: 730.6 | AH109: 737.41 | AI109: 729.86 | AJ109: 724.44 | AK109: 727.39 | AL109: 731.46 | AM109: 735.41 | AN109: 733.44 | AO109: 736.52 | AP109: 734.59 | AQ109: 732.33 | AR109: 721.48
A110: Bank of India Multi Asset Allocation Fund | B110: Bank of India | C110: MULTI ASSET ALLOCATION | D110: 337 | E110: 337.12 | G110: 339.28 | H110: 341.97 | I110: 342.06 | J110: 348.41 | K110: 349.59 | L110: 351.66 | M110: 351.66 | N110: 355.23 | O110: 356.19 | P110: 357.56 | Q110: 358.01 | R110: 358.97 | S110: 358.39 | T110: 357.5 | U110: 356.53 | V110: 358.15 | W110: 357.2 | X110: 357.94 | Y110: 357.41 | Z110: 357.76 | AA110: 358.85 | AB110: 361.39 | AC110: 362.61 | AD110: 362.47 | AE110: 359.51 | AF110: 357 | AG110: 360.07 | AH110: 360.58 | AI110: 358.71 | AJ110: 357.25 | AK110: 357.93 | AL110: 358.18 | AM110: 359.1 | AN110: 359.05 | AO110: 360.79 | AP110: 360.26 | AQ110: 360.33 | AR110: 358.95
A111: Bank of India Multicap Fund | B111: Bank of India | C111: MULTI CAP | D111: 937.4 | E111: 937.78 | F111: 956.75 | G111: 959.11 | H111: 971.5 | I111: 977.2 | J111: 1010.05 | K111: 1009.86 | L111: 1020.91 | M111: 1020.91 | N111: 1040.06 | O111: 1047.79 | P111: 1060.33 | Q111: 1056.05 | R111: 1064.57 | S111: 1064.32 | T111: 1065.08 | U111: 1057.89 | V111: 1071.9 | W111: 1072.35 | X111: 1079.34 | Y111: 1074.39 | Z111: 1085 | AA111: 1088.64 | AB111: 1100.87 | AC111: 1109.46 | AD111: 1106.16 | AE111: 1094.36 | AF111: 1076.01 | AG111: 1084.18 | AH111: 1092.29 | AI111: 1091.85 | AJ111: 1089.16 | AK111: 1094.93 | AL111: 1098.16 | AM111: 1105.58 | AN111: 1106.54 | AO111: 1114.53 | AP111: 1116.58 | AQ111: 1114.86 | AR111: 1108.31
A112: Bank of India Small Cap Fund | B112: Bank of India | C112: SMALL CAP | D112: 1770.32 | E112: 1770.44 | F112: 1830.19 | G112: 1833.14 | H112: 1864.04 | I112: 1875.68 | J112: 1944.43 | K112: 1952.31 | L112: 1991.21 | M112: 1991.21 | N112: 2041.64 | O112: 2074.26 | P112: 2104.43 | Q112: 2111.26 | R112: 2123.37 | S112: 2139.14 | T112: 2141.3 | U112: 2134.71 | V112: 2181.4 | W112: 2172.9 | X112: 2178.58 | Y112: 2167.57 | Z112: 2189.36 | AA112: 2203.18 | AB112: 2224.63 | AC112: 2261.89 | AD112: 2272.24 | AE112: 2252.55 | AF112: 2205.37 | AG112: 2218.56 | AH112: 2212.57 | AI112: 2206.16 | AJ112: 2187.59 | AK112: 2199.85 | AL112: 2210.43 | AM112: 2240.59 | AN112: 2238.52 | AO112: 2258.65 | AP112: 2285.83 | AQ112: 2304.87 | AR112: 2313.66
A113: Baroda BNP Paribas Aggressive Hybrid Fund | B113: Baroda BNP Paribas | C113: AGGRESSIVE HYBRID | D113: 1145.51 | E113: 1145.57 | F113: 1161.08 | G113: 1161.5 | H113: 1161.5 | I113: 1173.38 | J113: 1205.67 | K113: 1204.16 | L113: 1217.01 | M113: 1211.13 | N113: 1225.89 | O113: 1229.19 | P113: 1236.07 | Q113: 1236.1 | R113: 1241.9 | S113: 1238.44 | T113: 1235.53 | U113: 1226.62 | V113: 1237.53 | W113: 1238.26 | X113: 1243.06 | Y113: 1239.06 | Z113: 1243.25 | AA113: 1242.01 | AB113: 1251.33 | AC113: 1258.42 | AD113: 1252.81 | AE113: 1238.15 | AF113: 1220.41 | AG113: 1220.25 | AH113: 1229.91 | AI113: 1228.24 | AJ113: 1227.24 | AK113: 1229.33 | AL113: 1233.04 | AM113: 1231.91 | AN113: 1232.94 | AO113: 1243.08 | AP113: 1241.31 | AQ113: 1243.2 | AR113: 1234.23
A114: Baroda BNP Paribas Arbitrage Fund | B114: Baroda BNP Paribas | C114: ARBITRAGE | D114: 1252.83 | E114: 1276.21 | F114: 1275.66 | G114: 1276.83 | H114: 1276.83 | I114: 1278.79 | J114: 1265.14 | K114: 1265.31 | L114: 1269.91 | M114: 1268.05 | N114: 1265.76 | O114: 1275.5 | P114: 1275.37 | Q114: 1277.65 | R114: 1275.32 | S114: 1276.05 | T114: 1277.18 | U114: 1255.65 | V114: 1255.12 | W114: 1259.57 | X114: 1258.54 | Y114: 1255.41 | Z114: 1257.17 | AA114: 1247.81 | AB114: 1242.87 | AC114: 1248.87 | AD114: 1248.8 | AE114: 1254.53 | AF114: 1254.88 | AG114: 1255.8 | AH114: 1260.31 | AI114: 1262.82 | AJ114: 1267.55 | AK114: 1268.93 | AL114: 1266.32 | AM114: 1266.69 | AN114: 1266.26 | AO114: 1268.65 | AP114: 1263.87 | AQ114: 1266.91 | AR114: 1267.43
A115: Baroda BNP Paribas Balanced Advantage Fund | B115: Baroda BNP Paribas | C115: DYNAMIC ASSET ALLOCATION OR BALANCED ADVANTAGE | D115: 4364.42 | E115: 4365.23 | F115: 4421.08 | G115: 4402.28 | H115: 4402.28 | I115: 4452.23 | J115: 4588.65 | K115: 4584.57 | L115: 4636.95 | M115: 4621.87 | N115: 4690.05 | O115: 4701.83 | P115: 4743.73 | Q115: 4753.28 | R115: 4780.82 | S115: 4775.1 | T115: 4752.77 | U115: 4716.63 | V115: 4764.37 | W115: 4756.61 | X115: 4778.46 | Y115: 4755.77 | Z115: 4790.55 | AA115: 4797.95 | AB115: 4855.3 | AC115: 4896.93 | AD115: 4888.5 | AE115: 4841.9 | AF115: 4764.81 | AG115: 4775.09 | AH115: 4822.47 | AI115: 4813.2 | AJ115: 4802.02 | AK115: 4819.11 | AL115: 4838.71 | AM115: 4839.08 | AN115: 4839.88 | AO115: 4893.55 | AP115: 4895.36 | AQ115: 4920.8 | AR115: 4873.99
A116: Baroda BNP Paribas Banking and Financial Services Fund | B116: Baroda BNP Paribas | C116: SECTORAL / THEMATIC | D116: 345.42 | E116: 345.56 | F116: 353.55 | G116: 353.27 | H116: 353.27 | I116: 362.59 | J116: 382.43 | K116: 378.31 | L116: 388.43 | M116: 387.27 | N116: 393.41 | O116: 393.13 | P116: 394.8 | Q116: 395.17 | R116: 400.78 | S116: 398.77 | T116: 392.79 | U116: 391.2 | V116: 393.11 | W116: 389.87 | X116: 392.02 | Y116: 389.4 | Z116: 391.22 | AA116: 390.15 | AB116: 399.35 | AC116: 402.2 | AD116: 398.31 | AE116: 393.37 | AF116: 387.25 | AG116: 387.63 | AH116: 392.92 | AI116: 392.09 | AJ116: 390.03 | AK116: 390.46 | AL116: 391.36 | AM116: 391.02 | AN116: 393.18 | AO116: 401.75 | AP116: 401.18 | AQ116: 399.5 | AR116: 394.76
A117: Baroda BNP Paribas Business Conglomerates Fund | B117: Baroda BNP Paribas | C117: SECTORAL / THEMATIC | D117: 621.95 | E117: 621.82 | F117: 634 | G117: 632.63 | H117: 632.63 | I117: 641.16 | J117: 667.29 | K117: 664.12 | L117: 673.18 | M117: 666.78 | N117: 679.47 | O117: 682.73 | P117: 685.05 | Q117: 685.82 | R117: 687.49 | S117: 683.46 | T117: 678.04 | U117: 671.59 | V117: 682.33 | W117: 680.4 | X117: 685 | Y117: 679.85 | Z117: 684.5 | AA117: 685.44 | AB117: 693.03 | AC117: 693.44 | AD117: 691.98 | AE117: 680.95 | AF117: 665.86 | AG117: 666.4 | AH117: 672.71 | AI117: 669.06 | AJ117: 666.49 | AK117: 667.57 | AL117: 669.69 | AM117: 666.5 | AN117: 667.64 | AO117: 676.52 | AP117: 675.09 | AQ117: 675.91 | AR117: 666.7
A118: Baroda BNP Paribas Business Cycle Fund | B118: Baroda BNP Paribas | C118: SECTORAL / THEMATIC | D118: 507.45 | E118: 507.16 | F118: 515.75 | G118: 516.12 | H118: 516.12 | I118: 522.77 | J118: 541.36 | K118: 540.61 | L118: 548.33 | M118: 544.29 | N118: 553.12 | O118: 555.62 | P118: 559.89 | Q118: 560.29 | R118: 564.15 | S118: 562.39 | T118: 560.77 | U118: 555.33 | V118: 562.32 | W118: 561.17 | X118: 563.35 | Y118: 560.89 | Z118: 564.86 | AA118: 563.96 | AB118: 569.2 | AC118: 572.86 | AD118: 569.96 | AE118: 562.05 | AF118: 551.1 | AG118: 550.25 | AH118: 554.22 | AI118: 552.65 | AJ118: 552.47 | AK118: 553.02 | AL118: 556.11 | AM118: 556.39 | AN118: 556.8 | AO118: 563.17 | AP118: 561.16 | AQ118: 562.33 | AR118: 557.12
A119: Baroda BNP Paribas Conservative Hybrid Fund | B119: Baroda BNP Paribas | C119: CONSERVATIVE HYRBID | D119: 790.61 | E119: 790.59 | G119: 792.41 | H119: 792.41 | I119: 795.65 | J119: 805.7 | K119: 805.1 | L119: 808.84 | M119: 807.09 | N119: 811.24 | O119: 811.85 | P119: 813.21 | Q119: 813.46 | R119: 815.01 | S119: 814.1 | T119: 812.5 | U119: 810.37 | V119: 812.59 | W119: 811.92 | X119: 812.29 | Y119: 811.02 | Z119: 813.6 | AA119: 813.34 | AB119: 816.99 | AC119: 818.92 | AD119: 930.8 | AE119: 926.89 | AF119: 922.3 | AG119: 921.99 | AH119: 923.75 | AI119: 922.88 | AJ119: 920.68 | AK119: 921.8 | AL119: 922.29 | AM119: 920.7 | AN119: 921.09 | AO119: 924.74 | AP119: 924.12 | AQ119: 925.11 | AR119: 935.78
A120: Baroda BNP Paribas Dividend Yield Fund | B120: Baroda BNP Paribas | C120: DIVIDEND YIELD | D120: 603.95 | E120: 603.21 | F120: 610.92 | G120: 610.15 | H120: 610.15 | I120: 616.1 | J120: 632.31 | K120: 631.35 | L120: 638.68 | M120: 634.57 | N120: 644.77 | O120: 645.87 | P120: 651.38 | Q120: 650.78 | R120: 652.3 | S120: 647.97 | T120: 644.22 | U120: 638.02 | V120: 645.86 | W120: 645.92 | X120: 650.14 | Y120: 644.96 | Z120: 648.21 | AA120: 648 | AB120: 651.28 | AC120: 652.43 | AD120: 647.28 | AE120: 639.91 | AF120: 629.35 | AG120: 630.24 | AH120: 634.04 | AI120: 631.56 | AJ120: 629.81 | AK120: 629.04 | AL120: 630.85 | AM120: 630.13 | AN120: 630.08 | AO120: 635.14 | AP120: 633 | AQ120: 632.95 | AR120: 624.59
A121: Baroda BNP Paribas ELSS Tax Saver Fund | B121: Baroda BNP Paribas | C121: ELSS | D121: 808.69 | E121: 808.58 | F121: 822.62 | G121: 822.95 | H121: 822.95 | I121: 833.81 | J121: 866.34 | K121: 863.12 | L121: 876.28 | M121: 869 | N121: 882.31 | O121: 885.69 | P121: 892.67 | Q121: 893.8 | R121: 899.14 | S121: 895.05 | T121: 889.54 | U121: 882.07 | V121: 888.96 | W121: 887.32 | X121: 891.51 | Y121: 886.99 | Z121: 894.09 | AA121: 894.54 | AB121: 904.18 | AC121: 911.28 | AD121: 906.08 | AE121: 890.06 | AF121: 871.28 | AG121: 870.42 | AH121: 877.37 | AI121: 873.67 | AJ121: 869.84 | AK121: 872.37 | AL121: 876.94 | AM121: 876.02 | AN121: 877.36 | AO121: 889.97 | AP121: 888.85 | AQ121: 891.44 | AR121: 881.86
A122: Baroda BNP Paribas ESG Best-in-Class Strategy Fund | B122: Baroda BNP Paribas | C122: SECTORAL / THEMATIC | D122: 636.54 | E122: 634.62 | F122: 640.33 | G122: 641.54 | H122: 641.54 | I122: 644.37 | J122: 655.26 | K122: 654.74 | L122: 658.89 | M122: 654.78 | N122: 659.77 | O122: 659.46 | P122: 660.75 | Q122: 661.15 | R122: 664.77 | S122: 660.48 | T122: 654.66 | U122: 646.07 | V122: 651.51 | W122: 648.53 | X122: 651.39 | Y122: 646.93 | Z122: 648.05 | AA122: 648.09 | AB122: 655.52 | AC122: 657.21 | AD122: 653.87 | AE122: 643.51 | AF122: 631.48 | AG122: 628.73 | AH122: 635.19 | AI122: 634.82 | AJ122: 634.51 | AK122: 637.42 | AL122: 637.89 | AM122: 636.47 | AN122: 638.03 | AO122: 643.69 | AP122: 642.21 | AQ122: 643.55 | AR122: 636.48
A123: Baroda BNP Paribas Energy Opportunities Fund | B123: Baroda BNP Paribas | C123: SECTORAL / THEMATIC | D123: 640.2 | E123: 640.29 | F123: 648.61 | G123: 646.8 | H123: 646.8 | I123: 648.19 | J123: 656.88 | K123: 661.71 | L123: 666.11 | M123: 665.52 | N123: 676.12 | O123: 678.91 | P123: 688.28 | Q123: 691.57 | R123: 691.63 | S123: 698.79 | T123: 699.9 | U123: 698.16 | V123: 707.39 | W123: 712.97 | X123: 712.91 | Y123: 712.41 | Z123: 714.92 | AA123: 713.82 | AB123: 710.11 | AC123: 714.7 | AD123: 709.74 | AE123: 700.27 | AF123: 692.86 | AG123: 695.06 | AH123: 702.04 | AI123: 696.46 | AJ123: 691.73 | AK123: 693.26 | AL123: 701.72 | AM123: 701.2 | AN123: 697.55 | AO123: 699.94 | AP123: 700.63 | AQ123: 711.16 | AR123: 700.3
A124: Baroda BNP Paribas Equity Savings Fund | B124: Baroda BNP Paribas | C124: EQUITY SAVINGS | D124: 265.36 | E124: 268.37 | F124: 270.07 | G124: 269.89 | H124: 269.89 | I124: 271.09 | J124: 275.33 | K124: 275.44 | L124: 277.02 | M124: 276.6 | N124: 279.82 | O124: 280.14 | P124: 281.31 | Q124: 282.09 | R124: 282.73 | S124: 282.25 | T124: 281.35 | U124: 279.68 | V124: 281.19 | W124: 281.11 | X124: 281.53 | Y124: 280.83 | Z124: 281.69 | AA124: 281.63 | AB124: 283.09 | AC124: 284.64 | AD124: 277.95 | AE124: 276.14 | AF124: 273.67 | AG124: 273.02 | AH124: 274 | AI124: 273.52 | AJ124: 272.92 | AK124: 273.53 | AL124: 273.65 | AM124: 273.37 | AN124: 273.79 | AO124: 275.51 | AP124: 275.99 | AQ124: 275.82 | AR124: 274.54
A125: Baroda BNP Paribas Flexi Cap Fund | B125: Baroda BNP Paribas | C125: FLEXI CAP | D125: 1086.84 | E125: 1086.8 | F125: 1106.28 | G125: 1104.85 | H125: 1104.85 | I125: 1116.53 | J125: 1158.64 | K125: 1155.9 | L125: 1173.3 | M125: 1166.79 | N125: 1186.27 | O125: 1191.73 | P125: 1201.49 | Q125: 1202.39 | R125: 1210.01 | S125: 1209.27 | T125: 1203.84 | U125: 1192.97 | V125: 1205.35 | W125: 1203.22 | X125: 1206.54 | Y125: 1199.8 | Z125: 1210.52 | AA125: 1211.41 | AB125: 1226.69 | AC125: 1238.25 | AD125: 1235.48 | AE125: 1220.18 | AF125: 1195.82 | AG125: 1194.49 | AH125: 1207.94 | AI125: 1203.85 | AJ125: 1204.47 | AK125: 1208.77 | AL125: 1215.83 | AM125: 1214.05 | AN125: 1213.16 | AO125: 1226 | AP125: 1227.17 | AQ125: 1235.08 | AR125: 1221.77
A126: Baroda BNP Paribas Focused Fund | B126: Baroda BNP Paribas | C126: FOCUSED | D126: 595.83 | E126: 595.52 | F126: 603.05 | G126: 602.22 | H126: 602.22 | I126: 614.6 | J126: 635.36 | K126: 634.28 | L126: 639.61 | M126: 638.55 | N126: 649.51 | O126: 651.52 | P126: 655.93 | Q126: 656.27 | R126: 660.02 | S126: 654.19 | T126: 650.06 | U126: 643.77 | V126: 651.27 | W126: 652.12 | X126: 657.64 | Y126: 655.37 | Z126: 655.53 | AA126: 653.39 | AB126: 662.91 | AC126: 664.62 | AD126: 663.88 | AE126: 656.5 | AF126: 643.73 | AG126: 644.56 | AH126: 651.72 | AI126: 652.01 | AJ126: 652.64 | AK126: 654.53 | AL126: 654.65 | AM126: 652.99 | AN126: 651.43 | AO126: 660.54 | AP126: 658.81 | AQ126: 658.13 | AR126: 647.79
A127: Baroda BNP Paribas Health and Wellness Fund | B127: Baroda BNP Paribas | C127: SECTORAL / THEMATIC | D127: 516.03 | E127: 515.19 | F127: 512.96 | G127: 506.42 | H127: 506.42 | I127: 510.57 | J127: 515.4 | K127: 518.11 | L127: 521.05 | M127: 521.07 | N127: 527.16 | O127: 525.85 | P127: 527.97 | Q127: 525.8 | R127: 524.04 | S127: 523.66 | T127: 527.47 | U127: 521.37 | V127: 531.57 | W127: 529.4 | X127: 531.8 | Y127: 530.21 | Z127: 540.42 | AA127: 540.08 | AB127: 548.38 | AC127: 551 | AD127: 552.36 | AE127: 556.4 | AF127: 545.57 | AG127: 545.26 | AH127: 553.28 | AI127: 555.55 | AJ127: 557.35 | AK127: 561.3 | AL127: 559.14 | AM127: 560.4 | AN127: 555.66 | AO127: 557.64 | AP127: 554.63 | AQ127: 553.31 | AR127: 544.34
A128: Baroda BNP Paribas India Consumption Fund | B128: Baroda BNP Paribas | C128: SECTORAL / THEMATIC | D128: 1301.66 | E128: 1301.42 | F128: 1324.29 | G128: 1324.64 | H128: 1324.64 | I128: 1343.74 | J128: 1387.76 | K128: 1382.68 | L128: 1404.54 | M128: 1386.2 | N128: 1406.6 | O128: 1405.22 | P128: 1421.94 | Q128: 1423.59 | R128: 1441.02 | S128: 1438.94 | T128: 1424.76 | U128: 1413.98 | V128: 1425.08 | W128: 1418.91 | X128: 1434.45 | Y128: 1419.16 | Z128: 1421.42 | AA128: 1424.34 | AB128: 1438.57 | AC128: 1437.75 | AD128: 1439.42 | AE128: 1416.76 | AF128: 1389.59 | AG128: 1389.89 | AH128: 1401.29 | AI128: 1402.54 | AJ128: 1393.96 | AK128: 1391.82 | AL128: 1390.57 | AM128: 1389.19 | AN128: 1388.99 | AO128: 1400.14 | AP128: 1396.13 | AQ128: 1401 | AR128: 1383.44
A129: Baroda BNP Paribas Innovation Fund | B129: Baroda BNP Paribas | C129: SECTORAL / THEMATIC | D129: 781.67 | E129: 779.38 | F129: 793.31 | G129: 792.66 | H129: 792.66 | I129: 798.71 | J129: 829.61 | K129: 829.92 | L129: 845.35 | M129: 845.57 | N129: 856.69 | O129: 863.02 | P129: 868.99 | Q129: 870.03 | R129: 873.01 | S129: 870.81 | T129: 868.99 | U129: 863.57 | V129: 871.38 | W129: 871.45 | X129: 874.17 | Y129: 869.73 | Z129: 876.2 | AA129: 876.37 | AB129: 886.13 | AC129: 896.68 | AD129: 892.67 | AE129: 882.39 | AF129: 863.54 | AG129: 861.28 | AH129: 869.77 | AI129: 868.54 | AJ129: 863.24 | AK129: 871.18 | AL129: 875.03 | AM129: 875.13 | AN129: 871.9 | AO129: 878.1 | AP129: 880.09 | AQ129: 883.32 | AR129: 874.25
A130: Baroda BNP Paribas Large Cap Fund | B130: Baroda BNP Paribas | C130: LARGE CAP | D130: 2344.17 | E130: 2344.2 | F130: 2377.64 | G130: 2380.56 | H130: 2380.56 | I130: 2416.82 | J130: 2497.72 | K130: 2489.38 | L130: 2521.03 | M130: 2505.38 | N130: 2547.03 | O130: 2553.63 | P130: 2573.87 | Q130: 2576.69 | R130: 2596.15 | S130: 2586.05 | T130: 2571.84 | U130: 2546.9 | V130: 2576.15 | W130: 2573.9 | X130: 2592.07 | Y130: 2578.67 | Z130: 2589.32 | AA130: 2584.4 | AB130: 2607.81 | AC130: 2616.32 | AD130: 2598.69 | AE130: 2560.75 | AF130: 2518.31 | AG130: 2519.06 | AH130: 2546.35 | AI130: 2540.08 | AJ130: 2542.43 | AK130: 2545.94 | AL130: 2555.11 | AM130: 2548.1 | AN130: 2550.77 | AO130: 2581.7 | AP130: 2576.37 | AQ130: 2582.16 | AR130: 2552
A131: Baroda BNP Paribas Large and Mid Cap Fund | B131: Baroda BNP Paribas | C131: LARGE & MID CAP | D131: 1538.21 | E131: 1538.44 | F131: 1564.88 | G131: 1560.77 | H131: 1560.77 | I131: 1584.46 | J131: 1648.26 | K131: 1644.69 | L131: 1669.63 | M131: 1665.28 | N131: 1693.95 | O131: 1703.62 | P131: 1723.17 | Q131: 1728.58 | R131: 1738.36 | S131: 1732.36 | T131: 1719.12 | U131: 1702.23 | V131: 1724.94 | W131: 1722.38 | X131: 1727.66 | Y131: 1717.72 | Z131: 1732.41 | AA131: 1733.35 | AB131: 1763.97 | AC131: 1779.79 | AD131: 1773.5 | AE131: 1749.93 | AF131: 1713.61 | AG131: 1715.82 | AH131: 1735.96 | AI131: 1733.74 | AJ131: 1733.72 | AK131: 1742.42 | AL131: 1748.7 | AM131: 1748.31 | AN131: 1749.78 | AO131: 1770.89 | AP131: 1769.88 | AQ131: 1776.24 | AR131: 1752.22
... A139: Canara Robeco Banking and Financial Services Fund | B139: Canara Robeco | C139: SECTORAL / THEMATIC | D139: 533.4039 | E139: 524.1462 | F139: 529.7142 | G139: 530.398 | H139: 539.3455 | I139: 540.6793 | J139: 560.0267 | K139: 557.0782 | L139: 567.6415 | M139: 565.2105 | N139: 570.365 | O139: 571.2445 | P139: 575.8674 | Q139: 571.7446 | R139: 579.8657 | S139: 576.8423 | T139: 574.4302 | U139: 572.4162 | V139: 572.2156 | W139: 570.1435 | X139: 572.1109 | Y139: 569.0791 | Z139: 577.0899 | AA139: 577.4199 | AB139: 591.1584 | AC139: 596.1552 | AD139: 586.8294 | AE139: 579.0904 | AF139: 567.176 | AG139: 566.5002 | AH139: 575.0475 | AI139: 574.2286 | AJ139: 570.7805 | AK139: 572.0739 | AL139: 573.813 | AM139: 572.0996 | AN139: 575.5216 | AO139: 586.0903 | AP139: 585.7465 | AQ139: 581.955 | AR139: 574.8494
A140: Canara Robeco Conservative Hybrid Fund | B140: Canara Robeco | C140: CONSERVATIVE HYRBID | D140: 850.0326 | E140: 849.3517 | G140: 853.3786 | H140: 856.4361 | I140: 856.3447 | J140: 865.0077 | K140: 862.3978 | L140: 866.0099 | M140: 864.5343 | N140: 869.1793 | O140: 868.9929 | P140: 870.3984 | Q140: 870.8864 | R140: 871.425 | S140: 871.1422 | T140: 868.8095 | U140: 866.2008 | V140: 868.7142 | W140: 866.2888 | X140: 866.5592 | Y140: 863.5721 | Z140: 865.9614 | AA140: 865.5102 | AB140: 870.0602 | AC140: 870.5025 | AD140: 868.2335 | AE140: 865.1619 | AF140: 857.9111 | AG140: 856.438 | AH140: 858.6645 | AI140: 857.99 | AJ140: 856.9496 | AK140: 857.6623 | AL140: 856.3769 | AM140: 855.2187 | AN140: 855.7572 | AO140: 858.6973 | AP140: 857.0639 | AQ140: 856.7488 | AR140: 853.3741
A141: Canara Robeco Consumption Fund | B141: Canara Robeco | C141: SECTORAL / THEMATIC | D141: 1705.0303 | E141: 1705.0303 | F141: 1741.4374 | G141: 1739.3112 | H141: 1770.1318 | I141: 1770.3912 | J141: 1854.4255 | K141: 1838.8455 | L141: 1870.5337 | M141: 1851.7228 | N141: 1887.3359 | O141: 1891.7048 | P141: 1914.5345 | Q141: 1914.7219 | R141: 1941.8339 | S141: 1938.4047 | T141: 1912.949 | U141: 1900.4697 | V141: 1917.8663 | W141: 1911.9105 | X141: 1919.0413 | Y141: 1901.1632 | Z141: 1910.7448 | AA141: 1908.1262 | AB141: 1943.5916 | AC141: 1948.3864 | AD141: 1943.3907 | AE141: 1903.0892 | AF141: 1860.6909 | AG141: 1861.22 | AH141: 1888.5083 | AI141: 1888.9641 | AJ141: 1885.9169 | AK141: 1895.0208 | AL141: 1890.1761 | AM141: 1889.7555 | AN141: 1895.9908 | AO141: 1911.5092 | AP141: 1908.7537 | AQ141: 1913.8049 | AR141: 1883.531
A142: Canara Robeco ELSS Tax Saver Fund | B142: Canara Robeco | C142: ELSS | D142: 7816.385 | E142: 7809.637 | F142: 7957.861 | G142: 7961.528 | H142: 8056.7563 | I142: 8089.998 | J142: 8399.942 | K142: 8342.839 | L142: 8459.46 | M142: 8402.654 | N142: 8544.057 | O142: 8563.216 | P142: 8625.792 | Q142: 8634.321 | R142: 8722.69 | S142: 8697.732 | T142: 8628.227 | U142: 8544.878 | V142: 8625.303 | W142: 8576.919 | X142: 8601.845 | Y142: 8529.181 | Z142: 8584.948 | AA142: 8572.391 | AB142: 8697.513 | AC142: 8740.772 | AD142: 8682.2705 | AE142: 8549.01 | AF142: 8369.244 | AG142: 8374.176 | AH142: 8453.091 | AI142: 8439.138 | AJ142: 8417.601 | AK142: 8440.431 | AL142: 8459 | AM142: 8484.43 | AN142: 8504.911 | AO142: 8587.337 | AP142: 8561.496 | AQ142: 8587.491 | AR142: 8476.068
A143: Canara Robeco Equity Hybrid Fund | B143: Canara Robeco | C143: AGGRESSIVE HYBRID | D143: 10254.118 | E143: 10252.533 | F143: 10407.849 | G143: 10402.063 | H143: 10505.022 | I143: 10531.469 | J143: 10857.524 | K143: 10817.068 | L143: 10933.871 | M143: 10873.22 | N143: 11030.114 | O143: 11064.618 | P143: 11139.977 | Q143: 11152.729 | R143: 11220.854 | S143: 11201.532 | T143: 11130.276 | U143: 11048.802 | V143: 11123.15 | W143: 11084.25 | X143: 11103.774 | Y143: 11023.795 | Z143: 11073.686 | AA143: 11054.053 | AB143: 11190.45 | AC143: 11227.645 | AD143: 11183.027 | AE143: 11044.876 | AF143: 10858.275 | AG143: 10863.854 | AH143: 10952.177 | AI143: 10936.545 | AJ143: 10904.183 | AK143: 10939.138 | AL143: 10947.73 | AM143: 10964.351 | AN143: 10983.895 | AO143: 11080.811 | AP143: 11056.376 | AQ143: 11076.678 | AR143: 10952.959
A144: Canara Robeco Flexi Cap Fund | B144: Canara Robeco | C144: FLEXI CAP | D144: 11922.4 | E144: 11922.059 | F144: 12149.617 | G144: 12161.152 | H144: 12322.662 | I144: 12374.22 | J144: 12861.398 | K144: 12765.326 | L144: 12944.235 | M144: 12847.726 | N144: 13092.018 | O144: 13141.569 | P144: 13246.16 | Q144: 13271.482 | R144: 13379.029 | S144: 13320.327 | T144: 13202.926 | U144: 13064.171 | V144: 13180.934 | W144: 13137.072 | X144: 13197.668 | Y144: 13082.73 | Z144: 13151.608 | AA144: 13137.913 | AB144: 13333.928 | AC144: 13378.816 | AD144: 13320.461 | AE144: 13154.849 | AF144: 12882.183 | AG144: 12883.242 | AH144: 13031.129 | AI144: 13017.895 | AJ144: 13008.857 | AK144: 13036.973 | AL144: 13066.712 | AM144: 13079.069 | AN144: 13106.972 | AO144: 13228.763 | AP144: 13181.837 | AQ144: 13206.515 | AR144: 13012.593
A145: Canara Robeco Focused Fund | B145: Canara Robeco | C145: FOCUSED | D145: 2509.2756 | E145: 2510.0088 | F145: 2553.5813 | G145: 2550.383 | H145: 2588.6636 | I145: 2595.7056 | J145: 2699.8699 | K145: 2675.405 | L145: 2719.9487 | M145: 2702.39 | N145: 2748.855 | O145: 2760.1235 | P145: 2775.7344 | Q145: 2783.9255 | R145: 2810.0618 | S145: 2789.8843 | T145: 2763.2415 | U145: 2736.935 | V145: 2757.1777 | W145: 2743.551 | X145: 2756.1746 | Y145: 2725.4082 | Z145: 2739.9817 | AA145: 2733.049 | AB145: 2776.8054 | AC145: 2782.451 | AD145: 2758.848 | AE145: 2718.9324 | AF145: 2666.1294 | AG145: 2667.9463 | AH145: 2698.0261 | AI145: 2689.1987 | AJ145: 2688.122 | AK145: 2695.9214 | AL145: 2702.1436 | AM145: 2705.92 | AN145: 2713.7375 | AO145: 2738.1614 | AP145: 2725.4226 | AQ145: 2725.5422 | AR145: 2685.032
A146: Canara Robeco Infrastructure Fund | B146: Canara Robeco | C146: SECTORAL / THEMATIC | D146: 864.4878 | E146: 864.2531 | F146: 884.0978 | G146: 884.1746 | H146: 892.9968 | I146: 894.793 | J146: 923.3823 | K146: 926.6259 | L146: 940.6264 | M146: 938.1509 | N146: 959.4322 | O146: 965.109 | P146: 977.034 | Q146: 982.2516 | R146: 985.7127 | S146: 991.0024 | T146: 991.33 | U146: 985.7331 | V146: 998.3578 | W146: 999.8306 | X146: 998.8775 | Y146: 988.7776 | Z146: 994.1774 | AA146: 995.3645 | AB146: 1000.0938 | AC146: 1006.6182 | AD146: 1000.6734 | AE146: 982.3206 | AF146: 962.5482 | AG146: 968.7029 | AH146: 978.0294 | AI146: 973.9868 | AJ146: 967.2553 | AK146: 970.185 | AL146: 978.1105 | AM146: 984.2129 | AN146: 983.4339 | AO146: 990.0126 | AP146: 991.0092 | AQ146: 1005.129 | AR146: 992.1835
A147: Canara Robeco Large Cap Fund | B147: Canara Robeco | C147: LARGE CAP | D147: 15240.598 | E147: 15235.018 | F147: 15489.66 | G147: 15499.799 | H147: 15713.025 | I147: 15827.662 | J147: 16456.854 | K147: 16292.918 | L147: 16511.732 | M147: 16391.57 | N147: 16670.78 | O147: 16699.918 | P147: 16813.643 | Q147: 16827.883 | R147: 16987.432 | S147: 16880.08 | T147: 16712.094 | U147: 16544.186 | V147: 16665.379 | W147: 16584.945 | X147: 16682.256 | Y147: 16542.19 | Z147: 16618.156 | AA147: 16604.854 | AB147: 16848.377 | AC147: 16874.693 | AD147: 16768.975 | AE147: 16549.043 | AF147: 16226.004 | AG147: 16234.192 | AH147: 16405.357 | AI147: 16378.675 | AJ147: 16383.229 | AK147: 16393.56 | AL147: 16408.186 | AM147: 16393.98 | AN147: 16444.64 | AO147: 16635.354 | AP147: 16555.586 | AQ147: 16577.393 | AR147: 16328.531
A148: Canara Robeco Large and Mid Cap Fund | B148: Canara Robeco | C148: LARGE & MID CAP | D148: 22209.164 | E148: 22203.193 | F148: 22723.271 | G148: 22724.44 | H148: 23061.17 | I148: 23121.42 | J148: 23969.625 | K148: 23859.432 | L148: 24227.158 | M148: 24095.252 | N148: 24544.268 | O148: 24721.861 | P148: 24911.29 | Q148: 24990.463 | R148: 25225.393 | S148: 25169.662 | T148: 24974.578 | U148: 24706.406 | V148: 24956.451 | W148: 24887.588 | X148: 24901.838 | Y148: 24674.945 | Z148: 24816.32 | AA148: 24831.338 | AB148: 25225.893 | AC148: 25360.873 | AD148: 25283.762 | AE148: 24984.004 | AF148: 24357.457 | AG148: 24355.416 | AH148: 24583.72 | AI148: 24571.363 | AJ148: 24541.14 | AK148: 24688.342 | AL148: 24714.48 | AM148: 24721.953 | AN148: 24748.736 | AO148: 24958.562 | AP148: 24909.15 | AQ148: 24913.82 | AR148: 24497.516
A149: Canara Robeco Manufacturing Fund | B149: Canara Robeco | C149: SECTORAL / THEMATIC | D149: 1406.9117 | E149: 1405.3424 | F149: 1438.9603 | G149: 1433.4415 | H149: 1442.6595 | I149: 1447.6917 | J149: 1499.9016 | K149: 1510.8813 | L149: 1538.5509 | M149: 1528.9629 | N149: 1558.0262 | O149: 1573.5204 | P149: 1593.4432 | Q149: 1599.5416 | R149: 1604.6809 | S149: 1609.0273 | T149: 1601.5702 | U149: 1589.3143 | V149: 1613.1078 | W149: 1612.1241 | X149: 1618.177 | Y149: 1608.6659 | Z149: 1633.6854 | AA149: 1639.5583 | AB149: 1658.7329 | AC149: 1681.76 | AD149: 1673.8738 | AE149: 1651.1611 | AF149: 1611.3185 | AG149: 1619.1892 | AH149: 1636.6167 | AI149: 1626.1134 | AJ149: 1613.0681 | AK149: 1619.7971 | AL149: 1628.2351 | AM149: 1642.5405 | AN149: 1638.7384 | AO149: 1648.432 | AP149: 1651.5774 | AQ149: 1661.7725 | AR149: 1642.7015
A150: Canara Robeco Mid Cap Fund | B150: Canara Robeco | C150: MID CAP | D150: 3876.2854 | E150: 3879.5906 | F150: 3972.066 | G150: 3969.8464 | H150: 4040.7014 | I150: 4054.9438 | J150: 4212.4277 | K150: 4224.9463 | L150: 4304.4834 | M150: 4291.7197 | N150: 4376.5645 | O150: 4411.173 | P150: 4457.193 | Q150: 4482.0415 | R150: 4524.1646 | S150: 4521.2964 | T150: 4490.9473 | U150: 4451.058 | V150: 4508.0103 | W150: 4490.56 | X150: 4491.134 | Y150: 4451.588 | Z150: 4496.679 | AA150: 4501.4688 | AB150: 4600.0933 | AC150: 4655.1797 | AD150: 4655.896 | AE150: 4603.477 | AF150: 4490.7256 | AG150: 4497.4575 | AH150: 4540.3613 | AI150: 4527.33 | AJ150: 4527.569 | AK150: 4567.806 | AL150: 4586.5635 | AM150: 4604.799 | AN150: 4604.115 | AO150: 4639.9116 | AP150: 4650.6 | AQ150: 4669.8574 | AR150: 4619.0996
A151: Canara Robeco Multi Asset Allocation Fund | B151: Canara Robeco | C151: MULTI ASSET ALLOCATION | D151: 1197.2621 | E151: 1188.0455 | F151: 1204.5895 | G151: 1200.829 | H151: 1216.1736 | I151: 1217.2068 | J151: 1253.6322 | K151: 1245.9788 | L151: 1260.4535 | M151: 1252.4703 | N151: 1270.7761 | O151: 1274.763 | P151: 1280.15 | Q151: 1283.0046 | R151: 1294.0292 | S151: 1290.6626 | T151: 1280.501 | U151: 1276.1971 | V151: 1280.6224 | W151: 1275.3198 | X151: 1276.1898 | Y151: 1271.2161 | Z151: 1277.2665 | AA151: 1275.2856 | AB151: 1295.9824 | AC151: 1302.158 | AD151: 1297.0803 | AE151: 1286.6034 | AF151: 1272.4661 | AG151: 1283.8394 | AH151: 1294.2186 | AI151: 1288.3384 | AJ151: 1289.314 | AK151: 1293.0051 | AL151: 1294.1947 | AM151: 1294.3809 | AN151: 1295.632 | AO151: 1303.6963 | AP151: 1301.2976 | AQ151: 1300.6246 | AR151: 1288.9021
A152: Canara Robeco Multi Cap Fund | B152: Canara Robeco | C152: MULTI CAP | D152: 4677.377 | E152: 4679.321 | F152: 4772.609 | G152: 4767.933 | H152: 4830.607 | I152: 4839.6694 | J152: 5017.2964 | K152: 4999.307 | L152: 5076.136 | M152: 5049.5737 | N152: 5146.072 | O152: 5179.1963 | P152: 5229.5835 | Q152: 5237.6455 | R152: 5293.8545 | S152: 5293.438 | T152: 5255.127 | U152: 5205.842 | V152: 5264.4985 | W152: 5249.914 | X152: 5273.621 | Y152: 5229.324 | Z152: 5274.829 | AA152: 5273.235 | AB152: 5360.681 | AC152: 5388.1963 | AD152: 5367.764 | AE152: 5310.4146 | AF152: 5188.0947 | AG152: 5188.777 | AH152: 5241.853 | AI152: 5243.8984 | AJ152: 5232.9907 | AK152: 5270.4985 | AL152: 5270.762 | AM152: 5277.432 | AN152: 5281.817 | AO152: 5327.088 | AP152: 5319.9727 | AQ152: 5323.4453 | AR152: 5250.1
...

Sheet Detail1
A1: Details for Sum of Net flows_Apr26 - Fund Name: Nippon India, Category: AGGRESSIVE HYBRID (+)
A3: Scheme Name | B3: Fund Name | C3: Category | D3: 30-Mar-2026 | E3: 31-Mar-2026 | F3: 01-Apr-2026 | G3: 02-Apr-2026 | H3: 06-Apr-2026 | I3: 07-Apr-2026 | J3: 08-Apr-2026 | K3: 09-Apr-2026 | L3: 10-Apr-2026 | M3: 13-Apr-2026 | N3: 15-Apr-2026 | O3: 16-Apr-2026 | P3: 17-Apr-2026 | Q3: 20-Apr-2026 | R3: 21-Apr-2026 | S3: 22-Apr-2026 | T3: 23-Apr-2026 | U3: 24-Apr-2026 | V3: 27-Apr-2026 | W3: 28-Apr-2026 | X3: 29-Apr-2026 | Y3: 30-Apr-2026 | Z3: 04-May-2026 | AA3: 05-May-2026 | AB3: 06-May-2026 | AC3: 07-May-2026 | AD3: 08-May-2026 | AE3: 11-May-2026 | AF3: 12-May-2026 | AG3: 13-May-2026 | AH3: 14-May-2026 | AI3: 15-May-2026 | AJ3: 18-May-2026 | AK3: 19-May-2026 | AL3: 20-May-2026 | AM3: 21-May-2026 | AN3: 22-May-2026 | AO3: 25-May-2026 | AP3: 26-May-2026 | AQ3: 27-May-2026 | AR3: 29-May-2026 | AS3: Net flows_Apr26 | AT3: Net flows_maY26
A4: Nippon India Vision Large & Mid Cap Fund | B4: Nippon India | C4: LARGE & MID CAP | D4: 0 | E4: 11.566631 | F4: 0.011501751 | G4: 1.9579882 | H4: 13.69859 | I4: 14.3282 | J4: 7.8482896 | K4: 8.2683646 | L4: 11.785942 | M4: 11.132678 | N4: 5.5364291 | O4: 9.0776588 | P4: 5.3533921 | Q4: 7.4138738 | R4: 9.1112088 | S4: 3.1740726 | T4: 7.0133835 | U4: 2.9108903 | V4: 4.3881501 | W4: 7.9786046 | X4: 5.9513786 | Y4: 2.8673587 | Z4: -53.475838 | AA4: 65.028846 | AB4: 7.5837153 | AC4: 4.0743811 | AD4: 3.0123418 | AE4: 3.0643466 | AF4: 8.6364013 | AG4: 7.2155732 | AH4: 6.8710927 | AI4: 3.9985399 | AJ4: 6.6158385 | AK4: 5.682428 | AL4: 3.4724958 | AM4: 8.555569 | AN4: 2.4086919 | AO4: -57.01692 | AP4: 61.147234 | AQ4: 3.0010873 | AR4: 4.0001222 | AS4: 139.80796 | AT4: 93.875948
A5: Nippon India Value Fund | B5: Nippon India | C5: VALUE | D5: 0 | E5: -0.29158135 | F5: 0.016943193 | G5: -0.50686763 | H5: 3.7221237 | I5: 6.1055342 | J5: 2.4430446 | K5: 2.971952 | L5: 12.810244 | M5: 6.7316151 | N5: 1.610945 | O5: 3.3560788 | P5: 1.7681249 | Q5: -0.022986398 | R5: 2.9111841 | S5: 0.50390122 | T5: -1.558907 | U5: 1.7644355 | V5: 0.50258314 | W5: 2.0656661 | X5: 1.362712 | Y5: -0.16998538 | Z5: -61.726633 | AA5: 64.858879 | AB5: 2.8402497 | AC5: 0.29834723 | AD5: -1.7191444 | AE5: -0.61423965 | AF5: 6.3216273 | AG5: 2.3287621 | AH5: 1.0341541 | AI5: 1.7670554 | AJ5: 2.9845877 | AK5: 0.87864234 | AL5: -0.0030163291 | AM5: 1.9242895 | AN5: -0.4642405 | AO5: -107.9597 | AP5: 105.87528 | AQ5: -0.98251864 | AR5: -0.37871058 | AS5: 48.388341 | AT5: 17.263671
A6: Nippon India US Equity Opportunities Fund | B6: Nippon India | C6: SECTORAL / THEMATIC | D6: 0 | E6: -19.623957 | F6: 19.194832 | G6: -0.04179608 | H6: 0.14448117 | I6: 0.26247294 | J6: 0.01135525 | K6: -0.13048726 | L6: -0.062330895 | M6: 0.27690567 | N6: -0.042342855 | O6: -0.16071674 | P6: -0.097367015 | Q6: -0.067145838 | R6: 0.079533863 | S6: -0.064338509 | T6: -0.082041312 | U6: -0.018707226 | V6: 0.0017943241 | W6: 0.02873094 | X6: 0.053569012 | Y6: -0.048449422 | Z6: 1.4796363 | AA6: -9.0098721 | AB6: 7.5819797 | AC6: 0.017250683 | AD6: 0.0025035866 | AE6: -0.032594726 | AF6: 0.13905614 | AG6: 0.0038701192 | AH6: -0.14452202 | AI6: -0.02677751 | AJ6: 0.069007699 | AK6: -0.001097729 | AL6: -0.047510534 | AM6: -0.0066066744 | AN6: -0.062643685 | AO6: 0 | AP6: -0.031942003 | AQ6: -0.054006684 | AR6: -0.024632837 | AS6: 19.237952 | AT6: -0.14890221
A7: Nippon India Taiwan Equity Fund | B7: Nippon India | C7: SECTORAL / THEMATIC | D7: 0 | E7: 14.91765 | F7: 0.0065451808 | G7: 6.2488167 | H7: 14.776019 | I7: 0.0055019895 | J7: 22.174146 | K7: 10.101069 | L7: 14.607836 | M7: 19.491986 | N7: 33.88842 | O7: 27.590492 | P7: 29.805126 | Q7: 33.227382 | R7: 63.910053 | S7: 15.327799 | T7: 1.6142248 | U7: -1.0362301 | V7: -2.3896623 | W7: -2.2352248 | X7: -0.48916773 | Y7: -0.67666401 | Z7: -53.637769 | AA7: 52.751238 | AB7: -0.18597973 | AC7: 0.11028365 | AD7: -0.16102154 | AE7: -0.098649308 | AF7: -1.580212 | AG7: -0.6984962 | AH7: -0.73319826 | AI7: -0.77498922 | AJ7: -0.65463732 | AK7: -2.1068988 | AL7: -1.8789329 | AM7: -3.4491575 | AN7: -0.37269717 | AO7: -46.229904 | AP7: 46.491646 | AQ7: -0.38538776 | AR7: -0.62449658 | AS7: 285.94847 | AT7: -14.21926
A8: Nippon India Small Cap Fund | B8: Nippon India | C8: SMALL CAP | D8: 0 | E8: 17.348655 | F8: 0.40763202 | G8: 21.626387 | H8: 75.039234 | I8: 177.30046 | J8: 37.887791 | K8: 24.398721 | L8: 12.893368 | M8: 133.32574 | N8: 40.389297 | O8: 84.625722 | P8: 8.7277285 | Q8: -4.0136836 | R8: 70.945483 | S8: -1.8209897 | T8: -0.14407149 | U8: 2.4531542 | V8: 1.644671 | W8: 72.899103 | X8: 36.89758 | Y8: -8.6673731 | Z8: -831.3146 | AA8: 966.933 | AB8: 105.15148 | AC8: 15.256682 | AD8: 26.869035 | AE8: 13.173292 | AF8: 150.25907 | AG8: 10.520493 | AH8: -9.0844403 | AI8: -1.6624391 | AJ8: 80.640552 | AK8: 28.163528 | AL8: -7.1777605 | AM8: 44.754164 | AN8: 2.1087093 | AO8: -638.29984 | AP8: 699.93344 | AQ8: 3.2720424 | AR8: 5.9612937 | AS8: 786.81596 | AT8: 665.4577
A9: Nippon India Quant Fund | B9: Nippon India | C9: SECTORAL / THEMATIC | D9: 0 | E9: 0.032668547 | F9: 0.00050621464 | G9: 0.11808362 | H9: 0.11032423 | I9: 2.0062134 | J9: 0.12402079 | K9: 0.064373399 | L9: 0.075309137 | M9: 0.33969265 | N9: 0.059721232 | O9: 0.062716095 | P9: 0.16477424 | Q9: -0.23997589 | R9: 0.13191229 | S9: 0.073593014 | T9: 0.16635087 | U9: 0.087042649 | V9: 0.052189813 | W9: 0.085543461 | X9: -0.097553976 | Y9: 0.10336877 | Z9: -0.86797174 | AA9: 1.1258882 | AB9: 0.13646875 | AC9: 0.11031463 | AD9: -0.021238364 | AE9: 0.075308726 | AF9: 0.19273509 | AG9: 0.08456925 | AH9: 0.00056712626 | AI9: 0.040650319 | AJ9: 0.089099594 | AK9: 0.038780268 | AL9: -0.49334124 | AM9: 0.048224003 | AN9: -0.063298513 | AO9: -1.2073215 | AP9: 1.3348615 | AQ9: 0.058638925 | AR9: -0.38351702 | AS9: 3.488206 | AT9: 0.29941804
A10: Nippon India Power & Infra Fund | B10: Nippon India | C10: SECTORAL / THEMATIC | D10: 0 | E10: -1.4895033 | F10: 0.02883354 | G10: -1.1113374 | H10: 5.7789346 | I10: 8.8888464 | J10: 2.9038606 | K10: 2.7540552 | L10: 3.0948686 | M10: 7.3521419 | N10: 3.3269914 | O10: 4.5298671 | P10: 1.3724166 | Q10: -0.48544313 | R10: 2.6645588 | S10: 7.8845852 | T10: -1.3075157 | U10: 0.65709531 | V10: 3.6687454 | W10: 5.7802993 | X10: 2.8345601 | Y10: -0.54143138 | Z10: -87.141588 | AA10: 101.44284 | AB10: 9.8133548 | AC10: 7.9684035 | AD10: 8.7358823 | AE10: 8.6425939 | AF10: 12.812332 | AG10: 2.9416287 | AH10: 1.972283 | AI10: 1.6877223 | AJ10: 6.2907134 | AK10: 1.7730627 | AL10: 1.0220554 | AM10: 2.2046991 | AN10: 1.8049083 | AO10: -64.286722 | AP10: 69.657138 | AQ10: 1.830381 | AR10: 3.9652902 | AS10: 60.074932 | AT10: 93.136978
A11: Nippon India Pharma Fund | B11: Nippon India | C11: SECTORAL / THEMATIC | D11: 0 | E11: 0.10933668 | F11: 0.048717862 | G11: 0.16578258 | H11: 3.9074308 | I11: 3.6351415 | J11: 0.81697052 | K11: 3.2525489 | L11: 0.026560289 | M11: 4.1934017 | N11: 0.42577513 | O11: 2.0436935 | P11: 0.47598482 | Q11: 0.26630636 | R11: 2.2308775 | S11: 0.13780944 | T11: -0.35697234 | U11: 0.4532695 | V11: -0.96430498 | W11: 1.6254364 | X11: 1.8092696 | Y11: 0.82615068 | Z11: -104.8072 | AA11: 104.47903 | AB11: 0.41935986 | AC11: 0.059403877 | AD11: 1.1324731 | AE11: 0.67258996 | AF11: 4.77241 | AG11: -8.1533927 | AH11: -1.8508934 | AI11: -0.30677302 | AJ11: 2.4571582 | AK11: 2.6519662 | AL11: -0.37004985 | AM11: 1.3338057 | AN11: 0.6847604 | AO11: -13.151621 | AP11: 15.245242 | AQ11: 1.6423645 | AR11: 1.2864173 | AS11: 25.01985 | AT11: 8.1970484
A12: Nippon India Multicap Fund | B12: Nippon India | C12: MULTI CAP | D12: 0 | E12: 25.793084 | F12: 0.18413188 | G12: 15.566666 | H12: 78.031317 | I12: 139.88483 | J12: 49.513658 | K12: 68.052104 | L12: 51.979358 | M12: 95.105063 | N12: 48.130854 | O12: 66.590346 | P12: 36.707271 | Q12: 34.263658 | R12: 68.13966 | S12: 26.706301 | T12: 27.988727 | U12: 24.43363 | V12: 26.427868 | W12: 54.14932 | X12: 39.125903 | Y12: 29.148039 | Z12: -435.48258 | AA12: 509.55969 | AB12: 63.394138 | AC12: 29.982595 | AD12: 37.135893 | AE12: 37.958392 | AF12: 90.37405 | AG12: 39.62909 | AH12: 15.675068 | AI12: 9.4758962 | AJ12: 50.816915 | AK12: 30.827698 | AL12: 13.030578 | AM12: 32.437075 | AN12: 11.903046 | AO12: -419.29631 | AP12: 460.78034 | AQ12: 18.467907 | AR12: 17.048334 | AS12: 980.1287 | AT12: 613.71781
A13: Nippon India Multi Asset Allocation Fund | B13: Nippon India | C13: MULTI ASSET ALLOCATION | D13: 0 | E13: -30.920379 | F13: 50.541658 | G13: 23.061959 | H13: 44.198611 | I13: 61.764137 | J13: 31.134152 | K13: 44.453311 | L13: 57.231992 | M13: 38.305894 | N13: 34.038815 | O13: 34.912156 | P13: 42.37099 | Q13: 30.777711 | R13: 37.69116 | S13: 30.245 | T13: 33.644256 | U13: 28.752135 | V13: 29.984878 | W13: 33.537031 | X13: 30.183727 | Y13: 23.885185 | Z13: -38.568474 | AA13: 16.209703 | AB13: 131.75853 | AC13: 32.143331 | AD13: 30.461758 | AE13: 29.647918 | AF13: 46.689402 | AG13: 36.886709 | AH13: 28.833661 | AI13: 30.556561 | AJ13: 28.064397 | AK13: 34.730506 | AL13: 19.912636 | AM13: 24.814709 | AN13: 21.218258 | AO13: -82.534868 | AP13: 136.67708 | AQ13: 24.763702 | AR13: 31.528713 | AS13: 740.71476 | AT13: 583.79423
A14: Nippon India MNC Fund | B14: Nippon India | C14: SECTORAL / THEMATIC | D14: 0 | E14: 0.21785024 | F14: -0.0015336241 | G14: 0.13081033 | H14: 0.38482871 | I14: 0.098821934 | J14: 0.15952118 | K14: 0.15768711 | L14: 0.28502142 | M14: 0.46024017 | N14: 0.33837785 | O14: 0.16964046 | P14: 0.0084723178 | Q14: -1.406223 | R14: -0.32225737 | S14: 0.10256138 | T14: -0.13833326 | U14: 0.11830358 | V14: 0.064446456 | W14: 0.050101363 | X14: -0.08026059 | Y14: 0.032822649 | Z14: -3.0023232 | AA14: 3.4857744 | AB14: 0.23676371 | AC14: 0.011490395 | AD14: 0.067005563 | AE14: 0.065343573 | AF14: 0.50869538 | AG14: 0.011186572 | AH14: 0.057112893 | AI14: 0.01633773 | AJ14: 2.0074699 | AK14: -0.056534796 | AL14: 0.23729161 | AM14: 0.10682243 | AN14: -0.044461435 | AO14: -2.3720479 | AP14: 2.2647159 | AQ14: -0.24186558 | AR14: 0.00011568736 | AS14: 0.61304902 | AT14: 3.3588928
A15: Nippon India Large Cap Fund | B15: Nippon India | C15: LARGE CAP | D15: 0 | E15: 48.242393 | F15: 0.33491888 | G15: 42.176817 | H15: 110.21139 | I15: 157.39648 | J15: 51.953504 | K15: 84.825856 | L15: 63.220698 | M15: 87.975624 | N15: 23.431 | O15: 53.973902 | P15: 45.459408 | Q15: 42.031373 | R15: 59.052175 | S15: 15.767314 | T15: 28.515382 | U15: 37.636593 | V15: 54.339902 | W15: 63.183554 | X15: 24.761077 | Y15: 20.25215 | Z15: -277.65745 | AA15: 413.77585 | AB15: 62.675524 | AC15: 27.183957 | AD15: 39.620514 | AE15: 13.905232 | AF15: 100.76298 | AG15: 33.019724 | AH15: -40.257892 | AI15: 27.498072 | AJ15: 54.352864 | AK15: 27.583485 | AL15: 7.7415022 | AM15: 24.850002 | AN15: 4.3791092 | AO15: -549.80002 | AP15: 584.6883 | AQ15: 3.9175979 | AR15: 13.709926 | AS15: 1066.4991 | AT15: 571.94928
... A27: Nippon India Active Momentum Fund | B27: Nippon India | C27: SECTORAL / THEMATIC | D27: 0 | E27: 1.151409 | F27: 0.003051832 | G27: 0.70618056 | H27: 2.185876 | I27: 1.751355 | J27: 0.66262755 | K27: 1.5469682 | L27: 1.9043911 | M27: 2.0216738 | N27: 0.89024374 | O27: 1.4775595 | P27: 0.69375387 | Q27: 0.50518059 | R27: 0.98525693 | S27: 0.50586276 | T27: 0.4417444 | U27: 0.73511533 | V27: 0.68128767 | W27: 1.2280182 | X27: 0.66381494 | Y27: 0.52924564 | Z27: -2.1941241 | AA27: 3.8510412 | AB27: 1.147511 | AC27: 0.9271052 | AD27: 1.2027733 | AE27: 0.71036188 | AF27: 1.4138719 | AG27: 0.84587691 | AH27: 0.16962499 | AI27: 0.56580772 | AJ27: 0.96385825 | AK27: -0.12138485 | AL27: 0.088264745 | AM27: -0.24272658 | AN27: 0.06744232 | AO27: -4.3232573 | AP27: 5.8813376 | AQ27: 0.7852004 | AR27: 0.91533554 | AS27: 20.119208 | AT27: 12.65392

Sheet Net Flows
A1: Scheme Name | B1: Fund Name | C1: Category | D1: 46111 | E1: 46112 | F1: 46113 | G1: 46114 | H1: 46118 | I1: 46119 | J1: 46120 | K1: 46121 | L1: 46122 | M1: 46125 | N1: 46127 | O1: 46128 | P1: 46129 | Q1: 46132 | R1: 46133 | S1: 46134 | T1: 46135 | U1: 46136 | V1: 46139 | W1: 46140 | X1: 46141 | Y1: 46142 | Z1: 46146 | AA1: 46147 | AB1: 46148 | AC1: 46149 | AD1: 46150 | AE1: 46153 | AF1: 46154 | AG1: 46155 | AH1: 46156 | AI1: 46157 | AJ1: 46160 | AK1: 46161 | AL1: 46162 | AM1: 46163 | AN1: 46164 | AO1: 46167 | AP1: 46168 | AQ1: 46169 | AR1: 46171 | AS1: Net flows_Apr26 | AT1: Net flows_maY26
A2: 360 ONE Balanced Hybrid Fund | B2: 360 ONE | C2: BALANCED HYBRID | D2: =0 -> 0 | E2: =IF(OR('Daily AUM'!E2="",NAV!E2=""),0,IFERROR(IF(OR(IFERROR(LOOKUP(2,1/(('Daily AUM'!$D2:D2<>"")*(NAV!$D2:D2<>"")),'Daily AUM'!$D2:D2),"")="",IFERROR(LOOKUP(2,1/(('Daily AUM'!$D2:D2<>"")*(NAV!$D2:D2<>"")),NAV!$D2:D2),"")=""),0,'Daily AUM'!E2-(IFERROR(LOOKUP(2,1/(('Daily AUM'!$D2:D2<>"")*(NAV!$D2:D2<>"")),'Daily AUM'!$D2:D2),"")*(NAV!E2/IFERROR(LOOKUP(2,1/(('Daily AUM'!$D2:D2<>"")*(NAV!$D2:D2<>"")),NAV!$D2:D2),"")))),0)) -> -0.041745215 | F2: =IF(OR('Daily AUM'!F2="",NAV!F2=""),0,IFERROR(IF(OR(IFERROR(LOOKUP(2,1/(('Daily AUM'!$D2:E2<>"")*(NAV!$D2:E2<>"")),'Daily AUM'!$D2:E2),"")="",IFERROR(LOOKUP(2,1/(('Daily AUM'!$D2:E2<>"")*(NAV!$D2:E2<>"")),NAV!$D2:E2),"")=""),0,'Daily AUM'!F2-(IFERROR(LOOKUP(2,1/(('Daily AUM'!$D2:E2<>"")*(NAV!$D2:E2<>"")),'Daily AUM'!$D2:E2),"")*(NAV!F2/IFERROR(LOOKUP(2,1/(('Daily AUM'!$D2:E2<>"")*(NAV!$D2:E2<>"")),NAV!$D2:E2),"")))),0)) -> 0 | G2: =IF(OR('Daily AUM'!G2="",NAV!G2=""),0,IFERROR(IF(OR(IFERROR(LOOKUP(2,1/(('Daily AUM'!$D2:F2<>"")*(NAV!$D2:F2<>"")),'Daily AUM'!$D2:F2),"")="",IFERROR(LOOKUP(2,1/(('Daily AUM'!$D2:F2<>"")*(NAV!$D2:F2<>"")),NAV!$D2:F2),"")=""),0,'Daily AUM'!G2-(IFERROR(LOOKUP(2,1/(('Daily AUM'!$D2:F2<>"")*(NAV!$D2:F2<>"")),'Daily AUM'!$D2:F2),"")*(NAV!G2/IFERROR(LOOKUP(2,1/(('Daily AUM'!$D2:F2<>"")*(NAV!$D2:F2<>"")),NAV!$D2:F2),"")))),0)) -> -0.46802543 | H2: =IF(OR('Daily AUM'!H2="",NAV!H2=""),0,IFERROR(IF(OR(IFERROR(LOOKUP(2,1/(('Daily AUM'!$D2:G2<>"")*(NAV!$D2:G2<>"")),'Daily AUM'!$D2:G2),"")="",IFERROR(LOOKUP(2,1/(('Daily AUM'!$D2:G2<>"")*(NAV!$D2:G2<>"")),NAV!$D2:G2),"")=""),0,'Daily AUM'!H2-(IFERROR(LOOKUP(2,1/(('Daily AUM'!$D2:G2<>"")*(NAV!$D2:G2<>"")),'Daily AUM'!$D2:G2),"")*(NAV!H2/IFERROR(LOOKUP(2,1/(('Daily AUM'!$D2:G2<>"")*(NAV!$D2:G2<>"")),NAV!$D2:G2),"")))),0)) -> -2.436013 | I2: =IF(OR('Daily AUM'!I2="",NAV!I2=""),0,IFERROR(IF(OR(IFERROR(LOOKUP(2,1/(('Daily AUM'!$D2:H2<>"")*(NAV!$D2:H2<>"")),'Daily AUM'!$D2:H2),"")="",IFERROR(LOOKUP(2,1/(('Daily AUM'!$D2:H2<>"")*(NAV!$D2:H2<>"")),NAV!$D2:H2),"")=""),0,'Daily AUM'!I2-(IFERROR(LOOKUP(2,1/(('Daily AUM'!$D2:H2<>"")*(NAV!$D2:H2<>"")),'Daily AUM'!$D2:H2),"")*(NAV!I2/IFERROR(LOOKUP(2,1/(('Daily AUM'!$D2:H2<>"")*(NAV!$D2:H2<>"")),NAV!$D2:H2),"")))),0)) -> -1.1244614 | J2: =IF(OR('Daily AUM'!J2="",NAV!J2=""),0,IFERROR(IF(OR(IFERROR(LOOKUP(2,1/(('Daily AUM'!$D2:I2<>"")*(NAV!$D2:I2<>"")),'Daily AUM'!$D2:I2),"")="",IFERROR(LOOKUP(2,1/(('Daily AUM'!$D2:I2<>"")*(NAV!$D2:I2<>"")),NAV!$D2:I2),"")=""),0,'Daily AUM'!J2-(IFERROR(LOOKUP(2,1/(('Daily AUM'!$D2:I2<>"")*(NAV!$D2:I2<>"")),'Daily AUM'!$D2:I2),"")*(NAV!J2/IFERROR(LOOKUP(2,1/(('Daily AUM'!$D2:I2<>"")*(NAV!$D2:I2<>"")),NAV!$D2:I2),"")))),0)) -> -0.49350535 | K2: =IF(OR('Daily AUM'!K2="",NAV!K2=""),0,IFERROR(IF(OR(IFERROR(LOOKUP(2,1/(('Daily AUM'!$D2:J2<>"")*(NAV!$D2:J2<>"")),'Daily AUM'!$D2:J2),"")="",IFERROR(LOOKUP(2,1/(('Daily AUM'!$D2:J2<>"")*(NAV!$D2:J2<>"")),NAV!$D2:J2),"")=""),0,'Daily AUM'!K2-(IFERROR(LOOKUP(2,1/(('Daily AUM'!$D2:J2<>"")*(NAV!$D2:J2<>"")),'Daily AUM'!$D2:J2),"")*(NAV!K2/IFERROR(LOOKUP(2,1/(('Daily AUM'!$D2:J2<>"")*(NAV!$D2:J2<>"")),NAV!$D2:J2),"")))),0)) -> -0.046604469 | L2: =IF(OR('Daily AUM'!L2="",NAV!L2=""),0,IFERROR(IF(OR(IFERROR(LOOKUP(2,1/(('Daily AUM'!$D2:K2<>"")*(NAV!$D2:K2<>"")),'Daily AUM'!$D2:K2),"")="",IFERROR(LOOKUP(2,1/(('Daily AUM'!$D2:K2<>"")*(NAV!$D2:K2<>"")),NAV!$D2:K2),"")=""),0,'Daily AUM'!L2-(IFERROR(LOOKUP(2,1/(('Daily AUM'!$D2:K2<>"")*(NAV!$D2:K2<>"")),'Daily AUM'!$D2:K2),"")*(NAV!L2/IFERROR(LOOKUP(2,1/(('Daily AUM'!$D2:K2<>"")*(NAV!$D2:K2<>"")),NAV!$D2:K2),"")))),0)) -> 0.027553872 | ... AR2: =IF(OR('Daily AUM'!AR2="",NAV!AR2=""),0,IFERROR(IF(OR(IFERROR(LOOKUP(2,1/(('Daily AUM'!$D2:AQ2<>"")*(NAV!$D2:AQ2<>"")),'Daily AUM'!$D2:AQ2),"")="",IFERROR(LOOKUP(2,1/(('Daily AUM'!$D2:AQ2<>"")*(NAV!$D2:AQ2<>"")),NAV!$D2:AQ2),"")=""),0,'Daily AUM'!AR2-(IFERROR(LOOKUP(2,1/(('Daily AUM'!$D2:AQ2<>"")*(NAV!$D2:AQ2<>"")),'Daily AUM'!$D2:AQ2),"")*(NAV!AR2/IFERROR(LOOKUP(2,1/(('Daily AUM'!$D2:AQ2<>"")*(NAV!$D2:AQ2<>"")),NAV!$D2:AQ2),"")))),0)) -> 0.035031513 | AS2: =SUM(F2:Y2) -> -16.676315 | AT2: =SUM(Z2:AR2) -> -10.683135
A3: 360 ONE Flexicap Fund | B3: 360 ONE | C3: FLEXI CAP | D3: =0 -> 0 | E3: =IF(OR('Daily AUM'!E3="",NAV!E3=""),0,IFERROR(IF(OR(IFERROR(LOOKUP(2,1/(('Daily AUM'!$D3:D3<>"")*(NAV!$D3:D3<>"")),'Daily AUM'!$D3:D3),"")="",IFERROR(LOOKUP(2,1/(('Daily AUM'!$D3:D3<>"")*(NAV!$D3:D3<>"")),NAV!$D3:D3),"")=""),0,'Daily AUM'!E3-(IFERROR(LOOKUP(2,1/(('Daily AUM'!$D3:D3<>"")*(NAV!$D3:D3<>"")),'Daily AUM'!$D3:D3),"")*(NAV!E3/IFERROR(LOOKUP(2,1/(('Daily AUM'!$D3:D3<>"")*(NAV!$D3:D3<>"")),NAV!$D3:D3),"")))),0)) -> 0.095282304 | F3: =IF(OR('Daily AUM'!F3="",NAV!F3=""),0,IFERROR(IF(OR(IFERROR(LOOKUP(2,1/(('Daily AUM'!$D3:E3<>"")*(NAV!$D3:E3<>"")),'Daily AUM'!$D3:E3),"")="",IFERROR(LOOKUP(2,1/(('Daily AUM'!$D3:E3<>"")*(NAV!$D3:E3<>"")),NAV!$D3:E3),"")=""),0,'Daily AUM'!F3-(IFERROR(LOOKUP(2,1/(('Daily AUM'!$D3:E3<>"")*(NAV!$D3:E3<>"")),'Daily AUM'!$D3:E3),"")*(NAV!F3/IFERROR(LOOKUP(2,1/(('Daily AUM'!$D3:E3<>"")*(NAV!$D3:E3<>"")),NAV!$D3:E3),"")))),0)) -> -2.2079396 | G3: =IF(OR('Daily AUM'!G3="",NAV!G3=""),0,IFERROR(IF(OR(IFERROR(LOOKUP(2,1/(('Daily AUM'!$D3:F3<>"")*(NAV!$D3:F3<>"")),'Daily AUM'!$D3:F3),"")="",IFERROR(LOOKUP(2,1/(('Daily AUM'!$D3:F3<>"")*(NAV!$D3:F3<>"")),NAV!$D3:F3),"")=""),0,'Daily AUM'!G3-(IFERROR(LOOKUP(2,1/(('Daily AUM'!$D3:F3<>"")*(NAV!$D3:F3<>"")),'Daily AUM'!$D3:F3),"")*(NAV!G3/IFERROR(LOOKUP(2,1/(('Daily AUM'!$D3:F3<>"")*(NAV!$D3:F3<>"")),NAV!$D3:F3),"")))),0)) -> 0.45576178 | H3: =IF(OR('Daily AUM'!H3="",NAV!H3=""),0,IFERROR(IF(OR(IFERROR(LOOKUP(2,1/(('Daily AUM'!$D3:G3<>"")*(NAV!$D3:G3<>"")),'Daily AUM'!$D3:G3),"")="",IFERROR(LOOKUP(2,1/(('Daily AUM'!$D3:G3<>"")*(NAV!$D3:G3<>"")),NAV!$D3:G3),"")=""),0,'Daily AUM'!H3-(IFERROR(LOOKUP(2,1/(('Daily AUM'!$D3:G3<>"")*(NAV!$D3:G3<>"")),'Daily AUM'!$D3:G3),"")*(NAV!H3/IFERROR(LOOKUP(2,1/(('Daily AUM'!$D3:G3<>"")*(NAV!$D3:G3<>"")),NAV!$D3:G3),"")))),0)) -> 1.0773882 | I3: =IF(OR('Daily AUM'!I3="",NAV!I3=""),0,IFERROR(IF(OR(IFERROR(LOOKUP(2,1/(('Daily AUM'!$D3:H3<>"")*(NAV!$D3:H3<>"")),'Daily AUM'!$D3:H3),"")="",IFERROR(LOOKUP(2,1/(('Daily AUM'!$D3:H3<>"")*(NAV!$D3:H3<>"")),NAV!$D3:H3),"")=""),0,'Daily AUM'!I3-(IFERROR(LOOKUP(2,1/(('Daily AUM'!$D3:H3<>"")*(NAV!$D3:H3<>"")),'Daily AUM'!$D3:H3),"")*(NAV!I3/IFERROR(LOOKUP(2,1/(('Daily AUM'!$D3:H3<>"")*(NAV!$D3:H3<>"")),NAV!$D3:H3),"")))),0)) -> 2.1313664 | J3: =IF(OR('Daily AUM'!J3="",NAV!J3=""),0,IFERROR(IF(OR(IFERROR(LOOKUP(2,1/(('Daily AUM'!$D3:I3<>"")*(NAV!$D3:I3<>"")),'Daily AUM'!$D3:I3),"")="",IFERROR(LOOKUP(2,1/(('Daily AUM'!$D3:I3<>"")*(NAV!$D3:I3<>"")),NAV!$D3:I3),"")=""),0,'Daily AUM'!J3-(IFERROR(LOOKUP(2,1/(('Daily AUM'!$D3:I3<>"")*(NAV!$D3:I3<>"")),'Daily AUM'!$D3:I3),"")*(NAV!J3/IFERROR(LOOKUP(2,1/(('Daily AUM'!$D3:I3<>"")*(NAV!$D3:I3<>"")),NAV!$D3:I3),"")))),0)) -> 0.30250132 | K3: =IF(OR('Daily AUM'!K3="",NAV!K3=""),0,IFERROR(IF(OR(IFERROR(LOOKUP(2,1/(('Daily AUM'!$D3:J3<>"")*(NAV!$D3:J3<>"")),'Daily AUM'!$D3:J3),"")="",IFERROR(LOOKUP(2,1/(('Daily AUM'!$D3:J3<>"")*(NAV!$D3:J3<>"")),NAV!$D3:J3),"")=""),0,'Daily AUM'!K3-(IFERROR(LOOKUP(2,1/(('Daily AUM'!$D3:J3<>"")*(NAV!$D3:J3<>"")),'Daily AUM'!$D3:J3),"")*(NAV!K3/IFERROR(LOOKUP(2,1/(('Daily AUM'!$D3:J3<>"")*(NAV!$D3:J3<>"")),NAV!$D3:J3),"")))),0)) -> 0.80716104 | L3: =IF(OR('Daily AUM'!L3="",NAV!L3=""),0,IFERROR(IF(OR(IFERROR(LOOKUP(2,1/(('Daily AUM'!$D3:K3<>"")*(NAV!$D3:K3<>"")),'Daily AUM'!$D3:K3),"")="",IFERROR(LOOKUP(2,1/(('Daily AUM'!$D3:K3<>"")*(NAV!$D3:K3<>"")),NAV!$D3:K3),"")=""),0,'Daily AUM'!L3-(IFERROR(LOOKUP(2,1/(('Daily AUM'!$D3:K3<>"")*(NAV!$D3:K3<>"")),'Daily AUM'!$D3:K3),"")*(NAV!L3/IFERROR(LOOKUP(2,1/(('Daily AUM'!$D3:K3<>"")*(NAV!$D3:K3<>"")),NAV!$D3:K3),"")))),0)) -> -0.96524578 | ... AR3: =IF(OR('Daily AUM'!AR3="",NAV!AR3=""),0,IFERROR(IF(OR(IFERROR(LOOKUP(2,1/(('Daily AUM'!$D3:AQ3<>"")*(NAV!$D3:AQ3<>"")),'Daily AUM'!$D3:AQ3),"")="",IFERROR(LOOKUP(2,1/(('Daily AUM'!$D3:AQ3<>"")*(NAV!$D3:AQ3<>"")),NAV!$D3:AQ3),"")=""),0,'Daily AUM'!AR3-(IFERROR(LOOKUP(2,1/(('Daily AUM'!$D3:AQ3<>"")*(NAV!$D3:AQ3<>"")),'Daily AUM'!$D3:AQ3),"")*(NAV!AR3/IFERROR(LOOKUP(2,1/(('Daily AUM'!$D3:AQ3<>"")*(NAV!$D3:AQ3<>"")),NAV!$D3:AQ3),"")))),0)) -> -0.15973335 | AS3: =SUM(F3:Y3) -> 3.6798477 | AT3: =SUM(Z3:AR3) -> -3.6769087
A4: 360 ONE Focused Fund | B4: 360 ONE | C4: FOCUSED | D4: =0 -> 0 | E4: =IF(OR('Daily AUM'!E4="",NAV!E4=""),0,IFERROR(IF(OR(IFERROR(LOOKUP(2,1/(('Daily AUM'!$D4:D4<>"")*(NAV!$D4:D4<>"")),'Daily AUM'!$D4:D4),"")="",IFERROR(LOOKUP(2,1/(('Daily AUM'!$D4:D4<>"")*(NAV!$D4:D4<>"")),NAV!$D4:D4),"")=""),0,'Daily AUM'!E4-(IFERROR(LOOKUP(2,1/(('Daily AUM'!$D4:D4<>"")*(NAV!$D4:D4<>"")),'Daily AUM'!$D4:D4),"")*(NAV!E4/IFERROR(LOOKUP(2,1/(('Daily AUM'!$D4:D4<>"")*(NAV!$D4:D4<>"")),NAV!$D4:D4),"")))),0)) -> 0.29295041 | F4: =IF(OR('Daily AUM'!F4="",NAV!F4=""),0,IFERROR(IF(OR(IFERROR(LOOKUP(2,1/(('Daily AUM'!$D4:E4<>"")*(NAV!$D4:E4<>"")),'Daily AUM'!$D4:E4),"")="",IFERROR(LOOKUP(2,1/(('Daily AUM'!$D4:E4<>"")*(NAV!$D4:E4<>"")),NAV!$D4:E4),"")=""),0,'Daily AUM'!F4-(IFERROR(LOOKUP(2,1/(('Daily AUM'!$D4:E4<>"")*(NAV!$D4:E4<>"")),'Daily AUM'!$D4:E4),"")*(NAV!F4/IFERROR(LOOKUP(2,1/(('Daily AUM'!$D4:E4<>"")*(NAV!$D4:E4<>"")),NAV!$D4:E4),"")))),0)) -> -11.136632 | G4: =IF(OR('Daily AUM'!G4="",NAV!G4=""),0,IFERROR(IF(OR(IFERROR(LOOKUP(2,1/(('Daily AUM'!$D4:F4<>"")*(NAV!$D4:F4<>"")),'Daily AUM'!$D4:F4),"")="",IFERROR(LOOKUP(2,1/(('Daily AUM'!$D4:F4<>"")*(NAV!$D4:F4<>"")),NAV!$D4:F4),"")=""),0,'Daily AUM'!G4-(IFERROR(LOOKUP(2,1/(('Daily AUM'!$D4:F4<>"")*(NAV!$D4:F4<>"")),'Daily AUM'!$D4:F4),"")*(NAV!G4/IFERROR(LOOKUP(2,1/(('Daily AUM'!$D4:F4<>"")*(NAV!$D4:F4<>"")),NAV!$D4:F4),"")))),0)) -> -14.95118 | H4: =IF(OR('Daily AUM'!H4="",NAV!H4=""),0,IFERROR(IF(OR(IFERROR(LOOKUP(2,1/(('Daily AUM'!$D4:G4<>"")*(NAV!$D4:G4<>"")),'Daily AUM'!$D4:G4),"")="",IFERROR(LOOKUP(2,1/(('Daily AUM'!$D4:G4<>"")*(NAV!$D4:G4<>"")),NAV!$D4:G4),"")=""),0,'Daily AUM'!H4-(IFERROR(LOOKUP(2,1/(('Daily AUM'!$D4:G4<>"")*(NAV!$D4:G4<>"")),'Daily AUM'!$D4:G4),"")*(NAV!H4/IFERROR(LOOKUP(2,1/(('Daily AUM'!$D4:G4<>"")*(NAV!$D4:G4<>"")),NAV!$D4:G4),"")))),0)) -> -8.0425818 | I4: =IF(OR('Daily AUM'!I4="",NAV!I4=""),0,IFERROR(IF(OR(IFERROR(LOOKUP(2,1/(('Daily AUM'!$D4:H4<>"")*(NAV!$D4:H4<>"")),'Daily AUM'!$D4:H4),"")="",IFERROR(LOOKUP(2,1/(('Daily AUM'!$D4:H4<>"")*(NAV!$D4:H4<>"")),NAV!$D4:H4),"")=""),0,'Daily AUM'!I4-(IFERROR(LOOKUP(2,1/(('Daily AUM'!$D4:H4<>"")*(NAV!$D4:H4<>"")),'Daily AUM'!$D4:H4),"")*(NAV!I4/IFERROR(LOOKUP(2,1/(('Daily AUM'!$D4:H4<>"")*(NAV!$D4:H4<>"")),NAV!$D4:H4),"")))),0)) -> -1.9648873 | J4: =IF(OR('Daily AUM'!J4="",NAV!J4=""),0,IFERROR(IF(OR(IFERROR(LOOKUP(2,1/(('Daily AUM'!$D4:I4<>"")*(NAV!$D4:I4<>"")),'Daily AUM'!$D4:I4),"")="",IFERROR(LOOKUP(2,1/(('Daily AUM'!$D4:I4<>"")*(NAV!$D4:I4<>"")),NAV!$D4:I4),"")=""),0,'Daily AUM'!J4-(IFERROR(LOOKUP(2,1/(('Daily AUM'!$D4:I4<>"")*(NAV!$D4:I4<>"")),'Daily AUM'!$D4:I4),"")*(NAV!J4/IFERROR(LOOKUP(2,1/(('Daily AUM'!$D4:I4<>"")*(NAV!$D4:I4<>"")),NAV!$D4:I4),"")))),0)) -> -1.8549681 | K4: =IF(OR('Daily AUM'!K4="",NAV!K4=""),0,IFERROR(IF(OR(IFERROR(LOOKUP(2,1/(('Daily AUM'!$D4:J4<>"")*(NAV!$D4:J4<>"")),'Daily AUM'!$D4:J4),"")="",IFERROR(LOOKUP(2,1/(('Daily AUM'!$D4:J4<>"")*(NAV!$D4:J4<>"")),NAV!$D4:J4),"")=""),0,'Daily AUM'!K4-(IFERROR(LOOKUP(2,1/(('Daily AUM'!$D4:J4<>"")*(NAV!$D4:J4<>"")),'Daily AUM'!$D4:J4),"")*(NAV!K4/IFERROR(LOOKUP(2,1/(('Daily AUM'!$D4:J4<>"")*(NAV!$D4:J4<>"")),NAV!$D4:J4),"")))),0)) -> -0.96823196 | L4: =IF(OR('Daily AUM'!L4="",NAV!L4=""),0,IFERROR(IF(OR(IFERROR(LOOKUP(2,1/(('Daily AUM'!$D4:K4<>"")*(NAV!$D4:K4<>"")),'Daily AUM'!$D4:K4),"")="",IFERROR(LOOKUP(2,1/(('Daily AUM'!$D4:K4<>"")*(NAV!$D4:K4<>"")),NAV!$D4:K4),"")=""),0,'Daily AUM'!L4-(IFERROR(LOOKUP(2,1/(('Daily AUM'!$D4:K4<>"")*(NAV!$D4:K4<>"")),'Daily AUM'!$D4:K4),"")*(NAV!L4/IFERROR(LOOKUP(2,1/(('Daily AUM'!$D4:K4<>"")*(NAV!$D4:K4<>"")),NAV!$D4:K4),"")))),0)) -> -2.6643153 | ... AR4: =IF(OR('Daily AUM'!AR4="",NAV!AR4=""),0,IFERROR(IF(OR(IFERROR(LOOKUP(2,1/(('Daily AUM'!$D4:AQ4<>"")*(NAV!$D4:AQ4<>"")),'Daily AUM'!$D4:AQ4),"")="",IFERROR(LOOKUP(2,1/(('Daily AUM'!$D4:AQ4<>"")*(NAV!$D4:AQ4<>"")),NAV!$D4:AQ4),"")=""),0,'Daily AUM'!AR4-(IFERROR(LOOKUP(2,1/(('Daily AUM'!$D4:AQ4<>"")*(NAV!$D4:AQ4<>"")),'Daily AUM'!$D4:AQ4),"")*(NAV!AR4/IFERROR(LOOKUP(2,1/(('Daily AUM'!$D4:AQ4<>"")*(NAV!$D4:AQ4<>"")),NAV!$D4:AQ4),"")))),0)) -> -1.2371804 | AS4: =SUM(F4:Y4) -> -81.940427 | AT4: =SUM(Z4:AR4) -> -75.73627
A5: 360 ONE Multi Asset Allocation Fund | B5: 360 ONE | C5: MULTI ASSET ALLOCATION | D5: =0 -> 0 | E5: =IF(OR('Daily AUM'!E5="",NAV!E5=""),0,IFERROR(IF(OR(IFERROR(LOOKUP(2,1/(('Daily AUM'!$D5:D5<>"")*(NAV!$D5:D5<>"")),'Daily AUM'!$D5:D5),"")="",IFERROR(LOOKUP(2,1/(('Daily AUM'!$D5:D5<>"")*(NAV!$D5:D5<>"")),NAV!$D5:D5),"")=""),0,'Daily AUM'!E5-(IFERROR(LOOKUP(2,1/(('Daily AUM'!$D5:D5<>"")*(NAV!$D5:D5<>"")),'Daily AUM'!$D5:D5),"")*(NAV!E5/IFERROR(LOOKUP(2,1/(('Daily AUM'!$D5:D5<>"")*(NAV!$D5:D5<>"")),NAV!$D5:D5),"")))),0)) -> 0.12797792 | F5: =IF(OR('Daily AUM'!F5="",NAV!F5=""),0,IFERROR(IF(OR(IFERROR(LOOKUP(2,1/(('Daily AUM'!$D5:E5<>"")*(NAV!$D5:E5<>"")),'Daily AUM'!$D5:E5),"")="",IFERROR(LOOKUP(2,1/(('Daily AUM'!$D5:E5<>"")*(NAV!$D5:E5<>"")),NAV!$D5:E5),"")=""),0,'Daily AUM'!F5-(IFERROR(LOOKUP(2,1/(('Daily AUM'!$D5:E5<>"")*(NAV!$D5:E5<>"")),'Daily AUM'!$D5:E5),"")*(NAV!F5/IFERROR(LOOKUP(2,1/(('Daily AUM'!$D5:E5<>"")*(NAV!$D5:E5<>"")),NAV!$D5:E5),"")))),0)) -> 0 | G5: =IF(OR('Daily AUM'!G5="",NAV!G5=""),0,IFERROR(IF(OR(IFERROR(LOOKUP(2,1/(('Daily AUM'!$D5:F5<>"")*(NAV!$D5:F5<>"")),'Daily AUM'!$D5:F5),"")="",IFERROR(LOOKUP(2,1/(('Daily AUM'!$D5:F5<>"")*(NAV!$D5:F5<>"")),NAV!$D5:F5),"")=""),0,'Daily AUM'!G5-(IFERROR(LOOKUP(2,1/(('Daily AUM'!$D5:F5<>"")*(NAV!$D5:F5<>"")),'Daily AUM'!$D5:F5),"")*(NAV!G5/IFERROR(LOOKUP(2,1/(('Daily AUM'!$D5:F5<>"")*(NAV!$D5:F5<>"")),NAV!$D5:F5),"")))),0)) -> 0.290816 | H5: =IF(OR('Daily AUM'!H5="",NAV!H5=""),0,IFERROR(IF(OR(IFERROR(LOOKUP(2,1/(('Daily AUM'!$D5:G5<>"")*(NAV!$D5:G5<>"")),'Daily AUM'!$D5:G5),"")="",IFERROR(LOOKUP(2,1/(('Daily AUM'!$D5:G5<>"")*(NAV!$D5:G5<>"")),NAV!$D5:G5),"")=""),0,'Daily AUM'!H5-(IFERROR(LOOKUP(2,1/(('Daily AUM'!$D5:G5<>"")*(NAV!$D5:G5<>"")),'Daily AUM'!$D5:G5),"")*(NAV!H5/IFERROR(LOOKUP(2,1/(('Daily AUM'!$D5:G5<>"")*(NAV!$D5:G5<>"")),NAV!$D5:G5),"")))),0)) -> 1.3181242 | I5: =IF(OR('Daily AUM'!I5="",NAV!I5=""),0,IFERROR(IF(OR(IFERROR(LOOKUP(2,1/(('Daily AUM'!$D5:H5<>"")*(NAV!$D5:H5<>"")),'Daily AUM'!$D5:H5),"")="",IFERROR(LOOKUP(2,1/(('Daily AUM'!$D5:H5<>"")*(NAV!$D5:H5<>"")),NAV!$D5:H5),"")=""),0,'Daily AUM'!I5-(IFERROR(LOOKUP(2,1/(('Daily AUM'!$D5:H5<>"")*(NAV!$D5:H5<>"")),'Daily AUM'!$D5:H5),"")*(NAV!I5/IFERROR(LOOKUP(2,1/(('Daily AUM'!$D5:H5<>"")*(NAV!$D5:H5<>"")),NAV!$D5:H5),"")))),0)) -> 2.2203869 | J5: =IF(OR('Daily AUM'!J5="",NAV!J5=""),0,IFERROR(IF(OR(IFERROR(LOOKUP(2,1/(('Daily AUM'!$D5:I5<>"")*(NAV!$D5:I5<>"")),'Daily AUM'!$D5:I5),"")="",IFERROR(LOOKUP(2,1/(('Daily AUM'!$D5:I5<>"")*(NAV!$D5:I5<>"")),NAV!$D5:I5),"")=""),0,'Daily AUM'!J5-(IFERROR(LOOKUP(2,1/(('Daily AUM'!$D5:I5<>"")*(NAV!$D5:I5<>"")),'Daily AUM'!$D5:I5),"")*(NAV!J5/IFERROR(LOOKUP(2,1/(('Daily AUM'!$D5:I5<>"")*(NAV!$D5:I5<>"")),NAV!$D5:I5),"")))),0)) -> 1.2503564 | K5: =IF(OR('Daily AUM'!K5="",NAV!K5=""),0,IFERROR(IF(OR(IFERROR(LOOKUP(2,1/(('Daily AUM'!$D5:J5<>"")*(NAV!$D5:J5<>"")),'Daily AUM'!$D5:J5),"")="",IFERROR(LOOKUP(2,1/(('Daily AUM'!$D5:J5<>"")*(NAV!$D5:J5<>"")),NAV!$D5:J5),"")=""),0,'Daily AUM'!K5-(IFERROR(LOOKUP(2,1/(('Daily AUM'!$D5:J5<>"")*(NAV!$D5:J5<>"")),'Daily AUM'!$D5:J5),"")*(NAV!K5/IFERROR(LOOKUP(2,1/(('Daily AUM'!$D5:J5<>"")*(NAV!$D5:J5<>"")),NAV!$D5:J5),"")))),0)) -> 0.66497797 | L5: =IF(OR('Daily AUM'!L5="",NAV!L5=""),0,IFERROR(IF(OR(IFERROR(LOOKUP(2,1/(('Daily AUM'!$D5:K5<>"")*(NAV!$D5:K5<>"")),'Daily AUM'!$D5:K5),"")="",IFERROR(LOOKUP(2,1/(('Daily AUM'!$D5:K5<>"")*(NAV!$D5:K5<>"")),NAV!$D5:K5),"")=""),0,'Daily AUM'!L5-(IFERROR(LOOKUP(2,1/(('Daily AUM'!$D5:K5<>"")*(NAV!$D5:K5<>"")),'Daily AUM'!$D5:K5),"")*(NAV!L5/IFERROR(LOOKUP(2,1/(('Daily AUM'!$D5:K5<>"")*(NAV!$D5:K5<>"")),NAV!$D5:K5),"")))),0)) -> 2.9060301 | ... AR5: =IF(OR('Daily AUM'!AR5="",NAV!AR5=""),0,IFERROR(IF(OR(IFERROR(LOOKUP(2,1/(('Daily AUM'!$D5:AQ5<>"")*(NAV!$D5:AQ5<>"")),'Daily AUM'!$D5:AQ5),"")="",IFERROR(LOOKUP(2,1/(('Daily AUM'!$D5:AQ5<>"")*(NAV!$D5:AQ5<>"")),NAV!$D5:AQ5),"")=""),0,'Daily AUM'!AR5-(IFERROR(LOOKUP(2,1/(('Daily AUM'!$D5:AQ5<>"")*(NAV!$D5:AQ5<>"")),'Daily AUM'!$D5:AQ5),"")*(NAV!AR5/IFERROR(LOOKUP(2,1/(('Daily AUM'!$D5:AQ5<>"")*(NAV!$D5:AQ5<>"")),NAV!$D5:AQ5),"")))),0)) -> 0.44062136 | AS5: =SUM(F5:Y5) -> 30.48037 | AT5: =SUM(Z5:AR5) -> 16.848818
A6: 360 ONE Quant Fund | B6: 360 ONE | C6: SECTORAL / THEMATIC | D6: =0 -> 0 | E6: =IF(OR('Daily AUM'!E6="",NAV!E6=""),0,IFERROR(IF(OR(IFERROR(LOOKUP(2,1/(('Daily AUM'!$D6:D6<>"")*(NAV!$D6:D6<>"")),'Daily AUM'!$D6:D6),"")="",IFERROR(LOOKUP(2,1/(('Daily AUM'!$D6:D6<>"")*(NAV!$D6:D6<>"")),NAV!$D6:D6),"")=""),0,'Daily AUM'!E6-(IFERROR(LOOKUP(2,1/(('Daily AUM'!$D6:D6<>"")*(NAV!$D6:D6<>"")),'Daily AUM'!$D6:D6),"")*(NAV!E6/IFERROR(LOOKUP(2,1/(('Daily AUM'!$D6:D6<>"")*(NAV!$D6:D6<>"")),NAV!$D6:D6),"")))),0)) -> 0.042701422 | F6: =IF(OR('Daily AUM'!F6="",NAV!F6=""),0,IFERROR(IF(OR(IFERROR(LOOKUP(2,1/(('Daily AUM'!$D6:E6<>"")*(NAV!$D6:E6<>"")),'Daily AUM'!$D6:E6),"")="",IFERROR(LOOKUP(2,1/(('Daily AUM'!$D6:E6<>"")*(NAV!$D6:E6<>"")),NAV!$D6:E6),"")=""),0,'Daily AUM'!F6-(IFERROR(LOOKUP(2,1/(('Daily AUM'!$D6:E6<>"")*(NAV!$D6:E6<>"")),'Daily AUM'!$D6:E6),"")*(NAV!F6/IFERROR(LOOKUP(2,1/(('Daily AUM'!$D6:E6<>"")*(NAV!$D6:E6<>"")),NAV!$D6:E6),"")))),0)) -> 0.69637149 | G6: =IF(OR('Daily AUM'!G6="",NAV!G6=""),0,IFERROR(IF(OR(IFERROR(LOOKUP(2,1/(('Daily AUM'!$D6:F6<>"")*(NAV!$D6:F6<>"")),'Daily AUM'!$D6:F6),"")="",IFERROR(LOOKUP(2,1/(('Daily AUM'!$D6:F6<>"")*(NAV!$D6:F6<>"")),NAV!$D6:F6),"")=""),0,'Daily AUM'!G6-(IFERROR(LOOKUP(2,1/(('Daily AUM'!$D6:F6<>"")*(NAV!$D6:F6<>"")),'Daily AUM'!$D6:F6),"")*(NAV!G6/IFERROR(LOOKUP(2,1/(('Daily AUM'!$D6:F6<>"")*(NAV!$D6:F6<>"")),NAV!$D6:F6),"")))),0)) -> 0.17821943 | H6: =IF(OR('Daily AUM'!H6="",NAV!H6=""),0,IFERROR(IF(OR(IFERROR(LOOKUP(2,1/(('Daily AUM'!$D6:G6<>"")*(NAV!$D6:G6<>"")),'Daily AUM'!$D6:G6),"")="",IFERROR(LOOKUP(2,1/(('Daily AUM'!$D6:G6<>"")*(NAV!$D6:G6<>"")),NAV!$D6:G6),"")=""),0,'Daily AUM'!H6-(IFERROR(LOOKUP(2,1/(('Daily AUM'!$D6:G6<>"")*(NAV!$D6:G6<>"")),'Daily AUM'!$D6:G6),"")*(NAV!H6/IFERROR(LOOKUP(2,1/(('Daily AUM'!$D6:G6<>"")*(NAV!$D6:G6<>"")),NAV!$D6:G6),"")))),0)) -> 1.4968727 | I6: =IF(OR('Daily AUM'!I6="",NAV!I6=""),0,IFERROR(IF(OR(IFERROR(LOOKUP(2,1/(('Daily AUM'!$D6:H6<>"")*(NAV!$D6:H6<>"")),'Daily AUM'!$D6:H6),"")="",IFERROR(LOOKUP(2,1/(('Daily AUM'!$D6:H6<>"")*(NAV!$D6:H6<>"")),NAV!$D6:H6),"")=""),0,'Daily AUM'!I6-(IFERROR(LOOKUP(2,1/(('Daily AUM'!$D6:H6<>"")*(NAV!$D6:H6<>"")),'Daily AUM'!$D6:H6),"")*(NAV!I6/IFERROR(LOOKUP(2,1/(('Daily AUM'!$D6:H6<>"")*(NAV!$D6:H6<>"")),NAV!$D6:H6),"")))),0)) -> 3.8521493 | J6: =IF(OR('Daily AUM'!J6="",NAV!J6=""),0,IFERROR(IF(OR(IFERROR(LOOKUP(2,1/(('Daily AUM'!$D6:I6<>"")*(NAV!$D6:I6<>"")),'Daily AUM'!$D6:I6),"")="",IFERROR(LOOKUP(2,1/(('Daily AUM'!$D6:I6<>"")*(NAV!$D6:I6<>"")),NAV!$D6:I6),"")=""),0,'Daily AUM'!J6-(IFERROR(LOOKUP(2,1/(('Daily AUM'!$D6:I6<>"")*(NAV!$D6:I6<>"")),'Daily AUM'!$D6:I6),"")*(NAV!J6/IFERROR(LOOKUP(2,1/(('Daily AUM'!$D6:I6<>"")*(NAV!$D6:I6<>"")),NAV!$D6:I6),"")))),0)) -> 1.280352 | K6: =IF(OR('Daily AUM'!K6="",NAV!K6=""),0,IFERROR(IF(OR(IFERROR(LOOKUP(2,1/(('Daily AUM'!$D6:J6<>"")*(NAV!$D6:J6<>"")),'Daily AUM'!$D6:J6),"")="",IFERROR(LOOKUP(2,1/(('Daily AUM'!$D6:J6<>"")*(NAV!$D6:J6<>"")),NAV!$D6:J6),"")=""),0,'Daily AUM'!K6-(IFERROR(LOOKUP(2,1/(('Daily AUM'!$D6:J6<>"")*(NAV!$D6:J6<>"")),'Daily AUM'!$D6:J6),"")*(NAV!K6/IFERROR(LOOKUP(2,1/(('Daily AUM'!$D6:J6<>"")*(NAV!$D6:J6<>"")),NAV!$D6:J6),"")))),0)) -> 0.74701249 | L6: =IF(OR('Daily AUM'!L6="",NAV!L6=""),0,IFERROR(IF(OR(IFERROR(LOOKUP(2,1/(('Daily AUM'!$D6:K6<>"")*(NAV!$D6:K6<>"")),'Daily AUM'!$D6:K6),"")="",IFERROR(LOOKUP(2,1/(('Daily AUM'!$D6:K6<>"")*(NAV!$D6:K6<>"")),NAV!$D6:K6),"")=""),0,'Daily AUM'!L6-(IFERROR(LOOKUP(2,1/(('Daily AUM'!$D6:K6<>"")*(NAV!$D6:K6<>"")),'Daily AUM'!$D6:K6),"")*(NAV!L6/IFERROR(LOOKUP(2,1/(('Daily AUM'!$D6:K6<>"")*(NAV!$D6:K6<>"")),NAV!$D6:K6),"")))),0)) -> 0.69790977 | ... AR6: =IF(OR('Daily AUM'!AR6="",NAV!AR6=""),0,IFERROR(IF(OR(IFERROR(LOOKUP(2,1/(('Daily AUM'!$D6:AQ6<>"")*(NAV!$D6:AQ6<>"")),'Daily AUM'!$D6:AQ6),"")="",IFERROR(LOOKUP(2,1/(('Daily AUM'!$D6:AQ6<>"")*(NAV!$D6:AQ6<>"")),NAV!$D6:AQ6),"")=""),0,'Daily AUM'!AR6-(IFERROR(LOOKUP(2,1/(('Daily AUM'!$D6:AQ6<>"")*(NAV!$D6:AQ6<>"")),'Daily AUM'!$D6:AQ6),"")*(NAV!AR6/IFERROR(LOOKUP(2,1/(('Daily AUM'!$D6:AQ6<>"")*(NAV!$D6:AQ6<>"")),NAV!$D6:AQ6),"")))),0)) -> -0.090429024 | AS6: =SUM(F6:Y6) -> 12.435638 | AT6: =SUM(Z6:AR6) -> -23.589531
A7: Abakkus Flexi Cap Fund | B7: Abakkus | C7: FLEXI CAP | D7: =0 -> 0 | E7: =IF(OR('Daily AUM'!E7="",NAV!E7=""),0,IFERROR(IF(OR(IFERROR(LOOKUP(2,1/(('Daily AUM'!$D7:D7<>"")*(NAV!$D7:D7<>"")),'Daily AUM'!$D7:D7),"")="",IFERROR(LOOKUP(2,1/(('Daily AUM'!$D7:D7<>"")*(NAV!$D7:D7<>"")),NAV!$D7:D7),"")=""),0,'Daily AUM'!E7-(IFERROR(LOOKUP(2,1/(('Daily AUM'!$D7:D7<>"")*(NAV!$D7:D7<>"")),'Daily AUM'!$D7:D7),"")*(NAV!E7/IFERROR(LOOKUP(2,1/(('Daily AUM'!$D7:D7<>"")*(NAV!$D7:D7<>"")),NAV!$D7:D7),"")))),0)) -> 16.2196 | F7: =IF(OR('Daily AUM'!F7="",NAV!F7=""),0,IFERROR(IF(OR(IFERROR(LOOKUP(2,1/(('Daily AUM'!$D7:E7<>"")*(NAV!$D7:E7<>"")),'Daily AUM'!$D7:E7),"")="",IFERROR(LOOKUP(2,1/(('Daily AUM'!$D7:E7<>"")*(NAV!$D7:E7<>"")),NAV!$D7:E7),"")=""),0,'Daily AUM'!F7-(IFERROR(LOOKUP(2,1/(('Daily AUM'!$D7:E7<>"")*(NAV!$D7:E7<>"")),'Daily AUM'!$D7:E7),"")*(NAV!F7/IFERROR(LOOKUP(2,1/(('Daily AUM'!$D7:E7<>"")*(NAV!$D7:E7<>"")),NAV!$D7:E7),"")))),0)) -> 0.26209998 | G7: =IF(OR('Daily AUM'!G7="",NAV!G7=""),0,IFERROR(IF(OR(IFERROR(LOOKUP(2,1/(('Daily AUM'!$D7:F7<>"")*(NAV!$D7:F7<>"")),'Daily AUM'!$D7:F7),"")="",IFERROR(LOOKUP(2,1/(('Daily AUM'!$D7:F7<>"")*(NAV!$D7:F7<>"")),NAV!$D7:F7),"")=""),0,'Daily AUM'!G7-(IFERROR(LOOKUP(2,1/(('Daily AUM'!$D7:F7<>"")*(NAV!$D7:F7<>"")),'Daily AUM'!$D7:F7),"")*(NAV!G7/IFERROR(LOOKUP(2,1/(('Daily AUM'!$D7:F7<>"")*(NAV!$D7:F7<>"")),NAV!$D7:F7),"")))),0)) -> 9.9375478 | H7: =IF(OR('Daily AUM'!H7="",NAV!H7=""),0,IFERROR(IF(OR(IFERROR(LOOKUP(2,1/(('Daily AUM'!$D7:G7<>"")*(NAV!$D7:G7<>"")),'Daily AUM'!$D7:G7),"")="",IFERROR(LOOKUP(2,1/(('Daily AUM'!$D7:G7<>"")*(NAV!$D7:G7<>"")),NAV!$D7:G7),"")=""),0,'Daily AUM'!H7-(IFERROR(LOOKUP(2,1/(('Daily AUM'!$D7:G7<>"")*(NAV!$D7:G7<>"")),'Daily AUM'!$D7:G7),"")*(NAV!H7/IFERROR(LOOKUP(2,1/(('Daily AUM'!$D7:G7<>"")*(NAV!$D7:G7<>"")),NAV!$D7:G7),"")))),0)) -> 26.971839 | I7: =IF(OR('Daily AUM'!I7="",NAV!I7=""),0,IFERROR(IF(OR(IFERROR(LOOKUP(2,1/(('Daily AUM'!$D7:H7<>"")*(NAV!$D7:H7<>"")),'Daily AUM'!$D7:H7),"")="",IFERROR(LOOKUP(2,1/(('Daily AUM'!$D7:H7<>"")*(NAV!$D7:H7<>"")),NAV!$D7:H7),"")=""),0,'Daily AUM'!I7-(IFERROR(LOOKUP(2,1/(('Daily AUM'!$D7:H7<>"")*(NAV!$D7:H7<>"")),'Daily AUM'!$D7:H7),"")*(NAV!I7/IFERROR(LOOKUP(2,1/(('Daily AUM'!$D7:H7<>"")*(NAV!$D7:H7<>"")),NAV!$D7:H7),"")))),0)) -> 32.578621 | J7: =IF(OR('Daily AUM'!J7="",NAV!J7=""),0,IFERROR(IF(OR(IFERROR(LOOKUP(2,1/(('Daily AUM'!$D7:I7<>"")*(NAV!$D7:I7<>"")),'Daily AUM'!$D7:I7),"")="",IFERROR(LOOKUP(2,1/(('Daily AUM'!$D7:I7<>"")*(NAV!$D7:I7<>"")),NAV!$D7:I7),"")=""),0,'Daily AUM'!J7-(IFERROR(LOOKUP(2,1/(('Daily AUM'!$D7:I7<>"")*(NAV!$D7:I7<>"")),'Daily AUM'!$D7:I7),"")*(NAV!J7/IFERROR(LOOKUP(2,1/(('Daily AUM'!$D7:I7<>"")*(NAV!$D7:I7<>"")),NAV!$D7:I7),"")))),0)) -> 10.697335 | K7: =IF(OR('Daily AUM'!K7="",NAV!K7=""),0,IFERROR(IF(OR(IFERROR(LOOKUP(2,1/(('Daily AUM'!$D7:J7<>"")*(NAV!$D7:J7<>"")),'Daily AUM'!$D7:J7),"")="",IFERROR(LOOKUP(2,1/(('Daily AUM'!$D7:J7<>"")*(NAV!$D7:J7<>"")),NAV!$D7:J7),"")=""),0,'Daily AUM'!K7-(IFERROR(LOOKUP(2,1/(('Daily AUM'!$D7:J7<>"")*(NAV!$D7:J7<>"")),'Daily AUM'!$D7:J7),"")*(NAV!K7/IFERROR(LOOKUP(2,1/(('Daily AUM'!$D7:J7<>"")*(NAV!$D7:J7<>"")),NAV!$D7:J7),"")))),0)) -> 20.109871 | L7: =IF(OR('Daily AUM'!L7="",NAV!L7=""),0,IFERROR(IF(OR(IFERROR(LOOKUP(2,1/(('Daily AUM'!$D7:K7<>"")*(NAV!$D7:K7<>"")),'Daily AUM'!$D7:K7),"")="",IFERROR(LOOKUP(2,1/(('Daily AUM'!$D7:K7<>"")*(NAV!$D7:K7<>"")),NAV!$D7:K7),"")=""),0,'Daily AUM'!L7-(IFERROR(LOOKUP(2,1/(('Daily AUM'!$D7:K7<>"")*(NAV!$D7:K7<>"")),'Daily AUM'!$D7:K7),"")*(NAV!L7/IFERROR(LOOKUP(2,1/(('Daily AUM'!$D7:K7<>"")*(NAV!$D7:K7<>"")),NAV!$D7:K7),"")))),0)) -> 16.785926 | ... AR7: =IF(OR('Daily AUM'!AR7="",NAV!AR7=""),0,IFERROR(IF(OR(IFERROR(LOOKUP(2,1/(('Daily AUM'!$D7:AQ7<>"")*(NAV!$D7:AQ7<>"")),'Daily AUM'!$D7:AQ7),"")="",IFERROR(LOOKUP(2,1/(('Daily AUM'!$D7:AQ7<>"")*(NAV!$D7:AQ7<>"")),NAV!$D7:AQ7),"")=""),0,'Daily AUM'!AR7-(IFERROR(LOOKUP(2,1/(('Daily AUM'!$D7:AQ7<>"")*(NAV!$D7:AQ7<>"")),'Daily AUM'!$D7:AQ7),"")*(NAV!AR7/IFERROR(LOOKUP(2,1/(('Daily AUM'!$D7:AQ7<>"")*(NAV!$D7:AQ7<>"")),NAV!$D7:AQ7),"")))),0)) -> 34.382238 | AS7: =SUM(F7:Y7) -> 365.25465 | AT7: =SUM(Z7:AR7) -> 637.52115
A8: Abakkus Small Cap Fund | B8: Abakkus | C8: SMALL CAP | D8: =0 -> 0 | E8: =IF(OR('Daily AUM'!E8="",NAV!E8=""),0,IFERROR(IF(OR(IFERROR(LOOKUP(2,1/(('Daily AUM'!$D8:D8<>"")*(NAV!$D8:D8<>"")),'Daily AUM'!$D8:D8),"")="",IFERROR(LOOKUP(2,1/(('Daily AUM'!$D8:D8<>"")*(NAV!$D8:D8<>"")),NAV!$D8:D8),"")=""),0,'Daily AUM'!E8-(IFERROR(LOOKUP(2,1/(('Daily AUM'!$D8:D8<>"")*(NAV!$D8:D8<>"")),'Daily AUM'!$D8:D8),"")*(NAV!E8/IFERROR(LOOKUP(2,1/(('Daily AUM'!$D8:D8<>"")*(NAV!$D8:D8<>"")),NAV!$D8:D8),"")))),0)) -> 11.171229 | F8: =IF(OR('Daily AUM'!F8="",NAV!F8=""),0,IFERROR(IF(OR(IFERROR(LOOKUP(2,1/(('Daily AUM'!$D8:E8<>"")*(NAV!$D8:E8<>"")),'Daily AUM'!$D8:E8),"")="",IFERROR(LOOKUP(2,1/(('Daily AUM'!$D8:E8<>"")*(NAV!$D8:E8<>"")),NAV!$D8:E8),"")=""),0,'Daily AUM'!F8-(IFERROR(LOOKUP(2,1/(('Daily AUM'!$D8:E8<>"")*(NAV!$D8:E8<>"")),'Daily AUM'!$D8:E8),"")*(NAV!F8/IFERROR(LOOKUP(2,1/(('Daily AUM'!$D8:E8<>"")*(NAV!$D8:E8<>"")),NAV!$D8:E8),"")))),0)) -> 0.37408126 | G8: =IF(OR('Daily AUM'!G8="",NAV!G8=""),0,IFERROR(IF(OR(IFERROR(LOOKUP(2,1/(('Daily AUM'!$D8:F8<>"")*(NAV!$D8:F8<>"")),'Daily AUM'!$D8:F8),"")="",IFERROR(LOOKUP(2,1/(('Daily AUM'!$D8:F8<>"")*(NAV!$D8:F8<>"")),NAV!$D8:F8),"")=""),0,'Daily AUM'!G8-(IFERROR(LOOKUP(2,1/(('Daily AUM'!$D8:F8<>"")*(NAV!$D8:F8<>"")),'Daily AUM'!$D8:F8),"")*(NAV!G8/IFERROR(LOOKUP(2,1/(('Daily AUM'!$D8:F8<>"")*(NAV!$D8:F8<>"")),NAV!$D8:F8),"")))),0)) -> 6.4981685 | H8: =IF(OR('Daily AUM'!H8="",NAV!H8=""),0,IFERROR(IF(OR(IFERROR(LOOKUP(2,1/(('Daily AUM'!$D8:G8<>"")*(NAV!$D8:G8<>"")),'Daily AUM'!$D8:G8),"")="",IFERROR(LOOKUP(2,1/(('Daily AUM'!$D8:G8<>"")*(NAV!$D8:G8<>"")),NAV!$D8:G8),"")=""),0,'Daily AUM'!H8-(IFERROR(LOOKUP(2,1/(('Daily AUM'!$D8:G8<>"")*(NAV!$D8:G8<>"")),'Daily AUM'!$D8:G8),"")*(NAV!H8/IFERROR(LOOKUP(2,1/(('Daily AUM'!$D8:G8<>"")*(NAV!$D8:G8<>"")),NAV!$D8:G8),"")))),0)) -> 12.439394 | I8: =IF(OR('Daily AUM'!I8="",NAV!I8=""),0,IFERROR(IF(OR(IFERROR(LOOKUP(2,1/(('Daily AUM'!$D8:H8<>"")*(NAV!$D8:H8<>"")),'Daily AUM'!$D8:H8),"")="",IFERROR(LOOKUP(2,1/(('Daily AUM'!$D8:H8<>"")*(NAV!$D8:H8<>"")),NAV!$D8:H8),"")=""),0,'Daily AUM'!I8-(IFERROR(LOOKUP(2,1/(('Daily AUM'!$D8:H8<>"")*(NAV!$D8:H8<>"")),'Daily AUM'!$D8:H8),"")*(NAV!I8/IFERROR(LOOKUP(2,1/(('Daily AUM'!$D8:H8<>"")*(NAV!$D8:H8<>"")),NAV!$D8:H8),"")))),0)) -> 13.035509 | J8: =IF(OR('Daily AUM'!J8="",NAV!J8=""),0,IFERROR(IF(OR(IFERROR(LOOKUP(2,1/(('Daily AUM'!$D8:I8<>"")*(NAV!$D8:I8<>"")),'Daily AUM'!$D8:I8),"")="",IFERROR(LOOKUP(2,1/(('Daily AUM'!$D8:I8<>"")*(NAV!$D8:I8<>"")),NAV!$D8:I8),"")=""),0,'Daily AUM'!J8-(IFERROR(LOOKUP(2,1/(('Daily AUM'!$D8:I8<>"")*(NAV!$D8:I8<>"")),'Daily AUM'!$D8:I8),"")*(NAV!J8/IFERROR(LOOKUP(2,1/(('Daily AUM'!$D8:I8<>"")*(NAV!$D8:I8<>"")),NAV!$D8:I8),"")))),0)) -> 9.8141428 | K8: =IF(OR('Daily AUM'!K8="",NAV!K8=""),0,IFERROR(IF(OR(IFERROR(LOOKUP(2,1/(('Daily AUM'!$D8:J8<>"")*(NAV!$D8:J8<>"")),'Daily AUM'!$D8:J8),"")="",IFERROR(LOOKUP(2,1/(('Daily AUM'!$D8:J8<>"")*(NAV!$D8:J8<>"")),NAV!$D8:J8),"")=""),0,'Daily AUM'!K8-(IFERROR(LOOKUP(2,1/(('Daily AUM'!$D8:J8<>"")*(NAV!$D8:J8<>"")),'Daily AUM'!$D8:J8),"")*(NAV!K8/IFERROR(LOOKUP(2,1/(('Daily AUM'!$D8:J8<>"")*(NAV!$D8:J8<>"")),NAV!$D8:J8),"")))),0)) -> 15.959599 | L8: =IF(OR('Daily AUM'!L8="",NAV!L8=""),0,IFERROR(IF(OR(IFERROR(LOOKUP(2,1/(('Daily AUM'!$D8:K8<>"")*(NAV!$D8:K8<>"")),'Daily AUM'!$D8:K8),"")="",IFERROR(LOOKUP(2,1/(('Daily AUM'!$D8:K8<>"")*(NAV!$D8:K8<>"")),NAV!$D8:K8),"")=""),0,'Daily AUM'!L8-(IFERROR(LOOKUP(2,1/(('Daily AUM'!$D8:K8<>"")*(NAV!$D8:K8<>"")),'Daily AUM'!$D8:K8),"")*(NAV!L8/IFERROR(LOOKUP(2,1/(('Daily AUM'!$D8:K8<>"")*(NAV!$D8:K8<>"")),NAV!$D8:K8),"")))),0)) -> 20.709927 | ... AR8: =IF(OR('Daily AUM'!AR8="",NAV!AR8=""),0,IFERROR(IF(OR(IFERROR(LOOKUP(2,1/(('Daily AUM'!$D8:AQ8<>"")*(NAV!$D8:AQ8<>"")),'Daily AUM'!$D8:AQ8),"")="",IFERROR(LOOKUP(2,1/(('Daily AUM'!$D8:AQ8<>"")*(NAV!$D8:AQ8<>"")),NAV!$D8:AQ8),"")=""),0,'Daily AUM'!AR8-(IFERROR(LOOKUP(2,1/(('Daily AUM'!$D8:AQ8<>"")*(NAV!$D8:AQ8<>"")),'Daily AUM'!$D8:AQ8),"")*(NAV!AR8/IFERROR(LOOKUP(2,1/(('Daily AUM'!$D8:AQ8<>"")*(NAV!$D8:AQ8<>"")),NAV!$D8:AQ8),"")))),0)) -> 7.2084597 | AS8: =SUM(F8:Y8) -> 302.80193 | AT8: =SUM(Z8:AR8) -> 236.07277
A9: Aditya Birla Sun Life Arbitrage Fund | B9: Aditya Birla Sun Life | C9: ARBITRAGE | D9: =0 -> 0 | E9: =IF(OR('Daily AUM'!E9="",NAV!E9=""),0,IFERROR(IF(OR(IFERROR(LOOKUP(2,1/(('Daily AUM'!$D9:D9<>"")*(NAV!$D9:D9<>"")),'Daily AUM'!$D9:D9),"")="",IFERROR(LOOKUP(2,1/(('Daily AUM'!$D9:D9<>"")*(NAV!$D9:D9<>"")),NAV!$D9:D9),"")=""),0,'Daily AUM'!E9-(IFERROR(LOOKUP(2,1/(('Daily AUM'!$D9:D9<>"")*(NAV!$D9:D9<>"")),'Daily AUM'!$D9:D9),"")*(NAV!E9/IFERROR(LOOKUP(2,1/(('Daily AUM'!$D9:D9<>"")*(NAV!$D9:D9<>"")),NAV!$D9:D9),"")))),0)) -> 199.3622 | F9: =IF(OR('Daily AUM'!F9="",NAV!F9=""),0,IFERROR(IF(OR(IFERROR(LOOKUP(2,1/(('Daily AUM'!$D9:E9<>"")*(NAV!$D9:E9<>"")),'Daily AUM'!$D9:E9),"")="",IFERROR(LOOKUP(2,1/(('Daily AUM'!$D9:E9<>"")*(NAV!$D9:E9<>"")),NAV!$D9:E9),"")=""),0,'Daily AUM'!F9-(IFERROR(LOOKUP(2,1/(('Daily AUM'!$D9:E9<>"")*(NAV!$D9:E9<>"")),'Daily AUM'!$D9:E9),"")*(NAV!F9/IFERROR(LOOKUP(2,1/(('Daily AUM'!$D9:E9<>"")*(NAV!$D9:E9<>"")),NAV!$D9:E9),"")))),0)) -> 0.36384859 | G9: =IF(OR('Daily AUM'!G9="",NAV!G9=""),0,IFERROR(IF(OR(IFERROR(LOOKUP(2,1/(('Daily AUM'!$D9:F9<>"")*(NAV!$D9:F9<>"")),'Daily AUM'!$D9:F9),"")="",IFERROR(LOOKUP(2,1/(('Daily AUM'!$D9:F9<>"")*(NAV!$D9:F9<>"")),NAV!$D9:F9),"")=""),0,'Daily AUM'!G9-(IFERROR(LOOKUP(2,1/(('Daily AUM'!$D9:F9<>"")*(NAV!$D9:F9<>"")),'Daily AUM'!$D9:F9),"")*(NAV!G9/IFERROR(LOOKUP(2,1/(('Daily AUM'!$D9:F9<>"")*(NAV!$D9:F9<>"")),NAV!$D9:F9),"")))),0)) -> -54.195792 | H9: =IF(OR('Daily AUM'!H9="",NAV!H9=""),0,IFERROR(IF(OR(IFERROR(LOOKUP(2,1/(('Daily AUM'!$D9:G9<>"")*(NAV!$D9:G9<>"")),'Daily AUM'!$D9:G9),"")="",IFERROR(LOOKUP(2,1/(('Daily AUM'!$D9:G9<>"")*(NAV!$D9:G9<>"")),NAV!$D9:G9),"")=""),0,'Daily AUM'!H9-(IFERROR(LOOKUP(2,1/(('Daily AUM'!$D9:G9<>"")*(NAV!$D9:G9<>"")),'Daily AUM'!$D9:G9),"")*(NAV!H9/IFERROR(LOOKUP(2,1/(('Daily AUM'!$D9:G9<>"")*(NAV!$D9:G9<>"")),NAV!$D9:G9),"")))),0)) -> 133.48866 | I9: =IF(OR('Daily AUM'!I9="",NAV!I9=""),0,IFERROR(IF(OR(IFERROR(LOOKUP(2,1/(('Daily AUM'!$D9:H9<>"")*(NAV!$D9:H9<>"")),'Daily AUM'!$D9:H9),"")="",IFERROR(LOOKUP(2,1/(('Daily AUM'!$D9:H9<>"")*(NAV!$D9:H9<>"")),NAV!$D9:H9),"")=""),0,'Daily AUM'!I9-(IFERROR(LOOKUP(2,1/(('Daily AUM'!$D9:H9<>"")*(NAV!$D9:H9<>"")),'Daily AUM'!$D9:H9),"")*(NAV!I9/IFERROR(LOOKUP(2,1/(('Daily AUM'!$D9:H9<>"")*(NAV!$D9:H9<>"")),NAV!$D9:H9),"")))),0)) -> -20.943879 | J9: =IF(OR('Daily AUM'!J9="",NAV!J9=""),0,IFERROR(IF(OR(IFERROR(LOOKUP(2,1/(('Daily AUM'!$D9:I9<>"")*(NAV!$D9:I9<>"")),'Daily AUM'!$D9:I9),"")="",IFERROR(LOOKUP(2,1/(('Daily AUM'!$D9:I9<>"")*(NAV!$D9:I9<>"")),NAV!$D9:I9),"")=""),0,'Daily AUM'!J9-(IFERROR(LOOKUP(2,1/(('Daily AUM'!$D9:I9<>"")*(NAV!$D9:I9<>"")),'Daily AUM'!$D9:I9),"")*(NAV!J9/IFERROR(LOOKUP(2,1/(('Daily AUM'!$D9:I9<>"")*(NAV!$D9:I9<>"")),NAV!$D9:I9),"")))),0)) -> -7.567691 | K9: =IF(OR('Daily AUM'!K9="",NAV!K9=""),0,IFERROR(IF(OR(IFERROR(LOOKUP(2,1/(('Daily AUM'!$D9:J9<>"")*(NAV!$D9:J9<>"")),'Daily AUM'!$D9:J9),"")="",IFERROR(LOOKUP(2,1/(('Daily AUM'!$D9:J9<>"")*(NAV!$D9:J9<>"")),NAV!$D9:J9),"")=""),0,'Daily AUM'!K9-(IFERROR(LOOKUP(2,1/(('Daily AUM'!$D9:J9<>"")*(NAV!$D9:J9<>"")),'Daily AUM'!$D9:J9),"")*(NAV!K9/IFERROR(LOOKUP(2,1/(('Daily AUM'!$D9:J9<>"")*(NAV!$D9:J9<>"")),NAV!$D9:J9),"")))),0)) -> 163.55717 | L9: =IF(OR('Daily AUM'!L9="",NAV!L9=""),0,IFERROR(IF(OR(IFERROR(LOOKUP(2,1/(('Daily AUM'!$D9:K9<>"")*(NAV!$D9:K9<>"")),'Daily AUM'!$D9:K9),"")="",IFERROR(LOOKUP(2,1/(('Daily AUM'!$D9:K9<>"")*(NAV!$D9:K9<>"")),NAV!$D9:K9),"")=""),0,'Daily AUM'!L9-(IFERROR(LOOKUP(2,1/(('Daily AUM'!$D9:K9<>"")*(NAV!$D9:K9<>"")),'Daily AUM'!$D9:K9),"")*(NAV!L9/IFERROR(LOOKUP(2,1/(('Daily AUM'!$D9:K9<>"")*(NAV!$D9:K9<>"")),NAV!$D9:K9),"")))),0)) -> 180.78923 | ... AR9: =IF(OR('Daily AUM'!AR9="",NAV!AR9=""),0,IFERROR(IF(OR(IFERROR(LOOKUP(2,1/(('Daily AUM'!$D9:AQ9<>"")*(NAV!$D9:AQ9<>"")),'Daily AUM'!$D9:AQ9),"")="",IFERROR(LOOKUP(2,1/(('Daily AUM'!$D9:AQ9<>"")*(NAV!$D9:AQ9<>"")),NAV!$D9:AQ9),"")=""),0,'Daily AUM'!AR9-(IFERROR(LOOKUP(2,1/(('Daily AUM'!$D9:AQ9<>"")*(NAV!$D9:AQ9<>"")),'Daily AUM'!$D9:AQ9),"")*(NAV!AR9/IFERROR(LOOKUP(2,1/(('Daily AUM'!$D9:AQ9<>"")*(NAV!$D9:AQ9<>"")),NAV!$D9:AQ9),"")))),0)) -> 90.909573 | AS9: =SUM(F9:Y9) -> 513.65353 | AT9: =SUM(Z9:AR9) -> 376.26256
A10: Aditya Birla Sun Life Balanced Advantage Fund | B10: Aditya Birla Sun Life | C10: DYNAMIC ASSET ALLOCATION OR BALANCED ADVANTAGE | D10: =0 -> 0 | E10: =IF(OR('Daily AUM'!E10="",NAV!E10=""),0,IFERROR(IF(OR(IFERROR(LOOKUP(2,1/(('Daily AUM'!$D10:D10<>"")*(NAV!$D10:D10<>"")),'Daily AUM'!$D10:D10),"")="",IFERROR(LOOKUP(2,1/(('Daily AUM'!$D10:D10<>"")*(NAV!$D10:D10<>"")),NAV!$D10:D10),"")=""),0,'Daily AUM'!E10-(IFERROR(LOOKUP(2,1/(('Daily AUM'!$D10:D10<>"")*(NAV!$D10:D10<>"")),'Daily AUM'!$D10:D10),"")*(NAV!E10/IFERROR(LOOKUP(2,1/(('Daily AUM'!$D10:D10<>"")*(NAV!$D10:D10<>"")),NAV!$D10:D10),"")))),0)) -> 7.741 | F10: =IF(OR('Daily AUM'!F10="",NAV!F10=""),0,IFERROR(IF(OR(IFERROR(LOOKUP(2,1/(('Daily AUM'!$D10:E10<>"")*(NAV!$D10:E10<>"")),'Daily AUM'!$D10:E10),"")="",IFERROR(LOOKUP(2,1/(('Daily AUM'!$D10:E10<>"")*(NAV!$D10:E10<>"")),NAV!$D10:E10),"")=""),0,'Daily AUM'!F10-(IFERROR(LOOKUP(2,1/(('Daily AUM'!$D10:E10<>"")*(NAV!$D10:E10<>"")),'Daily AUM'!$D10:E10),"")*(NAV!F10/IFERROR(LOOKUP(2,1/(('Daily AUM'!$D10:E10<>"")*(NAV!$D10:E10<>"")),NAV!$D10:E10),"")))),0)) -> 0.17628782 | G10: =IF(OR('Daily AUM'!G10="",NAV!G10=""),0,IFERROR(IF(OR(IFERROR(LOOKUP(2,1/(('Daily AUM'!$D10:F10<>"")*(NAV!$D10:F10<>"")),'Daily AUM'!$D10:F10),"")="",IFERROR(LOOKUP(2,1/(('Daily AUM'!$D10:F10<>"")*(NAV!$D10:F10<>"")),NAV!$D10:F10),"")=""),0,'Daily AUM'!G10-(IFERROR(LOOKUP(2,1/(('Daily AUM'!$D10:F10<>"")*(NAV!$D10:F10<>"")),'Daily AUM'!$D10:F10),"")*(NAV!G10/IFERROR(LOOKUP(2,1/(('Daily AUM'!$D10:F10<>"")*(NAV!$D10:F10<>"")),NAV!$D10:F10),"")))),0)) -> -5.3279358 | H10: =IF(OR('Daily AUM'!H10="",NAV!H10=""),0,IFERROR(IF(OR(IFERROR(LOOKUP(2,1/(('Daily AUM'!$D10:G10<>"")*(NAV!$D10:G10<>"")),'Daily AUM'!$D10:G10),"")="",IFERROR(LOOKUP(2,1/(('Daily AUM'!$D10:G10<>"")*(NAV!$D10:G10<>"")),NAV!$D10:G10),"")=""),0,'Daily AUM'!H10-(IFERROR(LOOKUP(2,1/(('Daily AUM'!$D10:G10<>"")*(NAV!$D10:G10<>"")),'Daily AUM'!$D10:G10),"")*(NAV!H10/IFERROR(LOOKUP(2,1/(('Daily AUM'!$D10:G10<>"")*(NAV!$D10:G10<>"")),NAV!$D10:G10),"")))),0)) -> 5.7288158 | I10: =IF(OR('Daily AUM'!I10="",NAV!I10=""),0,IFERROR(IF(OR(IFERROR(LOOKUP(2,1/(('Daily AUM'!$D10:H10<>"")*(NAV!$D10:H10<>"")),'Daily AUM'!$D10:H10),"")="",IFERROR(LOOKUP(2,1/(('Daily AUM'!$D10:H10<>"")*(NAV!$D10:H10<>"")),NAV!$D10:H10),"")=""),0,'Daily AUM'!I10-(IFERROR(LOOKUP(2,1/(('Daily AUM'!$D10:H10<>"")*(NAV!$D10:H10<>"")),'Daily AUM'!$D10:H10),"")*(NAV!I10/IFERROR(LOOKUP(2,1/(('Daily AUM'!$D10:H10<>"")*(NAV!$D10:H10<>"")),NAV!$D10:H10),"")))),0)) -> -0.89240699 | J10: =IF(OR('Daily AUM'!J10="",NAV!J10=""),0,IFERROR(IF(OR(IFERROR(LOOKUP(2,1/(('Daily AUM'!$D10:I10<>"")*(NAV!$D10:I10<>"")),'Daily AUM'!$D10:I10),"")="",IFERROR(LOOKUP(2,1/(('Daily AUM'!$D10:I10<>"")*(NAV!$D10:I10<>"")),NAV!$D10:I10),"")=""),0,'Daily AUM'!J10-(IFERROR(LOOKUP(2,1/(('Daily AUM'!$D10:I10<>"")*(NAV!$D10:I10<>"")),'Daily AUM'!$D10:I10),"")*(NAV!J10/IFERROR(LOOKUP(2,1/(('Daily AUM'!$D10:I10<>"")*(NAV!$D10:I10<>"")),NAV!$D10:I10),"")))),0)) -> 10.352529 | K10: =IF(OR('Daily AUM'!K10="",NAV!K10=""),0,IFERROR(IF(OR(IFERROR(LOOKUP(2,1/(('Daily AUM'!$D10:J10<>"")*(NAV!$D10:J10<>"")),'Daily AUM'!$D10:J10),"")="",IFERROR(LOOKUP(2,1/(('Daily AUM'!$D10:J10<>"")*(NAV!$D10:J10<>"")),NAV!$D10:J10),"")=""),0,'Daily AUM'!K10-(IFERROR(LOOKUP(2,1/(('Daily AUM'!$D10:J10<>"")*(NAV!$D10:J10<>"")),'Daily AUM'!$D10:J10),"")*(NAV!K10/IFERROR(LOOKUP(2,1/(('Daily AUM'!$D10:J10<>"")*(NAV!$D10:J10<>"")),NAV!$D10:J10),"")))),0)) -> 6.9316184 | L10: =IF(OR('Daily AUM'!L10="",NAV!L10=""),0,IFERROR(IF(OR(IFERROR(LOOKUP(2,1/(('Daily AUM'!$D10:K10<>"")*(NAV!$D10:K10<>"")),'Daily AUM'!$D10:K10),"")="",IFERROR(LOOKUP(2,1/(('Daily AUM'!$D10:K10<>"")*(NAV!$D10:K10<>"")),NAV!$D10:K10),"")=""),0,'Daily AUM'!L10-(IFERROR(LOOKUP(2,1/(('Daily AUM'!$D10:K10<>"")*(NAV!$D10:K10<>"")),'Daily AUM'!$D10:K10),"")*(NAV!L10/IFERROR(LOOKUP(2,1/(('Daily AUM'!$D10:K10<>"")*(NAV!$D10:K10<>"")),NAV!$D10:K10),"")))),0)) -> 24.727794 | ... AR10: =IF(OR('Daily AUM'!AR10="",NAV!AR10=""),0,IFERROR(IF(OR(IFERROR(LOOKUP(2,1/(('Daily AUM'!$D10:AQ10<>"")*(NAV!$D10:AQ10<>"")),'Daily AUM'!$D10:AQ10),"")="",IFERROR(LOOKUP(2,1/(('Daily AUM'!$D10:AQ10<>"")*(NAV!$D10:AQ10<>"")),NAV!$D10:AQ10),"")=""),0,'Daily AUM'!AR10-(IFERROR(LOOKUP(2,1/(('Daily AUM'!$D10:AQ10<>"")*(NAV!$D10:AQ10<>"")),'Daily AUM'!$D10:AQ10),"")*(NAV!AR10/IFERROR(LOOKUP(2,1/(('Daily AUM'!$D10:AQ10<>"")*(NAV!$D10:AQ10<>"")),NAV!$D10:AQ10),"")))),0)) -> 4.0063991 | AS10: =SUM(F10:Y10) -> 119.00584 | AT10: =SUM(Z10:AR10) -> 53.448102
A11: Aditya Birla Sun Life Banking & Financial Services Fund | B11: Aditya Birla Sun Life | C11: SECTORAL / THEMATIC | D11: =0 -> 0 | E11: =IF(OR('Daily AUM'!E11="",NAV!E11=""),0,IFERROR(IF(OR(IFERROR(LOOKUP(2,1/(('Daily AUM'!$D11:D11<>"")*(NAV!$D11:D11<>"")),'Daily AUM'!$D11:D11),"")="",IFERROR(LOOKUP(2,1/(('Daily AUM'!$D11:D11<>"")*(NAV!$D11:D11<>"")),NAV!$D11:D11),"")=""),0,'Daily AUM'!E11-(IFERROR(LOOKUP(2,1/(('Daily AUM'!$D11:D11<>"")*(NAV!$D11:D11<>"")),'Daily AUM'!$D11:D11),"")*(NAV!E11/IFERROR(LOOKUP(2,1/(('Daily AUM'!$D11:D11<>"")*(NAV!$D11:D11<>"")),NAV!$D11:D11),"")))),0)) -> 0.019980278 | F11: =IF(OR('Daily AUM'!F11="",NAV!F11=""),0,IFERROR(IF(OR(IFERROR(LOOKUP(2,1/(('Daily AUM'!$D11:E11<>"")*(NAV!$D11:E11<>"")),'Daily AUM'!$D11:E11),"")="",IFERROR(LOOKUP(2,1/(('Daily AUM'!$D11:E11<>"")*(NAV!$D11:E11<>"")),NAV!$D11:E11),"")=""),0,'Daily AUM'!F11-(IFERROR(LOOKUP(2,1/(('Daily AUM'!$D11:E11<>"")*(NAV!$D11:E11<>"")),'Daily AUM'!$D11:E11),"")*(NAV!F11/IFERROR(LOOKUP(2,1/(('Daily AUM'!$D11:E11<>"")*(NAV!$D11:E11<>"")),NAV!$D11:E11),"")))),0)) -> -0.28833996 | G11: =IF(OR('Daily AUM'!G11="",NAV!G11=""),0,IFERROR(IF(OR(IFERROR(LOOKUP(2,1/(('Daily AUM'!$D11:F11<>"")*(NAV!$D11:F11<>"")),'Daily AUM'!$D11:F11),"")="",IFERROR(LOOKUP(2,1/(('Daily AUM'!$D11:F11<>"")*(NAV!$D11:F11<>"")),NAV!$D11:F11),"")=""),0,'Daily AUM'!G11-(IFERROR(LOOKUP(2,1/(('Daily AUM'!$D11:F11<>"")*(NAV!$D11:F11<>"")),'Daily AUM'!$D11:F11),"")*(NAV!G11/IFERROR(LOOKUP(2,1/(('Daily AUM'!$D11:F11<>"")*(NAV!$D11:F11<>"")),NAV!$D11:F11),"")))),0)) -> -0.41192628 | H11: =IF(OR('Daily AUM'!H11="",NAV!H11=""),0,IFERROR(IF(OR(IFERROR(LOOKUP(2,1/(('Daily AUM'!$D11:G11<>"")*(NAV!$D11:G11<>"")),'Daily AUM'!$D11:G11),"")="",IFERROR(LOOKUP(2,1/(('Daily AUM'!$D11:G11<>"")*(NAV!$D11:G11<>"")),NAV!$D11:G11),"")=""),0,'Daily AUM'!H11-(IFERROR(LOOKUP(2,1/(('Daily AUM'!$D11:G11<>"")*(NAV!$D11:G11<>"")),'Daily AUM'!$D11:G11),"")*(NAV!H11/IFERROR(LOOKUP(2,1/(('Daily AUM'!$D11:G11<>"")*(NAV!$D11:G11<>"")),NAV!$D11:G11),"")))),0)) -> 3.9005814 | I11: =IF(OR('Daily AUM'!I11="",NAV!I11=""),0,IFERROR(IF(OR(IFERROR(LOOKUP(2,1/(('Daily AUM'!$D11:H11<>"")*(NAV!$D11:H11<>"")),'Daily AUM'!$D11:H11),"")="",IFERROR(LOOKUP(2,1/(('Daily AUM'!$D11:H11<>"")*(NAV!$D11:H11<>"")),NAV!$D11:H11),"")=""),0,'Daily AUM'!I11-(IFERROR(LOOKUP(2,1/(('Daily AUM'!$D11:H11<>"")*(NAV!$D11:H11<>"")),'Daily AUM'!$D11:H11),"")*(NAV!I11/IFERROR(LOOKUP(2,1/(('Daily AUM'!$D11:H11<>"")*(NAV!$D11:H11<>"")),NAV!$D11:H11),"")))),0)) -> 1.2222855 | J11: =IF(OR('Daily AUM'!J11="",NAV!J11=""),0,IFERROR(IF(OR(IFERROR(LOOKUP(2,1/(('Daily AUM'!$D11:I11<>"")*(NAV!$D11:I11<>"")),'Daily AUM'!$D11:I11),"")="",IFERROR(LOOKUP(2,1/(('Daily AUM'!$D11:I11<>"")*(NAV!$D11:I11<>"")),NAV!$D11:I11),"")=""),0,'Daily AUM'!J11-(IFERROR(LOOKUP(2,1/(('Daily AUM'!$D11:I11<>"")*(NAV!$D11:I11<>"")),'Daily AUM'!$D11:I11),"")*(NAV!J11/IFERROR(LOOKUP(2,1/(('Daily AUM'!$D11:I11<>"")*(NAV!$D11:I11<>"")),NAV!$D11:I11),"")))),0)) -> 0.62346673 | K11: =IF(OR('Daily AUM'!K11="",NAV!K11=""),0,IFERROR(IF(OR(IFERROR(LOOKUP(2,1/(('Daily AUM'!$D11:J11<>"")*(NAV!$D11:J11<>"")),'Daily AUM'!$D11:J11),"")="",IFERROR(LOOKUP(2,1/(('Daily AUM'!$D11:J11<>"")*(NAV!$D11:J11<>"")),NAV!$D11:J11),"")=""),0,'Daily AUM'!K11-(IFERROR(LOOKUP(2,1/(('Daily AUM'!$D11:J11<>"")*(NAV!$D11:J11<>"")),'Daily AUM'!$D11:J11),"")*(NAV!K11/IFERROR(LOOKUP(2,1/(('Daily AUM'!$D11:J11<>"")*(NAV!$D11:J11<>"")),NAV!$D11:J11),"")))),0)) -> 0.90399489 | L11: =IF(OR('Daily AUM'!L11="",NAV!L11=""),0,IFERROR(IF(OR(IFERROR(LOOKUP(2,1/(('Daily AUM'!$D11:K11<>"")*(NAV!$D11:K11<>"")),'Daily AUM'!$D11:K11),"")="",IFERROR(LOOKUP(2,1/(('Daily AUM'!$D11:K11<>"")*(NAV!$D11:K11<>"")),NAV!$D11:K11),"")=""),0,'Daily AUM'!L11-(IFERROR(LOOKUP(2,1/(('Daily AUM'!$D11:K11<>"")*(NAV!$D11:K11<>"")),'Daily AUM'!$D11:K11),"")*(NAV!L11/IFERROR(LOOKUP(2,1/(('Daily AUM'!$D11:K11<>"")*(NAV!$D11:K11<>"")),NAV!$D11:K11),"")))),0)) -> -2.0269873 | ... AR11: =IF(OR('Daily AUM'!AR11="",NAV!AR11=""),0,IFERROR(IF(OR(IFERROR(LOOKUP(2,1/(('Daily AUM'!$D11:AQ11<>"")*(NAV!$D11:AQ11<>"")),'Daily AUM'!$D11:AQ11),"")="",IFERROR(LOOKUP(2,1/(('Daily AUM'!$D11:AQ11<>"")*(NAV!$D11:AQ11<>"")),NAV!$D11:AQ11),"")=""),0,'Daily AUM'!AR11-(IFERROR(LOOKUP(2,1/(('Daily AUM'!$D11:AQ11<>"")*(NAV!$D11:AQ11<>"")),'Daily AUM'!$D11:AQ11),"")*(NAV!AR11/IFERROR(LOOKUP(2,1/(('Daily AUM'!$D11:AQ11<>"")*(NAV!$D11:AQ11<>"")),NAV!$D11:AQ11),"")))),0)) -> -1.0727514 | AS11: =SUM(F11:Y11) -> 16.641577 | AT11: =SUM(Z11:AR11) -> -13.435794
