Workbook

Sheet USD summary 2005-2025
A1: UBS wealth management – revenue mix in USD, 2005–2025
A2: All figures USD millions, CHF years converted at each year's average rate (FX tab). A year shows a number only when every unit in that year has it; otherwise the cell is blank – see Raw data for the unit-level figures.
A4: Year | B4: Perimeter | C4: Basis | D4: Total revenue (USD m) | E4: Net interest income | F4: Recurring net fees | G4: Transaction-based | H4: Other revenues | I4: Recurring (old: NII+fees) | J4: Non-recurring (old) | K4: Sum of income lines | L4: NII share | M4: Recurring fee share | N4: Transaction share | O4: Other revenues share | P4: Recurring share (NII+fees) – continuous series | Q4: Note
A5: 2005 | B5: WM Intl & Switzerland + WM US | C5: Old (recurring vs non-recurring) | D5: =IF(SUMPRODUCT(('Raw data (as reported)'!$A$5:$A$37=$A5)*ISNUMBER('Raw data (as reported)'!T$5:T$37))=COUNTIF('Raw data (as reported)'!$A$5:$A$37,$A5),SUMIFS('Raw data (as reported)'!T$5:T$37,'Raw data (as reported)'!$A$5:$A$37,$A5),"") -> 11370.897 | E5: =IF(SUMPRODUCT(('Raw data (as reported)'!$A$5:$A$37=$A5)*ISNUMBER('Raw data (as reported)'!N$5:N$37))=COUNTIF('Raw data (as reported)'!$A$5:$A$37,$A5),SUMIFS('Raw data (as reported)'!N$5:N$37,'Raw data (as reported)'!$A$5:$A$37,$A5),"") | F5: =IF(SUMPRODUCT(('Raw data (as reported)'!$A$5:$A$37=$A5)*ISNUMBER('Raw data (as reported)'!O$5:O$37))=COUNTIF('Raw data (as reported)'!$A$5:$A$37,$A5),SUMIFS('Raw data (as reported)'!O$5:O$37,'Raw data (as reported)'!$A$5:$A$37,$A5),"") | G5: =IF(SUMPRODUCT(('Raw data (as reported)'!$A$5:$A$37=$A5)*ISNUMBER('Raw data (as reported)'!P$5:P$37))=COUNTIF('Raw data (as reported)'!$A$5:$A$37,$A5),SUMIFS('Raw data (as reported)'!P$5:P$37,'Raw data (as reported)'!$A$5:$A$37,$A5),"") | H5: =IF(SUMPRODUCT(('Raw data (as reported)'!$A$5:$A$37=$A5)*ISNUMBER('Raw data (as reported)'!Q$5:Q$37))=COUNTIF('Raw data (as reported)'!$A$5:$A$37,$A5),SUMIFS('Raw data (as reported)'!Q$5:Q$37,'Raw data (as reported)'!$A$5:$A$37,$A5),"") | I5: =IF(SUMPRODUCT(('Raw data (as reported)'!$A$5:$A$37=$A5)*ISNUMBER('Raw data (as reported)'!R$5:R$37))=COUNTIF('Raw data (as reported)'!$A$5:$A$37,$A5),SUMIFS('Raw data (as reported)'!R$5:R$37,'Raw data (as reported)'!$A$5:$A$37,$A5),"") | J5: =IF(SUMPRODUCT(('Raw data (as reported)'!$A$5:$A$37=$A5)*ISNUMBER('Raw data (as reported)'!S$5:S$37))=COUNTIF('Raw data (as reported)'!$A$5:$A$37,$A5),SUMIFS('Raw data (as reported)'!S$5:S$37,'Raw data (as reported)'!$A$5:$A$37,$A5),"") | K5: =IF(AND(ISNUMBER(E5),ISNUMBER(F5),ISNUMBER(G5)),E5+F5+G5+IF(ISNUMBER(H5),H5,0),"") | L5: =IF(ISNUMBER(K5),E5/K5,"") | M5: =IF(ISNUMBER(K5),F5/K5,"") | N5: =IF(ISNUMBER(K5),G5/K5,"") | O5: =IF(AND(ISNUMBER(K5),ISNUMBER(H5)),H5/K5,"") | P5: =IF(ISNUMBER(K5),(E5+F5)/K5,IF(AND(ISNUMBER(I5),ISNUMBER(J5)),I5/(I5+J5),"")) | Q5: Recurring split only for WM US (55% recurring) – see Raw.
A6: 2006 | B6: WM Intl & Switzerland + WM US | C6: Old (recurring vs non-recurring) | D6: =IF(SUMPRODUCT(('Raw data (as reported)'!$A$5:$A$37=$A6)*ISNUMBER('Raw data (as reported)'!T$5:T$37))=COUNTIF('Raw data (as reported)'!$A$5:$A$37,$A6),SUMIFS('Raw data (as reported)'!T$5:T$37,'Raw data (as reported)'!$A$5:$A$37,$A6),"") -> 13294.765 | E6: =IF(SUMPRODUCT(('Raw data (as reported)'!$A$5:$A$37=$A6)*ISNUMBER('Raw data (as reported)'!N$5:N$37))=COUNTIF('Raw data (as reported)'!$A$5:$A$37,$A6),SUMIFS('Raw data (as reported)'!N$5:N$37,'Raw data (as reported)'!$A$5:$A$37,$A6),"") | F6: =IF(SUMPRODUCT(('Raw data (as reported)'!$A$5:$A$37=$A6)*ISNUMBER('Raw data (as reported)'!O$5:O$37))=COUNTIF('Raw data (as reported)'!$A$5:$A$37,$A6),SUMIFS('Raw data (as reported)'!O$5:O$37,'Raw data (as reported)'!$A$5:$A$37,$A6),"") | G6: =IF(SUMPRODUCT(('Raw data (as reported)'!$A$5:$A$37=$A6)*ISNUMBER('Raw data (as reported)'!P$5:P$37))=COUNTIF('Raw data (as reported)'!$A$5:$A$37,$A6),SUMIFS('Raw data (as reported)'!P$5:P$37,'Raw data (as reported)'!$A$5:$A$37,$A6),"") | H6: =IF(SUMPRODUCT(('Raw data (as reported)'!$A$5:$A$37=$A6)*ISNUMBER('Raw data (as reported)'!Q$5:Q$37))=COUNTIF('Raw data (as reported)'!$A$5:$A$37,$A6),SUMIFS('Raw data (as reported)'!Q$5:Q$37,'Raw data (as reported)'!$A$5:$A$37,$A6),"") | I6: =IF(SUMPRODUCT(('Raw data (as reported)'!$A$5:$A$37=$A6)*ISNUMBER('Raw data (as reported)'!R$5:R$37))=COUNTIF('Raw data (as reported)'!$A$5:$A$37,$A6),SUMIFS('Raw data (as reported)'!R$5:R$37,'Raw data (as reported)'!$A$5:$A$37,$A6),"") | J6: =IF(SUMPRODUCT(('Raw data (as reported)'!$A$5:$A$37=$A6)*ISNUMBER('Raw data (as reported)'!S$5:S$37))=COUNTIF('Raw data (as reported)'!$A$5:$A$37,$A6),SUMIFS('Raw data (as reported)'!S$5:S$37,'Raw data (as reported)'!$A$5:$A$37,$A6),"") | K6: =IF(AND(ISNUMBER(E6),ISNUMBER(F6),ISNUMBER(G6)),E6+F6+G6+IF(ISNUMBER(H6),H6,0),"") | L6: =IF(ISNUMBER(K6),E6/K6,"") | M6: =IF(ISNUMBER(K6),F6/K6,"") | N6: =IF(ISNUMBER(K6),G6/K6,"") | O6: =IF(AND(ISNUMBER(K6),ISNUMBER(H6)),H6/K6,"") | P6: =IF(ISNUMBER(K6),(E6+F6)/K6,IF(AND(ISNUMBER(I6),ISNUMBER(J6)),I6/(I6+J6),"")) | Q6: Recurring split only for WM US (59% recurring) – see Raw.
A7: 2007 | B7: WM Intl & Switzerland + WM US | C7: Old (recurring vs non-recurring) | D7: =IF(SUMPRODUCT(('Raw data (as reported)'!$A$5:$A$37=$A7)*ISNUMBER('Raw data (as reported)'!T$5:T$37))=COUNTIF('Raw data (as reported)'!$A$5:$A$37,$A7),SUMIFS('Raw data (as reported)'!T$5:T$37,'Raw data (as reported)'!$A$5:$A$37,$A7),"") | E7: =IF(SUMPRODUCT(('Raw data (as reported)'!$A$5:$A$37=$A7)*ISNUMBER('Raw data (as reported)'!N$5:N$37))=COUNTIF('Raw data (as reported)'!$A$5:$A$37,$A7),SUMIFS('Raw data (as reported)'!N$5:N$37,'Raw data (as reported)'!$A$5:$A$37,$A7),"") | F7: =IF(SUMPRODUCT(('Raw data (as reported)'!$A$5:$A$37=$A7)*ISNUMBER('Raw data (as reported)'!O$5:O$37))=COUNTIF('Raw data (as reported)'!$A$5:$A$37,$A7),SUMIFS('Raw data (as reported)'!O$5:O$37,'Raw data (as reported)'!$A$5:$A$37,$A7),"") | G7: =IF(SUMPRODUCT(('Raw data (as reported)'!$A$5:$A$37=$A7)*ISNUMBER('Raw data (as reported)'!P$5:P$37))=COUNTIF('Raw data (as reported)'!$A$5:$A$37,$A7),SUMIFS('Raw data (as reported)'!P$5:P$37,'Raw data (as reported)'!$A$5:$A$37,$A7),"") | H7: =IF(SUMPRODUCT(('Raw data (as reported)'!$A$5:$A$37=$A7)*ISNUMBER('Raw data (as reported)'!Q$5:Q$37))=COUNTIF('Raw data (as reported)'!$A$5:$A$37,$A7),SUMIFS('Raw data (as reported)'!Q$5:Q$37,'Raw data (as reported)'!$A$5:$A$37,$A7),"") | I7: =IF(SUMPRODUCT(('Raw data (as reported)'!$A$5:$A$37=$A7)*ISNUMBER('Raw data (as reported)'!R$5:R$37))=COUNTIF('Raw data (as reported)'!$A$5:$A$37,$A7),SUMIFS('Raw data (as reported)'!R$5:R$37,'Raw data (as reported)'!$A$5:$A$37,$A7),"") | J7: =IF(SUMPRODUCT(('Raw data (as reported)'!$A$5:$A$37=$A7)*ISNUMBER('Raw data (as reported)'!S$5:S$37))=COUNTIF('Raw data (as reported)'!$A$5:$A$37,$A7),SUMIFS('Raw data (as reported)'!S$5:S$37,'Raw data (as reported)'!$A$5:$A$37,$A7),"") | K7: =IF(AND(ISNUMBER(E7),ISNUMBER(F7),ISNUMBER(G7)),E7+F7+G7+IF(ISNUMBER(H7),H7,0),"") | L7: =IF(ISNUMBER(K7),E7/K7,"") | M7: =IF(ISNUMBER(K7),F7/K7,"") | N7: =IF(ISNUMBER(K7),G7/K7,"") | O7: =IF(AND(ISNUMBER(K7),ISNUMBER(H7)),H7/K7,"") | P7: =IF(ISNUMBER(K7),(E7+F7)/K7,IF(AND(ISNUMBER(I7),ISNUMBER(J7)),I7/(I7+J7),"")) | Q7: Annual totals not found; WM US recurring USD 3.5bn. 3Q07 Intl & Swiss unit: 75% recurring.
A8: 2008 | B8: WM + WM Americas | C8: Old (recurring vs non-recurring) | D8: =IF(SUMPRODUCT(('Raw data (as reported)'!$A$5:$A$37=$A8)*ISNUMBER('Raw data (as reported)'!T$5:T$37))=COUNTIF('Raw data (as reported)'!$A$5:$A$37,$A8),SUMIFS('Raw data (as reported)'!T$5:T$37,'Raw data (as reported)'!$A$5:$A$37,$A8),"") | E8: =IF(SUMPRODUCT(('Raw data (as reported)'!$A$5:$A$37=$A8)*ISNUMBER('Raw data (as reported)'!N$5:N$37))=COUNTIF('Raw data (as reported)'!$A$5:$A$37,$A8),SUMIFS('Raw data (as reported)'!N$5:N$37,'Raw data (as reported)'!$A$5:$A$37,$A8),"") | F8: =IF(SUMPRODUCT(('Raw data (as reported)'!$A$5:$A$37=$A8)*ISNUMBER('Raw data (as reported)'!O$5:O$37))=COUNTIF('Raw data (as reported)'!$A$5:$A$37,$A8),SUMIFS('Raw data (as reported)'!O$5:O$37,'Raw data (as reported)'!$A$5:$A$37,$A8),"") | G8: =IF(SUMPRODUCT(('Raw data (as reported)'!$A$5:$A$37=$A8)*ISNUMBER('Raw data (as reported)'!P$5:P$37))=COUNTIF('Raw data (as reported)'!$A$5:$A$37,$A8),SUMIFS('Raw data (as reported)'!P$5:P$37,'Raw data (as reported)'!$A$5:$A$37,$A8),"") | H8: =IF(SUMPRODUCT(('Raw data (as reported)'!$A$5:$A$37=$A8)*ISNUMBER('Raw data (as reported)'!Q$5:Q$37))=COUNTIF('Raw data (as reported)'!$A$5:$A$37,$A8),SUMIFS('Raw data (as reported)'!Q$5:Q$37,'Raw data (as reported)'!$A$5:$A$37,$A8),"") | I8: =IF(SUMPRODUCT(('Raw data (as reported)'!$A$5:$A$37=$A8)*ISNUMBER('Raw data (as reported)'!R$5:R$37))=COUNTIF('Raw data (as reported)'!$A$5:$A$37,$A8),SUMIFS('Raw data (as reported)'!R$5:R$37,'Raw data (as reported)'!$A$5:$A$37,$A8),"") | J8: =IF(SUMPRODUCT(('Raw data (as reported)'!$A$5:$A$37=$A8)*ISNUMBER('Raw data (as reported)'!S$5:S$37))=COUNTIF('Raw data (as reported)'!$A$5:$A$37,$A8),SUMIFS('Raw data (as reported)'!S$5:S$37,'Raw data (as reported)'!$A$5:$A$37,$A8),"") | K8: =IF(AND(ISNUMBER(E8),ISNUMBER(F8),ISNUMBER(G8)),E8+F8+G8+IF(ISNUMBER(H8),H8,0),"") | L8: =IF(ISNUMBER(K8),E8/K8,"") | M8: =IF(ISNUMBER(K8),F8/K8,"") | N8: =IF(ISNUMBER(K8),G8/K8,"") | O8: =IF(AND(ISNUMBER(K8),ISNUMBER(H8)),H8/K8,"") | P8: =IF(ISNUMBER(K8),(E8+F8)/K8,IF(AND(ISNUMBER(I8),ISNUMBER(J8)),I8/(I8+J8),"")) | Q8: Only WM Americas found (65% recurring) – see Raw.
A9: 2009 | B9: WM + WM Americas | C9: Old (recurring vs non-recurring) | D9: =IF(SUMPRODUCT(('Raw data (as reported)'!$A$5:$A$37=$A9)*ISNUMBER('Raw data (as reported)'!T$5:T$37))=COUNTIF('Raw data (as reported)'!$A$5:$A$37,$A9),SUMIFS('Raw data (as reported)'!T$5:T$37,'Raw data (as reported)'!$A$5:$A$37,$A9),"") -> 11945.672 | E9: =IF(SUMPRODUCT(('Raw data (as reported)'!$A$5:$A$37=$A9)*ISNUMBER('Raw data (as reported)'!N$5:N$37))=COUNTIF('Raw data (as reported)'!$A$5:$A$37,$A9),SUMIFS('Raw data (as reported)'!N$5:N$37,'Raw data (as reported)'!$A$5:$A$37,$A9),"") | F9: =IF(SUMPRODUCT(('Raw data (as reported)'!$A$5:$A$37=$A9)*ISNUMBER('Raw data (as reported)'!O$5:O$37))=COUNTIF('Raw data (as reported)'!$A$5:$A$37,$A9),SUMIFS('Raw data (as reported)'!O$5:O$37,'Raw data (as reported)'!$A$5:$A$37,$A9),"") | G9: =IF(SUMPRODUCT(('Raw data (as reported)'!$A$5:$A$37=$A9)*ISNUMBER('Raw data (as reported)'!P$5:P$37))=COUNTIF('Raw data (as reported)'!$A$5:$A$37,$A9),SUMIFS('Raw data (as reported)'!P$5:P$37,'Raw data (as reported)'!$A$5:$A$37,$A9),"") | H9: =IF(SUMPRODUCT(('Raw data (as reported)'!$A$5:$A$37=$A9)*ISNUMBER('Raw data (as reported)'!Q$5:Q$37))=COUNTIF('Raw data (as reported)'!$A$5:$A$37,$A9),SUMIFS('Raw data (as reported)'!Q$5:Q$37,'Raw data (as reported)'!$A$5:$A$37,$A9),"") | I9: =IF(SUMPRODUCT(('Raw data (as reported)'!$A$5:$A$37=$A9)*ISNUMBER('Raw data (as reported)'!R$5:R$37))=COUNTIF('Raw data (as reported)'!$A$5:$A$37,$A9),SUMIFS('Raw data (as reported)'!R$5:R$37,'Raw data (as reported)'!$A$5:$A$37,$A9),"") -> 8243.0939 | J9: =IF(SUMPRODUCT(('Raw data (as reported)'!$A$5:$A$37=$A9)*ISNUMBER('Raw data (as reported)'!S$5:S$37))=COUNTIF('Raw data (as reported)'!$A$5:$A$37,$A9),SUMIFS('Raw data (as reported)'!S$5:S$37,'Raw data (as reported)'!$A$5:$A$37,$A9),"") -> 3702.5783 | K9: =IF(AND(ISNUMBER(E9),ISNUMBER(F9),ISNUMBER(G9)),E9+F9+G9+IF(ISNUMBER(H9),H9,0),"") | L9: =IF(ISNUMBER(K9),E9/K9,"") | M9: =IF(ISNUMBER(K9),F9/K9,"") | N9: =IF(ISNUMBER(K9),G9/K9,"") | O9: =IF(AND(ISNUMBER(K9),ISNUMBER(H9)),H9/K9,"") | P9: =IF(ISNUMBER(K9),(E9+F9)/K9,IF(AND(ISNUMBER(I9),ISNUMBER(J9)),I9/(I9+J9),"")) -> 0.69004856
A10: 2010 | B10: WM + WM Americas | C10: Old (recurring vs non-recurring) | D10: =IF(SUMPRODUCT(('Raw data (as reported)'!$A$5:$A$37=$A10)*ISNUMBER('Raw data (as reported)'!T$5:T$37))=COUNTIF('Raw data (as reported)'!$A$5:$A$37,$A10),SUMIFS('Raw data (as reported)'!T$5:T$37,'Raw data (as reported)'!$A$5:$A$37,$A10),"") -> 12375.383 | E10: =IF(SUMPRODUCT(('Raw data (as reported)'!$A$5:$A$37=$A10)*ISNUMBER('Raw data (as reported)'!N$5:N$37))=COUNTIF('Raw data (as reported)'!$A$5:$A$37,$A10),SUMIFS('Raw data (as reported)'!N$5:N$37,'Raw data (as reported)'!$A$5:$A$37,$A10),"") | F10: =IF(SUMPRODUCT(('Raw data (as reported)'!$A$5:$A$37=$A10)*ISNUMBER('Raw data (as reported)'!O$5:O$37))=COUNTIF('Raw data (as reported)'!$A$5:$A$37,$A10),SUMIFS('Raw data (as reported)'!O$5:O$37,'Raw data (as reported)'!$A$5:$A$37,$A10),"") | G10: =IF(SUMPRODUCT(('Raw data (as reported)'!$A$5:$A$37=$A10)*ISNUMBER('Raw data (as reported)'!P$5:P$37))=COUNTIF('Raw data (as reported)'!$A$5:$A$37,$A10),SUMIFS('Raw data (as reported)'!P$5:P$37,'Raw data (as reported)'!$A$5:$A$37,$A10),"") | H10: =IF(SUMPRODUCT(('Raw data (as reported)'!$A$5:$A$37=$A10)*ISNUMBER('Raw data (as reported)'!Q$5:Q$37))=COUNTIF('Raw data (as reported)'!$A$5:$A$37,$A10),SUMIFS('Raw data (as reported)'!Q$5:Q$37,'Raw data (as reported)'!$A$5:$A$37,$A10),"") | I10: =IF(SUMPRODUCT(('Raw data (as reported)'!$A$5:$A$37=$A10)*ISNUMBER('Raw data (as reported)'!R$5:R$37))=COUNTIF('Raw data (as reported)'!$A$5:$A$37,$A10),SUMIFS('Raw data (as reported)'!R$5:R$37,'Raw data (as reported)'!$A$5:$A$37,$A10),"") -> 8515.1457 | J10: =IF(SUMPRODUCT(('Raw data (as reported)'!$A$5:$A$37=$A10)*ISNUMBER('Raw data (as reported)'!S$5:S$37))=COUNTIF('Raw data (as reported)'!$A$5:$A$37,$A10),SUMIFS('Raw data (as reported)'!S$5:S$37,'Raw data (as reported)'!$A$5:$A$37,$A10),"") -> 3860.2377 | K10: =IF(AND(ISNUMBER(E10),ISNUMBER(F10),ISNUMBER(G10)),E10+F10+G10+IF(ISNUMBER(H10),H10,0),"") | L10: =IF(ISNUMBER(K10),E10/K10,"") | M10: =IF(ISNUMBER(K10),F10/K10,"") | N10: =IF(ISNUMBER(K10),G10/K10,"") | O10: =IF(AND(ISNUMBER(K10),ISNUMBER(H10)),H10/K10,"") | P10: =IF(ISNUMBER(K10),(E10+F10)/K10,IF(AND(ISNUMBER(I10),ISNUMBER(J10)),I10/(I10+J10),"")) -> 0.68807126
A11: 2011 | B11: WM + WM Americas | C11: Accounting lines | D11: =IF(SUMPRODUCT(('Raw data (as reported)'!$A$5:$A$37=$A11)*ISNUMBER('Raw data (as reported)'!T$5:T$37))=COUNTIF('Raw data (as reported)'!$A$5:$A$37,$A11),SUMIFS('Raw data (as reported)'!T$5:T$37,'Raw data (as reported)'!$A$5:$A$37,$A11),"") -> 14631.308 | E11: =IF(SUMPRODUCT(('Raw data (as reported)'!$A$5:$A$37=$A11)*ISNUMBER('Raw data (as reported)'!N$5:N$37))=COUNTIF('Raw data (as reported)'!$A$5:$A$37,$A11),SUMIFS('Raw data (as reported)'!N$5:N$37,'Raw data (as reported)'!$A$5:$A$37,$A11),"") -> 3048.7177 | F11: =IF(SUMPRODUCT(('Raw data (as reported)'!$A$5:$A$37=$A11)*ISNUMBER('Raw data (as reported)'!O$5:O$37))=COUNTIF('Raw data (as reported)'!$A$5:$A$37,$A11),SUMIFS('Raw data (as reported)'!O$5:O$37,'Raw data (as reported)'!$A$5:$A$37,$A11),"") | G11: =IF(SUMPRODUCT(('Raw data (as reported)'!$A$5:$A$37=$A11)*ISNUMBER('Raw data (as reported)'!P$5:P$37))=COUNTIF('Raw data (as reported)'!$A$5:$A$37,$A11),SUMIFS('Raw data (as reported)'!P$5:P$37,'Raw data (as reported)'!$A$5:$A$37,$A11),"") | H11: =IF(SUMPRODUCT(('Raw data (as reported)'!$A$5:$A$37=$A11)*ISNUMBER('Raw data (as reported)'!Q$5:Q$37))=COUNTIF('Raw data (as reported)'!$A$5:$A$37,$A11),SUMIFS('Raw data (as reported)'!Q$5:Q$37,'Raw data (as reported)'!$A$5:$A$37,$A11),"") -> 600.57572 | I11: =IF(SUMPRODUCT(('Raw data (as reported)'!$A$5:$A$37=$A11)*ISNUMBER('Raw data (as reported)'!R$5:R$37))=COUNTIF('Raw data (as reported)'!$A$5:$A$37,$A11),SUMIFS('Raw data (as reported)'!R$5:R$37,'Raw data (as reported)'!$A$5:$A$37,$A11),"") | J11: =IF(SUMPRODUCT(('Raw data (as reported)'!$A$5:$A$37=$A11)*ISNUMBER('Raw data (as reported)'!S$5:S$37))=COUNTIF('Raw data (as reported)'!$A$5:$A$37,$A11),SUMIFS('Raw data (as reported)'!S$5:S$37,'Raw data (as reported)'!$A$5:$A$37,$A11),"") | K11: =IF(AND(ISNUMBER(E11),ISNUMBER(F11),ISNUMBER(G11)),E11+F11+G11+IF(ISNUMBER(H11),H11,0),"") | L11: =IF(ISNUMBER(K11),E11/K11,"") | M11: =IF(ISNUMBER(K11),F11/K11,"") | N11: =IF(ISNUMBER(K11),G11/K11,"") | O11: =IF(AND(ISNUMBER(K11),ISNUMBER(H11)),H11/K11,"") | P11: =IF(ISNUMBER(K11),(E11+F11)/K11,IF(AND(ISNUMBER(I11),ISNUMBER(J11)),I11/(I11+J11),"")) | Q11: Only NII, other income and totals disclosed on a comparable basis.
A12: 2012 | B12: WM + WM Americas | C12: Accounting lines | D12: =IF(SUMPRODUCT(('Raw data (as reported)'!$A$5:$A$37=$A12)*ISNUMBER('Raw data (as reported)'!T$5:T$37))=COUNTIF('Raw data (as reported)'!$A$5:$A$37,$A12),SUMIFS('Raw data (as reported)'!T$5:T$37,'Raw data (as reported)'!$A$5:$A$37,$A12),"") -> 14054.732 | E12: =IF(SUMPRODUCT(('Raw data (as reported)'!$A$5:$A$37=$A12)*ISNUMBER('Raw data (as reported)'!N$5:N$37))=COUNTIF('Raw data (as reported)'!$A$5:$A$37,$A12),SUMIFS('Raw data (as reported)'!N$5:N$37,'Raw data (as reported)'!$A$5:$A$37,$A12),"") -> 2929.6228 | F12: =IF(SUMPRODUCT(('Raw data (as reported)'!$A$5:$A$37=$A12)*ISNUMBER('Raw data (as reported)'!O$5:O$37))=COUNTIF('Raw data (as reported)'!$A$5:$A$37,$A12),SUMIFS('Raw data (as reported)'!O$5:O$37,'Raw data (as reported)'!$A$5:$A$37,$A12),"") | G12: =IF(SUMPRODUCT(('Raw data (as reported)'!$A$5:$A$37=$A12)*ISNUMBER('Raw data (as reported)'!P$5:P$37))=COUNTIF('Raw data (as reported)'!$A$5:$A$37,$A12),SUMIFS('Raw data (as reported)'!P$5:P$37,'Raw data (as reported)'!$A$5:$A$37,$A12),"") | H12: =IF(SUMPRODUCT(('Raw data (as reported)'!$A$5:$A$37=$A12)*ISNUMBER('Raw data (as reported)'!Q$5:Q$37))=COUNTIF('Raw data (as reported)'!$A$5:$A$37,$A12),SUMIFS('Raw data (as reported)'!Q$5:Q$37,'Raw data (as reported)'!$A$5:$A$37,$A12),"") -> 305.45825 | I12: =IF(SUMPRODUCT(('Raw data (as reported)'!$A$5:$A$37=$A12)*ISNUMBER('Raw data (as reported)'!R$5:R$37))=COUNTIF('Raw data (as reported)'!$A$5:$A$37,$A12),SUMIFS('Raw data (as reported)'!R$5:R$37,'Raw data (as reported)'!$A$5:$A$37,$A12),"") | J12: =IF(SUMPRODUCT(('Raw data (as reported)'!$A$5:$A$37=$A12)*ISNUMBER('Raw data (as reported)'!S$5:S$37))=COUNTIF('Raw data (as reported)'!$A$5:$A$37,$A12),SUMIFS('Raw data (as reported)'!S$5:S$37,'Raw data (as reported)'!$A$5:$A$37,$A12),"") | K12: =IF(AND(ISNUMBER(E12),ISNUMBER(F12),ISNUMBER(G12)),E12+F12+G12+IF(ISNUMBER(H12),H12,0),"") | L12: =IF(ISNUMBER(K12),E12/K12,"") | M12: =IF(ISNUMBER(K12),F12/K12,"") | N12: =IF(ISNUMBER(K12),G12/K12,"") | O12: =IF(AND(ISNUMBER(K12),ISNUMBER(H12)),H12/K12,"") | P12: =IF(ISNUMBER(K12),(E12+F12)/K12,IF(AND(ISNUMBER(I12),ISNUMBER(J12)),I12/(I12+J12),"")) | Q12: Only NII, other income and totals disclosed on a comparable basis.
A13: 2013 | B13: WM + WM Americas | C13: New (NII / fees / transaction / other) | D13: =IF(SUMPRODUCT(('Raw data (as reported)'!$A$5:$A$37=$A13)*ISNUMBER('Raw data (as reported)'!T$5:T$37))=COUNTIF('Raw data (as reported)'!$A$5:$A$37,$A13),SUMIFS('Raw data (as reported)'!T$5:T$37,'Raw data (as reported)'!$A$5:$A$37,$A13),"") -> 15213.076 | E13: =IF(SUMPRODUCT(('Raw data (as reported)'!$A$5:$A$37=$A13)*ISNUMBER('Raw data (as reported)'!N$5:N$37))=COUNTIF('Raw data (as reported)'!$A$5:$A$37,$A13),SUMIFS('Raw data (as reported)'!N$5:N$37,'Raw data (as reported)'!$A$5:$A$37,$A13),"") -> 3233.3585 | F13: =IF(SUMPRODUCT(('Raw data (as reported)'!$A$5:$A$37=$A13)*ISNUMBER('Raw data (as reported)'!O$5:O$37))=COUNTIF('Raw data (as reported)'!$A$5:$A$37,$A13),SUMIFS('Raw data (as reported)'!O$5:O$37,'Raw data (as reported)'!$A$5:$A$37,$A13),"") -> 8000.8631 | G13: =IF(SUMPRODUCT(('Raw data (as reported)'!$A$5:$A$37=$A13)*ISNUMBER('Raw data (as reported)'!P$5:P$37))=COUNTIF('Raw data (as reported)'!$A$5:$A$37,$A13),SUMIFS('Raw data (as reported)'!P$5:P$37,'Raw data (as reported)'!$A$5:$A$37,$A13),"") -> 3978.8542 | H13: =IF(SUMPRODUCT(('Raw data (as reported)'!$A$5:$A$37=$A13)*ISNUMBER('Raw data (as reported)'!Q$5:Q$37))=COUNTIF('Raw data (as reported)'!$A$5:$A$37,$A13),SUMIFS('Raw data (as reported)'!Q$5:Q$37,'Raw data (as reported)'!$A$5:$A$37,$A13),"") | I13: =IF(SUMPRODUCT(('Raw data (as reported)'!$A$5:$A$37=$A13)*ISNUMBER('Raw data (as reported)'!R$5:R$37))=COUNTIF('Raw data (as reported)'!$A$5:$A$37,$A13),SUMIFS('Raw data (as reported)'!R$5:R$37,'Raw data (as reported)'!$A$5:$A$37,$A13),"") | J13: =IF(SUMPRODUCT(('Raw data (as reported)'!$A$5:$A$37=$A13)*ISNUMBER('Raw data (as reported)'!S$5:S$37))=COUNTIF('Raw data (as reported)'!$A$5:$A$37,$A13),SUMIFS('Raw data (as reported)'!S$5:S$37,'Raw data (as reported)'!$A$5:$A$37,$A13),"") | K13: =IF(AND(ISNUMBER(E13),ISNUMBER(F13),ISNUMBER(G13)),E13+F13+G13+IF(ISNUMBER(H13),H13,0),"") -> 15213.076 | L13: =IF(ISNUMBER(K13),E13/K13,"") -> 0.21253812 | M13: =IF(ISNUMBER(K13),F13/K13,"") -> 0.52592015 | N13: =IF(ISNUMBER(K13),G13/K13,"") -> 0.26154173 | O13: =IF(AND(ISNUMBER(K13),ISNUMBER(H13)),H13/K13,"") | P13: =IF(ISNUMBER(K13),(E13+F13)/K13,IF(AND(ISNUMBER(I13),ISNUMBER(J13)),I13/(I13+J13),"")) -> 0.73845827 | Q13: Other income not disclosed separately; it sits inside recurring fees (derived).
A14: 2014 | B14: WM + WM Americas | C14: New (NII / fees / transaction / other) | D14: =IF(SUMPRODUCT(('Raw data (as reported)'!$A$5:$A$37=$A14)*ISNUMBER('Raw data (as reported)'!T$5:T$37))=COUNTIF('Raw data (as reported)'!$A$5:$A$37,$A14),SUMIFS('Raw data (as reported)'!T$5:T$37,'Raw data (as reported)'!$A$5:$A$37,$A14),"") -> 16228.898 | E14: =IF(SUMPRODUCT(('Raw data (as reported)'!$A$5:$A$37=$A14)*ISNUMBER('Raw data (as reported)'!N$5:N$37))=COUNTIF('Raw data (as reported)'!$A$5:$A$37,$A14),SUMIFS('Raw data (as reported)'!N$5:N$37,'Raw data (as reported)'!$A$5:$A$37,$A14),"") -> 3433.8963 | F14: =IF(SUMPRODUCT(('Raw data (as reported)'!$A$5:$A$37=$A14)*ISNUMBER('Raw data (as reported)'!O$5:O$37))=COUNTIF('Raw data (as reported)'!$A$5:$A$37,$A14),SUMIFS('Raw data (as reported)'!O$5:O$37,'Raw data (as reported)'!$A$5:$A$37,$A14),"") -> 8801.7822 | G14: =IF(SUMPRODUCT(('Raw data (as reported)'!$A$5:$A$37=$A14)*ISNUMBER('Raw data (as reported)'!P$5:P$37))=COUNTIF('Raw data (as reported)'!$A$5:$A$37,$A14),SUMIFS('Raw data (as reported)'!P$5:P$37,'Raw data (as reported)'!$A$5:$A$37,$A14),"") -> 3932.7949 | H14: =IF(SUMPRODUCT(('Raw data (as reported)'!$A$5:$A$37=$A14)*ISNUMBER('Raw data (as reported)'!Q$5:Q$37))=COUNTIF('Raw data (as reported)'!$A$5:$A$37,$A14),SUMIFS('Raw data (as reported)'!Q$5:Q$37,'Raw data (as reported)'!$A$5:$A$37,$A14),"") -> 60.331365 | I14: =IF(SUMPRODUCT(('Raw data (as reported)'!$A$5:$A$37=$A14)*ISNUMBER('Raw data (as reported)'!R$5:R$37))=COUNTIF('Raw data (as reported)'!$A$5:$A$37,$A14),SUMIFS('Raw data (as reported)'!R$5:R$37,'Raw data (as reported)'!$A$5:$A$37,$A14),"") | J14: =IF(SUMPRODUCT(('Raw data (as reported)'!$A$5:$A$37=$A14)*ISNUMBER('Raw data (as reported)'!S$5:S$37))=COUNTIF('Raw data (as reported)'!$A$5:$A$37,$A14),SUMIFS('Raw data (as reported)'!S$5:S$37,'Raw data (as reported)'!$A$5:$A$37,$A14),"") | K14: =IF(AND(ISNUMBER(E14),ISNUMBER(F14),ISNUMBER(G14)),E14+F14+G14+IF(ISNUMBER(H14),H14,0),"") -> 16228.805 | L14: =IF(ISNUMBER(K14),E14/K14,"") -> 0.21159268 | M14: =IF(ISNUMBER(K14),F14/K14,"") -> 0.54235554 | N14: =IF(ISNUMBER(K14),G14/K14,"") -> 0.24233423 | O14: =IF(AND(ISNUMBER(K14),ISNUMBER(H14)),H14/K14,"") -> 0.0037175483 | P14: =IF(ISNUMBER(K14),(E14+F14)/K14,IF(AND(ISNUMBER(I14),ISNUMBER(J14)),I14/(I14+J14),"")) -> 0.75394822
A15: 2015 | B15: WM + WM Americas | C15: New (NII / fees / transaction / other) | D15: =IF(SUMPRODUCT(('Raw data (as reported)'!$A$5:$A$37=$A15)*ISNUMBER('Raw data (as reported)'!T$5:T$37))=COUNTIF('Raw data (as reported)'!$A$5:$A$37,$A15),SUMIFS('Raw data (as reported)'!T$5:T$37,'Raw data (as reported)'!$A$5:$A$37,$A15),"") -> 16127.087 | E15: =IF(SUMPRODUCT(('Raw data (as reported)'!$A$5:$A$37=$A15)*ISNUMBER('Raw data (as reported)'!N$5:N$37))=COUNTIF('Raw data (as reported)'!$A$5:$A$37,$A15),SUMIFS('Raw data (as reported)'!N$5:N$37,'Raw data (as reported)'!$A$5:$A$37,$A15),"") -> 3630.8704 | F15: =IF(SUMPRODUCT(('Raw data (as reported)'!$A$5:$A$37=$A15)*ISNUMBER('Raw data (as reported)'!O$5:O$37))=COUNTIF('Raw data (as reported)'!$A$5:$A$37,$A15),SUMIFS('Raw data (as reported)'!O$5:O$37,'Raw data (as reported)'!$A$5:$A$37,$A15),"") -> 8762.5945 | G15: =IF(SUMPRODUCT(('Raw data (as reported)'!$A$5:$A$37=$A15)*ISNUMBER('Raw data (as reported)'!P$5:P$37))=COUNTIF('Raw data (as reported)'!$A$5:$A$37,$A15),SUMIFS('Raw data (as reported)'!P$5:P$37,'Raw data (as reported)'!$A$5:$A$37,$A15),"") -> 3460.6971 | H15: =IF(SUMPRODUCT(('Raw data (as reported)'!$A$5:$A$37=$A15)*ISNUMBER('Raw data (as reported)'!Q$5:Q$37))=COUNTIF('Raw data (as reported)'!$A$5:$A$37,$A15),SUMIFS('Raw data (as reported)'!Q$5:Q$37,'Raw data (as reported)'!$A$5:$A$37,$A15),"") -> 271.92522 | I15: =IF(SUMPRODUCT(('Raw data (as reported)'!$A$5:$A$37=$A15)*ISNUMBER('Raw data (as reported)'!R$5:R$37))=COUNTIF('Raw data (as reported)'!$A$5:$A$37,$A15),SUMIFS('Raw data (as reported)'!R$5:R$37,'Raw data (as reported)'!$A$5:$A$37,$A15),"") | J15: =IF(SUMPRODUCT(('Raw data (as reported)'!$A$5:$A$37=$A15)*ISNUMBER('Raw data (as reported)'!S$5:S$37))=COUNTIF('Raw data (as reported)'!$A$5:$A$37,$A15),SUMIFS('Raw data (as reported)'!S$5:S$37,'Raw data (as reported)'!$A$5:$A$37,$A15),"") | K15: =IF(AND(ISNUMBER(E15),ISNUMBER(F15),ISNUMBER(G15)),E15+F15+G15+IF(ISNUMBER(H15),H15,0),"") -> 16126.087 | L15: =IF(ISNUMBER(K15),E15/K15,"") -> 0.22515507 | M15: =IF(ISNUMBER(K15),F15/K15,"") -> 0.54338008 | N15: =IF(ISNUMBER(K15),G15/K15,"") -> 0.21460241 | O15: =IF(AND(ISNUMBER(K15),ISNUMBER(H15)),H15/K15,"") -> 0.016862442 | P15: =IF(ISNUMBER(K15),(E15+F15)/K15,IF(AND(ISNUMBER(I15),ISNUMBER(J15)),I15/(I15+J15),"")) -> 0.76853515
A16: 2016 | B16: WM + WM Americas | C16: New (NII / fees / transaction / other) | D16: =IF(SUMPRODUCT(('Raw data (as reported)'!$A$5:$A$37=$A16)*ISNUMBER('Raw data (as reported)'!T$5:T$37))=COUNTIF('Raw data (as reported)'!$A$5:$A$37,$A16),SUMIFS('Raw data (as reported)'!T$5:T$37,'Raw data (as reported)'!$A$5:$A$37,$A16),"") -> 15281.611 | E16: =IF(SUMPRODUCT(('Raw data (as reported)'!$A$5:$A$37=$A16)*ISNUMBER('Raw data (as reported)'!N$5:N$37))=COUNTIF('Raw data (as reported)'!$A$5:$A$37,$A16),SUMIFS('Raw data (as reported)'!N$5:N$37,'Raw data (as reported)'!$A$5:$A$37,$A16),"") -> 3850.9781 | F16: =IF(SUMPRODUCT(('Raw data (as reported)'!$A$5:$A$37=$A16)*ISNUMBER('Raw data (as reported)'!O$5:O$37))=COUNTIF('Raw data (as reported)'!$A$5:$A$37,$A16),SUMIFS('Raw data (as reported)'!O$5:O$37,'Raw data (as reported)'!$A$5:$A$37,$A16),"") -> 8482.762 | G16: =IF(SUMPRODUCT(('Raw data (as reported)'!$A$5:$A$37=$A16)*ISNUMBER('Raw data (as reported)'!P$5:P$37))=COUNTIF('Raw data (as reported)'!$A$5:$A$37,$A16),SUMIFS('Raw data (as reported)'!P$5:P$37,'Raw data (as reported)'!$A$5:$A$37,$A16),"") -> 2892.5621 | H16: =IF(SUMPRODUCT(('Raw data (as reported)'!$A$5:$A$37=$A16)*ISNUMBER('Raw data (as reported)'!Q$5:Q$37))=COUNTIF('Raw data (as reported)'!$A$5:$A$37,$A16),SUMIFS('Raw data (as reported)'!Q$5:Q$37,'Raw data (as reported)'!$A$5:$A$37,$A16),"") -> 55.308692 | I16: =IF(SUMPRODUCT(('Raw data (as reported)'!$A$5:$A$37=$A16)*ISNUMBER('Raw data (as reported)'!R$5:R$37))=COUNTIF('Raw data (as reported)'!$A$5:$A$37,$A16),SUMIFS('Raw data (as reported)'!R$5:R$37,'Raw data (as reported)'!$A$5:$A$37,$A16),"") | J16: =IF(SUMPRODUCT(('Raw data (as reported)'!$A$5:$A$37=$A16)*ISNUMBER('Raw data (as reported)'!S$5:S$37))=COUNTIF('Raw data (as reported)'!$A$5:$A$37,$A16),SUMIFS('Raw data (as reported)'!S$5:S$37,'Raw data (as reported)'!$A$5:$A$37,$A16),"") | K16: =IF(AND(ISNUMBER(E16),ISNUMBER(F16),ISNUMBER(G16)),E16+F16+G16+IF(ISNUMBER(H16),H16,0),"") -> 15281.611 | L16: =IF(ISNUMBER(K16),E16/K16,"") -> 0.25200079 | M16: =IF(ISNUMBER(K16),F16/K16,"") -> 0.55509606 | N16: =IF(ISNUMBER(K16),G16/K16,"") -> 0.18928385 | O16: =IF(AND(ISNUMBER(K16),ISNUMBER(H16)),H16/K16,"") -> 0.0036192972 | P16: =IF(ISNUMBER(K16),(E16+F16)/K16,IF(AND(ISNUMBER(I16),ISNUMBER(J16)),I16/(I16+J16),"")) -> 0.80709685
A17: 2017 | B17: Global Wealth Management | C17: New (NII / fees / transaction / other) | D17: =IF(SUMPRODUCT(('Raw data (as reported)'!$A$5:$A$37=$A17)*ISNUMBER('Raw data (as reported)'!T$5:T$37))=COUNTIF('Raw data (as reported)'!$A$5:$A$37,$A17),SUMIFS('Raw data (as reported)'!T$5:T$37,'Raw data (as reported)'!$A$5:$A$37,$A17),"") -> 16295 | E17: =IF(SUMPRODUCT(('Raw data (as reported)'!$A$5:$A$37=$A17)*ISNUMBER('Raw data (as reported)'!N$5:N$37))=COUNTIF('Raw data (as reported)'!$A$5:$A$37,$A17),SUMIFS('Raw data (as reported)'!N$5:N$37,'Raw data (as reported)'!$A$5:$A$37,$A17),"") -> 4103 | F17: =IF(SUMPRODUCT(('Raw data (as reported)'!$A$5:$A$37=$A17)*ISNUMBER('Raw data (as reported)'!O$5:O$37))=COUNTIF('Raw data (as reported)'!$A$5:$A$37,$A17),SUMIFS('Raw data (as reported)'!O$5:O$37,'Raw data (as reported)'!$A$5:$A$37,$A17),"") -> 8968 | G17: =IF(SUMPRODUCT(('Raw data (as reported)'!$A$5:$A$37=$A17)*ISNUMBER('Raw data (as reported)'!P$5:P$37))=COUNTIF('Raw data (as reported)'!$A$5:$A$37,$A17),SUMIFS('Raw data (as reported)'!P$5:P$37,'Raw data (as reported)'!$A$5:$A$37,$A17),"") -> 3159 | H17: =IF(SUMPRODUCT(('Raw data (as reported)'!$A$5:$A$37=$A17)*ISNUMBER('Raw data (as reported)'!Q$5:Q$37))=COUNTIF('Raw data (as reported)'!$A$5:$A$37,$A17),SUMIFS('Raw data (as reported)'!Q$5:Q$37,'Raw data (as reported)'!$A$5:$A$37,$A17),"") -> 65 | I17: =IF(SUMPRODUCT(('Raw data (as reported)'!$A$5:$A$37=$A17)*ISNUMBER('Raw data (as reported)'!R$5:R$37))=COUNTIF('Raw data (as reported)'!$A$5:$A$37,$A17),SUMIFS('Raw data (as reported)'!R$5:R$37,'Raw data (as reported)'!$A$5:$A$37,$A17),"") | J17: =IF(SUMPRODUCT(('Raw data (as reported)'!$A$5:$A$37=$A17)*ISNUMBER('Raw data (as reported)'!S$5:S$37))=COUNTIF('Raw data (as reported)'!$A$5:$A$37,$A17),SUMIFS('Raw data (as reported)'!S$5:S$37,'Raw data (as reported)'!$A$5:$A$37,$A17),"") | K17: =IF(AND(ISNUMBER(E17),ISNUMBER(F17),ISNUMBER(G17)),E17+F17+G17+IF(ISNUMBER(H17),H17,0),"") -> 16295 | L17: =IF(ISNUMBER(K17),E17/K17,"") -> 0.25179503 | M17: =IF(ISNUMBER(K17),F17/K17,"") -> 0.55035287 | N17: =IF(ISNUMBER(K17),G17/K17,"") -> 0.19386315 | O17: =IF(AND(ISNUMBER(K17),ISNUMBER(H17)),H17/K17,"") -> 0.0039889537 | P17: =IF(ISNUMBER(K17),(E17+F17)/K17,IF(AND(ISNUMBER(I17),ISNUMBER(J17)),I17/(I17+J17),"")) -> 0.8021479
A18: 2018 | B18: Global Wealth Management | C18: New (NII / fees / transaction / other) | D18: =IF(SUMPRODUCT(('Raw data (as reported)'!$A$5:$A$37=$A18)*ISNUMBER('Raw data (as reported)'!T$5:T$37))=COUNTIF('Raw data (as reported)'!$A$5:$A$37,$A18),SUMIFS('Raw data (as reported)'!T$5:T$37,'Raw data (as reported)'!$A$5:$A$37,$A18),"") -> 16956 | E18: =IF(SUMPRODUCT(('Raw data (as reported)'!$A$5:$A$37=$A18)*ISNUMBER('Raw data (as reported)'!N$5:N$37))=COUNTIF('Raw data (as reported)'!$A$5:$A$37,$A18),SUMIFS('Raw data (as reported)'!N$5:N$37,'Raw data (as reported)'!$A$5:$A$37,$A18),"") -> 4310 | F18: =IF(SUMPRODUCT(('Raw data (as reported)'!$A$5:$A$37=$A18)*ISNUMBER('Raw data (as reported)'!O$5:O$37))=COUNTIF('Raw data (as reported)'!$A$5:$A$37,$A18),SUMIFS('Raw data (as reported)'!O$5:O$37,'Raw data (as reported)'!$A$5:$A$37,$A18),"") -> 9585 | G18: =IF(SUMPRODUCT(('Raw data (as reported)'!$A$5:$A$37=$A18)*ISNUMBER('Raw data (as reported)'!P$5:P$37))=COUNTIF('Raw data (as reported)'!$A$5:$A$37,$A18),SUMIFS('Raw data (as reported)'!P$5:P$37,'Raw data (as reported)'!$A$5:$A$37,$A18),"") -> 2911 | H18: =IF(SUMPRODUCT(('Raw data (as reported)'!$A$5:$A$37=$A18)*ISNUMBER('Raw data (as reported)'!Q$5:Q$37))=COUNTIF('Raw data (as reported)'!$A$5:$A$37,$A18),SUMIFS('Raw data (as reported)'!Q$5:Q$37,'Raw data (as reported)'!$A$5:$A$37,$A18),"") -> 151 | I18: =IF(SUMPRODUCT(('Raw data (as reported)'!$A$5:$A$37=$A18)*ISNUMBER('Raw data (as reported)'!R$5:R$37))=COUNTIF('Raw data (as reported)'!$A$5:$A$37,$A18),SUMIFS('Raw data (as reported)'!R$5:R$37,'Raw data (as reported)'!$A$5:$A$37,$A18),"") | J18: =IF(SUMPRODUCT(('Raw data (as reported)'!$A$5:$A$37=$A18)*ISNUMBER('Raw data (as reported)'!S$5:S$37))=COUNTIF('Raw data (as reported)'!$A$5:$A$37,$A18),SUMIFS('Raw data (as reported)'!S$5:S$37,'Raw data (as reported)'!$A$5:$A$37,$A18),"") | K18: =IF(AND(ISNUMBER(E18),ISNUMBER(F18),ISNUMBER(G18)),E18+F18+G18+IF(ISNUMBER(H18),H18,0),"") -> 16957 | L18: =IF(ISNUMBER(K18),E18/K18,"") -> 0.25417232 | M18: =IF(ISNUMBER(K18),F18/K18,"") -> 0.56525329 | N18: =IF(ISNUMBER(K18),G18/K18,"") -> 0.17166952 | O18: =IF(AND(ISNUMBER(K18),ISNUMBER(H18)),H18/K18,"") -> 0.008904877 | P18: =IF(ISNUMBER(K18),(E18+F18)/K18,IF(AND(ISNUMBER(I18),ISNUMBER(J18)),I18/(I18+J18),"")) -> 0.81942561
A19: 2019 | B19: Global Wealth Management | C19: New (NII / fees / transaction / other) | D19: =IF(SUMPRODUCT(('Raw data (as reported)'!$A$5:$A$37=$A19)*ISNUMBER('Raw data (as reported)'!T$5:T$37))=COUNTIF('Raw data (as reported)'!$A$5:$A$37,$A19),SUMIFS('Raw data (as reported)'!T$5:T$37,'Raw data (as reported)'!$A$5:$A$37,$A19),"") -> 16373 | E19: =IF(SUMPRODUCT(('Raw data (as reported)'!$A$5:$A$37=$A19)*ISNUMBER('Raw data (as reported)'!N$5:N$37))=COUNTIF('Raw data (as reported)'!$A$5:$A$37,$A19),SUMIFS('Raw data (as reported)'!N$5:N$37,'Raw data (as reported)'!$A$5:$A$37,$A19),"") -> 3947 | F19: =IF(SUMPRODUCT(('Raw data (as reported)'!$A$5:$A$37=$A19)*ISNUMBER('Raw data (as reported)'!O$5:O$37))=COUNTIF('Raw data (as reported)'!$A$5:$A$37,$A19),SUMIFS('Raw data (as reported)'!O$5:O$37,'Raw data (as reported)'!$A$5:$A$37,$A19),"") -> 9258 | G19: =IF(SUMPRODUCT(('Raw data (as reported)'!$A$5:$A$37=$A19)*ISNUMBER('Raw data (as reported)'!P$5:P$37))=COUNTIF('Raw data (as reported)'!$A$5:$A$37,$A19),SUMIFS('Raw data (as reported)'!P$5:P$37,'Raw data (as reported)'!$A$5:$A$37,$A19),"") -> 3059 | H19: =IF(SUMPRODUCT(('Raw data (as reported)'!$A$5:$A$37=$A19)*ISNUMBER('Raw data (as reported)'!Q$5:Q$37))=COUNTIF('Raw data (as reported)'!$A$5:$A$37,$A19),SUMIFS('Raw data (as reported)'!Q$5:Q$37,'Raw data (as reported)'!$A$5:$A$37,$A19),"") -> 110 | I19: =IF(SUMPRODUCT(('Raw data (as reported)'!$A$5:$A$37=$A19)*ISNUMBER('Raw data (as reported)'!R$5:R$37))=COUNTIF('Raw data (as reported)'!$A$5:$A$37,$A19),SUMIFS('Raw data (as reported)'!R$5:R$37,'Raw data (as reported)'!$A$5:$A$37,$A19),"") | J19: =IF(SUMPRODUCT(('Raw data (as reported)'!$A$5:$A$37=$A19)*ISNUMBER('Raw data (as reported)'!S$5:S$37))=COUNTIF('Raw data (as reported)'!$A$5:$A$37,$A19),SUMIFS('Raw data (as reported)'!S$5:S$37,'Raw data (as reported)'!$A$5:$A$37,$A19),"") | K19: =IF(AND(ISNUMBER(E19),ISNUMBER(F19),ISNUMBER(G19)),E19+F19+G19+IF(ISNUMBER(H19),H19,0),"") -> 16374 | L19: =IF(ISNUMBER(K19),E19/K19,"") -> 0.24105289 | M19: =IF(ISNUMBER(K19),F19/K19,"") -> 0.56540857 | N19: =IF(ISNUMBER(K19),G19/K19,"") -> 0.18682057 | O19: =IF(AND(ISNUMBER(K19),ISNUMBER(H19)),H19/K19,"") -> 0.0067179675 | P19: =IF(ISNUMBER(K19),(E19+F19)/K19,IF(AND(ISNUMBER(I19),ISNUMBER(J19)),I19/(I19+J19),"")) -> 0.80646146
A20: 2020 | B20: Global Wealth Management | C20: New (NII / fees / transaction / other) | D20: =IF(SUMPRODUCT(('Raw data (as reported)'!$A$5:$A$37=$A20)*ISNUMBER('Raw data (as reported)'!T$5:T$37))=COUNTIF('Raw data (as reported)'!$A$5:$A$37,$A20),SUMIFS('Raw data (as reported)'!T$5:T$37,'Raw data (as reported)'!$A$5:$A$37,$A20),"") -> 17134 | E20: =IF(SUMPRODUCT(('Raw data (as reported)'!$A$5:$A$37=$A20)*ISNUMBER('Raw data (as reported)'!N$5:N$37))=COUNTIF('Raw data (as reported)'!$A$5:$A$37,$A20),SUMIFS('Raw data (as reported)'!N$5:N$37,'Raw data (as reported)'!$A$5:$A$37,$A20),"") -> 4027 | F20: =IF(SUMPRODUCT(('Raw data (as reported)'!$A$5:$A$37=$A20)*ISNUMBER('Raw data (as reported)'!O$5:O$37))=COUNTIF('Raw data (as reported)'!$A$5:$A$37,$A20),SUMIFS('Raw data (as reported)'!O$5:O$37,'Raw data (as reported)'!$A$5:$A$37,$A20),"") -> 9372 | G20: =IF(SUMPRODUCT(('Raw data (as reported)'!$A$5:$A$37=$A20)*ISNUMBER('Raw data (as reported)'!P$5:P$37))=COUNTIF('Raw data (as reported)'!$A$5:$A$37,$A20),SUMIFS('Raw data (as reported)'!P$5:P$37,'Raw data (as reported)'!$A$5:$A$37,$A20),"") -> 3576 | H20: =IF(SUMPRODUCT(('Raw data (as reported)'!$A$5:$A$37=$A20)*ISNUMBER('Raw data (as reported)'!Q$5:Q$37))=COUNTIF('Raw data (as reported)'!$A$5:$A$37,$A20),SUMIFS('Raw data (as reported)'!Q$5:Q$37,'Raw data (as reported)'!$A$5:$A$37,$A20),"") -> 159 | I20: =IF(SUMPRODUCT(('Raw data (as reported)'!$A$5:$A$37=$A20)*ISNUMBER('Raw data (as reported)'!R$5:R$37))=COUNTIF('Raw data (as reported)'!$A$5:$A$37,$A20),SUMIFS('Raw data (as reported)'!R$5:R$37,'Raw data (as reported)'!$A$5:$A$37,$A20),"") | J20: =IF(SUMPRODUCT(('Raw data (as reported)'!$A$5:$A$37=$A20)*ISNUMBER('Raw data (as reported)'!S$5:S$37))=COUNTIF('Raw data (as reported)'!$A$5:$A$37,$A20),SUMIFS('Raw data (as reported)'!S$5:S$37,'Raw data (as reported)'!$A$5:$A$37,$A20),"") | K20: =IF(AND(ISNUMBER(E20),ISNUMBER(F20),ISNUMBER(G20)),E20+F20+G20+IF(ISNUMBER(H20),H20,0),"") -> 17134 | L20: =IF(ISNUMBER(K20),E20/K20,"") -> 0.23502977 | M20: =IF(ISNUMBER(K20),F20/K20,"") -> 0.54698261 | N20: =IF(ISNUMBER(K20),G20/K20,"") -> 0.20870783 | O20: =IF(AND(ISNUMBER(K20),ISNUMBER(H20)),H20/K20,"") -> 0.0092797946 | P20: =IF(ISNUMBER(K20),(E20+F20)/K20,IF(AND(ISNUMBER(I20),ISNUMBER(J20)),I20/(I20+J20),"")) -> 0.78201237
A21: 2021 | B21: Global Wealth Management | C21: New (NII / fees / transaction / other) | D21: =IF(SUMPRODUCT(('Raw data (as reported)'!$A$5:$A$37=$A21)*ISNUMBER('Raw data (as reported)'!T$5:T$37))=COUNTIF('Raw data (as reported)'!$A$5:$A$37,$A21),SUMIFS('Raw data (as reported)'!T$5:T$37,'Raw data (as reported)'!$A$5:$A$37,$A21),"") -> 19419 | E21: =IF(SUMPRODUCT(('Raw data (as reported)'!$A$5:$A$37=$A21)*ISNUMBER('Raw data (as reported)'!N$5:N$37))=COUNTIF('Raw data (as reported)'!$A$5:$A$37,$A21),SUMIFS('Raw data (as reported)'!N$5:N$37,'Raw data (as reported)'!$A$5:$A$37,$A21),"") -> 4244 | F21: =IF(SUMPRODUCT(('Raw data (as reported)'!$A$5:$A$37=$A21)*ISNUMBER('Raw data (as reported)'!O$5:O$37))=COUNTIF('Raw data (as reported)'!$A$5:$A$37,$A21),SUMIFS('Raw data (as reported)'!O$5:O$37,'Raw data (as reported)'!$A$5:$A$37,$A21),"") -> 11170 | G21: =IF(SUMPRODUCT(('Raw data (as reported)'!$A$5:$A$37=$A21)*ISNUMBER('Raw data (as reported)'!P$5:P$37))=COUNTIF('Raw data (as reported)'!$A$5:$A$37,$A21),SUMIFS('Raw data (as reported)'!P$5:P$37,'Raw data (as reported)'!$A$5:$A$37,$A21),"") -> 3836 | H21: =IF(SUMPRODUCT(('Raw data (as reported)'!$A$5:$A$37=$A21)*ISNUMBER('Raw data (as reported)'!Q$5:Q$37))=COUNTIF('Raw data (as reported)'!$A$5:$A$37,$A21),SUMIFS('Raw data (as reported)'!Q$5:Q$37,'Raw data (as reported)'!$A$5:$A$37,$A21),"") -> 168 | I21: =IF(SUMPRODUCT(('Raw data (as reported)'!$A$5:$A$37=$A21)*ISNUMBER('Raw data (as reported)'!R$5:R$37))=COUNTIF('Raw data (as reported)'!$A$5:$A$37,$A21),SUMIFS('Raw data (as reported)'!R$5:R$37,'Raw data (as reported)'!$A$5:$A$37,$A21),"") | J21: =IF(SUMPRODUCT(('Raw data (as reported)'!$A$5:$A$37=$A21)*ISNUMBER('Raw data (as reported)'!S$5:S$37))=COUNTIF('Raw data (as reported)'!$A$5:$A$37,$A21),SUMIFS('Raw data (as reported)'!S$5:S$37,'Raw data (as reported)'!$A$5:$A$37,$A21),"") | K21: =IF(AND(ISNUMBER(E21),ISNUMBER(F21),ISNUMBER(G21)),E21+F21+G21+IF(ISNUMBER(H21),H21,0),"") -> 19418 | L21: =IF(ISNUMBER(K21),E21/K21,"") -> 0.2185601 | M21: =IF(ISNUMBER(K21),F21/K21,"") -> 0.57523947 | N21: =IF(ISNUMBER(K21),G21/K21,"") -> 0.19754867 | O21: =IF(AND(ISNUMBER(K21),ISNUMBER(H21)),H21/K21,"") -> 0.0086517664 | P21: =IF(ISNUMBER(K21),(E21+F21)/K21,IF(AND(ISNUMBER(I21),ISNUMBER(J21)),I21/(I21+J21),"")) -> 0.79379957
A22: 2022 | B22: Global Wealth Management | C22: New (NII / fees / transaction / other) | D22: =IF(SUMPRODUCT(('Raw data (as reported)'!$A$5:$A$37=$A22)*ISNUMBER('Raw data (as reported)'!T$5:T$37))=COUNTIF('Raw data (as reported)'!$A$5:$A$37,$A22),SUMIFS('Raw data (as reported)'!T$5:T$37,'Raw data (as reported)'!$A$5:$A$37,$A22),"") -> 18967 | E22: =IF(SUMPRODUCT(('Raw data (as reported)'!$A$5:$A$37=$A22)*ISNUMBER('Raw data (as reported)'!N$5:N$37))=COUNTIF('Raw data (as reported)'!$A$5:$A$37,$A22),SUMIFS('Raw data (as reported)'!N$5:N$37,'Raw data (as reported)'!$A$5:$A$37,$A22),"") -> 5273 | F22: =IF(SUMPRODUCT(('Raw data (as reported)'!$A$5:$A$37=$A22)*ISNUMBER('Raw data (as reported)'!O$5:O$37))=COUNTIF('Raw data (as reported)'!$A$5:$A$37,$A22),SUMIFS('Raw data (as reported)'!O$5:O$37,'Raw data (as reported)'!$A$5:$A$37,$A22),"") -> 10282 | G22: =IF(SUMPRODUCT(('Raw data (as reported)'!$A$5:$A$37=$A22)*ISNUMBER('Raw data (as reported)'!P$5:P$37))=COUNTIF('Raw data (as reported)'!$A$5:$A$37,$A22),SUMIFS('Raw data (as reported)'!P$5:P$37,'Raw data (as reported)'!$A$5:$A$37,$A22),"") -> 3137 | H22: =IF(SUMPRODUCT(('Raw data (as reported)'!$A$5:$A$37=$A22)*ISNUMBER('Raw data (as reported)'!Q$5:Q$37))=COUNTIF('Raw data (as reported)'!$A$5:$A$37,$A22),SUMIFS('Raw data (as reported)'!Q$5:Q$37,'Raw data (as reported)'!$A$5:$A$37,$A22),"") -> 275 | I22: =IF(SUMPRODUCT(('Raw data (as reported)'!$A$5:$A$37=$A22)*ISNUMBER('Raw data (as reported)'!R$5:R$37))=COUNTIF('Raw data (as reported)'!$A$5:$A$37,$A22),SUMIFS('Raw data (as reported)'!R$5:R$37,'Raw data (as reported)'!$A$5:$A$37,$A22),"") | J22: =IF(SUMPRODUCT(('Raw data (as reported)'!$A$5:$A$37=$A22)*ISNUMBER('Raw data (as reported)'!S$5:S$37))=COUNTIF('Raw data (as reported)'!$A$5:$A$37,$A22),SUMIFS('Raw data (as reported)'!S$5:S$37,'Raw data (as reported)'!$A$5:$A$37,$A22),"") | K22: =IF(AND(ISNUMBER(E22),ISNUMBER(F22),ISNUMBER(G22)),E22+F22+G22+IF(ISNUMBER(H22),H22,0),"") -> 18967 | L22: =IF(ISNUMBER(K22),E22/K22,"") -> 0.27800917 | M22: =IF(ISNUMBER(K22),F22/K22,"") -> 0.54209944 | N22: =IF(ISNUMBER(K22),G22/K22,"") -> 0.16539252 | O22: =IF(AND(ISNUMBER(K22),ISNUMBER(H22)),H22/K22,"") -> 0.014498866 | P22: =IF(ISNUMBER(K22),(E22+F22)/K22,IF(AND(ISNUMBER(I22),ISNUMBER(J22)),I22/(I22+J22),"")) -> 0.82010861
A23: 2023 | B23: GWM + Credit Suisse (7 months) | C23: New (NII / fees / transaction / other) | D23: =IF(SUMPRODUCT(('Raw data (as reported)'!$A$5:$A$37=$A23)*ISNUMBER('Raw data (as reported)'!T$5:T$37))=COUNTIF('Raw data (as reported)'!$A$5:$A$37,$A23),SUMIFS('Raw data (as reported)'!T$5:T$37,'Raw data (as reported)'!$A$5:$A$37,$A23),"") -> 21556 | E23: =IF(SUMPRODUCT(('Raw data (as reported)'!$A$5:$A$37=$A23)*ISNUMBER('Raw data (as reported)'!N$5:N$37))=COUNTIF('Raw data (as reported)'!$A$5:$A$37,$A23),SUMIFS('Raw data (as reported)'!N$5:N$37,'Raw data (as reported)'!$A$5:$A$37,$A23),"") -> 7082 | F23: =IF(SUMPRODUCT(('Raw data (as reported)'!$A$5:$A$37=$A23)*ISNUMBER('Raw data (as reported)'!O$5:O$37))=COUNTIF('Raw data (as reported)'!$A$5:$A$37,$A23),SUMIFS('Raw data (as reported)'!O$5:O$37,'Raw data (as reported)'!$A$5:$A$37,$A23),"") -> 10988 | G23: =IF(SUMPRODUCT(('Raw data (as reported)'!$A$5:$A$37=$A23)*ISNUMBER('Raw data (as reported)'!P$5:P$37))=COUNTIF('Raw data (as reported)'!$A$5:$A$37,$A23),SUMIFS('Raw data (as reported)'!P$5:P$37,'Raw data (as reported)'!$A$5:$A$37,$A23),"") -> 3623 | H23: =IF(SUMPRODUCT(('Raw data (as reported)'!$A$5:$A$37=$A23)*ISNUMBER('Raw data (as reported)'!Q$5:Q$37))=COUNTIF('Raw data (as reported)'!$A$5:$A$37,$A23),SUMIFS('Raw data (as reported)'!Q$5:Q$37,'Raw data (as reported)'!$A$5:$A$37,$A23),"") -> -137 | I23: =IF(SUMPRODUCT(('Raw data (as reported)'!$A$5:$A$37=$A23)*ISNUMBER('Raw data (as reported)'!R$5:R$37))=COUNTIF('Raw data (as reported)'!$A$5:$A$37,$A23),SUMIFS('Raw data (as reported)'!R$5:R$37,'Raw data (as reported)'!$A$5:$A$37,$A23),"") | J23: =IF(SUMPRODUCT(('Raw data (as reported)'!$A$5:$A$37=$A23)*ISNUMBER('Raw data (as reported)'!S$5:S$37))=COUNTIF('Raw data (as reported)'!$A$5:$A$37,$A23),SUMIFS('Raw data (as reported)'!S$5:S$37,'Raw data (as reported)'!$A$5:$A$37,$A23),"") | K23: =IF(AND(ISNUMBER(E23),ISNUMBER(F23),ISNUMBER(G23)),E23+F23+G23+IF(ISNUMBER(H23),H23,0),"") -> 21556 | L23: =IF(ISNUMBER(K23),E23/K23,"") -> 0.32853962 | M23: =IF(ISNUMBER(K23),F23/K23,"") -> 0.50974207 | N23: =IF(ISNUMBER(K23),G23/K23,"") -> 0.16807385 | O23: =IF(AND(ISNUMBER(K23),ISNUMBER(H23)),H23/K23,"") -> -0.0063555391 | P23: =IF(ISNUMBER(K23),(E23+F23)/K23,IF(AND(ISNUMBER(I23),ISNUMBER(J23)),I23/(I23+J23),"")) -> 0.83828168 | Q23: Includes Credit Suisse from June 2023; other revenues negative.
A24: 2024 | B24: GWM + Credit Suisse | C24: New (NII / fees / transaction / other) | D24: =IF(SUMPRODUCT(('Raw data (as reported)'!$A$5:$A$37=$A24)*ISNUMBER('Raw data (as reported)'!T$5:T$37))=COUNTIF('Raw data (as reported)'!$A$5:$A$37,$A24),SUMIFS('Raw data (as reported)'!T$5:T$37,'Raw data (as reported)'!$A$5:$A$37,$A24),"") -> 24516 | E24: =IF(SUMPRODUCT(('Raw data (as reported)'!$A$5:$A$37=$A24)*ISNUMBER('Raw data (as reported)'!N$5:N$37))=COUNTIF('Raw data (as reported)'!$A$5:$A$37,$A24),SUMIFS('Raw data (as reported)'!N$5:N$37,'Raw data (as reported)'!$A$5:$A$37,$A24),"") -> 7358 | F24: =IF(SUMPRODUCT(('Raw data (as reported)'!$A$5:$A$37=$A24)*ISNUMBER('Raw data (as reported)'!O$5:O$37))=COUNTIF('Raw data (as reported)'!$A$5:$A$37,$A24),SUMIFS('Raw data (as reported)'!O$5:O$37,'Raw data (as reported)'!$A$5:$A$37,$A24),"") -> 12625 | G24: =IF(SUMPRODUCT(('Raw data (as reported)'!$A$5:$A$37=$A24)*ISNUMBER('Raw data (as reported)'!P$5:P$37))=COUNTIF('Raw data (as reported)'!$A$5:$A$37,$A24),SUMIFS('Raw data (as reported)'!P$5:P$37,'Raw data (as reported)'!$A$5:$A$37,$A24),"") -> 4503 | H24: =IF(SUMPRODUCT(('Raw data (as reported)'!$A$5:$A$37=$A24)*ISNUMBER('Raw data (as reported)'!Q$5:Q$37))=COUNTIF('Raw data (as reported)'!$A$5:$A$37,$A24),SUMIFS('Raw data (as reported)'!Q$5:Q$37,'Raw data (as reported)'!$A$5:$A$37,$A24),"") -> 31 | I24: =IF(SUMPRODUCT(('Raw data (as reported)'!$A$5:$A$37=$A24)*ISNUMBER('Raw data (as reported)'!R$5:R$37))=COUNTIF('Raw data (as reported)'!$A$5:$A$37,$A24),SUMIFS('Raw data (as reported)'!R$5:R$37,'Raw data (as reported)'!$A$5:$A$37,$A24),"") | J24: =IF(SUMPRODUCT(('Raw data (as reported)'!$A$5:$A$37=$A24)*ISNUMBER('Raw data (as reported)'!S$5:S$37))=COUNTIF('Raw data (as reported)'!$A$5:$A$37,$A24),SUMIFS('Raw data (as reported)'!S$5:S$37,'Raw data (as reported)'!$A$5:$A$37,$A24),"") | K24: =IF(AND(ISNUMBER(E24),ISNUMBER(F24),ISNUMBER(G24)),E24+F24+G24+IF(ISNUMBER(H24),H24,0),"") -> 24517 | L24: =IF(ISNUMBER(K24),E24/K24,"") -> 0.30011829 | M24: =IF(ISNUMBER(K24),F24/K24,"") -> 0.51494881 | N24: =IF(ISNUMBER(K24),G24/K24,"") -> 0.18366847 | O24: =IF(AND(ISNUMBER(K24),ISNUMBER(H24)),H24/K24,"") -> 0.0012644288 | P24: =IF(ISNUMBER(K24),(E24+F24)/K24,IF(AND(ISNUMBER(I24),ISNUMBER(J24)),I24/(I24+J24),"")) -> 0.8150671
A25: 2025 | B25: GWM + Credit Suisse | C25: New (NII / fees / transaction / other) | D25: =IF(SUMPRODUCT(('Raw data (as reported)'!$A$5:$A$37=$A25)*ISNUMBER('Raw data (as reported)'!T$5:T$37))=COUNTIF('Raw data (as reported)'!$A$5:$A$37,$A25),SUMIFS('Raw data (as reported)'!T$5:T$37,'Raw data (as reported)'!$A$5:$A$37,$A25),"") -> 25960 | E25: =IF(SUMPRODUCT(('Raw data (as reported)'!$A$5:$A$37=$A25)*ISNUMBER('Raw data (as reported)'!N$5:N$37))=COUNTIF('Raw data (as reported)'!$A$5:$A$37,$A25),SUMIFS('Raw data (as reported)'!N$5:N$37,'Raw data (as reported)'!$A$5:$A$37,$A25),"") -> 7018 | F25: =IF(SUMPRODUCT(('Raw data (as reported)'!$A$5:$A$37=$A25)*ISNUMBER('Raw data (as reported)'!O$5:O$37))=COUNTIF('Raw data (as reported)'!$A$5:$A$37,$A25),SUMIFS('Raw data (as reported)'!O$5:O$37,'Raw data (as reported)'!$A$5:$A$37,$A25),"") -> 13671 | G25: =IF(SUMPRODUCT(('Raw data (as reported)'!$A$5:$A$37=$A25)*ISNUMBER('Raw data (as reported)'!P$5:P$37))=COUNTIF('Raw data (as reported)'!$A$5:$A$37,$A25),SUMIFS('Raw data (as reported)'!P$5:P$37,'Raw data (as reported)'!$A$5:$A$37,$A25),"") -> 5208 | H25: =IF(SUMPRODUCT(('Raw data (as reported)'!$A$5:$A$37=$A25)*ISNUMBER('Raw data (as reported)'!Q$5:Q$37))=COUNTIF('Raw data (as reported)'!$A$5:$A$37,$A25),SUMIFS('Raw data (as reported)'!Q$5:Q$37,'Raw data (as reported)'!$A$5:$A$37,$A25),"") -> 62 | I25: =IF(SUMPRODUCT(('Raw data (as reported)'!$A$5:$A$37=$A25)*ISNUMBER('Raw data (as reported)'!R$5:R$37))=COUNTIF('Raw data (as reported)'!$A$5:$A$37,$A25),SUMIFS('Raw data (as reported)'!R$5:R$37,'Raw data (as reported)'!$A$5:$A$37,$A25),"") | J25: =IF(SUMPRODUCT(('Raw data (as reported)'!$A$5:$A$37=$A25)*ISNUMBER('Raw data (as reported)'!S$5:S$37))=COUNTIF('Raw data (as reported)'!$A$5:$A$37,$A25),SUMIFS('Raw data (as reported)'!S$5:S$37,'Raw data (as reported)'!$A$5:$A$37,$A25),"") | K25: =IF(AND(ISNUMBER(E25),ISNUMBER(F25),ISNUMBER(G25)),E25+F25+G25+IF(ISNUMBER(H25),H25,0),"") -> 25959 | L25: =IF(ISNUMBER(K25),E25/K25,"") -> 0.2703494 | M25: =IF(ISNUMBER(K25),F25/K25,"") -> 0.52663816 | N25: =IF(ISNUMBER(K25),G25/K25,"") -> 0.20062406 | O25: =IF(AND(ISNUMBER(K25),ISNUMBER(H25)),H25/K25,"") -> 0.0023883817 | P25: =IF(ISNUMBER(K25),(E25+F25)/K25,IF(AND(ISNUMBER(I25),ISNUMBER(J25)),I25/(I25+J25),"")) -> 0.79698756 | Q25: UBS renamed 'Other income' to 'Other revenues' from 4Q25.
A28: NII share in 2011–2012 (WM + WMA): see Raw data – NII was about 21% of revenue in both years.
A29: Shares use the sum of all four income lines (NII + recurring fees + transaction + other revenues) as the denominator; recurring share (NII+fees) links both reporting bases.

Sheet Verification
A1: Verification log – how each input was checked
A2: Status key: VERBATIM = row read word-for-word from the filing table · TWO SOURCES = two separate filings show the same number · TIES = the lines add exactly to the reported total · QUARTERLY CHECK = consistent with quarterly figures · DERIVED = calculated by me · NOT VERIFIED = left blank.
A4: Year | B4: Unit | C4: Figures | D4: Status | E4: How it was checked
A5: 2005 | B5: WM Intl & Switzerland | C5: Total CHF 9,011m | D5: VERBATIM + TIES | E5: 4Q05 6-K table row 'Total operating income … 9,011 | 7,693'; Handbook: 9,011 + 5,156 + 5,071 (Business Banking) = 19,238 business-group total.
A6: 2005–06 | B6: WM US | C6: Totals 5,156 / 5,863 | D6: TIES | E6: UBS Handbook table; unit totals add exactly to the business-group totals 19,238 (2005) and 21,931 (2006).
A7: 2006 | B7: WM Intl & Switzerland | C7: Total 10,798 | D7: TIES | E7: As above: 10,798 + 5,863 + 5,270 = 21,931.
A8: 2005–07 | B8: WM US | C8: Recurring 2,834 / 3,488 / 4,173 | D8: QUARTERLY CHECK | E8: Text from 20-F 2007. Unit confirmed by quarterly reports: WM US recurring was CHF 1,040m (2Q07) and 1,092m (3Q07), consistent with ~4.2bn a year; the Intl & Swiss unit ran ~2.5bn a quarter, so it cannot be that unit.
A9: 2008 | B9: WM Americas | C9: Income 6,278; recurring 4,076 | D9: VERBATIM | E9: 4Q09 6-K table, 'Year ended 31.12.08' column.
A10: 2009–10 | B10: WM and WM Americas | C10: Recurring / non-recurring / income | D10: VERBATIM + TIES | E10: 4Q10 6-K tables, 'Year ended' columns; recurring + non-recurring = income exactly (e.g. 5,411 + 1,934 = 7,345).
A11: 2011–12 | B11: WM | C11: NII 1,968 / 1,951; income 7,634 / 7,040 | D11: VERBATIM | E11: 4Q12 6-K table, 'Year ended' columns.
A12: 2011–12 | B12: WM Americas | C12: NII 828 / 849; income 6,017 / 6,547 | D12: VERBATIM | E12: 4Q12 6-K US-dollar table.
A13: 2011–12 | B13: WM Americas | C13: Recurring income | D13: NOT VERIFIED – REMOVED | E13: An earlier extraction said 65.2% / 65.3%; the filing text shows 2012 recurring as '4,26…' (cut off), i.e. ~65.1%, so the earlier figure could not be confirmed. Left blank.
A14: 2013 | B14: WM and WM Americas | C14: NII, transaction, total | D14: VERBATIM | E14: 4Q14 6-K comparison table (13 vs 14) as indexed from the SEC filing.
A15: 2013 | B15: WM and WM Americas | C15: Recurring fees | D15: DERIVED | E15: Total less NII and transaction (includes small other income).
... A24: All CHF years | B24: FX | C24: Annual average CHF per USD | D24: PRIMARY SOURCE | E24: FRED series AEXSZUS (Federal Reserve).

Sheet Reconciliation
A1: Reconciliation: do the four income lines add up to the total UBS reported?
A2: UBS files Form 20-F (annual) and Form 6-K (quarterly reports) with the SEC – it is a foreign private issuer, so there are no 10-K/10-Q filings. Every line links to the Raw data tab.
A4: Year | B4: Unit | C4: Ccy | D4: SEC form | E4: NII + recurring fees + transaction + other | F4: Reported total | G4: Difference | H4: What explains the difference
A5: ='Raw data (as reported)'!A5 -> 2005 | B5: ='Raw data (as reported)'!B5 -> WM International & Switzerland | C5: ='Raw data (as reported)'!C5 -> CHF | D5: 20-F 2007 / Handbook | E5: =IF(AND(ISNUMBER('Raw data (as reported)'!E5),ISNUMBER('Raw data (as reported)'!F5),ISNUMBER('Raw data (as reported)'!G5),ISNUMBER('Raw data (as reported)'!H5)),'Raw data (as reported)'!E5+'Raw data (as reported)'!F5+'Raw data (as reported)'!G5+'Raw data (as reported)'!H5,IF(AND(ISNUMBER('Raw data (as reported)'!I5),ISNUMBER('Raw data (as reported)'!J5)),'Raw data (as reported)'!I5+'Raw data (as reported)'!J5,"")) | F5: =IF(ISNUMBER('Raw data (as reported)'!K5),'Raw data (as reported)'!K5,"") -> 9011 | G5: =IF(AND(ISNUMBER(E5),ISNUMBER(F5)),F5-E5,"") | H5: Only a total (or nothing) found – nothing to reconcile.
A6: ='Raw data (as reported)'!A6 -> 2005 | B6: ='Raw data (as reported)'!B6 -> Wealth Management US | C6: ='Raw data (as reported)'!C6 -> CHF | D6: 20-F 2007 / Handbook | E6: =IF(AND(ISNUMBER('Raw data (as reported)'!E6),ISNUMBER('Raw data (as reported)'!F6),ISNUMBER('Raw data (as reported)'!G6),ISNUMBER('Raw data (as reported)'!H6)),'Raw data (as reported)'!E6+'Raw data (as reported)'!F6+'Raw data (as reported)'!G6+'Raw data (as reported)'!H6,IF(AND(ISNUMBER('Raw data (as reported)'!I6),ISNUMBER('Raw data (as reported)'!J6)),'Raw data (as reported)'!I6+'Raw data (as reported)'!J6,"")) -> 5156 | F6: =IF(ISNUMBER('Raw data (as reported)'!K6),'Raw data (as reported)'!K6,"") -> 5156 | G6: =IF(AND(ISNUMBER(E6),ISNUMBER(F6)),F6-E6,"") -> 0 | H6: Non-recurring derived as total less recurring, so ties by construction.
A7: ='Raw data (as reported)'!A7 -> 2006 | B7: ='Raw data (as reported)'!B7 -> WM International & Switzerland | C7: ='Raw data (as reported)'!C7 -> CHF | D7: 20-F 2007 / Handbook | E7: =IF(AND(ISNUMBER('Raw data (as reported)'!E7),ISNUMBER('Raw data (as reported)'!F7),ISNUMBER('Raw data (as reported)'!G7),ISNUMBER('Raw data (as reported)'!H7)),'Raw data (as reported)'!E7+'Raw data (as reported)'!F7+'Raw data (as reported)'!G7+'Raw data (as reported)'!H7,IF(AND(ISNUMBER('Raw data (as reported)'!I7),ISNUMBER('Raw data (as reported)'!J7)),'Raw data (as reported)'!I7+'Raw data (as reported)'!J7,"")) | F7: =IF(ISNUMBER('Raw data (as reported)'!K7),'Raw data (as reported)'!K7,"") -> 10798 | G7: =IF(AND(ISNUMBER(E7),ISNUMBER(F7)),F7-E7,"") | H7: Only a total (or nothing) found – nothing to reconcile.
A8: ='Raw data (as reported)'!A8 -> 2006 | B8: ='Raw data (as reported)'!B8 -> Wealth Management US | C8: ='Raw data (as reported)'!C8 -> CHF | D8: 20-F 2007 / Handbook | E8: =IF(AND(ISNUMBER('Raw data (as reported)'!E8),ISNUMBER('Raw data (as reported)'!F8),ISNUMBER('Raw data (as reported)'!G8),ISNUMBER('Raw data (as reported)'!H8)),'Raw data (as reported)'!E8+'Raw data (as reported)'!F8+'Raw data (as reported)'!G8+'Raw data (as reported)'!H8,IF(AND(ISNUMBER('Raw data (as reported)'!I8),ISNUMBER('Raw data (as reported)'!J8)),'Raw data (as reported)'!I8+'Raw data (as reported)'!J8,"")) -> 5863 | F8: =IF(ISNUMBER('Raw data (as reported)'!K8),'Raw data (as reported)'!K8,"") -> 5863 | G8: =IF(AND(ISNUMBER(E8),ISNUMBER(F8)),F8-E8,"") -> 0 | H8: Non-recurring derived as total less recurring, so ties by construction.
A9: ='Raw data (as reported)'!A9 -> 2007 | B9: ='Raw data (as reported)'!B9 -> WM International & Switzerland | C9: ='Raw data (as reported)'!C9 -> CHF | D9: 20-F 2007 | E9: =IF(AND(ISNUMBER('Raw data (as reported)'!E9),ISNUMBER('Raw data (as reported)'!F9),ISNUMBER('Raw data (as reported)'!G9),ISNUMBER('Raw data (as reported)'!H9)),'Raw data (as reported)'!E9+'Raw data (as reported)'!F9+'Raw data (as reported)'!G9+'Raw data (as reported)'!H9,IF(AND(ISNUMBER('Raw data (as reported)'!I9),ISNUMBER('Raw data (as reported)'!J9)),'Raw data (as reported)'!I9+'Raw data (as reported)'!J9,"")) | F9: =IF(ISNUMBER('Raw data (as reported)'!K9),'Raw data (as reported)'!K9,"") | G9: =IF(AND(ISNUMBER(E9),ISNUMBER(F9)),F9-E9,"") | H9: Only a total (or nothing) found – nothing to reconcile.
A10: ='Raw data (as reported)'!A10 -> 2007 | B10: ='Raw data (as reported)'!B10 -> Wealth Management US | C10: ='Raw data (as reported)'!C10 -> CHF | D10: 20-F 2007 | E10: =IF(AND(ISNUMBER('Raw data (as reported)'!E10),ISNUMBER('Raw data (as reported)'!F10),ISNUMBER('Raw data (as reported)'!G10),ISNUMBER('Raw data (as reported)'!H10)),'Raw data (as reported)'!E10+'Raw data (as reported)'!F10+'Raw data (as reported)'!G10+'Raw data (as reported)'!H10,IF(AND(ISNUMBER('Raw data (as reported)'!I10),ISNUMBER('Raw data (as reported)'!J10)),'Raw data (as reported)'!I10+'Raw data (as reported)'!J10,"")) | F10: =IF(ISNUMBER('Raw data (as reported)'!K10),'Raw data (as reported)'!K10,"") | G10: =IF(AND(ISNUMBER(E10),ISNUMBER(F10)),F10-E10,"") | H10: Non-recurring derived as total less recurring, so ties by construction.
A11: ='Raw data (as reported)'!A11 -> 2008 | B11: ='Raw data (as reported)'!B11 -> Wealth Management (excl. Swiss retail) | C11: ='Raw data (as reported)'!C11 -> CHF | D11: 6-K (4Q09 report) | E11: =IF(AND(ISNUMBER('Raw data (as reported)'!E11),ISNUMBER('Raw data (as reported)'!F11),ISNUMBER('Raw data (as reported)'!G11),ISNUMBER('Raw data (as reported)'!H11)),'Raw data (as reported)'!E11+'Raw data (as reported)'!F11+'Raw data (as reported)'!G11+'Raw data (as reported)'!H11,IF(AND(ISNUMBER('Raw data (as reported)'!I11),ISNUMBER('Raw data (as reported)'!J11)),'Raw data (as reported)'!I11+'Raw data (as reported)'!J11,"")) | F11: =IF(ISNUMBER('Raw data (as reported)'!K11),'Raw data (as reported)'!K11,"") | G11: =IF(AND(ISNUMBER(E11),ISNUMBER(F11)),F11-E11,"") | H11: Only a total (or nothing) found – nothing to reconcile.
A12: ='Raw data (as reported)'!A12 -> 2008 | B12: ='Raw data (as reported)'!B12 -> Wealth Management Americas | C12: ='Raw data (as reported)'!C12 -> CHF | D12: 6-K (4Q09 report) | E12: =IF(AND(ISNUMBER('Raw data (as reported)'!E12),ISNUMBER('Raw data (as reported)'!F12),ISNUMBER('Raw data (as reported)'!G12),ISNUMBER('Raw data (as reported)'!H12)),'Raw data (as reported)'!E12+'Raw data (as reported)'!F12+'Raw data (as reported)'!G12+'Raw data (as reported)'!H12,IF(AND(ISNUMBER('Raw data (as reported)'!I12),ISNUMBER('Raw data (as reported)'!J12)),'Raw data (as reported)'!I12+'Raw data (as reported)'!J12,"")) -> 6278 | F12: =IF(ISNUMBER('Raw data (as reported)'!K12),'Raw data (as reported)'!K12,"") -> 6278 | G12: =IF(AND(ISNUMBER(E12),ISNUMBER(F12)),F12-E12,"") -> 0 | H12: Non-recurring derived as total less recurring, so ties by construction.
A13: ='Raw data (as reported)'!A13 -> 2009 | B13: ='Raw data (as reported)'!B13 -> Wealth Management | C13: ='Raw data (as reported)'!C13 -> CHF | D13: 6-K (4Q10 report) | E13: =IF(AND(ISNUMBER('Raw data (as reported)'!E13),ISNUMBER('Raw data (as reported)'!F13),ISNUMBER('Raw data (as reported)'!G13),ISNUMBER('Raw data (as reported)'!H13)),'Raw data (as reported)'!E13+'Raw data (as reported)'!F13+'Raw data (as reported)'!G13+'Raw data (as reported)'!H13,IF(AND(ISNUMBER('Raw data (as reported)'!I13),ISNUMBER('Raw data (as reported)'!J13)),'Raw data (as reported)'!I13+'Raw data (as reported)'!J13,"")) -> 7427 | F13: =IF(ISNUMBER('Raw data (as reported)'!K13),'Raw data (as reported)'!K13,"") -> 7427 | G13: =IF(AND(ISNUMBER(E13),ISNUMBER(F13)),F13-E13,"") -> 0 | H13: Recurring + non-recurring = income before credit loss (by construction).
A14: ='Raw data (as reported)'!A14 -> 2009 | B14: ='Raw data (as reported)'!B14 -> Wealth Management Americas | C14: ='Raw data (as reported)'!C14 -> CHF | D14: 6-K (4Q10 report) | E14: =IF(AND(ISNUMBER('Raw data (as reported)'!E14),ISNUMBER('Raw data (as reported)'!F14),ISNUMBER('Raw data (as reported)'!G14),ISNUMBER('Raw data (as reported)'!H14)),'Raw data (as reported)'!E14+'Raw data (as reported)'!F14+'Raw data (as reported)'!G14+'Raw data (as reported)'!H14,IF(AND(ISNUMBER('Raw data (as reported)'!I14),ISNUMBER('Raw data (as reported)'!J14)),'Raw data (as reported)'!I14+'Raw data (as reported)'!J14,"")) -> 5546 | F14: =IF(ISNUMBER('Raw data (as reported)'!K14),'Raw data (as reported)'!K14,"") -> 5546 | G14: =IF(AND(ISNUMBER(E14),ISNUMBER(F14)),F14-E14,"") -> 0 | H14: Recurring + non-recurring = income before credit loss (by construction).
A15: ='Raw data (as reported)'!A15 -> 2010 | B15: ='Raw data (as reported)'!B15 -> Wealth Management | C15: ='Raw data (as reported)'!C15 -> CHF | D15: 6-K (4Q10 report) | E15: =IF(AND(ISNUMBER('Raw data (as reported)'!E15),ISNUMBER('Raw data (as reported)'!F15),ISNUMBER('Raw data (as reported)'!G15),ISNUMBER('Raw data (as reported)'!H15)),'Raw data (as reported)'!E15+'Raw data (as reported)'!F15+'Raw data (as reported)'!G15+'Raw data (as reported)'!H15,IF(AND(ISNUMBER('Raw data (as reported)'!I15),ISNUMBER('Raw data (as reported)'!J15)),'Raw data (as reported)'!I15+'Raw data (as reported)'!J15,"")) -> 7345 | F15: =IF(ISNUMBER('Raw data (as reported)'!K15),'Raw data (as reported)'!K15,"") -> 7345 | G15: =IF(AND(ISNUMBER(E15),ISNUMBER(F15)),F15-E15,"") -> 0 | H15: Recurring + non-recurring = income before credit loss (by construction).
A16: ='Raw data (as reported)'!A16 -> 2010 | B16: ='Raw data (as reported)'!B16 -> Wealth Management Americas | C16: ='Raw data (as reported)'!C16 -> CHF | D16: 6-K (4Q10 report) | E16: =IF(AND(ISNUMBER('Raw data (as reported)'!E16),ISNUMBER('Raw data (as reported)'!F16),ISNUMBER('Raw data (as reported)'!G16),ISNUMBER('Raw data (as reported)'!H16)),'Raw data (as reported)'!E16+'Raw data (as reported)'!F16+'Raw data (as reported)'!G16+'Raw data (as reported)'!H16,IF(AND(ISNUMBER('Raw data (as reported)'!I16),ISNUMBER('Raw data (as reported)'!J16)),'Raw data (as reported)'!I16+'Raw data (as reported)'!J16,"")) -> 5565 | F16: =IF(ISNUMBER('Raw data (as reported)'!K16),'Raw data (as reported)'!K16,"") -> 5565 | G16: =IF(AND(ISNUMBER(E16),ISNUMBER(F16)),F16-E16,"") -> 0 | H16: Recurring + non-recurring = income before credit loss (by construction).
... A37: ='Raw data (as reported)'!A37 -> 2025 | B37: ='Raw data (as reported)'!B37 -> GWM incl. Credit Suisse | C37: ='Raw data (as reported)'!C37 -> USD | D37: 6-K (4Q25 report) | E37: =IF(AND(ISNUMBER('Raw data (as reported)'!E37),ISNUMBER('Raw data (as reported)'!F37),ISNUMBER('Raw data (as reported)'!G37),ISNUMBER('Raw data (as reported)'!H37)),'Raw data (as reported)'!E37+'Raw data (as reported)'!F37+'Raw data (as reported)'!G37+'Raw data (as reported)'!H37,IF(AND(ISNUMBER('Raw data (as reported)'!I37),ISNUMBER('Raw data (as reported)'!J37)),'Raw data (as reported)'!I37+'Raw data (as reported)'!J37,"")) -> 25959 | F37: =IF(ISNUMBER('Raw data (as reported)'!K37),'Raw data (as reported)'!K37,"") -> 25960 | G37: =IF(AND(ISNUMBER(E37),ISNUMBER(F37)),F37-E37,"") -> 1 | H37: Ties (±1 rounding): all lines reported in 4Q25 report.

Sheet Raw data (as reported)
A1: UBS wealth management – data as reported, then converted to USD
A2: Blue = reported by UBS (millions, reporting currency). Black = formula. Green = pulled from another tab. 'Old' basis = Recurring (NII + recurring fees) vs Non-recurring (transactions); 'New' basis = NII / Recurring fees / Transaction.
A4: Year | B4: Unit | C4: Ccy | D4: Basis | E4: Net interest income | F4: Recurring net fee income | G4: Transaction-based income | H4: Other income | I4: Recurring income (old: NII+fees) | J4: Non-recurring income (old) | K4: Total revenue (before credit loss) | L4: Source / note | M4: FX (CHF per USD) | N4: NII (USD m) | O4: Recurring fees (USD m) | P4: Transaction (USD m) | Q4: Other (USD m) | R4: Recurring old (USD m) | S4: Non-recurring old (USD m) | T4: Total revenue (USD m) | U4: Recurring share (NII+fees)
A5: 2005 | B5: WM International & Switzerland | C5: CHF | D5: Old | K5: 9011 | L5: Total: UBS Handbook 2005/06. Recurring split not found. | M5: =INDEX(FX!$B$5:$B$25,MATCH($A5,FX!$A$5:$A$25,0)) -> 1.2459 | N5: =IF(E5="","",IF($C5="USD",E5,E5/$M5)) | O5: =IF(F5="","",IF($C5="USD",F5,F5/$M5)) | P5: =IF(G5="","",IF($C5="USD",G5,G5/$M5)) | Q5: =IF(H5="","",IF($C5="USD",H5,H5/$M5)) | R5: =IF(I5="","",IF($C5="USD",I5,I5/$M5)) | S5: =IF(J5="","",IF($C5="USD",J5,J5/$M5)) | T5: =IF(K5="","",IF($C5="USD",K5,K5/$M5)) -> 7232.5227 | U5: =IF(AND(ISNUMBER(N5),ISNUMBER(O5),ISNUMBER(P5)),(N5+O5)/(N5+O5+P5),IF(AND(ISNUMBER(S5),ISNUMBER(T5)),S5/T5,""))
A6: 2005 | B6: Wealth Management US | C6: CHF | D6: Old | I6: 2834 | J6: =K6-I6 -> 2322 | K6: 5156 | L6: UBS 20-F 2007 (WM US recurring income) https://www.sec.gov/Archives/edgar/data/1114446/000095012308003086/y51182e20vf.htm; totals: UBS Handbook 2005/06 & 2006/07 | M6: =INDEX(FX!$B$5:$B$25,MATCH($A6,FX!$A$5:$A$25,0)) -> 1.2459 | N6: =IF(E6="","",IF($C6="USD",E6,E6/$M6)) | O6: =IF(F6="","",IF($C6="USD",F6,F6/$M6)) | P6: =IF(G6="","",IF($C6="USD",G6,G6/$M6)) | Q6: =IF(H6="","",IF($C6="USD",H6,H6/$M6)) | R6: =IF(I6="","",IF($C6="USD",I6,I6/$M6)) -> 2274.6609 | S6: =IF(J6="","",IF($C6="USD",J6,J6/$M6)) -> 1863.713 | T6: =IF(K6="","",IF($C6="USD",K6,K6/$M6)) -> 4138.3739 | U6: =IF(AND(ISNUMBER(N6),ISNUMBER(O6),ISNUMBER(P6)),(N6+O6)/(N6+O6+P6),IF(AND(ISNUMBER(S6),ISNUMBER(T6)),S6/T6,"")) -> 0.45034911
A7: 2006 | B7: WM International & Switzerland | C7: CHF | D7: Old | K7: 10798 | L7: Total: UBS Handbook 2006/07. Recurring split not found. | M7: =INDEX(FX!$B$5:$B$25,MATCH($A7,FX!$A$5:$A$25,0)) -> 1.2532 | N7: =IF(E7="","",IF($C7="USD",E7,E7/$M7)) | O7: =IF(F7="","",IF($C7="USD",F7,F7/$M7)) | P7: =IF(G7="","",IF($C7="USD",G7,G7/$M7)) | Q7: =IF(H7="","",IF($C7="USD",H7,H7/$M7)) | R7: =IF(I7="","",IF($C7="USD",I7,I7/$M7)) | S7: =IF(J7="","",IF($C7="USD",J7,J7/$M7)) | T7: =IF(K7="","",IF($C7="USD",K7,K7/$M7)) -> 8616.3422 | U7: =IF(AND(ISNUMBER(N7),ISNUMBER(O7),ISNUMBER(P7)),(N7+O7)/(N7+O7+P7),IF(AND(ISNUMBER(S7),ISNUMBER(T7)),S7/T7,""))
A8: 2006 | B8: Wealth Management US | C8: CHF | D8: Old | I8: 3488 | J8: =K8-I8 -> 2375 | K8: 5863 | L8: UBS 20-F 2007 (WM US recurring income) https://www.sec.gov/Archives/edgar/data/1114446/000095012308003086/y51182e20vf.htm; totals: UBS Handbook 2005/06 & 2006/07 | M8: =INDEX(FX!$B$5:$B$25,MATCH($A8,FX!$A$5:$A$25,0)) -> 1.2532 | N8: =IF(E8="","",IF($C8="USD",E8,E8/$M8)) | O8: =IF(F8="","",IF($C8="USD",F8,F8/$M8)) | P8: =IF(G8="","",IF($C8="USD",G8,G8/$M8)) | Q8: =IF(H8="","",IF($C8="USD",H8,H8/$M8)) | R8: =IF(I8="","",IF($C8="USD",I8,I8/$M8)) -> 2783.2748 | S8: =IF(J8="","",IF($C8="USD",J8,J8/$M8)) -> 1895.1484 | T8: =IF(K8="","",IF($C8="USD",K8,K8/$M8)) -> 4678.4232 | U8: =IF(AND(ISNUMBER(N8),ISNUMBER(O8),ISNUMBER(P8)),(N8+O8)/(N8+O8+P8),IF(AND(ISNUMBER(S8),ISNUMBER(T8)),S8/T8,"")) -> 0.40508272
A9: 2007 | B9: WM International & Switzerland | C9: CHF | D9: Old | L9: Annual figures not found (3Q07 quarter: recurring 2,498, non-recurring 824 – see Notes). | M9: =INDEX(FX!$B$5:$B$25,MATCH($A9,FX!$A$5:$A$25,0)) -> 1.1999 | N9: =IF(E9="","",IF($C9="USD",E9,E9/$M9)) | O9: =IF(F9="","",IF($C9="USD",F9,F9/$M9)) | P9: =IF(G9="","",IF($C9="USD",G9,G9/$M9)) | Q9: =IF(H9="","",IF($C9="USD",H9,H9/$M9)) | R9: =IF(I9="","",IF($C9="USD",I9,I9/$M9)) | S9: =IF(J9="","",IF($C9="USD",J9,J9/$M9)) | T9: =IF(K9="","",IF($C9="USD",K9,K9/$M9)) | U9: =IF(AND(ISNUMBER(N9),ISNUMBER(O9),ISNUMBER(P9)),(N9+O9)/(N9+O9+P9),IF(AND(ISNUMBER(S9),ISNUMBER(T9)),S9/T9,""))
A10: 2007 | B10: Wealth Management US | C10: CHF | D10: Old | I10: 4173 | L10: UBS 20-F 2007 (WM US recurring income) https://www.sec.gov/Archives/edgar/data/1114446/000095012308003086/y51182e20vf.htm; totals: UBS Handbook 2005/06 & 2006/07 – total not found | M10: =INDEX(FX!$B$5:$B$25,MATCH($A10,FX!$A$5:$A$25,0)) -> 1.1999 | N10: =IF(E10="","",IF($C10="USD",E10,E10/$M10)) | O10: =IF(F10="","",IF($C10="USD",F10,F10/$M10)) | P10: =IF(G10="","",IF($C10="USD",G10,G10/$M10)) | Q10: =IF(H10="","",IF($C10="USD",H10,H10/$M10)) | R10: =IF(I10="","",IF($C10="USD",I10,I10/$M10)) -> 3477.7898 | S10: =IF(J10="","",IF($C10="USD",J10,J10/$M10)) | T10: =IF(K10="","",IF($C10="USD",K10,K10/$M10)) | U10: =IF(AND(ISNUMBER(N10),ISNUMBER(O10),ISNUMBER(P10)),(N10+O10)/(N10+O10+P10),IF(AND(ISNUMBER(S10),ISNUMBER(T10)),S10/T10,""))
A11: 2008 | B11: Wealth Management (excl. Swiss retail) | C11: CHF | D11: Old | L11: Not found on a comparable basis (2008 restated only as 'WM & Swiss Bank', which includes Swiss retail/corporate). | M11: =INDEX(FX!$B$5:$B$25,MATCH($A11,FX!$A$5:$A$25,0)) -> 1.0816 | N11: =IF(E11="","",IF($C11="USD",E11,E11/$M11)) | O11: =IF(F11="","",IF($C11="USD",F11,F11/$M11)) | P11: =IF(G11="","",IF($C11="USD",G11,G11/$M11)) | Q11: =IF(H11="","",IF($C11="USD",H11,H11/$M11)) | R11: =IF(I11="","",IF($C11="USD",I11,I11/$M11)) | S11: =IF(J11="","",IF($C11="USD",J11,J11/$M11)) | T11: =IF(K11="","",IF($C11="USD",K11,K11/$M11)) | U11: =IF(AND(ISNUMBER(N11),ISNUMBER(O11),ISNUMBER(P11)),(N11+O11)/(N11+O11+P11),IF(AND(ISNUMBER(S11),ISNUMBER(T11)),S11/T11,""))
A12: 2008 | B12: Wealth Management Americas | C12: CHF | D12: Old | I12: 4076 | J12: =K12-I12 -> 2202 | K12: 6278 | L12: UBS 4Q09 report, 6-K 9-Feb-2010 https://www.sec.gov/Archives/edgar/data/1114446/000095012310010264/y81900e6vk.htm (total = income before credit loss) | M12: =INDEX(FX!$B$5:$B$25,MATCH($A12,FX!$A$5:$A$25,0)) -> 1.0816 | N12: =IF(E12="","",IF($C12="USD",E12,E12/$M12)) | O12: =IF(F12="","",IF($C12="USD",F12,F12/$M12)) | P12: =IF(G12="","",IF($C12="USD",G12,G12/$M12)) | Q12: =IF(H12="","",IF($C12="USD",H12,H12/$M12)) | R12: =IF(I12="","",IF($C12="USD",I12,I12/$M12)) -> 3768.4911 | S12: =IF(J12="","",IF($C12="USD",J12,J12/$M12)) -> 2035.8728 | T12: =IF(K12="","",IF($C12="USD",K12,K12/$M12)) -> 5804.3639 | U12: =IF(AND(ISNUMBER(N12),ISNUMBER(O12),ISNUMBER(P12)),(N12+O12)/(N12+O12+P12),IF(AND(ISNUMBER(S12),ISNUMBER(T12)),S12/T12,"")) -> 0.35074865
A13: 2009 | B13: Wealth Management | C13: CHF | D13: Old | I13: 5696 | J13: 1731 | K13: =I13+J13 -> 7427 | L13: UBS 4Q10 report, 6-K 8-Feb-2011 https://www.sec.gov/Archives/edgar/data/1114446/000095012311010017/y89488e6vk.htm | M13: =INDEX(FX!$B$5:$B$25,MATCH($A13,FX!$A$5:$A$25,0)) -> 1.086 | N13: =IF(E13="","",IF($C13="USD",E13,E13/$M13)) | O13: =IF(F13="","",IF($C13="USD",F13,F13/$M13)) | P13: =IF(G13="","",IF($C13="USD",G13,G13/$M13)) | Q13: =IF(H13="","",IF($C13="USD",H13,H13/$M13)) | R13: =IF(I13="","",IF($C13="USD",I13,I13/$M13)) -> 5244.9355 | S13: =IF(J13="","",IF($C13="USD",J13,J13/$M13)) -> 1593.9227 | T13: =IF(K13="","",IF($C13="USD",K13,K13/$M13)) -> 6838.8582 | U13: =IF(AND(ISNUMBER(N13),ISNUMBER(O13),ISNUMBER(P13)),(N13+O13)/(N13+O13+P13),IF(AND(ISNUMBER(S13),ISNUMBER(T13)),S13/T13,"")) -> 0.23306853
A14: 2009 | B14: Wealth Management Americas | C14: CHF | D14: Old | I14: 3256 | J14: 2290 | K14: =I14+J14 -> 5546 | L14: UBS 4Q10 report, 6-K 8-Feb-2011 https://www.sec.gov/Archives/edgar/data/1114446/000095012311010017/y89488e6vk.htm | M14: =INDEX(FX!$B$5:$B$25,MATCH($A14,FX!$A$5:$A$25,0)) -> 1.086 | N14: =IF(E14="","",IF($C14="USD",E14,E14/$M14)) | O14: =IF(F14="","",IF($C14="USD",F14,F14/$M14)) | P14: =IF(G14="","",IF($C14="USD",G14,G14/$M14)) | Q14: =IF(H14="","",IF($C14="USD",H14,H14/$M14)) | R14: =IF(I14="","",IF($C14="USD",I14,I14/$M14)) -> 2998.1584 | S14: =IF(J14="","",IF($C14="USD",J14,J14/$M14)) -> 2108.6556 | T14: =IF(K14="","",IF($C14="USD",K14,K14/$M14)) -> 5106.814 | U14: =IF(AND(ISNUMBER(N14),ISNUMBER(O14),ISNUMBER(P14)),(N14+O14)/(N14+O14+P14),IF(AND(ISNUMBER(S14),ISNUMBER(T14)),S14/T14,"")) -> 0.41291021
A15: 2010 | B15: Wealth Management | C15: CHF | D15: Old | I15: 5411 | J15: 1934 | K15: =I15+J15 -> 7345 | L15: UBS 4Q10 report, 6-K 8-Feb-2011 https://www.sec.gov/Archives/edgar/data/1114446/000095012311010017/y89488e6vk.htm | M15: =INDEX(FX!$B$5:$B$25,MATCH($A15,FX!$A$5:$A$25,0)) -> 1.0432 | N15: =IF(E15="","",IF($C15="USD",E15,E15/$M15)) | O15: =IF(F15="","",IF($C15="USD",F15,F15/$M15)) | P15: =IF(G15="","",IF($C15="USD",G15,G15/$M15)) | Q15: =IF(H15="","",IF($C15="USD",H15,H15/$M15)) | R15: =IF(I15="","",IF($C15="USD",I15,I15/$M15)) -> 5186.9248 | S15: =IF(J15="","",IF($C15="USD",J15,J15/$M15)) -> 1853.911 | T15: =IF(K15="","",IF($C15="USD",K15,K15/$M15)) -> 7040.8359 | U15: =IF(AND(ISNUMBER(N15),ISNUMBER(O15),ISNUMBER(P15)),(N15+O15)/(N15+O15+P15),IF(AND(ISNUMBER(S15),ISNUMBER(T15)),S15/T15,"")) -> 0.26330837
A16: 2010 | B16: Wealth Management Americas | C16: CHF | D16: Old | I16: 3472 | J16: 2093 | K16: =I16+J16 -> 5565 | L16: UBS 4Q10 report, 6-K 8-Feb-2011 https://www.sec.gov/Archives/edgar/data/1114446/000095012311010017/y89488e6vk.htm | M16: =INDEX(FX!$B$5:$B$25,MATCH($A16,FX!$A$5:$A$25,0)) -> 1.0432 | N16: =IF(E16="","",IF($C16="USD",E16,E16/$M16)) | O16: =IF(F16="","",IF($C16="USD",F16,F16/$M16)) | P16: =IF(G16="","",IF($C16="USD",G16,G16/$M16)) | Q16: =IF(H16="","",IF($C16="USD",H16,H16/$M16)) | R16: =IF(I16="","",IF($C16="USD",I16,I16/$M16)) -> 3328.2209 | S16: =IF(J16="","",IF($C16="USD",J16,J16/$M16)) -> 2006.3267 | T16: =IF(K16="","",IF($C16="USD",K16,K16/$M16)) -> 5334.5475 | U16: =IF(AND(ISNUMBER(N16),ISNUMBER(O16),ISNUMBER(P16)),(N16+O16)/(N16+O16+P16),IF(AND(ISNUMBER(S16),ISNUMBER(T16)),S16/T16,"")) -> 0.37610063
A17: 2011 | B17: Wealth Management | C17: CHF | D17: Accounting lines | E17: 1968 | H17: 425 | K17: 7634 | L17: UBS 4Q12 report, 6-K 5-Feb-2013 https://www.sec.gov/Archives/edgar/data/1114446/000119312513037560/d477497d6k.htm (NII known; recurring split not disclosed) | M17: =INDEX(FX!$B$5:$B$25,MATCH($A17,FX!$A$5:$A$25,0)) -> 0.8862 | N17: =IF(E17="","",IF($C17="USD",E17,E17/$M17)) -> 2220.7177 | O17: =IF(F17="","",IF($C17="USD",F17,F17/$M17)) | P17: =IF(G17="","",IF($C17="USD",G17,G17/$M17)) | Q17: =IF(H17="","",IF($C17="USD",H17,H17/$M17)) -> 479.57572 | R17: =IF(I17="","",IF($C17="USD",I17,I17/$M17)) | S17: =IF(J17="","",IF($C17="USD",J17,J17/$M17)) | T17: =IF(K17="","",IF($C17="USD",K17,K17/$M17)) -> 8614.3083 | U17: =IF(AND(ISNUMBER(N17),ISNUMBER(O17),ISNUMBER(P17)),(N17+O17)/(N17+O17+P17),IF(AND(ISNUMBER(S17),ISNUMBER(T17)),S17/T17,""))
A18: 2011 | B18: Wealth Management Americas | C18: USD | D18: Accounting lines | E18: 828 | H18: 121 | K18: 6017 | L18: UBS 4Q12 report, 6-K 5-Feb-2013 https://www.sec.gov/Archives/edgar/data/1114446/000119312513037560/d477497d6k.htm (NII known; recurring income not verified, left blank) | M18: =INDEX(FX!$B$5:$B$25,MATCH($A18,FX!$A$5:$A$25,0)) -> 0.8862 | N18: =IF(E18="","",IF($C18="USD",E18,E18/$M18)) -> 828 | O18: =IF(F18="","",IF($C18="USD",F18,F18/$M18)) | P18: =IF(G18="","",IF($C18="USD",G18,G18/$M18)) | Q18: =IF(H18="","",IF($C18="USD",H18,H18/$M18)) -> 121 | R18: =IF(I18="","",IF($C18="USD",I18,I18/$M18)) | S18: =IF(J18="","",IF($C18="USD",J18,J18/$M18)) | T18: =IF(K18="","",IF($C18="USD",K18,K18/$M18)) -> 6017 | U18: =IF(AND(ISNUMBER(N18),ISNUMBER(O18),ISNUMBER(P18)),(N18+O18)/(N18+O18+P18),IF(AND(ISNUMBER(S18),ISNUMBER(T18)),S18/T18,""))
A19: 2012 | B19: Wealth Management | C19: CHF | D19: Accounting lines | E19: 1951 | H19: 37 | K19: 7040 | L19: UBS 4Q12 report, 6-K 5-Feb-2013 https://www.sec.gov/Archives/edgar/data/1114446/000119312513037560/d477497d6k.htm (NII known; recurring split not disclosed) | M19: =INDEX(FX!$B$5:$B$25,MATCH($A19,FX!$A$5:$A$25,0)) -> 0.9377 | N19: =IF(E19="","",IF($C19="USD",E19,E19/$M19)) -> 2080.6228 | O19: =IF(F19="","",IF($C19="USD",F19,F19/$M19)) | P19: =IF(G19="","",IF($C19="USD",G19,G19/$M19)) | Q19: =IF(H19="","",IF($C19="USD",H19,H19/$M19)) -> 39.458249 | R19: =IF(I19="","",IF($C19="USD",I19,I19/$M19)) | S19: =IF(J19="","",IF($C19="USD",J19,J19/$M19)) | T19: =IF(K19="","",IF($C19="USD",K19,K19/$M19)) -> 7507.7317 | U19: =IF(AND(ISNUMBER(N19),ISNUMBER(O19),ISNUMBER(P19)),(N19+O19)/(N19+O19+P19),IF(AND(ISNUMBER(S19),ISNUMBER(T19)),S19/T19,""))
A20: 2012 | B20: Wealth Management Americas | C20: USD | D20: Accounting lines | E20: 849 | H20: 266 | K20: 6547 | L20: UBS 4Q12 report, 6-K 5-Feb-2013 https://www.sec.gov/Archives/edgar/data/1114446/000119312513037560/d477497d6k.htm (NII known; recurring income cut off in filing text at '4,26x', left blank) | M20: =INDEX(FX!$B$5:$B$25,MATCH($A20,FX!$A$5:$A$25,0)) -> 0.9377 | N20: =IF(E20="","",IF($C20="USD",E20,E20/$M20)) -> 849 | O20: =IF(F20="","",IF($C20="USD",F20,F20/$M20)) | P20: =IF(G20="","",IF($C20="USD",G20,G20/$M20)) | Q20: =IF(H20="","",IF($C20="USD",H20,H20/$M20)) -> 266 | R20: =IF(I20="","",IF($C20="USD",I20,I20/$M20)) | S20: =IF(J20="","",IF($C20="USD",J20,J20/$M20)) | T20: =IF(K20="","",IF($C20="USD",K20,K20/$M20)) -> 6547 | U20: =IF(AND(ISNUMBER(N20),ISNUMBER(O20),ISNUMBER(P20)),(N20+O20)/(N20+O20+P20),IF(AND(ISNUMBER(S20),ISNUMBER(T20)),S20/T20,""))
A21: 2013 | B21: Wealth Management | C21: CHF | D21: New | E21: 2061 | F21: =K21-E21-G21 -> 3614 | G21: 1888 | K21: 7563 | L21: UBS 4Q14 report, 6-K Feb-2015 https://www.sec.gov/Archives/edgar/data/0001610520/000119312515040199/d865106d6k.htm (recurring fees derived, incl. other) | M21: =INDEX(FX!$B$5:$B$25,MATCH($A21,FX!$A$5:$A$25,0)) -> 0.9269 | N21: =IF(E21="","",IF($C21="USD",E21,E21/$M21)) -> 2223.5408 | O21: =IF(F21="","",IF($C21="USD",F21,F21/$M21)) -> 3899.0182 | P21: =IF(G21="","",IF($C21="USD",G21,G21/$M21)) -> 2036.8972 | Q21: =IF(H21="","",IF($C21="USD",H21,H21/$M21)) | R21: =IF(I21="","",IF($C21="USD",I21,I21/$M21)) | S21: =IF(J21="","",IF($C21="USD",J21,J21/$M21)) | T21: =IF(K21="","",IF($C21="USD",K21,K21/$M21)) -> 8159.4563 | U21: =IF(AND(ISNUMBER(N21),ISNUMBER(O21),ISNUMBER(P21)),(N21+O21)/(N21+O21+P21),IF(AND(ISNUMBER(S21),ISNUMBER(T21)),S21/T21,"")) -> 0.75036361
A22: 2013 | B22: Wealth Management Americas | C22: CHF | D22: New | E22: 936 | F22: =K22-E22-G22 -> 3802 | G22: 1800 | K22: 6538 | L22: UBS 4Q14 report, 6-K Feb-2015 https://www.sec.gov/Archives/edgar/data/0001610520/000119312515040199/d865106d6k.htm (recurring fees derived, incl. other) | M22: =INDEX(FX!$B$5:$B$25,MATCH($A22,FX!$A$5:$A$25,0)) -> 0.9269 | N22: =IF(E22="","",IF($C22="USD",E22,E22/$M22)) -> 1009.8177 | O22: =IF(F22="","",IF($C22="USD",F22,F22/$M22)) -> 4101.8449 | P22: =IF(G22="","",IF($C22="USD",G22,G22/$M22)) -> 1941.9571 | Q22: =IF(H22="","",IF($C22="USD",H22,H22/$M22)) | R22: =IF(I22="","",IF($C22="USD",I22,I22/$M22)) | S22: =IF(J22="","",IF($C22="USD",J22,J22/$M22)) | T22: =IF(K22="","",IF($C22="USD",K22,K22/$M22)) -> 7053.6196 | U22: =IF(AND(ISNUMBER(N22),ISNUMBER(O22),ISNUMBER(P22)),(N22+O22)/(N22+O22+P22),IF(AND(ISNUMBER(S22),ISNUMBER(T22)),S22/T22,"")) -> 0.72468645
A23: 2014 | B23: Wealth Management | C23: CHF | D23: New | E23: 2165 | F23: 3783 | G23: 1928 | H23: 25 | K23: 7902 | L23: UBS 4Q15 report, 6-K 2-Feb-2016 https://www.sec.gov/Archives/edgar/data/1610520/000161052016000031/6k20160202ER.htm | M23: =INDEX(FX!$B$5:$B$25,MATCH($A23,FX!$A$5:$A$25,0)) -> 0.9147 | N23: =IF(E23="","",IF($C23="USD",E23,E23/$M23)) -> 2366.8963 | O23: =IF(F23="","",IF($C23="USD",F23,F23/$M23)) -> 4135.7822 | P23: =IF(G23="","",IF($C23="USD",G23,G23/$M23)) -> 2107.7949 | Q23: =IF(H23="","",IF($C23="USD",H23,H23/$M23)) -> 27.331365 | R23: =IF(I23="","",IF($C23="USD",I23,I23/$M23)) | S23: =IF(J23="","",IF($C23="USD",J23,J23/$M23)) | T23: =IF(K23="","",IF($C23="USD",K23,K23/$M23)) -> 8638.898 | U23: =IF(AND(ISNUMBER(N23),ISNUMBER(O23),ISNUMBER(P23)),(N23+O23)/(N23+O23+P23),IF(AND(ISNUMBER(S23),ISNUMBER(T23)),S23/T23,"")) -> 0.75520569
A24: 2014 | B24: Wealth Management Americas | C24: USD | D24: New | E24: 1067 | F24: 4666 | G24: 1825 | H24: 33 | K24: 7590 | L24: UBS 4Q15 report, 6-K 2-Feb-2016 https://www.sec.gov/Archives/edgar/data/1610520/000161052016000031/6k20160202ER.htm | M24: =INDEX(FX!$B$5:$B$25,MATCH($A24,FX!$A$5:$A$25,0)) -> 0.9147 | N24: =IF(E24="","",IF($C24="USD",E24,E24/$M24)) -> 1067 | O24: =IF(F24="","",IF($C24="USD",F24,F24/$M24)) -> 4666 | P24: =IF(G24="","",IF($C24="USD",G24,G24/$M24)) -> 1825 | Q24: =IF(H24="","",IF($C24="USD",H24,H24/$M24)) -> 33 | R24: =IF(I24="","",IF($C24="USD",I24,I24/$M24)) | S24: =IF(J24="","",IF($C24="USD",J24,J24/$M24)) | T24: =IF(K24="","",IF($C24="USD",K24,K24/$M24)) -> 7590 | U24: =IF(AND(ISNUMBER(N24),ISNUMBER(O24),ISNUMBER(P24)),(N24+O24)/(N24+O24+P24),IF(AND(ISNUMBER(S24),ISNUMBER(T24)),S24/T24,"")) -> 0.758534
A25: 2015 | B25: Wealth Management | C25: CHF | D25: New | E25: 2326 | F25: 3820 | G25: 1778 | H25: 231 | K25: 8155 | L25: UBS 4Q16 report, 6-K 27-Jan-2017 https://www.sec.gov/Archives/edgar/data/1610520/000161052017000002/6kubsgroupag4q16.htm | M25: =INDEX(FX!$B$5:$B$25,MATCH($A25,FX!$A$5:$A$25,0)) -> 0.9628 | N25: =IF(E25="","",IF($C25="USD",E25,E25/$M25)) -> 2415.8704 | O25: =IF(F25="","",IF($C25="USD",F25,F25/$M25)) -> 3967.5945 | P25: =IF(G25="","",IF($C25="USD",G25,G25/$M25)) -> 1846.6971 | Q25: =IF(H25="","",IF($C25="USD",H25,H25/$M25)) -> 239.92522 | R25: =IF(I25="","",IF($C25="USD",I25,I25/$M25)) | S25: =IF(J25="","",IF($C25="USD",J25,J25/$M25)) | T25: =IF(K25="","",IF($C25="USD",K25,K25/$M25)) -> 8470.0872 | U25: =IF(AND(ISNUMBER(N25),ISNUMBER(O25),ISNUMBER(P25)),(N25+O25)/(N25+O25+P25),IF(AND(ISNUMBER(S25),ISNUMBER(T25)),S25/T25,"")) -> 0.77561837
A26: 2015 | B26: Wealth Management Americas | C26: USD | D26: New | E26: 1215 | F26: 4795 | G26: 1614 | H26: 32 | K26: 7657 | L26: UBS 4Q16 report, 6-K 27-Jan-2017 https://www.sec.gov/Archives/edgar/data/1610520/000161052017000002/6kubsgroupag4q16.htm | M26: =INDEX(FX!$B$5:$B$25,MATCH($A26,FX!$A$5:$A$25,0)) -> 0.9628 | N26: =IF(E26="","",IF($C26="USD",E26,E26/$M26)) -> 1215 | O26: =IF(F26="","",IF($C26="USD",F26,F26/$M26)) -> 4795 | P26: =IF(G26="","",IF($C26="USD",G26,G26/$M26)) -> 1614 | Q26: =IF(H26="","",IF($C26="USD",H26,H26/$M26)) -> 32 | R26: =IF(I26="","",IF($C26="USD",I26,I26/$M26)) | S26: =IF(J26="","",IF($C26="USD",J26,J26/$M26)) | T26: =IF(K26="","",IF($C26="USD",K26,K26/$M26)) -> 7657 | U26: =IF(AND(ISNUMBER(N26),ISNUMBER(O26),ISNUMBER(P26)),(N26+O26)/(N26+O26+P26),IF(AND(ISNUMBER(S26),ISNUMBER(T26)),S26/T26,"")) -> 0.7883001
A27: 2016 | B27: Wealth Management | C27: CHF | D27: New | E27: 2331 | F27: 3548 | G27: 1397 | H27: 20 | K27: 7296 | L27: UBS 4Q16 report, 6-K 27-Jan-2017 https://www.sec.gov/Archives/edgar/data/1610520/000161052017000002/6kubsgroupag4q16.htm | M27: =INDEX(FX!$B$5:$B$25,MATCH($A27,FX!$A$5:$A$25,0)) -> 0.9848 | N27: =IF(E27="","",IF($C27="USD",E27,E27/$M27)) -> 2366.9781 | O27: =IF(F27="","",IF($C27="USD",F27,F27/$M27)) -> 3602.762 | P27: =IF(G27="","",IF($C27="USD",G27,G27/$M27)) -> 1418.5621 | Q27: =IF(H27="","",IF($C27="USD",H27,H27/$M27)) -> 20.308692 | R27: =IF(I27="","",IF($C27="USD",I27,I27/$M27)) | S27: =IF(J27="","",IF($C27="USD",J27,J27/$M27)) | T27: =IF(K27="","",IF($C27="USD",K27,K27/$M27)) -> 7408.6109 | U27: =IF(AND(ISNUMBER(N27),ISNUMBER(O27),ISNUMBER(P27)),(N27+O27)/(N27+O27+P27),IF(AND(ISNUMBER(S27),ISNUMBER(T27)),S27/T27,"")) -> 0.8079989
A28: 2016 | B28: Wealth Management Americas | C28: USD | D28: New | E28: 1484 | F28: 4880 | G28: 1474 | H28: 35 | K28: 7873 | L28: UBS 4Q16 report, 6-K 27-Jan-2017 https://www.sec.gov/Archives/edgar/data/1610520/000161052017000002/6kubsgroupag4q16.htm | M28: =INDEX(FX!$B$5:$B$25,MATCH($A28,FX!$A$5:$A$25,0)) -> 0.9848 | N28: =IF(E28="","",IF($C28="USD",E28,E28/$M28)) -> 1484 | O28: =IF(F28="","",IF($C28="USD",F28,F28/$M28)) -> 4880 | P28: =IF(G28="","",IF($C28="USD",G28,G28/$M28)) -> 1474 | Q28: =IF(H28="","",IF($C28="USD",H28,H28/$M28)) -> 35 | R28: =IF(I28="","",IF($C28="USD",I28,I28/$M28)) | S28: =IF(J28="","",IF($C28="USD",J28,J28/$M28)) | T28: =IF(K28="","",IF($C28="USD",K28,K28/$M28)) -> 7873 | U28: =IF(AND(ISNUMBER(N28),ISNUMBER(O28),ISNUMBER(P28)),(N28+O28)/(N28+O28+P28),IF(AND(ISNUMBER(S28),ISNUMBER(T28)),S28/T28,"")) -> 0.81194182
A29: 2017 | B29: Global Wealth Management (restated) | C29: USD | D29: New | E29: 4103 | F29: 8968 | G29: 3159 | H29: 65 | K29: 16295 | L29: UBS 4Q18 report, 6-K 22-Jan-2019 (GWM restated) https://www.sec.gov/Archives/edgar/data/1610520/000161052019000002/6kubsgroupag4q18.htm | M29: =INDEX(FX!$B$5:$B$25,MATCH($A29,FX!$A$5:$A$25,0)) -> 0.9842 | N29: =IF(E29="","",IF($C29="USD",E29,E29/$M29)) -> 4103 | O29: =IF(F29="","",IF($C29="USD",F29,F29/$M29)) -> 8968 | P29: =IF(G29="","",IF($C29="USD",G29,G29/$M29)) -> 3159 | Q29: =IF(H29="","",IF($C29="USD",H29,H29/$M29)) -> 65 | R29: =IF(I29="","",IF($C29="USD",I29,I29/$M29)) | S29: =IF(J29="","",IF($C29="USD",J29,J29/$M29)) | T29: =IF(K29="","",IF($C29="USD",K29,K29/$M29)) -> 16295 | U29: =IF(AND(ISNUMBER(N29),ISNUMBER(O29),ISNUMBER(P29)),(N29+O29)/(N29+O29+P29),IF(AND(ISNUMBER(S29),ISNUMBER(T29)),S29/T29,"")) -> 0.80536044
A30: 2018 | B30: Global Wealth Management | C30: USD | D30: New | E30: 4310 | F30: 9585 | G30: 2911 | H30: 151 | K30: 16956 | L30: UBS 4Q18 report, 6-K 22-Jan-2019 (GWM restated) https://www.sec.gov/Archives/edgar/data/1610520/000161052019000002/6kubsgroupag4q18.htm | M30: =INDEX(FX!$B$5:$B$25,MATCH($A30,FX!$A$5:$A$25,0)) -> 0.9784 | N30: =IF(E30="","",IF($C30="USD",E30,E30/$M30)) -> 4310 | O30: =IF(F30="","",IF($C30="USD",F30,F30/$M30)) -> 9585 | P30: =IF(G30="","",IF($C30="USD",G30,G30/$M30)) -> 2911 | Q30: =IF(H30="","",IF($C30="USD",H30,H30/$M30)) -> 151 | R30: =IF(I30="","",IF($C30="USD",I30,I30/$M30)) | S30: =IF(J30="","",IF($C30="USD",J30,J30/$M30)) | T30: =IF(K30="","",IF($C30="USD",K30,K30/$M30)) -> 16956 | U30: =IF(AND(ISNUMBER(N30),ISNUMBER(O30),ISNUMBER(P30)),(N30+O30)/(N30+O30+P30),IF(AND(ISNUMBER(S30),ISNUMBER(T30)),S30/T30,"")) -> 0.82678805
A31: 2019 | B31: Global Wealth Management | C31: USD | D31: New | E31: 3947 | F31: 9258 | G31: 3059 | H31: 110 | K31: 16373 | L31: UBS 4Q20 report, 6-K Jan-2021 https://www.sec.gov/Archives/edgar/data/1610520/000161052021000008/6kubsgroupag4q20.htm | M31: =INDEX(FX!$B$5:$B$25,MATCH($A31,FX!$A$5:$A$25,0)) -> 0.9937 | N31: =IF(E31="","",IF($C31="USD",E31,E31/$M31)) -> 3947 | O31: =IF(F31="","",IF($C31="USD",F31,F31/$M31)) -> 9258 | P31: =IF(G31="","",IF($C31="USD",G31,G31/$M31)) -> 3059 | Q31: =IF(H31="","",IF($C31="USD",H31,H31/$M31)) -> 110 | R31: =IF(I31="","",IF($C31="USD",I31,I31/$M31)) | S31: =IF(J31="","",IF($C31="USD",J31,J31/$M31)) | T31: =IF(K31="","",IF($C31="USD",K31,K31/$M31)) -> 16373 | U31: =IF(AND(ISNUMBER(N31),ISNUMBER(O31),ISNUMBER(P31)),(N31+O31)/(N31+O31+P31),IF(AND(ISNUMBER(S31),ISNUMBER(T31)),S31/T31,"")) -> 0.81191589
A32: 2020 | B32: Global Wealth Management | C32: USD | D32: New | E32: 4027 | F32: 9372 | G32: 3576 | H32: 159 | K32: 17134 | L32: UBS 4Q20 report, 6-K Jan-2021 https://www.sec.gov/Archives/edgar/data/1610520/000161052021000008/6kubsgroupag4q20.htm | M32: =INDEX(FX!$B$5:$B$25,MATCH($A32,FX!$A$5:$A$25,0)) -> 0.9389 | N32: =IF(E32="","",IF($C32="USD",E32,E32/$M32)) -> 4027 | O32: =IF(F32="","",IF($C32="USD",F32,F32/$M32)) -> 9372 | P32: =IF(G32="","",IF($C32="USD",G32,G32/$M32)) -> 3576 | Q32: =IF(H32="","",IF($C32="USD",H32,H32/$M32)) -> 159 | R32: =IF(I32="","",IF($C32="USD",I32,I32/$M32)) | S32: =IF(J32="","",IF($C32="USD",J32,J32/$M32)) | T32: =IF(K32="","",IF($C32="USD",K32,K32/$M32)) -> 17134 | U32: =IF(AND(ISNUMBER(N32),ISNUMBER(O32),ISNUMBER(P32)),(N32+O32)/(N32+O32+P32),IF(AND(ISNUMBER(S32),ISNUMBER(T32)),S32/T32,"")) -> 0.78933726
A33: 2021 | B33: Global Wealth Management | C33: USD | D33: New | E33: 4244 | F33: 11170 | G33: 3836 | H33: 168 | K33: 19419 | L33: UBS 4Q22 report https://www.sec.gov/Archives/edgar/data/1610520/000161052023000011/EDGARq22ubsgroupag.htm | M33: =INDEX(FX!$B$5:$B$25,MATCH($A33,FX!$A$5:$A$25,0)) -> 0.9144 | N33: =IF(E33="","",IF($C33="USD",E33,E33/$M33)) -> 4244 | O33: =IF(F33="","",IF($C33="USD",F33,F33/$M33)) -> 11170 | P33: =IF(G33="","",IF($C33="USD",G33,G33/$M33)) -> 3836 | Q33: =IF(H33="","",IF($C33="USD",H33,H33/$M33)) -> 168 | R33: =IF(I33="","",IF($C33="USD",I33,I33/$M33)) | S33: =IF(J33="","",IF($C33="USD",J33,J33/$M33)) | T33: =IF(K33="","",IF($C33="USD",K33,K33/$M33)) -> 19419 | U33: =IF(AND(ISNUMBER(N33),ISNUMBER(O33),ISNUMBER(P33)),(N33+O33)/(N33+O33+P33),IF(AND(ISNUMBER(S33),ISNUMBER(T33)),S33/T33,"")) -> 0.80072727
A34: 2022 | B34: Global Wealth Management | C34: USD | D34: New | E34: 5273 | F34: 10282 | G34: 3137 | H34: 275 | K34: 18967 | L34: UBS 4Q22 report https://www.sec.gov/Archives/edgar/data/1610520/000161052023000011/EDGARq22ubsgroupag.htm | M34: =INDEX(FX!$B$5:$B$25,MATCH($A34,FX!$A$5:$A$25,0)) -> 0.955 | N34: =IF(E34="","",IF($C34="USD",E34,E34/$M34)) -> 5273 | O34: =IF(F34="","",IF($C34="USD",F34,F34/$M34)) -> 10282 | P34: =IF(G34="","",IF($C34="USD",G34,G34/$M34)) -> 3137 | Q34: =IF(H34="","",IF($C34="USD",H34,H34/$M34)) -> 275 | R34: =IF(I34="","",IF($C34="USD",I34,I34/$M34)) | S34: =IF(J34="","",IF($C34="USD",J34,J34/$M34)) | T34: =IF(K34="","",IF($C34="USD",K34,K34/$M34)) -> 18967 | U34: =IF(AND(ISNUMBER(N34),ISNUMBER(O34),ISNUMBER(P34)),(N34+O34)/(N34+O34+P34),IF(AND(ISNUMBER(S34),ISNUMBER(T34)),S34/T34,"")) -> 0.83217419
... A37: 2025 | B37: GWM incl. Credit Suisse | C37: USD | D37: New | E37: 7018 | F37: 13671 | G37: 5208 | H37: 62 | K37: 25960 | L37: UBS 4Q25 report https://www.ubs.com/content/dam/assets/cc/investor-relations/quarterlies/2025/4q25/full-report-ubs-group-consolidated-4q25.pdf ('Other revenues' as reported) | M37: =INDEX(FX!$B$5:$B$25,MATCH($A37,FX!$A$5:$A$25,0)) -> 0.8305 | N37: =IF(E37="","",IF($C37="USD",E37,E37/$M37)) -> 7018 | O37: =IF(F37="","",IF($C37="USD",F37,F37/$M37)) -> 13671 | P37: =IF(G37="","",IF($C37="USD",G37,G37/$M37)) -> 5208 | Q37: =IF(H37="","",IF($C37="USD",H37,H37/$M37)) -> 62 | R37: =IF(I37="","",IF($C37="USD",I37,I37/$M37)) | S37: =IF(J37="","",IF($C37="USD",J37,J37/$M37)) | T37: =IF(K37="","",IF($C37="USD",K37,K37/$M37)) -> 25960 | U37: =IF(AND(ISNUMBER(N37),ISNUMBER(O37),ISNUMBER(P37)),(N37+O37)/(N37+O37+P37),IF(AND(ISNUMBER(S37),ISNUMBER(T37)),S37/T37,"")) -> 0.79889562
A39: Recurring share (NII+fees): new-basis rows = (NII + recurring fees) ÷ sum of the three lines; old-basis rows = recurring income ÷ total. This is the one ratio comparable across all years.

Sheet FX
A1: Annual average CHF per USD
A2: Source: Federal Reserve via FRED, series AEXSZUS (annual average). https://fred.stlouisfed.org/series/AEXSZUS — USD = CHF ÷ rate.
A4: Year | B4: CHF per USD
A5: 2005 | B5: 1.2459
A6: 2006 | B6: 1.2532
A7: 2007 | B7: 1.1999
A8: 2008 | B8: 1.0816
A9: 2009 | B9: 1.086
A10: 2010 | B10: 1.0432
A11: 2011 | B11: 0.8862
A12: 2012 | B12: 0.9377
A13: 2013 | B13: 0.9269
A14: 2014 | B14: 0.9147
A15: 2015 | B15: 0.9628
A16: 2016 | B16: 0.9848
... A25: 2025 | B25: 0.8305

Sheet Notes
A1: How to read this
A2: • Every UBS figure is in blue on the Raw data tab in the currency UBS reported it; the USD columns convert CHF at the FRED annual average rate.
A3: • The Summary tab only adds up a year when all units for that year have the number, so a blank means 'not complete', never zero.
A5: Reporting bases
A6: • 2005–2010 (old): UBS split revenue into Recurring (interest + recurring fees) and Non-recurring (transactions).
A7: • 2011–2012: both units reported only accounting lines (NII, net fees, trading); the recurring split could not be verified, so it is left blank.
A8: • 2013 onward (new): Net interest income / Recurring net fee income / Transaction-based income.
A10: Perimeter breaks
A11: • 2005–2008: WM International & Switzerland + WM US (inside Global Wealth Management & Business Banking).
A12: • 2009–2016: Wealth Management (CHF) + Wealth Management Americas (USD) reported separately.
A13: • 2017 onward: Global Wealth Management (2017 restated by UBS); from June 2023 includes Credit Suisse.
A15: Gaps (left blank on purpose)
... A22: • Transaction income fell from ~25–30% of revenue to ~17–20%; NII share swings with rates (22% in 2021 → 33% in 2023 → 27% in 2025).
